Workbook

Sheet 日报
A1: 太樾旗舰店推广报表
A2: 目标ROI | B2: 渠道 | C2: 日期 | D2: 12月总计 | E2: 46011 | F2: 46012 | G2: 46013 | H2: 46014 | I2: 46015 | J2: 46016 | K2: 46017 | L2: 46018 | M2: 46019 | N2: 46020 | O2: 46021 | P2: 46022 | Q2: 1月总计 | R2: 46023 | S2: 46024 | T2: 46025 | U2: 46026 | V2: 46027 | W2: 46028 | X2: 46029 | Y2: 46030 | Z2: 46031 | AA2: 46032 | AB2: 46033 | AC2: 46034 | AD2: 46035 | AE2: 46036 | AF2: 46037 | AG2: 46038 | AH2: 46039 | AI2: 46040 | AJ2: 46041 | AK2: 46042 | AL2: 46043 | AM2: 46044 | AN2: 46045 | AO2: 46046 | AP2: 46047 | AQ2: 46048 | AR2: 46049 | AS2: 46050 | AT2: 46051 | AU2: 46052 | AV2: 46053 | AW2: 2月总计 | AX2: 46054 | AY2: 46055 | AZ2: 46056 | BA2: 46057 | BB2: 46058 | BC2: 46059 | BD2: 46060 | BE2: 46061 | BF2: 46062 | BG2: 46063 | BH2: 46064 | BI2: 46065 | BJ2: 46066 | BK2: 46067 | BL2: 46068 | BM2: 46069 | BN2: 46070 | BO2: 46071 | BP2: 46072 | BQ2: 46073 | BR2: 46074 | BS2: 46075 | BT2: 46076 | BU2: 46077 | BV2: 46078 | BW2: 46079 | BX2: 46080 | BY2: 46081 | BZ2: 3月总计 | CA2: 46082 | CB2: 46083 | CC2: 46084 | CD2: 46085 | CE2: 46086 | CF2: 46087 | CG2: 46088 | CH2: 46089 | CI2: 46090 | CJ2: 46091 | CK2: 46092 | CL2: 46093 | CM2: 46094 | CN2: 46095 | CO2: 46096 | CP2: 46097 | CQ2: 46098 | CR2: 46099 | CS2: 46100 | CT2: 46101 | CU2: 46102 | CV2: 46103 | CW2: 46104 | CX2: 46105 | CY2: 46106 | CZ2: 46107 | DA2: 46108 | DB2: 46109 | DC2: 46110 | DD2: 46111 | DE2: 46112 | DF2: 4月总计 | DG2: 46113 | DH2: 46114 | DI2: 46115 | DJ2: 46116 | DK2: 46117 | DL2: 46118 | DM2: 46119 | DN2: 46120 | DO2: 46121 | DP2: 46122 | DQ2: 46123 | DR2: 46124 | DS2: 46125 | DT2: 46126 | DU2: 46127 | DV2: 46128 | DW2: 46129 | DX2: 46130 | DY2: 46131 | DZ2: 46132 | EA2: 46133 | EB2: 46134 | EC2: 46135 | ED2: 46136 | EE2: 46137 | EF2: 46138 | EG2: 46139 | EH2: 46140 | EI2: 46141 | EJ2: 46142 | EK2: 5月总计 | EL2: 46143 | EM2: 46144 | EN2: 46145 | EO2: 46146 | EP2: 46147 | EQ2: 46148 | ER2: 46149 | ES2: 46150 | ET2: 46151 | EU2: 46152 | EV2: 46153 | EW2: 46154 | EX2: 46155 | EY2: 46156 | EZ2: 46157 | FA2: 46158 | FB2: 46159 | FC2: 46160 | FD2: 46161 | FE2: 46162 | FF2: 46163 | FG2: 46164 | FH2: 46165 | FI2: 46166 | FJ2: 46167 | FK2: 46168 | FL2: 46169 | FM2: 46170 | FN2: 46171 | FO2: 46172 | FP2: 46173 | FQ2: 6月总计 | FR2: 46174 | FS2: 46175 | FT2: 46176 | FU2: 46177 | FV2: 46178 | FW2: 46179 | FX2: 46180 | FY2: 46181 | FZ2: 46182 | GA2: 46183 | GB2: 46184 | GC2: 46185 | GD2: 46186 | GE2: 46187 | GF2: 46188 | GG2: 46189 | GH2: 46190 | GI2: 46191 | GJ2: 46192 | GK2: 46193 | GL2: 46194 | GM2: 46195 | GN2: 46196 | GO2: 46197 | GP2: 46198
B3: 推广汇总 | C3: 花费 | D3: =SUM(E3:P3) -> #REF! | E3: =E20+E29+E38+E47+E56+E65 -> #REF! | F3: =F20+F29+F38+F47+F56+F65 -> #REF! | G3: =G20+G29+G38+G47+G56+G65 -> #REF! | H3: =H20+H29+H38+H47+H56+H65 -> #REF! | I3: =I20+I29+I38+I47+I56+I65 -> #REF! | J3: =J20+J29+J38+J47+J56+J65 -> #REF! | K3: =K20+K29+K38+K47+K56+K65 -> #REF! | L3: =L20+L29+L38+L47+L56+L65 -> #REF! | ... P3: =P20+P29+P38+P47+P56+P65 -> #REF! | Q3: =SUM(R3:AV3) -> 10202.72 | R3: =R20+R29+R38+R47+R56+R65 -> 230.73 | S3: =S20+S29+S38+S47+S56+S65 -> 229.7 | T3: =T20+T29+T38+T47+T56+T65 -> 286.36 | U3: =U20+U29+U38+U47+U56+U65 -> 428.62 | V3: =V20+V29+V38+V47+V56+V65 -> 348.76 | W3: =W20+W29+W38+W47+W56+W65 -> 374.2 | X3: =X20+X29+X38+X47+X56+X65 -> 313.85 | Y3: =Y20+Y29+Y38+Y47+Y56+Y65 -> 377 | ... AV3: =AV20+AV29+AV38+AV47+AV56+AV65 -> 267.44 | AW3: =SUM(AX3:BY3) -> 5679.7 | AX3: =AX20+AX29+AX38+AX47+AX56+AX65 -> 273.95 | AY3: =AY20+AY29+AY38+AY47+AY56+AY65 -> 285.71 | AZ3: =AZ20+AZ29+AZ38+AZ47+AZ56+AZ65 -> 260.76 | BA3: =BA20+BA29+BA38+BA47+BA56+BA65 -> 261.42 | BB3: =BB20+BB29+BB38+BB47+BB56+BB65 -> 272.63 | BC3: =BC20+BC29+BC38+BC47+BC56+BC65 -> 261.13 | BD3: =BD20+BD29+BD38+BD47+BD56+BD65 -> 256.67 | BE3: =BE20+BE29+BE38+BE47+BE56+BE65 -> 270.07 | ... BY3: =BY20+BY29+BY38+BY47+BY56+BY65 -> 235.04 | BZ3: =SUM(CA3:DE3) -> 10435.87 | CA3: =CA20+CA29+CA38+CA47+CA56+CA65 -> 215.8 | CB3: =CB20+CB29+CB38+CB47+CB56+CB65 -> 225.78 | CC3: =CC20+CC29+CC38+CC47+CC56+CC65 -> 237.53 | CD3: =CD20+CD29+CD38+CD47+CD56+CD65 -> 306.96 | CE3: =CE20+CE29+CE38+CE47+CE56+CE65 -> 338.82 | CF3: =CF20+CF29+CF38+CF47+CF56+CF65 -> 306.52 | CG3: =CG20+CG29+CG38+CG47+CG56+CG65 -> 231.74 | CH3: =CH20+CH29+CH38+CH47+CH56+CH65 -> 273.86 | ... DE3: =DE20+DE29+DE38+DE47+DE56+DE65 -> 321.02 | DF3: =SUM(DG3:EJ3) -> 10737.69 | DG3: =DG20+DG29+DG38+DG47+DG56+DG65 -> 269.05 | DH3: =DH20+DH29+DH38+DH47+DH56+DH65 -> 223.4 | DI3: =DI20+DI29+DI38+DI47+DI56+DI65 -> 280.21 | DJ3: =DJ20+DJ29+DJ38+DJ47+DJ56+DJ65 -> 266.99 | DK3: =DK20+DK29+DK38+DK47+DK56+DK65 -> 338.86 | DL3: =DL20+DL29+DL38+DL47+DL56+DL65 -> 265.57 | DM3: =DM20+DM29+DM38+DM47+DM56+DM65 -> 507.4 | DN3: =DN20+DN29+DN38+DN47+DN56+DN65 -> 685.11 | ... EJ3: =EJ20+EJ29+EJ38+EJ47+EJ56+EJ65 -> 246 | EK3: =SUM(EL3:FP3) -> 10292.28 | EL3: =EL20+EL29+EL38+EL47+EL56+EL65 -> 251.35 | EM3: =EM20+EM29+EM38+EM47+EM56+EM65 -> 237.78 | EN3: =EN20+EN29+EN38+EN47+EN56+EN65 -> 257.04 | EO3: =EO20+EO29+EO38+EO47+EO56+EO65 -> 246.18 | EP3: =EP20+EP29+EP38+EP47+EP56+EP65 -> 263.29 | EQ3: =EQ20+EQ29+EQ38+EQ47+EQ56+EQ65 -> 251.64 | ER3: =ER20+ER29+ER38+ER47+ER56+ER65 -> 243.45 | ES3: =ES20+ES29+ES38+ES47+ES56+ES65 -> 438.23 | ... FP3: =FP20+FP29+FP38+FP47+FP56+FP65 -> 337.54 | FQ3: =SUM(FR3:GX3) -> 7384.34 | FR3: =FR20+FR29+FR38+FR47+FR56+FR65 -> 312.68 | FS3: =FS20+FS29+FS38+FS47+FS56+FS65 -> 300.42 | FT3: =FT20+FT29+FT38+FT47+FT56+FT65 -> 279.32 | FU3: =FU20+FU29+FU38+FU47+FU56+FU65 -> 332 | FV3: =FV20+FV29+FV38+FV47+FV56+FV65 -> 301.96 | FW3: =FW20+FW29+FW38+FW47+FW56+FW65 -> 336.92 | FX3: =FX20+FX29+FX38+FX47+FX56+FX65 -> 361.92 | FY3: =FY20+FY29+FY38+FY47+FY56+FY65 -> 357.64 | ... GP3: =GP20+GP29+GP38+GP47+GP56+GP65 -> 0
A4: 实际ROI (除品销宝) | C4: ROI | D4: =(D24+D33+D42+D51+D60+D69)/(D3) -> #REF! | E4: =(E24+E33+E42+E51+E60+E69)/(E3) -> #REF! | F4: =(F24+F33+F42+F51+F60+F69)/(F3) -> #REF! | G4: =(G24+G33+G42+G51+G60+G69)/(G3) -> #REF! | H4: =(H24+H33+H42+H51+H60+H69)/(H3) -> #REF! | I4: =(I24+I33+I42+I51+I60+I69)/(I3) -> #REF! | J4: =(J24+J33+J42+J51+J60+J69)/(J3) -> #REF! | K4: =(K24+K33+K42+K51+K60+K69)/(K3) -> #REF! | ... GP4: =(GP24+GP33+GP42+GP51+GP60+GP69)/(GP3) -> #DIV/0!
A5: =D4 -> #REF! | C5: 店铺销售额 | D5: =SUM(E5:P5) -> 39572.03 | E5: 5285.21 | F5: 351.94 | G5: 22254.41 | H5: 2589.55 | I5: 847.83 | J5: 1257.21 | K5: 231.18 | L5: 3071.4 | M5: 998 | N5: 1983.45 | O5: 701.85 | P5: 0 | Q5: =SUM(R5:AV5) -> 56457.53 | R5: 1796.9 | S5: 4627.64 | T5: 81.18 | U5: 3169.29 | V5: 3934.14 | W5: 1045.14 | X5: 86.82 | Y5: 3141.89 | Z5: 2283.55 | AA5: 464.34 | AB5: 5882.5 | AC5: 71.38 | AD5: 824.95 | AE5: 3302.01 | AF5: 235.67 | AG5: 965.87 | AH5: 955.4 | AI5: 595.85 | AJ5: 1899.68 | AK5: 742.55 | AL5: 74.1 | AM5: 879.16 | AN5: 3254.86 | AO5: 3605.35 | AP5: 2106.35 | AQ5: 971.69 | AR5: 1527.21 | AS5: 357.76 | AT5: 4015.47 | AU5: 1540.29 | AV5: 2018.54 | AW5: =SUM(AX5:BY5) -> 214430.41 | AX5: 105954.8 | AY5: 63126.76 | AZ5: 1603.24 | BA5: 11950.28 | BB5: 4024.13 | BC5: 4827.08 | BD5: 1732.22 | BE5: 2662.23 | BF5: 27.95 | BG5: 1714.09 | BQ5: 0 | BR5: 562.44 | BS5: 4360.36 | BT5: 57.27 | BU5: 3007.73 | BV5: 649.74 | BW5: 7250.41 | BX5: 615.82 | BY5: 303.86 | BZ5: =SUM(CA5:DE5) -> 75865.11 | CA5: 1645.81 | CB5: 514.64 | CC5: 19371.4 | CD5: 2896.7 | CE5: 3865.25 | CF5: 540.32 | CG5: 654.65 | CH5: 3285.2 | CI5: 2267.67 | CJ5: 1402.74 | CK5: 3288.2 | CL5: 906.18 | CM5: 2681.15 | CN5: 3487.1 | CO5: 1928.22 | CP5: 1950.16 | CQ5: 2301.99 | CR5: 6835.97 | CS5: 2445.09 | CT5: 928.53 | CU5: 1034.96 | CV5: 999.74 | CW5: 3669.31 | CX5: 1746.05 | CY5: 887.26 | CZ5: 518 | DA5: 270.77 | DB5: 1787.01 | DC5: 693.51 | DD5: 473.9 | DE5: 587.63 | DF5: =SUM(DG5:EJ5) -> 43628.54 | DG5: 252.2 | DH5: 752.64 | DI5: 1408.91 | DJ5: 978.97 | DK5: 1040.79 | DL5: 743.92 | DM5: 4088.38 | DN5: 1736.2 | DO5: 4668.49 | DP5: 1985.64 | DQ5: 660.3 | DR5: 343.54 | DS5: 738.95 | DT5: 1984.44 | DU5: 4053.14 | DV5: 1559.09 | DW5: 502.12 | DX5: 965.11 | DY5: 1529.09 | DZ5: 508.41 | EA5: 26.1 | EB5: 570.05 | EC5: 1654.72 | ED5: 4636.29 | EE5: 708.12 | EF5: 940.43 | EG5: 1171.27 | EH5: 2609.61 | EI5: 172.5 | EJ5: 639.12 | EK5: =SUM(EL5:FP5) -> 54561.76 | EL5: 217.84 | EM5: 345.91 | EN5: 108 | EO5: 318.75 | EP5: 3300.33 | EQ5: 451.5 | ER5: 10780.74 | ES5: 607.46 | ET5: 2321.59 | EU5: 471.97 | EV5: 472.97 | EW5: 706.64 | EX5: 443.08 | EY5: 888.04 | EZ5: 2054.76 | FA5: 5023.51 | FB5: 1260.35 | FC5: 142 | FD5: 547.4 | FE5: 1628.4 | FF5: 9940.79 | FG5: 1711.8 | FH5: 644.2 | FI5: 744.09 | FJ5: 400.53 | FK5: 636.45 | FL5: 4822.18 | FM5: 1525.46 | FN5: 549.27 | FO5: 1062.17 | FP5: 433.58 | FQ5: =SUM(FR5:GX5) -> 32437.81 | FR5: 476.16 | FS5: 1515.25 | FT5: 1724.26 | FU5: 1081.31 | FV5: 3335.66 | FW5: 348.71 | FX5: 1286.86 | FY5: 254.57 | FZ5: 1054.93 | GA5: 3428.62 | GB5: 835.6 | GC5: 271.49 | GD5: 1427.73 | GE5: 4931.24 | GF5: 3302.78 | GG5: 792.18 | GH5: 444.45 | GI5: 394.95 | GJ5: 944.65 | GK5: 929.89 | GL5: 457.8 | GM5: 798.18 | GN5: 799.18 | GO5: 800.18 | GP5: 801.18
C6: 费率 | D6: =D3/D5 -> #REF! | E6: =E3/E5 -> #REF! | F6: =F3/F5 -> #REF! | G6: =G3/G5 -> #REF! | H6: =H3/H5 -> #REF! | I6: =I3/I5 -> #REF! | J6: =J3/J5 -> #REF! | K6: =K3/K5 -> #REF! | ... GP6: =GP3/GP5 -> 0
C7: 花费(除淘宝客) | D7: =SUM(E7:P7) -> #REF! | E7: =E20+#REF!+E38+E47 -> #REF! | F7: =F20+#REF!+F38+F47 -> #REF! | G7: =G20+#REF!+G38+G47 -> #REF! | H7: =H20+#REF!+H38+H47 -> #REF! | I7: =I20+#REF!+I38+I47 -> #REF! | J7: =J20+#REF!+J38+J47 -> #REF! | K7: =K20+#REF!+K38+K47 -> #REF! | L7: =L20+#REF!+L38+L47 -> #REF! | ... P7: =P20+#REF!+P38+P47 -> #REF! | Q7: =SUM(R7:AV7) -> #REF! | R7: =R20+#REF!+R38+R47 -> #REF! | S7: =S20+#REF!+S38+S47 -> #REF! | T7: =T20+#REF!+T38+T47 -> #REF! | U7: =U20+#REF!+U38+U47 -> #REF! | V7: =V20+#REF!+V38+V47 -> #REF! | W7: =W20+#REF!+W38+W47 -> #REF! | X7: =X20+#REF!+X38+X47 -> #REF! | Y7: =Y20+#REF!+Y38+Y47 -> #REF! | ... AV7: =AV20+#REF!+AV38+AV47 -> #REF! | AW7: =SUM(AX7:BY7) -> #REF! | AX7: =AX20+#REF!+AX38+AX47 -> #REF! | AY7: =AY20+#REF!+AY38+AY47 -> #REF! | AZ7: =AZ20+#REF!+AZ38+AZ47 -> #REF! | BA7: =BA20+#REF!+BA38+BA47 -> #REF! | BB7: =BB20+#REF!+BB38+BB47 -> #REF! | BC7: =BC20+#REF!+BC38+BC47 -> #REF! | BD7: =BD20+#REF!+BD38+BD47 -> #REF! | BE7: =BE20+#REF!+BE38+BE47 -> #REF! | ... BY7: =BY20+#REF!+BY38+BY47 -> #REF! | BZ7: =SUM(CA7:DE7) -> #REF! | CA7: =CA20+#REF!+CA38+CA47 -> #REF! | CB7: =CB20+#REF!+CB38+CB47 -> #REF! | CC7: =CC20+#REF!+CC38+CC47 -> #REF! | CD7: =CD20+#REF!+CD38+CD47 -> #REF! | CE7: =CE20+#REF!+CE38+CE47 -> #REF! | CF7: =CF20+#REF!+CF38+CF47 -> #REF! | CG7: =CG20+#REF!+CG38+CG47 -> #REF! | CH7: =CH20+#REF!+CH38+CH47 -> #REF! | ... DE7: =DE20+#REF!+DE38+DE47 -> #REF! | DF7: =SUM(DG7:EJ7) -> #REF! | DG7: =DG20+#REF!+DG38+DG47 -> #REF! | DH7: =DH20+#REF!+DH38+DH47 -> #REF! | DI7: =DI20+#REF!+DI38+DI47 -> #REF! | DJ7: =DJ20+#REF!+DJ38+DJ47 -> #REF! | DK7: =DK20+#REF!+DK38+DK47 -> #REF! | DL7: =DL20+#REF!+DL38+DL47 -> #REF! | DM7: =DM20+#REF!+DM38+DM47 -> #REF! | DN7: =DN20+#REF!+DN38+DN47 -> #REF! | ... EJ7: =EJ20+#REF!+EJ38+EJ47 -> #REF! | EK7: =SUM(EL7:FP7) -> #REF! | EL7: =EL20+#REF!+EL38+EL47 -> #REF! | EM7: =EM20+#REF!+EM38+EM47 -> #REF! | EN7: =EN20+#REF!+EN38+EN47 -> #REF! | EO7: =EO20+#REF!+EO38+EO47 -> #REF! | EP7: =EP20+#REF!+EP38+EP47 -> #REF! | EQ7: =EQ20+#REF!+EQ38+EQ47 -> #REF! | ER7: =ER20+#REF!+ER38+ER47 -> #REF! | ES7: =ES20+#REF!+ES38+ES47 -> #REF! | ... FP7: =FP20+#REF!+FP38+FP47 -> #REF! | FQ7: =SUM(FR7:GX7) -> #REF! | FR7: =FR20+#REF!+FR38+FR47 -> #REF! | FS7: =FS20+#REF!+FS38+FS47 -> #REF! | FT7: =FT20+#REF!+FT38+FT47 -> #REF! | FU7: =FU20+#REF!+FU38+FU47 -> #REF! | FV7: =FV20+#REF!+FV38+FV47 -> #REF! | FW7: =FW20+#REF!+FW38+FW47 -> #REF! | FX7: =FX20+#REF!+FX38+FX47 -> #REF! | FY7: =FY20+#REF!+FY38+FY47 -> #REF! | ... GP7: =GP20+#REF!+GP38+GP47 -> #REF!
C8: 费率(除淘宝客) | D8: =D7/D5 -> #REF! | E8: =E7/E5 -> #REF! | F8: =F7/F5 -> #REF! | G8: =G7/G5 -> #REF! | H8: =H7/H5 -> #REF! | I8: =I7/I5 -> #REF! | J8: =J7/J5 -> #REF! | K8: =K7/K5 -> #REF! | ... GP8: =GP7/GP5 -> #REF!
C9: ROI(含品销宝) | D9: =D15/D7 -> #REF! | E9: =E15/E7 -> #REF! | F9: =F15/F7 -> #REF! | G9: =G15/G7 -> #REF! | H9: =H15/H7 -> #REF! | I9: =I15/I7 -> #REF! | J9: =J15/J7 -> #REF! | K9: =K15/K7 -> #REF! | ... GP9: =GP15/GP7 -> #REF!
A10: 店铺GMV | C10: 点击量 | D10: =SUM(E10:P10) -> #REF! | E10: =E21+E30+E48+E39+E57+E66 -> #REF! | F10: =F21+F30+F48+F39+F57+F66 -> #REF! | G10: =G21+G30+G48+G39+G57+G66 -> #REF! | H10: =H21+H30+H48+H39+H57+H66 -> #REF! | I10: =I21+I30+I48+I39+I57+I66 -> #REF! | J10: =J21+J30+J48+J39+J57+J66 -> #REF! | K10: =K21+K30+K48+K39+K57+K66 -> #REF! | L10: =L21+L30+L48+L39+L57+L66 -> #REF! | ... P10: =P21+P30+P48+P39+P57+P66 -> #REF! | Q10: =SUM(R10:AV10) -> 6166 | R10: =R21+R30+R48+R39+R57+R66 -> 143 | S10: =S21+S30+S48+S39+S57+S66 -> 188 | T10: =T21+T30+T48+T39+T57+T66 -> 201 | U10: =U21+U30+U48+U39+U57+U66 -> 264 | V10: =V21+V30+V48+V39+V57+V66 -> 244 | W10: =W21+W30+W48+W39+W57+W66 -> 196 | X10: =X21+X30+X48+X39+X57+X66 -> 238 | Y10: =Y21+Y30+Y48+Y39+Y57+Y66 -> 204 | ... AV10: =AV21+AV30+AV48+AV39+AV57+AV66 -> 175 | AW10: =SUM(AX10:BY10) -> 5850 | AX10: =AX21+AX30+AX48+AX39+AX57+AX66 -> 214 | AY10: =AY21+AY30+AY48+AY39+AY57+AY66 -> 244 | AZ10: =AZ21+AZ30+AZ48+AZ39+AZ57+AZ66 -> 210 | BA10: =BA21+BA30+BA48+BA39+BA57+BA66 -> 251 | BB10: =BB21+BB30+BB48+BB39+BB57+BB66 -> 223 | BC10: =BC21+BC30+BC48+BC39+BC57+BC66 -> 239 | BD10: =BD21+BD30+BD48+BD39+BD57+BD66 -> 176 | BE10: =BE21+BE30+BE48+BE39+BE57+BE66 -> 221 | ... BY10: =BY21+BY30+BY48+BY39+BY57+BY66 -> 224 | BZ10: =SUM(CA10:DE10) -> 9876 | CA10: =CA21+CA30+CA48+CA39+CA57+CA66 -> 245 | CB10: =CB21+CB30+CB48+CB39+CB57+CB66 -> 223 | CC10: =CC21+CC30+CC48+CC39+CC57+CC66 -> 236 | CD10: =CD21+CD30+CD48+CD39+CD57+CD66 -> 221 | CE10: =CE21+CE30+CE48+CE39+CE57+CE66 -> 348 | CF10: =CF21+CF30+CF48+CF39+CF57+CF66 -> 288 | CG10: =CG21+CG30+CG48+CG39+CG57+CG66 -> 230 | CH10: =CH21+CH30+CH48+CH39+CH57+CH66 -> 306 | ... DE10: =DE21+DE30+DE48+DE39+DE57+DE66 -> 360 | DF10: =SUM(DG10:EJ10) -> 12247 | DG10: =DG21+DG30+DG48+DG39+DG57+DG66 -> 370 | DH10: =DH21+DH30+DH48+DH39+DH57+DH66 -> 305 | DI10: =DI21+DI30+DI48+DI39+DI57+DI66 -> 353 | DJ10: =DJ21+DJ30+DJ48+DJ39+DJ57+DJ66 -> 360 | DK10: =DK21+DK30+DK48+DK39+DK57+DK66 -> 338 | DL10: =DL21+DL30+DL48+DL39+DL57+DL66 -> 318 | DM10: =DM21+DM30+DM48+DM39+DM57+DM66 -> 389 | DN10: =DN21+DN30+DN48+DN39+DN57+DN66 -> 541 | ... EJ10: =EJ21+EJ30+EJ48+EJ39+EJ57+EJ66 -> 399 | EK10: =SUM(EL10:FP10) -> 14458 | EL10: =EL21+EL30+EL48+EL39+EL57+EL66 -> 427 | EM10: =EM21+EM30+EM48+EM39+EM57+EM66 -> 396 | EN10: =EN21+EN30+EN48+EN39+EN57+EN66 -> 414 | EO10: =EO21+EO30+EO48+EO39+EO57+EO66 -> 408 | EP10: =EP21+EP30+EP48+EP39+EP57+EP66 -> 432 | EQ10: =EQ21+EQ30+EQ48+EQ39+EQ57+EQ66 -> 371 | ER10: =ER21+ER30+ER48+ER39+ER57+ER66 -> 348 | ES10: =ES21+ES30+ES48+ES39+ES57+ES66 -> 687 | ... FP10: =FP21+FP30+FP48+FP39+FP57+FP66 -> 540 | FQ10: =SUM(FR10:GX10) -> 8339 | FR10: =FR21+FR30+FR48+FR39+FR57+FR66 -> 361 | FS10: =FS21+FS30+FS48+FS39+FS57+FS66 -> 315 | FT10: =FT21+FT30+FT48+FT39+FT57+FT66 -> 295 | FU10: =FU21+FU30+FU48+FU39+FU57+FU66 -> 370 | FV10: =FV21+FV30+FV48+FV39+FV57+FV66 -> 356 | FW10: =FW21+FW30+FW48+FW39+FW57+FW66 -> 463 | FX10: =FX21+FX30+FX48+FX39+FX57+FX66 -> 523 | FY10: =FY21+FY30+FY48+FY39+FY57+FY66 -> 414 | ... GP10: =GP21+GP30+GP48+GP39+GP57+GP66 -> 0
A11: =D5 -> 39572.03 | C11: 点击单价 | D11: =D3/D10 -> #REF! | E11: =E3/E10 -> #REF! | F11: =F3/F10 -> #REF! | G11: =G3/G10 -> #REF! | H11: =H3/H10 -> #REF! | I11: =I3/I10 -> #REF! | J11: =J3/J10 -> #REF! | K11: =K3/K10 -> #REF! | ... GP11: =GP3/GP10 -> #DIV/0!
C12: 总购物车数 | D12: =SUM(E12:P12) -> #REF! | E12: =E22+E31+E40+E49+E58+E67 -> #REF! | F12: =F22+F31+F40+F49+F58+F67 -> #REF! | G12: =G22+G31+G40+G49+G58+G67 -> #REF! | H12: =H22+H31+H40+H49+H58+H67 -> #REF! | I12: =I22+I31+I40+I49+I58+I67 -> #REF! | J12: =J22+J31+J40+J49+J58+J67 -> #REF! | K12: =K22+K31+K40+K49+K58+K67 -> #REF! | L12: =L22+L31+L40+L49+L58+L67 -> #REF! | ... P12: =P22+P31+P40+P49+P58+P67 -> #REF! | Q12: =SUM(R12:AV12) -> 573 | R12: =R22+R31+R40+R49+R58+R67 -> 11 | S12: =S22+S31+S40+S49+S58+S67 -> 17 | T12: =T22+T31+T40+T49+T58+T67 -> 11 | U12: =U22+U31+U40+U49+U58+U67 -> 17 | V12: =V22+V31+V40+V49+V58+V67 -> 17 | W12: =W22+W31+W40+W49+W58+W67 -> 17 | X12: =X22+X31+X40+X49+X58+X67 -> 18 | Y12: =Y22+Y31+Y40+Y49+Y58+Y67 -> 20 | ... AV12: =AV22+AV31+AV40+AV49+AV58+AV67 -> 24 | AW12: =SUM(AX12:BY12) -> 518 | AX12: =AX22+AX31+AX40+AX49+AX58+AX67 -> 37 | AY12: =AY22+AY31+AY40+AY49+AY58+AY67 -> 17 | AZ12: =AZ22+AZ31+AZ40+AZ49+AZ58+AZ67 -> 23 | BA12: =BA22+BA31+BA40+BA49+BA58+BA67 -> 12 | BB12: =BB22+BB31+BB40+BB49+BB58+BB67 -> 19 | BC12: =BC22+BC31+BC40+BC49+BC58+BC67 -> 51 | BD12: =BD22+BD31+BD40+BD49+BD58+BD67 -> 25 | BE12: =BE22+BE31+BE40+BE49+BE58+BE67 -> 36 | ... BY12: =BY22+BY31+BY40+BY49+BY58+BY67 -> 15 | BZ12: =SUM(CA12:DE12) -> 938 | CA12: =CA22+CA31+CA40+CA49+CA58+CA67 -> 22 | CB12: =CB22+CB31+CB40+CB49+CB58+CB67 -> 17 | CC12: =CC22+CC31+CC40+CC49+CC58+CC67 -> 28 | CD12: =CD22+CD31+CD40+CD49+CD58+CD67 -> 25 | CE12: =CE22+CE31+CE40+CE49+CE58+CE67 -> 23 | CF12: =CF22+CF31+CF40+CF49+CF58+CF67 -> 11 | CG12: =CG22+CG31+CG40+CG49+CG58+CG67 -> 27 | CH12: =CH22+CH31+CH40+CH49+CH58+CH67 -> 69 | ... DE12: =DE22+DE31+DE40+DE49+DE58+DE67 -> 14 | DF12: =SUM(DG12:EJ12) -> 522 | DG12: =DG22+DG31+DG40+DG49+DG58+DG67 -> 10 | DH12: =DH22+DH31+DH40+DH49+DH58+DH67 -> 12 | DI12: =DI22+DI31+DI40+DI49+DI58+DI67 -> 10 | DJ12: =DJ22+DJ31+DJ40+DJ49+DJ58+DJ67 -> 9 | DK12: =DK22+DK31+DK40+DK49+DK58+DK67 -> 16 | DL12: =DL22+DL31+DL40+DL49+DL58+DL67 -> 15 | DM12: =DM22+DM31+DM40+DM49+DM58+DM67 -> 16 | DN12: =DN22+DN31+DN40+DN49+DN58+DN67 -> 23 | ... EJ12: =EJ22+EJ31+EJ40+EJ49+EJ58+EJ67 -> 15 | EK12: =SUM(EL12:FP12) -> 627 | EL12: =EL22+EL31+EL40+EL49+EL58+EL67 -> 18 | EM12: =EM22+EM31+EM40+EM49+EM58+EM67 -> 9 | EN12: =EN22+EN31+EN40+EN49+EN58+EN67 -> 13 | EO12: =EO22+EO31+EO40+EO49+EO58+EO67 -> 15 | EP12: =EP22+EP31+EP40+EP49+EP58+EP67 -> 35 | EQ12: =EQ22+EQ31+EQ40+EQ49+EQ58+EQ67 -> 19 | ER12: =ER22+ER31+ER40+ER49+ER58+ER67 -> 28 | ES12: =ES22+ES31+ES40+ES49+ES58+ES67 -> 15 | ... FP12: =FP22+FP31+FP40+FP49+FP58+FP67 -> 23 | FQ12: =SUM(FR12:GX12) -> 428 | FR12: =FR22+FR31+FR40+FR49+FR58+FR67 -> 12 | FS12: =FS22+FS31+FS40+FS49+FS58+FS67 -> 12 | FT12: =FT22+FT31+FT40+FT49+FT58+FT67 -> 20 | FU12: =FU22+FU31+FU40+FU49+FU58+FU67 -> 15 | FV12: =FV22+FV31+FV40+FV49+FV58+FV67 -> 15 | FW12: =FW22+FW31+FW40+FW49+FW58+FW67 -> 20 | FX12: =FX22+FX31+FX40+FX49+FX58+FX67 -> 32 | FY12: =FY22+FY31+FY40+FY49+FY58+FY67 -> 23 | ... GP12: =GP22+GP31+GP40+GP49+GP58+GP67 -> 0
C13: 加购成本 | D13: =D3/D12 -> #REF! | E13: =E3/E12 -> #REF! | F13: =F3/F12 -> #REF! | G13: =G3/G12 -> #REF! | H13: =H3/H12 -> #REF! | I13: =I3/I12 -> #REF! | J13: =J3/J12 -> #REF! | K13: =K3/K12 -> #REF! | ... GP13: =GP3/GP12 -> #DIV/0!
C14: 总成交量 | D14: =SUM(E14:P14) -> #REF! | E14: =E23+E32+E41+E50+E59+E68 -> #REF! | F14: =F23+F32+F41+F50+F59+F68 -> #REF! | G14: =G23+G32+G41+G50+G59+G68 -> #REF! | H14: =H23+H32+H41+H50+H59+H68 -> #REF! | I14: =I23+I32+I41+I50+I59+I68 -> #REF! | J14: =J23+J32+J41+J50+J59+J68 -> #REF! | K14: =K23+K32+K41+K50+K59+K68 -> #REF! | L14: =L23+L32+L41+L50+L59+L68 -> #REF! | ... P14: =P23+P32+P41+P50+P59+P68 -> #REF! | Q14: =SUM(R14:AV14) -> 123 | R14: =R23+R32+R41+R50+R59+R68 -> 2 | S14: =S23+S32+S41+S50+S59+S68 -> 3 | T14: =T23+T32+T41+T50+T59+T68 -> 2 | U14: =U23+U32+U41+U50+U59+U68 -> 10 | V14: =V23+V32+V41+V50+V59+V68 -> 2 | W14: =W23+W32+W41+W50+W59+W68 -> 3 | X14: =X23+X32+X41+X50+X59+X68 -> 2 | Y14: =Y23+Y32+Y41+Y50+Y59+Y68 -> 3 | ... AV14: =AV23+AV32+AV41+AV50+AV59+AV68 -> 5 | AW14: =SUM(AX14:BY14) -> 98 | AX14: =AX23+AX32+AX41+AX50+AX59+AX68 -> 7 | AY14: =AY23+AY32+AY41+AY50+AY59+AY68 -> 4 | AZ14: =AZ23+AZ32+AZ41+AZ50+AZ59+AZ68 -> 4 | BA14: =BA23+BA32+BA41+BA50+BA59+BA68 -> 8 | BB14: =BB23+BB32+BB41+BB50+BB59+BB68 -> 8 | BC14: =BC23+BC32+BC41+BC50+BC59+BC68 -> 16 | BD14: =BD23+BD32+BD41+BD50+BD59+BD68 -> 9 | BE14: =BE23+BE32+BE41+BE50+BE59+BE68 -> 5 | ... BY14: =BY23+BY32+BY41+BY50+BY59+BY68 -> 1 | BZ14: =SUM(CA14:DE14) -> 165 | CA14: =CA23+CA32+CA41+CA50+CA59+CA68 -> 4 | CB14: =CB23+CB32+CB41+CB50+CB59+CB68 -> 1 | CC14: =CC23+CC32+CC41+CC50+CC59+CC68 -> 4 | CD14: =CD23+CD32+CD41+CD50+CD59+CD68 -> 6 | CE14: =CE23+CE32+CE41+CE50+CE59+CE68 -> 4 | CF14: =CF23+CF32+CF41+CF50+CF59+CF68 -> 2 | CG14: =CG23+CG32+CG41+CG50+CG59+CG68 -> 3 | CH14: =CH23+CH32+CH41+CH50+CH59+CH68 -> 8 | ... DE14: =DE23+DE32+DE41+DE50+DE59+DE68 -> 5 | DF14: =SUM(DG14:EJ14) -> 137 | DG14: =DG23+DG32+DG41+DG50+DG59+DG68 -> 4 | DH14: =DH23+DH32+DH41+DH50+DH59+DH68 -> 3 | DI14: =DI23+DI32+DI41+DI50+DI59+DI68 -> 4 | DJ14: =DJ23+DJ32+DJ41+DJ50+DJ59+DJ68 -> 1 | DK14: =DK23+DK32+DK41+DK50+DK59+DK68 -> 6 | DL14: =DL23+DL32+DL41+DL50+DL59+DL68 -> 2 | DM14: =DM23+DM32+DM41+DM50+DM59+DM68 -> 7 | DN14: =DN23+DN32+DN41+DN50+DN59+DN68 -> 4 | ... EJ14: =EJ23+EJ32+EJ41+EJ50+EJ59+EJ68 -> 1 | EK14: =SUM(EL14:FP14) -> 128 | EL14: =EL23+EL32+EL41+EL50+EL59+EL68 -> 3 | EM14: =EM23+EM32+EM41+EM50+EM59+EM68 -> 1 | EN14: =EN23+EN32+EN41+EN50+EN59+EN68 -> 2 | EO14: =EO23+EO32+EO41+EO50+EO59+EO68 -> 0 | EP14: =EP23+EP32+EP41+EP50+EP59+EP68 -> 20 | EQ14: =EQ23+EQ32+EQ41+EQ50+EQ59+EQ68 -> 4 | ER14: =ER23+ER32+ER41+ER50+ER59+ER68 -> 2 | ES14: =ES23+ES32+ES41+ES50+ES59+ES68 -> 1 | ... FP14: =FP23+FP32+FP41+FP50+FP59+FP68 -> 1 | FQ14: =SUM(FR14:GX14) -> 105 | FR14: =FR23+FR32+FR41+FR50+FR59+FR68 -> 3 | FS14: =FS23+FS32+FS41+FS50+FS59+FS68 -> 5 | FT14: =FT23+FT32+FT41+FT50+FT59+FT68 -> 8 | FU14: =FU23+FU32+FU41+FU50+FU59+FU68 -> 6 | FV14: =FV23+FV32+FV41+FV50+FV59+FV68 -> 10 | FW14: =FW23+FW32+FW41+FW50+FW59+FW68 -> 7 | FX14: =FX23+FX32+FX41+FX50+FX59+FX68 -> 8 | FY14: =FY23+FY32+FY41+FY50+FY59+FY68 -> 7 | ... GP14: =GP23+GP32+GP41+GP50+GP59+GP68 -> 0
C15: 总成交金额 | D15: =SUM(E15:P15) -> #REF! | E15: =E24+E33+E42+E51+E60+E69 -> #REF! | F15: =F24+F33+F42+F51+F60+F69 -> #REF! | G15: =G24+G33+G42+G51+G60+G69 -> #REF! | H15: =H24+H33+H42+H51+H60+H69 -> #REF! | I15: =I24+I33+I42+I51+I60+I69 -> #REF! | J15: =J24+J33+J42+J51+J60+J69 -> #REF! | K15: =K24+K33+K42+K51+K60+K69 -> #REF! | L15: =L24+L33+L42+L51+L60+L69 -> #REF! | ... P15: =P24+P33+P42+P51+P60+P69 -> #REF! | Q15: =SUM(R15:AV15) -> 200211.68 | R15: =R24+R33+R42+R51+R60+R69 -> 617.1 | S15: =S24+S33+S42+S51+S60+S69 -> 401.91 | T15: =T24+T33+T42+T51+T60+T69 -> 96.9 | U15: =U24+U33+U42+U51+U60+U69 -> 6951.49 | V15: =V24+V33+V42+V51+V60+V69 -> 1793.4 | W15: =W24+W33+W42+W51+W60+W69 -> 1128 | X15: =X24+X33+X42+X51+X60+X69 -> 122.56 | Y15: =Y24+Y33+Y42+Y51+Y60+Y69 -> 2407.44 | ... AV15: =AV24+AV33+AV42+AV51+AV60+AV69 -> 1870.48 | AW15: =SUM(AX15:BY15) -> 39122.11 | AX15: =AX24+AX33+AX42+AX51+AX60+AX69 -> 8390.74 | AY15: =AY24+AY33+AY42+AY51+AY60+AY69 -> 2790.18 | AZ15: =AZ24+AZ33+AZ42+AZ51+AZ60+AZ69 -> 427.16 | BA15: =BA24+BA33+BA42+BA51+BA60+BA69 -> 5809.76 | BB15: =BB24+BB33+BB42+BB51+BB60+BB69 -> 3601.82 | BC15: =BC24+BC33+BC42+BC51+BC60+BC69 -> 2667.24 | BD15: =BD24+BD33+BD42+BD51+BD60+BD69 -> 1270.24 | BE15: =BE24+BE33+BE42+BE51+BE60+BE69 -> 826.81 | ... BY15: =BY24+BY33+BY42+BY51+BY60+BY69 -> 176 | BZ15: =SUM(CA15:DE15) -> 32451.21 | CA15: =CA24+CA33+CA42+CA51+CA60+CA69 -> 567.87 | CB15: =CB24+CB33+CB42+CB51+CB60+CB69 -> 236 | CC15: =CC24+CC33+CC42+CC51+CC60+CC69 -> 426.28 | CD15: =CD24+CD33+CD42+CD51+CD60+CD69 -> 3328.08 | CE15: =CE24+CE33+CE42+CE51+CE60+CE69 -> 1610.9 | CF15: =CF24+CF33+CF42+CF51+CF60+CF69 -> 1046.82 | CG15: =CG24+CG33+CG42+CG51+CG60+CG69 -> 320.4 | CH15: =CH24+CH33+CH42+CH51+CH60+CH69 -> 1211.17 | ... DE15: =DE24+DE33+DE42+DE51+DE60+DE69 -> 293.11 | DF15: =SUM(DG15:EJ15) -> 29052.16 | DG15: =DG24+DG33+DG42+DG51+DG60+DG69 -> 272.22 | DH15: =DH24+DH33+DH42+DH51+DH60+DH69 -> 333.54 | DI15: =DI24+DI33+DI42+DI51+DI60+DI69 -> 440.52 | DJ15: =DJ24+DJ33+DJ42+DJ51+DJ60+DJ69 -> 84.15 | DK15: =DK24+DK33+DK42+DK51+DK60+DK69 -> 1162.18 | DL15: =DL24+DL33+DL42+DL51+DL60+DL69 -> 194.9 | DM15: =DM24+DM33+DM42+DM51+DM60+DM69 -> 2210.48 | DN15: =DN24+DN33+DN42+DN51+DN60+DN69 -> 2936.93 | ... EJ15: =EJ24+EJ33+EJ42+EJ51+EJ60+EJ69 -> 85.12 | EK15: =SUM(EL15:FP15) -> 42473.03 | EL15: =EL24+EL33+EL42+EL51+EL60+EL69 -> 259.25 | EM15: =EM24+EM33+EM42+EM51+EM60+EM69 -> 151 | EN15: =EN24+EN33+EN42+EN51+EN60+EN69 -> 125.1 | EO15: =EO24+EO33+EO42+EO51+EO60+EO69 -> 0 | EP15: =EP24+EP33+EP42+EP51+EP60+EP69 -> 4676.39 | EQ15: =EQ24+EQ33+EQ42+EQ51+EQ60+EQ69 -> 1121.56 | ER15: =ER24+ER33+ER42+ER51+ER60+ER69 -> 8156.9 | ES15: =ES24+ES33+ES42+ES51+ES60+ES69 -> 81.13 | ... FP15: =FP24+FP33+FP42+FP51+FP60+FP69 -> 42.4 | FQ15: =SUM(FR15:GX15) -> 33318.12 | FR15: =FR24+FR33+FR42+FR51+FR60+FR69 -> 155.66 | FS15: =FS24+FS33+FS42+FS51+FS60+FS69 -> 389.31 | FT15: =FT24+FT33+FT42+FT51+FT60+FT69 -> 1615.04 | FU15: =FU24+FU33+FU42+FU51+FU60+FU69 -> 726.77 | FV15: =FV24+FV33+FV42+FV51+FV60+FV69 -> 18001.69 | FW15: =FW24+FW33+FW42+FW51+FW60+FW69 -> 424.26 | FX15: =FX24+FX33+FX42+FX51+FX60+FX69 -> 884.58 | FY15: =FY24+FY33+FY42+FY51+FY60+FY69 -> 841.6 | ... GP15: =GP24+GP33+GP42+GP51+GP60+GP69 -> 0
C16: 推广成交占比 | Q16: =Q15/Q5 -> 3.5462352 | R16: =R15/R5 -> 0.34342479 | S16: =S15/S5 -> 0.086849885 | T16: =T15/T5 -> 1.1936438 | U16: =U15/U5 -> 2.1933903 | V16: =V15/V5 -> 0.45585566 | W16: =W15/W5 -> 1.0792812 | X16: =X15/X5 -> 1.4116563 | ... GP16: =GP15/GP5 -> 0
C17: 加购率 | D17: =D12/D10 -> #REF! | E17: =E12/E10 -> #REF! | F17: =F12/F10 -> #REF! | G17: =G12/G10 -> #REF! | H17: =H12/H10 -> #REF! | I17: =I12/I10 -> #REF! | J17: =J12/J10 -> #REF! | K17: =K12/K10 -> #REF! | ... GP17: =GP12/GP10 -> #DIV/0!
C18: 点击转化率 | D18: =D14/D10 -> #REF! | Q18: =Q14/Q10 -> 0.019948102 | R18: =R14/R10 -> 0.013986014 | S18: =S14/S10 -> 0.015957447 | T18: =T14/T10 -> 0.0099502488 | U18: =U14/U10 -> 0.037878788 | V18: =V14/V10 -> 0.0081967213 | W18: =W14/W10 -> 0.015306122 | X18: =X14/X10 -> 0.0084033613 | ... GP18: =GP14/GP10 -> #DIV/0!
C19: 加购转化率 | D19: =D14/D12 -> #REF! | Q19: =Q14/Q12 -> 0.21465969 | R19: =R14/R12 -> 0.18181818 | S19: =S14/S12 -> 0.17647059 | T19: =T14/T12 -> 0.18181818 | U19: =U14/U12 -> 0.58823529 | V19: =V14/V12 -> 0.11764706 | W19: =W14/W12 -> 0.17647059 | X19: =X14/X12 -> 0.11111111 | ... GP19: =GP14/GP12 -> #DIV/0!
A20: 目标费率 | B20: 关键词推广 | C20: 花费 | D20: =SUM(E20:P20) -> #REF! | E20: =#REF! -> #REF! | F20: =#REF! -> #REF! | G20: =#REF! -> #REF! | H20: =#REF! -> #REF! | I20: =#REF! -> #REF! | J20: =#REF! -> #REF! | K20: =#REF! -> #REF! | L20: =#REF! -> #REF! | ... P20: =#REF! -> #REF! | Q20: =SUM(R20:AV20) -> 264.98 | R20: =SUMIFS(营销场景数据源!$H:$H,营销场景数据源!$C:$C,$B$20,营销场景数据源!$A:$A,R2) -> 0 | S20: =SUMIFS(营销场景数据源!$H:$H,营销场景数据源!$C:$C,$B$20,营销场景数据源!$A:$A,S2) -> 0 | T20: =SUMIFS(营销场景数据源!$H:$H,营销场景数据源!$C:$C,$B$20,营销场景数据源!$A:$A,T2) -> 0 | U20: =SUMIFS(营销场景数据源!$H:$H,营销场景数据源!$C:$C,$B$20,营销场景数据源!$A:$A,U2) -> 0 | V20: =SUMIFS(营销场景数据源!$H:$H,营销场景数据源!$C:$C,$B$20,营销场景数据源!$A:$A,V2) -> 0 | W20: =SUMIFS(营销场景数据源!$H:$H,营销场景数据源!$C:$C,$B$20,营销场景数据源!$A:$A,W2) -> 0 | X20: =SUMIFS(营销场景数据源!$H:$H,营销场景数据源!$C:$C,$B$20,营销场景数据源!$A:$A,X2) -> 0 | Y20: =SUMIFS(营销场景数据源!$H:$H,营销场景数据源!$C:$C,$B$20,营销场景数据源!$A:$A,Y2) -> 0 | ... AV20: =SUMIFS(营销场景数据源!$H:$H,营销场景数据源!$C:$C,$B$20,营销场景数据源!$A:$A,AV2) -> 12.05 | AW20: =SUM(AX20:BY20) -> 904.05 | AX20: =SUMIFS(营销场景数据源!$H:$H,营销场景数据源!$C:$C,$B$20,营销场景数据源!$A:$A,AX2) -> 19.92 | AY20: =SUMIFS(营销场景数据源!$H:$H,营销场景数据源!$C:$C,$B$20,营销场景数据源!$A:$A,AY2) -> 24.1 | AZ20: =SUMIFS(营销场景数据源!$H:$H,营销场景数据源!$C:$C,$B$20,营销场景数据源!$A:$A,AZ2) -> 31.76 | BA20: =SUMIFS(营销场景数据源!$H:$H,营销场景数据源!$C:$C,$B$20,营销场景数据源!$A:$A,BA2) -> 31.99 | BB20: =SUMIFS(营销场景数据源!$H:$H,营销场景数据源!$C:$C,$B$20,营销场景数据源!$A:$A,BB2) -> 29.14 | BC20: =SUMIFS(营销场景数据源!$H:$H,营销场景数据源!$C:$C,$B$20,营销场景数据源!$A:$A,BC2) -> 32.41 | BD20: =SUMIFS(营销场景数据源!$H:$H,营销场景数据源!$C:$C,$B$20,营销场景数据源!$A:$A,BD2) -> 25.39 | BE20: =SUMIFS(营销场景数据源!$H:$H,营销场景数据源!$C:$C,$B$20,营销场景数据源!$A:$A,BE2) -> 33.67 | ... BY20: =SUMIFS(营销场景数据源!$H:$H,营销场景数据源!$C:$C,$B$20,营销场景数据源!$A:$A,BY2) -> 32 | BZ20: =SUM(CA20:DE20) -> 1236.75 | CA20: =SUMIFS(营销场景数据源!$H:$H,营销场景数据源!$C:$C,$B$20,营销场景数据源!$A:$A,CA2) -> 32.18 | CB20: =SUMIFS(营销场景数据源!$H:$H,营销场景数据源!$C:$C,$B$20,营销场景数据源!$A:$A,CB2) -> 32.77 | CC20: =SUMIFS(营销场景数据源!$H:$H,营销场景数据源!$C:$C,$B$20,营销场景数据源!$A:$A,CC2) -> 26.16 | CD20: =SUMIFS(营销场景数据源!$H:$H,营销场景数据源!$C:$C,$B$20,营销场景数据源!$A:$A,CD2) -> 20.34 | CE20: =SUMIFS(营销场景数据源!$H:$H,营销场景数据源!$C:$C,$B$20,营销场景数据源!$A:$A,CE2) -> 50.75 | CF20: =SUMIFS(营销场景数据源!$H:$H,营销场景数据源!$C:$C,$B$20,营销场景数据源!$A:$A,CF2) -> 29.88 | CG20: =SUMIFS(营销场景数据源!$H:$H,营销场景数据源!$C:$C,$B$20,营销场景数据源!$A:$A,CG2) -> 30.01 | CH20: =SUMIFS(营销场景数据源!$H:$H,营销场景数据源!$C:$C,$B$20,营销场景数据源!$A:$A,CH2) -> 34.45 | ... DE20: =SUMIFS(营销场景数据源!$H:$H,营销场景数据源!$C:$C,$B$20,营销场景数据源!$A:$A,DE2) -> 58.54 | DF20: =SUM(DG20:EJ20) -> 1684.53 | DG20: =SUMIFS(营销场景数据源!$H:$H,营销场景数据源!$C:$C,$B$20,营销场景数据源!$A:$A,DG2) -> 59.72 | DH20: =SUMIFS(营销场景数据源!$H:$H,营销场景数据源!$C:$C,$B$20,营销场景数据源!$A:$A,DH2) -> 52.36 | DI20: =SUMIFS(营销场景数据源!$H:$H,营销场景数据源!$C:$C,$B$20,营销场景数据源!$A:$A,DI2) -> 59.53 | DJ20: =SUMIFS(营销场景数据源!$H:$H,营销场景数据源!$C:$C,$B$20,营销场景数据源!$A:$A,DJ2) -> 59.41 | DK20: =SUMIFS(营销场景数据源!$H:$H,营销场景数据源!$C:$C,$B$20,营销场景数据源!$A:$A,DK2) -> 59.33 | DL20: =SUMIFS(营销场景数据源!$H:$H,营销场景数据源!$C:$C,$B$20,营销场景数据源!$A:$A,DL2) -> 58.25 | DM20: =SUMIFS(营销场景数据源!$H:$H,营销场景数据源!$C:$C,$B$20,营销场景数据源!$A:$A,DM2) -> 58.46 | DN20: =SUMIFS(营销场景数据源!$H:$H,营销场景数据源!$C:$C,$B$20,营销场景数据源!$A:$A,DN2) -> 57.17 | ... EJ20: =SUMIFS(营销场景数据源!$H:$H,营销场景数据源!$C:$C,$B$20,营销场景数据源!$A:$A,EJ2) -> 21.1 | EK20: =SUM(EL20:FP20) -> 2319.42 | EL20: =SUMIFS(营销场景数据源!$H:$H,营销场景数据源!$C:$C,$B$20,营销场景数据源!$A:$A,EL2) -> 12.04 | EM20: =SUMIFS(营销场景数据源!$H:$H,营销场景数据源!$C:$C,$B$20,营销场景数据源!$A:$A,EM2) -> 11.76 | EN20: =SUMIFS(营销场景数据源!$H:$H,营销场景数据源!$C:$C,$B$20,营销场景数据源!$A:$A,EN2) -> 12.37 | EO20: =SUMIFS(营销场景数据源!$H:$H,营销场景数据源!$C:$C,$B$20,营销场景数据源!$A:$A,EO2) -> 12.16 | EP20: =SUMIFS(营销场景数据源!$H:$H,营销场景数据源!$C:$C,$B$20,营销场景数据源!$A:$A,EP2) -> 10.14 | EQ20: =SUMIFS(营销场景数据源!$H:$H,营销场景数据源!$C:$C,$B$20,营销场景数据源!$A:$A,EQ2) -> 20.71 | ER20: =SUMIFS(营销场景数据源!$H:$H,营销场景数据源!$C:$C,$B$20,营销场景数据源!$A:$A,ER2) -> 21.81 | ES20: =SUMIFS(营销场景数据源!$H:$H,营销场景数据源!$C:$C,$B$20,营销场景数据源!$A:$A,ES2) -> 19.64 | ... FP20: =SUMIFS(营销场景数据源!$H:$H,营销场景数据源!$C:$C,$B$20,营销场景数据源!$A:$A,FP2) -> 112.12 | FQ20: =SUM(FR20:GX20) -> 2486.34 | FR20: =SUMIFS(营销场景数据源!$H:$H,营销场景数据源!$C:$C,$B$20,营销场景数据源!$A:$A,FR2) -> 91.6 | FS20: =SUMIFS(营销场景数据源!$H:$H,营销场景数据源!$C:$C,$B$20,营销场景数据源!$A:$A,FS2) -> 85.51 | FT20: =SUMIFS(营销场景数据源!$H:$H,营销场景数据源!$C:$C,$B$20,营销场景数据源!$A:$A,FT2) -> 67.72 | FU20: =SUMIFS(营销场景数据源!$H:$H,营销场景数据源!$C:$C,$B$20,营销场景数据源!$A:$A,FU2) -> 111.06 | FV20: =SUMIFS(营销场景数据源!$H:$H,营销场景数据源!$C:$C,$B$20,营销场景数据源!$A:$A,FV2) -> 108.79 | FW20: =SUMIFS(营销场景数据源!$H:$H,营销场景数据源!$C:$C,$B$20,营销场景数据源!$A:$A,FW2) -> 105.42 | FX20: =SUMIFS(营销场景数据源!$H:$H,营销场景数据源!$C:$C,$B$20,营销场景数据源!$A:$A,FX2) -> 113.8 | FY20: =SUMIFS(营销场景数据源!$H:$H,营销场景数据源!$C:$C,$B$20,营销场景数据源!$A:$A,FY2) -> 137.03 | ... GP20: =SUMIFS(营销场景数据源!$H:$H,营销场景数据源!$C:$C,$B$20,营销场景数据源!$A:$A,GP2) -> 0
C21: 点击量 | D21: =SUM(E21:P21) -> #REF! | E21: =#REF! -> #REF! | F21: =#REF! -> #REF! | G21: =#REF! -> #REF! | H21: =#REF! -> #REF! | I21: =#REF! -> #REF! | J21: =#REF! -> #REF! | K21: =#REF! -> #REF! | L21: =#REF! -> #REF! | ... P21: =#REF! -> #REF! | Q21: =SUM(R21:AV21) -> 377 | R21: =SUMIFS(营销场景数据源!$G:$G,营销场景数据源!$C:$C,$B$20,营销场景数据源!$A:$A,R2) -> 0 | S21: =SUMIFS(营销场景数据源!$G:$G,营销场景数据源!$C:$C,$B$20,营销场景数据源!$A:$A,S2) -> 0 | T21: =SUMIFS(营销场景数据源!$G:$G,营销场景数据源!$C:$C,$B$20,营销场景数据源!$A:$A,T2) -> 0 | U21: =SUMIFS(营销场景数据源!$G:$G,营销场景数据源!$C:$C,$B$20,营销场景数据源!$A:$A,U2) -> 0 | V21: =SUMIFS(营销场景数据源!$G:$G,营销场景数据源!$C:$C,$B$20,营销场景数据源!$A:$A,V2) -> 0 | W21: =SUMIFS(营销场景数据源!$G:$G,营销场景数据源!$C:$C,$B$20,营销场景数据源!$A:$A,W2) -> 0 | X21: =SUMIFS(营销场景数据源!$G:$G,营销场景数据源!$C:$C,$B$20,营销场景数据源!$A:$A,X2) -> 0 | Y21: =SUMIFS(营销场景数据源!$G:$G,营销场景数据源!$C:$C,$B$20,营销场景数据源!$A:$A,Y2) -> 0 | ... AV21: =SUMIFS(营销场景数据源!$G:$G,营销场景数据源!$C:$C,$B$20,营销场景数据源!$A:$A,AV2) -> 44 | AW21: =SUM(AX21:BY21) -> 3059 | AX21: =SUMIFS(营销场景数据源!$G:$G,营销场景数据源!$C:$C,$B$20,营销场景数据源!$A:$A,AX2) -> 70 | AY21: =SUMIFS(营销场景数据源!$G:$G,营销场景数据源!$C:$C,$B$20,营销场景数据源!$A:$A,AY2) -> 83 | AZ21: =SUMIFS(营销场景数据源!$G:$G,营销场景数据源!$C:$C,$B$20,营销场景数据源!$A:$A,AZ2) -> 91 | BA21: =SUMIFS(营销场景数据源!$G:$G,营销场景数据源!$C:$C,$B$20,营销场景数据源!$A:$A,BA2) -> 95 | BB21: =SUMIFS(营销场景数据源!$G:$G,营销场景数据源!$C:$C,$B$20,营销场景数据源!$A:$A,BB2) -> 93 | BC21: =SUMIFS(营销场景数据源!$G:$G,营销场景数据源!$C:$C,$B$20,营销场景数据源!$A:$A,BC2) -> 100 | BD21: =SUMIFS(营销场景数据源!$G:$G,营销场景数据源!$C:$C,$B$20,营销场景数据源!$A:$A,BD2) -> 82 | BE21: =SUMIFS(营销场景数据源!$G:$G,营销场景数据源!$C:$C,$B$20,营销场景数据源!$A:$A,BE2) -> 107 | ... BY21: =SUMIFS(营销场景数据源!$G:$G,营销场景数据源!$C:$C,$B$20,营销场景数据源!$A:$A,BY2) -> 124 | BZ21: =SUM(CA21:DE21) -> 4069 | CA21: =SUMIFS(营销场景数据源!$G:$G,营销场景数据源!$C:$C,$B$20,营销场景数据源!$A:$A,CA2) -> 127 | CB21: =SUMIFS(营销场景数据源!$G:$G,营销场景数据源!$C:$C,$B$20,营销场景数据源!$A:$A,CB2) -> 123 | CC21: =SUMIFS(营销场景数据源!$G:$G,营销场景数据源!$C:$C,$B$20,营销场景数据源!$A:$A,CC2) -> 106 | CD21: =SUMIFS(营销场景数据源!$G:$G,营销场景数据源!$C:$C,$B$20,营销场景数据源!$A:$A,CD2) -> 84 | CE21: =SUMIFS(营销场景数据源!$G:$G,营销场景数据源!$C:$C,$B$20,营销场景数据源!$A:$A,CE2) -> 154 | CF21: =SUMIFS(营销场景数据源!$G:$G,营销场景数据源!$C:$C,$B$20,营销场景数据源!$A:$A,CF2) -> 98 | CG21: =SUMIFS(营销场景数据源!$G:$G,营销场景数据源!$C:$C,$B$20,营销场景数据源!$A:$A,CG2) -> 104 | CH21: =SUMIFS(营销场景数据源!$G:$G,营销场景数据源!$C:$C,$B$20,营销场景数据源!$A:$A,CH2) -> 119 | ... DE21: =SUMIFS(营销场景数据源!$G:$G,营销场景数据源!$C:$C,$B$20,营销场景数据源!$A:$A,DE2) -> 199 | DF21: =SUM(DG21:EJ21) -> 4853 | DG21: =SUMIFS(营销场景数据源!$G:$G,营销场景数据源!$C:$C,$B$20,营销场景数据源!$A:$A,DG2) -> 237 | DH21: =SUMIFS(营销场景数据源!$G:$G,营销场景数据源!$C:$C,$B$20,营销场景数据源!$A:$A,DH2) -> 215 | DI21: =SUMIFS(营销场景数据源!$G:$G,营销场景数据源!$C:$C,$B$20,营销场景数据源!$A:$A,DI2) -> 222 | DJ21: =SUMIFS(营销场景数据源!$G:$G,营销场景数据源!$C:$C,$B$20,营销场景数据源!$A:$A,DJ2) -> 208 | DK21: =SUMIFS(营销场景数据源!$G:$G,营销场景数据源!$C:$C,$B$20,营销场景数据源!$A:$A,DK2) -> 183 | DL21: =SUMIFS(营销场景数据源!$G:$G,营销场景数据源!$C:$C,$B$20,营销场景数据源!$A:$A,DL2) -> 174 | DM21: =SUMIFS(营销场景数据源!$G:$G,营销场景数据源!$C:$C,$B$20,营销场景数据源!$A:$A,DM2) -> 171 | DN21: =SUMIFS(营销场景数据源!$G:$G,营销场景数据源!$C:$C,$B$20,营销场景数据源!$A:$A,DN2) -> 181 | ... EJ21: =SUMIFS(营销场景数据源!$G:$G,营销场景数据源!$C:$C,$B$20,营销场景数据源!$A:$A,EJ2) -> 71 | EK21: =SUM(EL21:FP21) -> 4180 | EL21: =SUMIFS(营销场景数据源!$G:$G,营销场景数据源!$C:$C,$B$20,营销场景数据源!$A:$A,EL2) -> 38 | EM21: =SUMIFS(营销场景数据源!$G:$G,营销场景数据源!$C:$C,$B$20,营销场景数据源!$A:$A,EM2) -> 35 | EN21: =SUMIFS(营销场景数据源!$G:$G,营销场景数据源!$C:$C,$B$20,营销场景数据源!$A:$A,EN2) -> 32 | EO21: =SUMIFS(营销场景数据源!$G:$G,营销场景数据源!$C:$C,$B$20,营销场景数据源!$A:$A,EO2) -> 33 | EP21: =SUMIFS(营销场景数据源!$G:$G,营销场景数据源!$C:$C,$B$20,营销场景数据源!$A:$A,EP2) -> 31 | EQ21: =SUMIFS(营销场景数据源!$G:$G,营销场景数据源!$C:$C,$B$20,营销场景数据源!$A:$A,EQ2) -> 48 | ER21: =SUMIFS(营销场景数据源!$G:$G,营销场景数据源!$C:$C,$B$20,营销场景数据源!$A:$A,ER2) -> 53 | ES21: =SUMIFS(营销场景数据源!$G:$G,营销场景数据源!$C:$C,$B$20,营销场景数据源!$A:$A,ES2) -> 39 | ... FP21: =SUMIFS(营销场景数据源!$G:$G,营销场景数据源!$C:$C,$B$20,营销场景数据源!$A:$A,FP2) -> 258 | FQ21: =SUM(FR21:GX21) -> 3583 | FR21: =SUMIFS(营销场景数据源!$G:$G,营销场景数据源!$C:$C,$B$20,营销场景数据源!$A:$A,FR2) -> 163 | FS21: =SUMIFS(营销场景数据源!$G:$G,营销场景数据源!$C:$C,$B$20,营销场景数据源!$A:$A,FS2) -> 134 | FT21: =SUMIFS(营销场景数据源!$G:$G,营销场景数据源!$C:$C,$B$20,营销场景数据源!$A:$A,FT2) -> 102 | FU21: =SUMIFS(营销场景数据源!$G:$G,营销场景数据源!$C:$C,$B$20,营销场景数据源!$A:$A,FU2) -> 191 | FV21: =SUMIFS(营销场景数据源!$G:$G,营销场景数据源!$C:$C,$B$20,营销场景数据源!$A:$A,FV2) -> 176 | FW21: =SUMIFS(营销场景数据源!$G:$G,营销场景数据源!$C:$C,$B$20,营销场景数据源!$A:$A,FW2) -> 160 | FX21: =SUMIFS(营销场景数据源!$G:$G,营销场景数据源!$C:$C,$B$20,营销场景数据源!$A:$A,FX2) -> 174 | FY21: =SUMIFS(营销场景数据源!$G:$G,营销场景数据源!$C:$C,$B$20,营销场景数据源!$A:$A,FY2) -> 183 | ... GP21: =SUMIFS(营销场景数据源!$G:$G,营销场景数据源!$C:$C,$B$20,营销场景数据源!$A:$A,GP2) -> 0
A22: 实际费率 | C22: 总购物车数 | D22: =SUM(E22:P22) -> #REF! | E22: =#REF! -> #REF! | F22: =#REF! -> #REF! | G22: =#REF! -> #REF! | H22: =#REF! -> #REF! | I22: =#REF! -> #REF! | J22: =#REF! -> #REF! | K22: =#REF! -> #REF! | L22: =#REF! -> #REF! | ... P22: =#REF! -> #REF! | Q22: =SUM(R22:AV22) -> 10 | R22: =SUMIFS(营销场景数据源!$AB:$AB,营销场景数据源!$C:$C,$B$20,营销场景数据源!$A:$A,R2) -> 0 | S22: =SUMIFS(营销场景数据源!$AB:$AB,营销场景数据源!$C:$C,$B$20,营销场景数据源!$A:$A,S2) -> 0 | T22: =SUMIFS(营销场景数据源!$AB:$AB,营销场景数据源!$C:$C,$B$20,营销场景数据源!$A:$A,T2) -> 0 | U22: =SUMIFS(营销场景数据源!$AB:$AB,营销场景数据源!$C:$C,$B$20,营销场景数据源!$A:$A,U2) -> 0 | V22: =SUMIFS(营销场景数据源!$AB:$AB,营销场景数据源!$C:$C,$B$20,营销场景数据源!$A:$A,V2) -> 0 | W22: =SUMIFS(营销场景数据源!$AB:$AB,营销场景数据源!$C:$C,$B$20,营销场景数据源!$A:$A,W2) -> 0 | X22: =SUMIFS(营销场景数据源!$AB:$AB,营销场景数据源!$C:$C,$B$20,营销场景数据源!$A:$A,X2) -> 0 | Y22: =SUMIFS(营销场景数据源!$AB:$AB,营销场景数据源!$C:$C,$B$20,营销场景数据源!$A:$A,Y2) -> 0 | ... AV22: =SUMIFS(营销场景数据源!$AB:$AB,营销场景数据源!$C:$C,$B$20,营销场景数据源!$A:$A,AV2) -> 0 | AW22: =SUM(AX22:BY22) -> 81 | AX22: =SUMIFS(营销场景数据源!$AB:$AB,营销场景数据源!$C:$C,$B$20,营销场景数据源!$A:$A,AX2) -> 3 | AY22: =SUMIFS(营销场景数据源!$AB:$AB,营销场景数据源!$C:$C,$B$20,营销场景数据源!$A:$A,AY2) -> 2 | AZ22: =SUMIFS(营销场景数据源!$AB:$AB,营销场景数据源!$C:$C,$B$20,营销场景数据源!$A:$A,AZ2) -> 0 | BA22: =SUMIFS(营销场景数据源!$AB:$AB,营销场景数据源!$C:$C,$B$20,营销场景数据源!$A:$A,BA2) -> 0 | BB22: =SUMIFS(营销场景数据源!$AB:$AB,营销场景数据源!$C:$C,$B$20,营销场景数据源!$A:$A,BB2) -> 2 | BC22: =SUMIFS(营销场景数据源!$AB:$AB,营销场景数据源!$C:$C,$B$20,营销场景数据源!$A:$A,BC2) -> 7 | BD22: =SUMIFS(营销场景数据源!$AB:$AB,营销场景数据源!$C:$C,$B$20,营销场景数据源!$A:$A,BD2) -> 0 | BE22: =SUMIFS(营销场景数据源!$AB:$AB,营销场景数据源!$C:$C,$B$20,营销场景数据源!$A:$A,BE2) -> 3 | ... BY22: =SUMIFS(营销场景数据源!$AB:$AB,营销场景数据源!$C:$C,$B$20,营销场景数据源!$A:$A,BY2) -> 1 | BZ22: =SUM(CA22:DE22) -> 95 | CA22: =SUMIFS(营销场景数据源!$AB:$AB,营销场景数据源!$C:$C,$B$20,营销场景数据源!$A:$A,CA2) -> 1 | CB22: =SUMIFS(营销场景数据源!$AB:$AB,营销场景数据源!$C:$C,$B$20,营销场景数据源!$A:$A,CB2) -> 2 | CC22: =SUMIFS(营销场景数据源!$AB:$AB,营销场景数据源!$C:$C,$B$20,营销场景数据源!$A:$A,CC2) -> 9 | CD22: =SUMIFS(营销场景数据源!$AB:$AB,营销场景数据源!$C:$C,$B$20,营销场景数据源!$A:$A,CD2) -> 1 | CE22: =SUMIFS(营销场景数据源!$AB:$AB,营销场景数据源!$C:$C,$B$20,营销场景数据源!$A:$A,CE2) -> 6 | CF22: =SUMIFS(营销场景数据源!$AB:$AB,营销场景数据源!$C:$C,$B$20,营销场景数据源!$A:$A,CF2) -> 0 | CG22: =SUMIFS(营销场景数据源!$AB:$AB,营销场景数据源!$C:$C,$B$20,营销场景数据源!$A:$A,CG2) -> 1 | CH22: =SUMIFS(营销场景数据源!$AB:$AB,营销场景数据源!$C:$C,$B$20,营销场景数据源!$A:$A,CH2) -> 12 | ... DE22: =SUMIFS(营销场景数据源!$AB:$AB,营销场景数据源!$C:$C,$B$20,营销场景数据源!$A:$A,DE2) -> 1 | DF22: =SUM(DG22:EJ22) -> 91 | DG22: =SUMIFS(营销场景数据源!$AB:$AB,营销场景数据源!$C:$C,$B$20,营销场景数据源!$A:$A,DG2) -> 2 | DH22: =SUMIFS(营销场景数据源!$AB:$AB,营销场景数据源!$C:$C,$B$20,营销场景数据源!$A:$A,DH2) -> 4 | DI22: =SUMIFS(营销场景数据源!$AB:$AB,营销场景数据源!$C:$C,$B$20,营销场景数据源!$A:$A,DI2) -> 2 | DJ22: =SUMIFS(营销场景数据源!$AB:$AB,营销场景数据源!$C:$C,$B$20,营销场景数据源!$A:$A,DJ2) -> 0 | DK22: =SUMIFS(营销场景数据源!$AB:$AB,营销场景数据源!$C:$C,$B$20,营销场景数据源!$A:$A,DK2) -> 0 | DL22: =SUMIFS(营销场景数据源!$AB:$AB,营销场景数据源!$C:$C,$B$20,营销场景数据源!$A:$A,DL2) -> 1 | DM22: =SUMIFS(营销场景数据源!$AB:$AB,营销场景数据源!$C:$C,$B$20,营销场景数据源!$A:$A,DM2) -> 0 | DN22: =SUMIFS(营销场景数据源!$AB:$AB,营销场景数据源!$C:$C,$B$20,营销场景数据源!$A:$A,DN2) -> 0 | ... EJ22: =SUMIFS(营销场景数据源!$AB:$AB,营销场景数据源!$C:$C,$B$20,营销场景数据源!$A:$A,EJ2) -> 1 | EK22: =SUM(EL22:FP22) -> 128 | EL22: =SUMIFS(营销场景数据源!$AB:$AB,营销场景数据源!$C:$C,$B$20,营销场景数据源!$A:$A,EL2) -> 3 | EM22: =SUMIFS(营销场景数据源!$AB:$AB,营销场景数据源!$C:$C,$B$20,营销场景数据源!$A:$A,EM2) -> 2 | EN22: =SUMIFS(营销场景数据源!$AB:$AB,营销场景数据源!$C:$C,$B$20,营销场景数据源!$A:$A,EN2) -> 1 | EO22: =SUMIFS(营销场景数据源!$AB:$AB,营销场景数据源!$C:$C,$B$20,营销场景数据源!$A:$A,EO2) -> 2 | EP22: =SUMIFS(营销场景数据源!$AB:$AB,营销场景数据源!$C:$C,$B$20,营销场景数据源!$A:$A,EP2) -> 3 | EQ22: =SUMIFS(营销场景数据源!$AB:$AB,营销场景数据源!$C:$C,$B$20,营销场景数据源!$A:$A,EQ2) -> 4 | ER22: =SUMIFS(营销场景数据源!$AB:$AB,营销场景数据源!$C:$C,$B$20,营销场景数据源!$A:$A,ER2) -> 6 | ES22: =SUMIFS(营销场景数据源!$AB:$AB,营销场景数据源!$C:$C,$B$20,营销场景数据源!$A:$A,ES2) -> 2 | ... FP22: =SUMIFS(营销场景数据源!$AB:$AB,营销场景数据源!$C:$C,$B$20,营销场景数据源!$A:$A,FP2) -> 2 | FQ22: =SUM(FR22:GX22) -> 119 | FR22: =SUMIFS(营销场景数据源!$AB:$AB,营销场景数据源!$C:$C,$B$20,营销场景数据源!$A:$A,FR2) -> 1 | FS22: =SUMIFS(营销场景数据源!$AB:$AB,营销场景数据源!$C:$C,$B$20,营销场景数据源!$A:$A,FS2) -> 2 | FT22: =SUMIFS(营销场景数据源!$AB:$AB,营销场景数据源!$C:$C,$B$20,营销场景数据源!$A:$A,FT2) -> 9 | FU22: =SUMIFS(营销场景数据源!$AB:$AB,营销场景数据源!$C:$C,$B$20,营销场景数据源!$A:$A,FU2) -> 2 | FV22: =SUMIFS(营销场景数据源!$AB:$AB,营销场景数据源!$C:$C,$B$20,营销场景数据源!$A:$A,FV2) -> 1 | FW22: =SUMIFS(营销场景数据源!$AB:$AB,营销场景数据源!$C:$C,$B$20,营销场景数据源!$A:$A,FW2) -> 9 | FX22: =SUMIFS(营销场景数据源!$AB:$AB,营销场景数据源!$C:$C,$B$20,营销场景数据源!$A:$A,FX2) -> 10 | FY22: =SUMIFS(营销场景数据源!$AB:$AB,营销场景数据源!$C:$C,$B$20,营销场景数据源!$A:$A,FY2) -> 6 | ... GP22: =SUMIFS(营销场景数据源!$AB:$AB,营销场景数据源!$C:$C,$B$20,营销场景数据源!$A:$A,GP2) -> 0
A23: =D6 -> #REF! | C23: 总成交量 | D23: =SUM(E23:P23) -> #REF! | E23: =#REF! -> #REF! | F23: =#REF! -> #REF! | G23: =#REF! -> #REF! | H23: =#REF! -> #REF! | I23: =#REF! -> #REF! | J23: =#REF! -> #REF! | K23: =#REF! -> #REF! | L23: =#REF! -> #REF! | ... P23: =#REF! -> #REF! | Q23: =SUM(R23:AV23) -> 0 | R23: =SUMIFS(营销场景数据源!$U:$U,营销场景数据源!$C:$C,$B$20,营销场景数据源!$A:$A,R2) -> 0 | S23: =SUMIFS(营销场景数据源!$U:$U,营销场景数据源!$C:$C,$B$20,营销场景数据源!$A:$A,S2) -> 0 | T23: =SUMIFS(营销场景数据源!$U:$U,营销场景数据源!$C:$C,$B$20,营销场景数据源!$A:$A,T2) -> 0 | U23: =SUMIFS(营销场景数据源!$U:$U,营销场景数据源!$C:$C,$B$20,营销场景数据源!$A:$A,U2) -> 0 | V23: =SUMIFS(营销场景数据源!$U:$U,营销场景数据源!$C:$C,$B$20,营销场景数据源!$A:$A,V2) -> 0 | W23: =SUMIFS(营销场景数据源!$U:$U,营销场景数据源!$C:$C,$B$20,营销场景数据源!$A:$A,W2) -> 0 | X23: =SUMIFS(营销场景数据源!$U:$U,营销场景数据源!$C:$C,$B$20,营销场景数据源!$A:$A,X2) -> 0 | Y23: =SUMIFS(营销场景数据源!$U:$U,营销场景数据源!$C:$C,$B$20,营销场景数据源!$A:$A,Y2) -> 0 | ... AV23: =SUMIFS(营销场景数据源!$U:$U,营销场景数据源!$C:$C,$B$20,营销场景数据源!$A:$A,AV2) -> 0 | AW23: =SUM(AX23:BY23) -> 10 | AX23: =SUMIFS(营销场景数据源!$U:$U,营销场景数据源!$C:$C,$B$20,营销场景数据源!$A:$A,AX2) -> 3 | AY23: =SUMIFS(营销场景数据源!$U:$U,营销场景数据源!$C:$C,$B$20,营销场景数据源!$A:$A,AY2) -> 2 | AZ23: =SUMIFS(营销场景数据源!$U:$U,营销场景数据源!$C:$C,$B$20,营销场景数据源!$A:$A,AZ2) -> 0 | BA23: =SUMIFS(营销场景数据源!$U:$U,营销场景数据源!$C:$C,$B$20,营销场景数据源!$A:$A,BA2) -> 0 | BB23: =SUMIFS(营销场景数据源!$U:$U,营销场景数据源!$C:$C,$B$20,营销场景数据源!$A:$A,BB2) -> 0 | BC23: =SUMIFS(营销场景数据源!$U:$U,营销场景数据源!$C:$C,$B$20,营销场景数据源!$A:$A,BC2) -> 2 | BD23: =SUMIFS(营销场景数据源!$U:$U,营销场景数据源!$C:$C,$B$20,营销场景数据源!$A:$A,BD2) -> 0 | BE23: =SUMIFS(营销场景数据源!$U:$U,营销场景数据源!$C:$C,$B$20,营销场景数据源!$A:$A,BE2) -> 0 | ... BY23: =SUMIFS(营销场景数据源!$U:$U,营销场景数据源!$C:$C,$B$20,营销场景数据源!$A:$A,BY2) -> 0 | BZ23: =SUM(CA23:DE23) -> 8 | CA23: =SUMIFS(营销场景数据源!$U:$U,营销场景数据源!$C:$C,$B$20,营销场景数据源!$A:$A,CA2) -> 0 | CB23: =SUMIFS(营销场景数据源!$U:$U,营销场景数据源!$C:$C,$B$20,营销场景数据源!$A:$A,CB2) -> 0 | CC23: =SUMIFS(营销场景数据源!$U:$U,营销场景数据源!$C:$C,$B$20,营销场景数据源!$A:$A,CC2) -> 0 | CD23: =SUMIFS(营销场景数据源!$U:$U,营销场景数据源!$C:$C,$B$20,营销场景数据源!$A:$A,CD2) -> 1 | CE23: =SUMIFS(营销场景数据源!$U:$U,营销场景数据源!$C:$C,$B$20,营销场景数据源!$A:$A,CE2) -> 2 | CF23: =SUMIFS(营销场景数据源!$U:$U,营销场景数据源!$C:$C,$B$20,营销场景数据源!$A:$A,CF2) -> 0 | CG23: =SUMIFS(营销场景数据源!$U:$U,营销场景数据源!$C:$C,$B$20,营销场景数据源!$A:$A,CG2) -> 0 | CH23: =SUMIFS(营销场景数据源!$U:$U,营销场景数据源!$C:$C,$B$20,营销场景数据源!$A:$A,CH2) -> 0 | ... DE23: =SUMIFS(营销场景数据源!$U:$U,营销场景数据源!$C:$C,$B$20,营销场景数据源!$A:$A,DE2) -> 0 | DF23: =SUM(DG23:EJ23) -> 14 | DG23: =SUMIFS(营销场景数据源!$U:$U,营销场景数据源!$C:$C,$B$20,营销场景数据源!$A:$A,DG2) -> 0 | DH23: =SUMIFS(营销场景数据源!$U:$U,营销场景数据源!$C:$C,$B$20,营销场景数据源!$A:$A,DH2) -> 0 | DI23: =SUMIFS(营销场景数据源!$U:$U,营销场景数据源!$C:$C,$B$20,营销场景数据源!$A:$A,DI2) -> 0 | DJ23: =SUMIFS(营销场景数据源!$U:$U,营销场景数据源!$C:$C,$B$20,营销场景数据源!$A:$A,DJ2) -> 0 | DK23: =SUMIFS(营销场景数据源!$U:$U,营销场景数据源!$C:$C,$B$20,营销场景数据源!$A:$A,DK2) -> 0 | DL23: =SUMIFS(营销场景数据源!$U:$U,营销场景数据源!$C:$C,$B$20,营销场景数据源!$A:$A,DL2) -> 0 | DM23: =SUMIFS(营销场景数据源!$U:$U,营销场景数据源!$C:$C,$B$20,营销场景数据源!$A:$A,DM2) -> 0 | DN23: =SUMIFS(营销场景数据源!$U:$U,营销场景数据源!$C:$C,$B$20,营销场景数据源!$A:$A,DN2) -> 0 | ... EJ23: =SUMIFS(营销场景数据源!$U:$U,营销场景数据源!$C:$C,$B$20,营销场景数据源!$A:$A,EJ2) -> 0 | EK23: =SUM(EL23:FP23) -> 25 | EL23: =SUMIFS(营销场景数据源!$U:$U,营销场景数据源!$C:$C,$B$20,营销场景数据源!$A:$A,EL2) -> 0 | EM23: =SUMIFS(营销场景数据源!$U:$U,营销场景数据源!$C:$C,$B$20,营销场景数据源!$A:$A,EM2) -> 1 | EN23: =SUMIFS(营销场景数据源!$U:$U,营销场景数据源!$C:$C,$B$20,营销场景数据源!$A:$A,EN2) -> 0 | EO23: =SUMIFS(营销场景数据源!$U:$U,营销场景数据源!$C:$C,$B$20,营销场景数据源!$A:$A,EO2) -> 0 | EP23: =SUMIFS(营销场景数据源!$U:$U,营销场景数据源!$C:$C,$B$20,营销场景数据源!$A:$A,EP2) -> 0 | EQ23: =SUMIFS(营销场景数据源!$U:$U,营销场景数据源!$C:$C,$B$20,营销场景数据源!$A:$A,EQ2) -> 1 | ER23: =SUMIFS(营销场景数据源!$U:$U,营销场景数据源!$C:$C,$B$20,营销场景数据源!$A:$A,ER2) -> 1 | ES23: =SUMIFS(营销场景数据源!$U:$U,营销场景数据源!$C:$C,$B$20,营销场景数据源!$A:$A,ES2) -> 0 | ... FP23: =SUMIFS(营销场景数据源!$U:$U,营销场景数据源!$C:$C,$B$20,营销场景数据源!$A:$A,FP2) -> 0 | FQ23: =SUM(FR23:GX23) -> 30 | FR23: =SUMIFS(营销场景数据源!$U:$U,营销场景数据源!$C:$C,$B$20,营销场景数据源!$A:$A,FR2) -> 1 | FS23: =SUMIFS(营销场景数据源!$U:$U,营销场景数据源!$C:$C,$B$20,营销场景数据源!$A:$A,FS2) -> 2 | FT23: =SUMIFS(营销场景数据源!$U:$U,营销场景数据源!$C:$C,$B$20,营销场景数据源!$A:$A,FT2) -> 4 | FU23: =SUMIFS(营销场景数据源!$U:$U,营销场景数据源!$C:$C,$B$20,营销场景数据源!$A:$A,FU2) -> 0 | FV23: =SUMIFS(营销场景数据源!$U:$U,营销场景数据源!$C:$C,$B$20,营销场景数据源!$A:$A,FV2) -> 0 | FW23: =SUMIFS(营销场景数据源!$U:$U,营销场景数据源!$C:$C,$B$20,营销场景数据源!$A:$A,FW2) -> 3 | FX23: =SUMIFS(营销场景数据源!$U:$U,营销场景数据源!$C:$C,$B$20,营销场景数据源!$A:$A,FX2) -> 3 | FY23: =SUMIFS(营销场景数据源!$U:$U,营销场景数据源!$C:$C,$B$20,营销场景数据源!$A:$A,FY2) -> 3 | ... GP23: =SUMIFS(营销场景数据源!$U:$U,营销场景数据源!$C:$C,$B$20,营销场景数据源!$A:$A,GP2) -> 0
A24: 目标销售占比 | C24: 总成交金额 | D24: =SUM(E24:P24) -> #REF! | E24: =#REF! -> #REF! | F24: =#REF! -> #REF! | G24: =#REF! -> #REF! | H24: =#REF! -> #REF! | I24: =#REF! -> #REF! | J24: =#REF! -> #REF! | K24: =#REF! -> #REF! | L24: =#REF! -> #REF! | ... P24: =#REF! -> #REF! | Q24: =SUM(R24:AV24) -> 0 | R24: =SUMIFS(营销场景数据源!$T:$T,营销场景数据源!$C:$C,$B$20,营销场景数据源!$A:$A,R2) -> 0 | S24: =SUMIFS(营销场景数据源!$T:$T,营销场景数据源!$C:$C,$B$20,营销场景数据源!$A:$A,S2) -> 0 | T24: =SUMIFS(营销场景数据源!$T:$T,营销场景数据源!$C:$C,$B$20,营销场景数据源!$A:$A,T2) -> 0 | U24: =SUMIFS(营销场景数据源!$T:$T,营销场景数据源!$C:$C,$B$20,营销场景数据源!$A:$A,U2) -> 0 | V24: =SUMIFS(营销场景数据源!$T:$T,营销场景数据源!$C:$C,$B$20,营销场景数据源!$A:$A,V2) -> 0 | W24: =SUMIFS(营销场景数据源!$T:$T,营销场景数据源!$C:$C,$B$20,营销场景数据源!$A:$A,W2) -> 0 | X24: =SUMIFS(营销场景数据源!$T:$T,营销场景数据源!$C:$C,$B$20,营销场景数据源!$A:$A,X2) -> 0 | Y24: =SUMIFS(营销场景数据源!$T:$T,营销场景数据源!$C:$C,$B$20,营销场景数据源!$A:$A,Y2) -> 0 | ... AV24: =SUMIFS(营销场景数据源!$T:$T,营销场景数据源!$C:$C,$B$20,营销场景数据源!$A:$A,AV2) -> 0 | AW24: =SUM(AX24:BY24) -> 9369.48 | AX24: =SUMIFS(营销场景数据源!$T:$T,营销场景数据源!$C:$C,$B$20,营销场景数据源!$A:$A,AX2) -> 5612.15 | AY24: =SUMIFS(营销场景数据源!$T:$T,营销场景数据源!$C:$C,$B$20,营销场景数据源!$A:$A,AY2) -> 2358.18 | AZ24: =SUMIFS(营销场景数据源!$T:$T,营销场景数据源!$C:$C,$B$20,营销场景数据源!$A:$A,AZ2) -> 0 | BA24: =SUMIFS(营销场景数据源!$T:$T,营销场景数据源!$C:$C,$B$20,营销场景数据源!$A:$A,BA2) -> 0 | BB24: =SUMIFS(营销场景数据源!$T:$T,营销场景数据源!$C:$C,$B$20,营销场景数据源!$A:$A,BB2) -> 0 | BC24: =SUMIFS(营销场景数据源!$T:$T,营销场景数据源!$C:$C,$B$20,营销场景数据源!$A:$A,BC2) -> 75.45 | BD24: =SUMIFS(营销场景数据源!$T:$T,营销场景数据源!$C:$C,$B$20,营销场景数据源!$A:$A,BD2) -> 0 | BE24: =SUMIFS(营销场景数据源!$T:$T,营销场景数据源!$C:$C,$B$20,营销场景数据源!$A:$A,BE2) -> 0 | ... BY24: =SUMIFS(营销场景数据源!$T:$T,营销场景数据源!$C:$C,$B$20,营销场景数据源!$A:$A,BY2) -> 0 | BZ24: =SUM(CA24:DE24) -> 4362.62 | CA24: =SUMIFS(营销场景数据源!$T:$T,营销场景数据源!$C:$C,$B$20,营销场景数据源!$A:$A,CA2) -> 0 | CB24: =SUMIFS(营销场景数据源!$T:$T,营销场景数据源!$C:$C,$B$20,营销场景数据源!$A:$A,CB2) -> 0 | CC24: =SUMIFS(营销场景数据源!$T:$T,营销场景数据源!$C:$C,$B$20,营销场景数据源!$A:$A,CC2) -> 0 | CD24: =SUMIFS(营销场景数据源!$T:$T,营销场景数据源!$C:$C,$B$20,营销场景数据源!$A:$A,CD2) -> 1413.55 | CE24: =SUMIFS(营销场景数据源!$T:$T,营销场景数据源!$C:$C,$B$20,营销场景数据源!$A:$A,CE2) -> 1301.46 | CF24: =SUMIFS(营销场景数据源!$T:$T,营销场景数据源!$C:$C,$B$20,营销场景数据源!$A:$A,CF2) -> 0 | CG24: =SUMIFS(营销场景数据源!$T:$T,营销场景数据源!$C:$C,$B$20,营销场景数据源!$A:$A,CG2) -> 0 | CH24: =SUMIFS(营销场景数据源!$T:$T,营销场景数据源!$C:$C,$B$20,营销场景数据源!$A:$A,CH2) -> 0 | ... DE24: =SUMIFS(营销场景数据源!$T:$T,营销场景数据源!$C:$C,$B$20,营销场景数据源!$A:$A,DE2) -> 0 | DF24: =SUM(DG24:EJ24) -> 2311.48 | DG24: =SUMIFS(营销场景数据源!$T:$T,营销场景数据源!$C:$C,$B$20,营销场景数据源!$A:$A,DG2) -> 0 | DH24: =SUMIFS(营销场景数据源!$T:$T,营销场景数据源!$C:$C,$B$20,营销场景数据源!$A:$A,DH2) -> 0 | DI24: =SUMIFS(营销场景数据源!$T:$T,营销场景数据源!$C:$C,$B$20,营销场景数据源!$A:$A,DI2) -> 0 | DJ24: =SUMIFS(营销场景数据源!$T:$T,营销场景数据源!$C:$C,$B$20,营销场景数据源!$A:$A,DJ2) -> 0 | DK24: =SUMIFS(营销场景数据源!$T:$T,营销场景数据源!$C:$C,$B$20,营销场景数据源!$A:$A,DK2) -> 0 | DL24: =SUMIFS(营销场景数据源!$T:$T,营销场景数据源!$C:$C,$B$20,营销场景数据源!$A:$A,DL2) -> 0 | DM24: =SUMIFS(营销场景数据源!$T:$T,营销场景数据源!$C:$C,$B$20,营销场景数据源!$A:$A,DM2) -> 0 | DN24: =SUMIFS(营销场景数据源!$T:$T,营销场景数据源!$C:$C,$B$20,营销场景数据源!$A:$A,DN2) -> 0 | ... EJ24: =SUMIFS(营销场景数据源!$T:$T,营销场景数据源!$C:$C,$B$20,营销场景数据源!$A:$A,EJ2) -> 0 | EK24: =SUM(EL24:FP24) -> 11122.7 | EL24: =SUMIFS(营销场景数据源!$T:$T,营销场景数据源!$C:$C,$B$20,营销场景数据源!$A:$A,EL2) -> 0 | EM24: =SUMIFS(营销场景数据源!$T:$T,营销场景数据源!$C:$C,$B$20,营销场景数据源!$A:$A,EM2) -> 151 | EN24: =SUMIFS(营销场景数据源!$T:$T,营销场景数据源!$C:$C,$B$20,营销场景数据源!$A:$A,EN2) -> 0 | EO24: =SUMIFS(营销场景数据源!$T:$T,营销场景数据源!$C:$C,$B$20,营销场景数据源!$A:$A,EO2) -> 0 | EP24: =SUMIFS(营销场景数据源!$T:$T,营销场景数据源!$C:$C,$B$20,营销场景数据源!$A:$A,EP2) -> 0 | EQ24: =SUMIFS(营销场景数据源!$T:$T,营销场景数据源!$C:$C,$B$20,营销场景数据源!$A:$A,EQ2) -> 33.9 | ER24: =SUMIFS(营销场景数据源!$T:$T,营销场景数据源!$C:$C,$B$20,营销场景数据源!$A:$A,ER2) -> 8074 | ES24: =SUMIFS(营销场景数据源!$T:$T,营销场景数据源!$C:$C,$B$20,营销场景数据源!$A:$A,ES2) -> 0 | ... FP24: =SUMIFS(营销场景数据源!$T:$T,营销场景数据源!$C:$C,$B$20,营销场景数据源!$A:$A,FP2) -> 0 | FQ24: =SUM(FR24:GX24) -> 2298.61 | FR24: =SUMIFS(营销场景数据源!$T:$T,营销场景数据源!$C:$C,$B$20,营销场景数据源!$A:$A,FR2) -> 79.8 | FS24: =SUMIFS(营销场景数据源!$T:$T,营销场景数据源!$C:$C,$B$20,营销场景数据源!$A:$A,FS2) -> 75.39 | FT24: =SUMIFS(营销场景数据源!$T:$T,营销场景数据源!$C:$C,$B$20,营销场景数据源!$A:$A,FT2) -> 403.61 | FU24: =SUMIFS(营销场景数据源!$T:$T,营销场景数据源!$C:$C,$B$20,营销场景数据源!$A:$A,FU2) -> 0 | FV24: =SUMIFS(营销场景数据源!$T:$T,营销场景数据源!$C:$C,$B$20,营销场景数据源!$A:$A,FV2) -> 0 | FW24: =SUMIFS(营销场景数据源!$T:$T,营销场景数据源!$C:$C,$B$20,营销场景数据源!$A:$A,FW2) -> 161.58 | FX24: =SUMIFS(营销场景数据源!$T:$T,营销场景数据源!$C:$C,$B$20,营销场景数据源!$A:$A,FX2) -> 242.82 | FY24: =SUMIFS(营销场景数据源!$T:$T,营销场景数据源!$C:$C,$B$20,营销场景数据源!$A:$A,FY2) -> 156.41 | ... GP24: =SUMIFS(营销场景数据源!$T:$T,营销场景数据源!$C:$C,$B$20,营销场景数据源!$A:$A,GP2) -> 0
A25: =A3*A21 -> 0 | C25: 点击单价 | D25: =IFERROR(D20/D21,0) -> 0 | E25: =IFERROR(E20/E21,0) -> 0 | F25: =IFERROR(F20/F21,0) -> 0 | G25: =IFERROR(G20/G21,0) -> 0 | H25: =IFERROR(H20/H21,0) -> 0 | I25: =IFERROR(I20/I21,0) -> 0 | J25: =IFERROR(J20/J21,0) -> 0 | K25: =IFERROR(K20/K21,0) -> 0 | ... GP25: =IFERROR(GP20/GP21,0) -> 0
A26: 实际销售占比 | C26: 加购成本 | D26: =IFERROR(D20/D22,0) -> 0 | E26: =IFERROR(E20/E22,0) -> 0 | F26: =IFERROR(F20/F22,0) -> 0 | G26: =IFERROR(G20/G22,0) -> 0 | H26: =IFERROR(H20/H22,0) -> 0 | I26: =IFERROR(I20/I22,0) -> 0 | J26: =IFERROR(J20/J22,0) -> 0 | K26: =IFERROR(K20/K22,0) -> 0 | ... GP26: =IFERROR(GP20/GP22,0) -> 0
A27: =A5*A23 -> #REF! | C27: ROI | D27: =IFERROR(D24/D20,0) -> 0 | E27: =IFERROR(E24/E20,0) -> 0 | F27: =IFERROR(F24/F20,0) -> 0 | G27: =IFERROR(G24/G20,0) -> 0 | H27: =IFERROR(H24/H20,0) -> 0 | I27: =IFERROR(I24/I20,0) -> 0 | J27: =IFERROR(J24/J20,0) -> 0 | K27: =IFERROR(K24/K20,0) -> 0 | ... GP27: =IFERROR(GP24/GP20,0) -> 0
C28: 费用占比 | D28: =D20/D$130 -> #REF! | E28: =E20/E$130 -> #REF! | F28: =F20/F$130 -> #REF! | G28: =G20/G$130 -> #REF! | H28: =H20/H$130 -> #REF! | I28: =I20/I$130 -> #REF! | J28: =J20/J$130 -> #REF! | K28: =K20/K$130 -> #REF! | ... GP28: =GP20/GP$130 -> #DIV/0!
B29: 人群推广 | C29: 花费 | D29: =SUM(E29:P29) -> #REF! | E29: =#REF! -> #REF! | F29: =#REF! -> #REF! | G29: =#REF! -> #REF! | H29: =#REF! -> #REF! | I29: =#REF! -> #REF! | J29: =#REF! -> #REF! | K29: =#REF! -> #REF! | L29: =#REF! -> #REF! | ... P29: =#REF! -> #REF! | Q29: =SUM(R29:AV29) -> 3304.75 | R29: =SUMIFS(营销场景数据源!$H:$H,营销场景数据源!$C:$C,$B$29,营销场景数据源!$A:$A,R2) -> 99.76 | S29: =SUMIFS(营销场景数据源!$H:$H,营销场景数据源!$C:$C,$B$29,营销场景数据源!$A:$A,S2) -> 87.67 | T29: =SUMIFS(营销场景数据源!$H:$H,营销场景数据源!$C:$C,$B$29,营销场景数据源!$A:$A,T2) -> 138.13 | U29: =SUMIFS(营销场景数据源!$H:$H,营销场景数据源!$C:$C,$B$29,营销场景数据源!$A:$A,U2) -> 187.34 | V29: =SUMIFS(营销场景数据源!$H:$H,营销场景数据源!$C:$C,$B$29,营销场景数据源!$A:$A,V2) -> 132.55 | W29: =SUMIFS(营销场景数据源!$H:$H,营销场景数据源!$C:$C,$B$29,营销场景数据源!$A:$A,W2) -> 151.03 | X29: =SUMIFS(营销场景数据源!$H:$H,营销场景数据源!$C:$C,$B$29,营销场景数据源!$A:$A,X2) -> 139.72 | Y29: =SUMIFS(营销场景数据源!$H:$H,营销场景数据源!$C:$C,$B$29,营销场景数据源!$A:$A,Y2) -> 131.9 | ... AV29: =SUMIFS(营销场景数据源!$H:$H,营销场景数据源!$C:$C,$B$29,营销场景数据源!$A:$A,AV2) -> 51.47 | AW29: =SUM(AX29:BY29) -> 352.13 | AX29: =SUMIFS(营销场景数据源!$H:$H,营销场景数据源!$C:$C,$B$29,营销场景数据源!$A:$A,AX2) -> 56.2 | AY29: =SUMIFS(营销场景数据源!$H:$H,营销场景数据源!$C:$C,$B$29,营销场景数据源!$A:$A,AY2) -> 60.23 | AZ29: =SUMIFS(营销场景数据源!$H:$H,营销场景数据源!$C:$C,$B$29,营销场景数据源!$A:$A,AZ2) -> 37.32 | BA29: =SUMIFS(营销场景数据源!$H:$H,营销场景数据源!$C:$C,$B$29,营销场景数据源!$A:$A,BA2) -> 31.01 | BB29: =SUMIFS(营销场景数据源!$H:$H,营销场景数据源!$C:$C,$B$29,营销场景数据源!$A:$A,BB2) -> 42.08 | BC29: =SUMIFS(营销场景数据源!$H:$H,营销场景数据源!$C:$C,$B$29,营销场景数据源!$A:$A,BC2) -> 20.9 | BD29: =SUMIFS(营销场景数据源!$H:$H,营销场景数据源!$C:$C,$B$29,营销场景数据源!$A:$A,BD2) -> 32.71 | BE29: =SUMIFS(营销场景数据源!$H:$H,营销场景数据源!$C:$C,$B$29,营销场景数据源!$A:$A,BE2) -> 35 | ... BY29: =SUMIFS(营销场景数据源!$H:$H,营销场景数据源!$C:$C,$B$29,营销场景数据源!$A:$A,BY2) -> 0 | BZ29: =SUM(CA29:DE29) -> 0 | CA29: =SUMIFS(营销场景数据源!$H:$H,营销场景数据源!$C:$C,$B$29,营销场景数据源!$A:$A,CA2) -> 0 | CB29: =SUMIFS(营销场景数据源!$H:$H,营销场景数据源!$C:$C,$B$29,营销场景数据源!$A:$A,CB2) -> 0 | CC29: =SUMIFS(营销场景数据源!$H:$H,营销场景数据源!$C:$C,$B$29,营销场景数据源!$A:$A,CC2) -> 0 | CD29: =SUMIFS(营销场景数据源!$H:$H,营销场景数据源!$C:$C,$B$29,营销场景数据源!$A:$A,CD2) -> 0 | CE29: =SUMIFS(营销场景数据源!$H:$H,营销场景数据源!$C:$C,$B$29,营销场景数据源!$A:$A,CE2) -> 0 | CF29: =SUMIFS(营销场景数据源!$H:$H,营销场景数据源!$C:$C,$B$29,营销场景数据源!$A:$A,CF2) -> 0 | CG29: =SUMIFS(营销场景数据源!$H:$H,营销场景数据源!$C:$C,$B$29,营销场景数据源!$A:$A,CG2) -> 0 | CH29: =SUMIFS(营销场景数据源!$H:$H,营销场景数据源!$C:$C,$B$29,营销场景数据源!$A:$A,CH2) -> 0 | ... DE29: =SUMIFS(营销场景数据源!$H:$H,营销场景数据源!$C:$C,$B$29,营销场景数据源!$A:$A,DE2) -> 0 | DF29: =SUM(DG29:EJ29) -> 2308.45 | DG29: =SUMIFS(营销场景数据源!$H:$H,营销场景数据源!$C:$C,$B$29,营销场景数据源!$A:$A,DG2) -> 0 | DH29: =SUMIFS(营销场景数据源!$H:$H,营销场景数据源!$C:$C,$B$29,营销场景数据源!$A:$A,DH2) -> 0 | DI29: =SUMIFS(营销场景数据源!$H:$H,营销场景数据源!$C:$C,$B$29,营销场景数据源!$A:$A,DI2) -> 49.84 | DJ29: =SUMIFS(营销场景数据源!$H:$H,营销场景数据源!$C:$C,$B$29,营销场景数据源!$A:$A,DJ2) -> 50 | DK29: =SUMIFS(营销场景数据源!$H:$H,营销场景数据源!$C:$C,$B$29,营销场景数据源!$A:$A,DK2) -> 108 | DL29: =SUMIFS(营销场景数据源!$H:$H,营销场景数据源!$C:$C,$B$29,营销场景数据源!$A:$A,DL2) -> 50 | DM29: =SUMIFS(营销场景数据源!$H:$H,营销场景数据源!$C:$C,$B$29,营销场景数据源!$A:$A,DM2) -> 100 | DN29: =SUMIFS(营销场景数据源!$H:$H,营销场景数据源!$C:$C,$B$29,营销场景数据源!$A:$A,DN2) -> 211.61 | ... EJ29: =SUMIFS(营销场景数据源!$H:$H,营销场景数据源!$C:$C,$B$29,营销场景数据源!$A:$A,EJ2) -> 70.03 | EK29: =SUM(EL29:FP29) -> 2337.35 | EL29: =SUMIFS(营销场景数据源!$H:$H,营销场景数据源!$C:$C,$B$29,营销场景数据源!$A:$A,EL2) -> 90.15 | EM29: =SUMIFS(营销场景数据源!$H:$H,营销场景数据源!$C:$C,$B$29,营销场景数据源!$A:$A,EM2) -> 83.83 | EN29: =SUMIFS(营销场景数据源!$H:$H,营销场景数据源!$C:$C,$B$29,营销场景数据源!$A:$A,EN2) -> 100.4 | EO29: =SUMIFS(营销场景数据源!$H:$H,营销场景数据源!$C:$C,$B$29,营销场景数据源!$A:$A,EO2) -> 90.27 | EP29: =SUMIFS(营销场景数据源!$H:$H,营销场景数据源!$C:$C,$B$29,营销场景数据源!$A:$A,EP2) -> 101.66 | EQ29: =SUMIFS(营销场景数据源!$H:$H,营销场景数据源!$C:$C,$B$29,营销场景数据源!$A:$A,EQ2) -> 77.37 | ER29: =SUMIFS(营销场景数据源!$H:$H,营销场景数据源!$C:$C,$B$29,营销场景数据源!$A:$A,ER2) -> 72.05 | ES29: =SUMIFS(营销场景数据源!$H:$H,营销场景数据源!$C:$C,$B$29,营销场景数据源!$A:$A,ES2) -> 94.72 | ... FP29: =SUMIFS(营销场景数据源!$H:$H,营销场景数据源!$C:$C,$B$29,营销场景数据源!$A:$A,FP2) -> 79.89 | FQ29: =SUM(FR29:GX29) -> 1261.23 | FR29: =SUMIFS(营销场景数据源!$H:$H,营销场景数据源!$C:$C,$B$29,营销场景数据源!$A:$A,FR2) -> 54.7 | FS29: =SUMIFS(营销场景数据源!$H:$H,营销场景数据源!$C:$C,$B$29,营销场景数据源!$A:$A,FS2) -> 52.78 | FT29: =SUMIFS(营销场景数据源!$H:$H,营销场景数据源!$C:$C,$B$29,营销场景数据源!$A:$A,FT2) -> 40.39 | FU29: =SUMIFS(营销场景数据源!$H:$H,营销场景数据源!$C:$C,$B$29,营销场景数据源!$A:$A,FU2) -> 54.26 | FV29: =SUMIFS(营销场景数据源!$H:$H,营销场景数据源!$C:$C,$B$29,营销场景数据源!$A:$A,FV2) -> 29.89 | FW29: =SUMIFS(营销场景数据源!$H:$H,营销场景数据源!$C:$C,$B$29,营销场景数据源!$A:$A,FW2) -> 73.06 | FX29: =SUMIFS(营销场景数据源!$H:$H,营销场景数据源!$C:$C,$B$29,营销场景数据源!$A:$A,FX2) -> 83.17 | FY29: =SUMIFS(营销场景数据源!$H:$H,营销场景数据源!$C:$C,$B$29,营销场景数据源!$A:$A,FY2) -> 68.12 | ... GP29: =SUMIFS(营销场景数据源!$H:$H,营销场景数据源!$C:$C,$B$29,营销场景数据源!$A:$A,GP2) -> 0
C30: 点击量 | D30: =SUM(E30:P30) -> #REF! | E30: =#REF! -> #REF! | F30: =#REF! -> #REF! | G30: =#REF! -> #REF! | H30: =#REF! -> #REF! | I30: =#REF! -> #REF! | J30: =#REF! -> #REF! | K30: =#REF! -> #REF! | L30: =#REF! -> #REF! | ... P30: =#REF! -> #REF! | Q30: =SUM(R30:AV30) -> 1840 | R30: =SUMIFS(营销场景数据源!$G:$G,营销场景数据源!$C:$C,$B$29,营销场景数据源!$A:$A,R2) -> 78 | S30: =SUMIFS(营销场景数据源!$G:$G,营销场景数据源!$C:$C,$B$29,营销场景数据源!$A:$A,S2) -> 95 | T30: =SUMIFS(营销场景数据源!$G:$G,营销场景数据源!$C:$C,$B$29,营销场景数据源!$A:$A,T2) -> 127 | U30: =SUMIFS(营销场景数据源!$G:$G,营销场景数据源!$C:$C,$B$29,营销场景数据源!$A:$A,U2) -> 127 | V30: =SUMIFS(营销场景数据源!$G:$G,营销场景数据源!$C:$C,$B$29,营销场景数据源!$A:$A,V2) -> 112 | W30: =SUMIFS(营销场景数据源!$G:$G,营销场景数据源!$C:$C,$B$29,营销场景数据源!$A:$A,W2) -> 73 | X30: =SUMIFS(营销场景数据源!$G:$G,营销场景数据源!$C:$C,$B$29,营销场景数据源!$A:$A,X2) -> 90 | Y30: =SUMIFS(营销场景数据源!$G:$G,营销场景数据源!$C:$C,$B$29,营销场景数据源!$A:$A,Y2) -> 64 | ... AV30: =SUMIFS(营销场景数据源!$G:$G,营销场景数据源!$C:$C,$B$29,营销场景数据源!$A:$A,AV2) -> 25 | AW30: =SUM(AX30:BY30) -> 154 | AX30: =SUMIFS(营销场景数据源!$G:$G,营销场景数据源!$C:$C,$B$29,营销场景数据源!$A:$A,AX2) -> 22 | AY30: =SUMIFS(营销场景数据源!$G:$G,营销场景数据源!$C:$C,$B$29,营销场景数据源!$A:$A,AY2) -> 28 | AZ30: =SUMIFS(营销场景数据源!$G:$G,营销场景数据源!$C:$C,$B$29,营销场景数据源!$A:$A,AZ2) -> 15 | BA30: =SUMIFS(营销场景数据源!$G:$G,营销场景数据源!$C:$C,$B$29,营销场景数据源!$A:$A,BA2) -> 11 | BB30: =SUMIFS(营销场景数据源!$G:$G,营销场景数据源!$C:$C,$B$29,营销场景数据源!$A:$A,BB2) -> 15 | BC30: =SUMIFS(营销场景数据源!$G:$G,营销场景数据源!$C:$C,$B$29,营销场景数据源!$A:$A,BC2) -> 11 | BD30: =SUMIFS(营销场景数据源!$G:$G,营销场景数据源!$C:$C,$B$29,营销场景数据源!$A:$A,BD2) -> 19 | BE30: =SUMIFS(营销场景数据源!$G:$G,营销场景数据源!$C:$C,$B$29,营销场景数据源!$A:$A,BE2) -> 19 | ... BY30: =SUMIFS(营销场景数据源!$G:$G,营销场景数据源!$C:$C,$B$29,营销场景数据源!$A:$A,BY2) -> 0 | BZ30: =SUM(CA30:DE30) -> 0 | CA30: =SUMIFS(营销场景数据源!$G:$G,营销场景数据源!$C:$C,$B$29,营销场景数据源!$A:$A,CA2) -> 0 | CB30: =SUMIFS(营销场景数据源!$G:$G,营销场景数据源!$C:$C,$B$29,营销场景数据源!$A:$A,CB2) -> 0 | CC30: =SUMIFS(营销场景数据源!$G:$G,营销场景数据源!$C:$C,$B$29,营销场景数据源!$A:$A,CC2) -> 0 | CD30: =SUMIFS(营销场景数据源!$G:$G,营销场景数据源!$C:$C,$B$29,营销场景数据源!$A:$A,CD2) -> 0 | CE30: =SUMIFS(营销场景数据源!$G:$G,营销场景数据源!$C:$C,$B$29,营销场景数据源!$A:$A,CE2) -> 0 | CF30: =SUMIFS(营销场景数据源!$G:$G,营销场景数据源!$C:$C,$B$29,营销场景数据源!$A:$A,CF2) -> 0 | CG30: =SUMIFS(营销场景数据源!$G:$G,营销场景数据源!$C:$C,$B$29,营销场景数据源!$A:$A,CG2) -> 0 | CH30: =SUMIFS(营销场景数据源!$G:$G,营销场景数据源!$C:$C,$B$29,营销场景数据源!$A:$A,CH2) -> 0 | ... DE30: =SUMIFS(营销场景数据源!$G:$G,营销场景数据源!$C:$C,$B$29,营销场景数据源!$A:$A,DE2) -> 0 | DF30: =SUM(DG30:EJ30) -> 3735 | DG30: =SUMIFS(营销场景数据源!$G:$G,营销场景数据源!$C:$C,$B$29,营销场景数据源!$A:$A,DG2) -> 0 | DH30: =SUMIFS(营销场景数据源!$G:$G,营销场景数据源!$C:$C,$B$29,营销场景数据源!$A:$A,DH2) -> 0 | DI30: =SUMIFS(营销场景数据源!$G:$G,营销场景数据源!$C:$C,$B$29,营销场景数据源!$A:$A,DI2) -> 40 | DJ30: =SUMIFS(营销场景数据源!$G:$G,营销场景数据源!$C:$C,$B$29,营销场景数据源!$A:$A,DJ2) -> 27 | DK30: =SUMIFS(营销场景数据源!$G:$G,营销场景数据源!$C:$C,$B$29,营销场景数据源!$A:$A,DK2) -> 75 | DL30: =SUMIFS(营销场景数据源!$G:$G,营销场景数据源!$C:$C,$B$29,营销场景数据源!$A:$A,DL2) -> 23 | DM30: =SUMIFS(营销场景数据源!$G:$G,营销场景数据源!$C:$C,$B$29,营销场景数据源!$A:$A,DM2) -> 64 | DN30: =SUMIFS(营销场景数据源!$G:$G,营销场景数据源!$C:$C,$B$29,营销场景数据源!$A:$A,DN2) -> 148 | ... EJ30: =SUMIFS(营销场景数据源!$G:$G,营销场景数据源!$C:$C,$B$29,营销场景数据源!$A:$A,EJ2) -> 221 | EK30: =SUM(EL30:FP30) -> 6320 | EL30: =SUMIFS(营销场景数据源!$G:$G,营销场景数据源!$C:$C,$B$29,营销场景数据源!$A:$A,EL2) -> 287 | EM30: =SUMIFS(营销场景数据源!$G:$G,营销场景数据源!$C:$C,$B$29,营销场景数据源!$A:$A,EM2) -> 268 | EN30: =SUMIFS(营销场景数据源!$G:$G,营销场景数据源!$C:$C,$B$29,营销场景数据源!$A:$A,EN2) -> 290 | EO30: =SUMIFS(营销场景数据源!$G:$G,营销场景数据源!$C:$C,$B$29,营销场景数据源!$A:$A,EO2) -> 277 | EP30: =SUMIFS(营销场景数据源!$G:$G,营销场景数据源!$C:$C,$B$29,营销场景数据源!$A:$A,EP2) -> 300 | EQ30: =SUMIFS(营销场景数据源!$G:$G,营销场景数据源!$C:$C,$B$29,营销场景数据源!$A:$A,EQ2) -> 239 | ER30: =SUMIFS(营销场景数据源!$G:$G,营销场景数据源!$C:$C,$B$29,营销场景数据源!$A:$A,ER2) -> 214 | ES30: =SUMIFS(营销场景数据源!$G:$G,营销场景数据源!$C:$C,$B$29,营销场景数据源!$A:$A,ES2) -> 282 | ... FP30: =SUMIFS(营销场景数据源!$G:$G,营销场景数据源!$C:$C,$B$29,营销场景数据源!$A:$A,FP2) -> 196 | FQ30: =SUM(FR30:GX30) -> 2797 | FR30: =SUMIFS(营销场景数据源!$G:$G,营销场景数据源!$C:$C,$B$29,营销场景数据源!$A:$A,FR2) -> 111 | FS30: =SUMIFS(营销场景数据源!$G:$G,营销场景数据源!$C:$C,$B$29,营销场景数据源!$A:$A,FS2) -> 90 | FT30: =SUMIFS(营销场景数据源!$G:$G,营销场景数据源!$C:$C,$B$29,营销场景数据源!$A:$A,FT2) -> 78 | FU30: =SUMIFS(营销场景数据源!$G:$G,营销场景数据源!$C:$C,$B$29,营销场景数据源!$A:$A,FU2) -> 96 | FV30: =SUMIFS(营销场景数据源!$G:$G,营销场景数据源!$C:$C,$B$29,营销场景数据源!$A:$A,FV2) -> 52 | FW30: =SUMIFS(营销场景数据源!$G:$G,营销场景数据源!$C:$C,$B$29,营销场景数据源!$A:$A,FW2) -> 159 | FX30: =SUMIFS(营销场景数据源!$G:$G,营销场景数据源!$C:$C,$B$29,营销场景数据源!$A:$A,FX2) -> 213 | FY30: =SUMIFS(营销场景数据源!$G:$G,营销场景数据源!$C:$C,$B$29,营销场景数据源!$A:$A,FY2) -> 147 | ... GP30: =SUMIFS(营销场景数据源!$G:$G,营销场景数据源!$C:$C,$B$29,营销场景数据源!$A:$A,GP2) -> 0
C31: 总购物车数 | D31: =SUM(E31:P31) -> #REF! | E31: =#REF! -> #REF! | F31: =#REF! -> #REF! | G31: =#REF! -> #REF! | H31: =#REF! -> #REF! | I31: =#REF! -> #REF! | J31: =#REF! -> #REF! | K31: =#REF! -> #REF! | L31: =#REF! -> #REF! | ... P31: =#REF! -> #REF! | Q31: =SUM(R31:AV31) -> 93 | R31: =SUMIFS(营销场景数据源!$AB:$AB,营销场景数据源!$C:$C,$B$29,营销场景数据源!$A:$A,R2) -> 5 | S31: =SUMIFS(营销场景数据源!$AB:$AB,营销场景数据源!$C:$C,$B$29,营销场景数据源!$A:$A,S2) -> 10 | T31: =SUMIFS(营销场景数据源!$AB:$AB,营销场景数据源!$C:$C,$B$29,营销场景数据源!$A:$A,T2) -> 5 | U31: =SUMIFS(营销场景数据源!$AB:$AB,营销场景数据源!$C:$C,$B$29,营销场景数据源!$A:$A,U2) -> 2 | V31: =SUMIFS(营销场景数据源!$AB:$AB,营销场景数据源!$C:$C,$B$29,营销场景数据源!$A:$A,V2) -> 3 | W31: =SUMIFS(营销场景数据源!$AB:$AB,营销场景数据源!$C:$C,$B$29,营销场景数据源!$A:$A,W2) -> 3 | X31: =SUMIFS(营销场景数据源!$AB:$AB,营销场景数据源!$C:$C,$B$29,营销场景数据源!$A:$A,X2) -> 3 | Y31: =SUMIFS(营销场景数据源!$AB:$AB,营销场景数据源!$C:$C,$B$29,营销场景数据源!$A:$A,Y2) -> 4 | ... AV31: =SUMIFS(营销场景数据源!$AB:$AB,营销场景数据源!$C:$C,$B$29,营销场景数据源!$A:$A,AV2) -> 2 | AW31: =SUM(AX31:BY31) -> 26 | AX31: =SUMIFS(营销场景数据源!$AB:$AB,营销场景数据源!$C:$C,$B$29,营销场景数据源!$A:$A,AX2) -> 0 | AY31: =SUMIFS(营销场景数据源!$AB:$AB,营销场景数据源!$C:$C,$B$29,营销场景数据源!$A:$A,AY2) -> 1 | AZ31: =SUMIFS(营销场景数据源!$AB:$AB,营销场景数据源!$C:$C,$B$29,营销场景数据源!$A:$A,AZ2) -> 8 | BA31: =SUMIFS(营销场景数据源!$AB:$AB,营销场景数据源!$C:$C,$B$29,营销场景数据源!$A:$A,BA2) -> 3 | BB31: =SUMIFS(营销场景数据源!$AB:$AB,营销场景数据源!$C:$C,$B$29,营销场景数据源!$A:$A,BB2) -> 0 | BC31: =SUMIFS(营销场景数据源!$AB:$AB,营销场景数据源!$C:$C,$B$29,营销场景数据源!$A:$A,BC2) -> 1 | BD31: =SUMIFS(营销场景数据源!$AB:$AB,营销场景数据源!$C:$C,$B$29,营销场景数据源!$A:$A,BD2) -> 7 | BE31: =SUMIFS(营销场景数据源!$AB:$AB,营销场景数据源!$C:$C,$B$29,营销场景数据源!$A:$A,BE2) -> 6 | ... BY31: =SUMIFS(营销场景数据源!$AB:$AB,营销场景数据源!$C:$C,$B$29,营销场景数据源!$A:$A,BY2) -> 0 | BZ31: =SUM(CA31:DE31) -> 0 | CA31: =SUMIFS(营销场景数据源!$AB:$AB,营销场景数据源!$C:$C,$B$29,营销场景数据源!$A:$A,CA2) -> 0 | CB31: =SUMIFS(营销场景数据源!$AB:$AB,营销场景数据源!$C:$C,$B$29,营销场景数据源!$A:$A,CB2) -> 0 | CC31: =SUMIFS(营销场景数据源!$AB:$AB,营销场景数据源!$C:$C,$B$29,营销场景数据源!$A:$A,CC2) -> 0 | CD31: =SUMIFS(营销场景数据源!$AB:$AB,营销场景数据源!$C:$C,$B$29,营销场景数据源!$A:$A,CD2) -> 0 | CE31: =SUMIFS(营销场景数据源!$AB:$AB,营销场景数据源!$C:$C,$B$29,营销场景数据源!$A:$A,CE2) -> 0 | CF31: =SUMIFS(营销场景数据源!$AB:$AB,营销场景数据源!$C:$C,$B$29,营销场景数据源!$A:$A,CF2) -> 0 | CG31: =SUMIFS(营销场景数据源!$AB:$AB,营销场景数据源!$C:$C,$B$29,营销场景数据源!$A:$A,CG2) -> 0 | CH31: =SUMIFS(营销场景数据源!$AB:$AB,营销场景数据源!$C:$C,$B$29,营销场景数据源!$A:$A,CH2) -> 0 | ... DE31: =SUMIFS(营销场景数据源!$AB:$AB,营销场景数据源!$C:$C,$B$29,营销场景数据源!$A:$A,DE2) -> 0 | DF31: =SUM(DG31:EJ31) -> 106 | DG31: =SUMIFS(营销场景数据源!$AB:$AB,营销场景数据源!$C:$C,$B$29,营销场景数据源!$A:$A,DG2) -> 0 | DH31: =SUMIFS(营销场景数据源!$AB:$AB,营销场景数据源!$C:$C,$B$29,营销场景数据源!$A:$A,DH2) -> 0 | DI31: =SUMIFS(营销场景数据源!$AB:$AB,营销场景数据源!$C:$C,$B$29,营销场景数据源!$A:$A,DI2) -> 6 | DJ31: =SUMIFS(营销场景数据源!$AB:$AB,营销场景数据源!$C:$C,$B$29,营销场景数据源!$A:$A,DJ2) -> 2 | DK31: =SUMIFS(营销场景数据源!$AB:$AB,营销场景数据源!$C:$C,$B$29,营销场景数据源!$A:$A,DK2) -> 7 | DL31: =SUMIFS(营销场景数据源!$AB:$AB,营销场景数据源!$C:$C,$B$29,营销场景数据源!$A:$A,DL2) -> 1 | DM31: =SUMIFS(营销场景数据源!$AB:$AB,营销场景数据源!$C:$C,$B$29,营销场景数据源!$A:$A,DM2) -> 3 | DN31: =SUMIFS(营销场景数据源!$AB:$AB,营销场景数据源!$C:$C,$B$29,营销场景数据源!$A:$A,DN2) -> 3 | ... EJ31: =SUMIFS(营销场景数据源!$AB:$AB,营销场景数据源!$C:$C,$B$29,营销场景数据源!$A:$A,EJ2) -> 2 | EK31: =SUM(EL31:FP31) -> 147 | EL31: =SUMIFS(营销场景数据源!$AB:$AB,营销场景数据源!$C:$C,$B$29,营销场景数据源!$A:$A,EL2) -> 8 | EM31: =SUMIFS(营销场景数据源!$AB:$AB,营销场景数据源!$C:$C,$B$29,营销场景数据源!$A:$A,EM2) -> 4 | EN31: =SUMIFS(营销场景数据源!$AB:$AB,营销场景数据源!$C:$C,$B$29,营销场景数据源!$A:$A,EN2) -> 4 | EO31: =SUMIFS(营销场景数据源!$AB:$AB,营销场景数据源!$C:$C,$B$29,营销场景数据源!$A:$A,EO2) -> 7 | EP31: =SUMIFS(营销场景数据源!$AB:$AB,营销场景数据源!$C:$C,$B$29,营销场景数据源!$A:$A,EP2) -> 7 | EQ31: =SUMIFS(营销场景数据源!$AB:$AB,营销场景数据源!$C:$C,$B$29,营销场景数据源!$A:$A,EQ2) -> 4 | ER31: =SUMIFS(营销场景数据源!$AB:$AB,营销场景数据源!$C:$C,$B$29,营销场景数据源!$A:$A,ER2) -> 15 | ES31: =SUMIFS(营销场景数据源!$AB:$AB,营销场景数据源!$C:$C,$B$29,营销场景数据源!$A:$A,ES2) -> 8 | ... FP31: =SUMIFS(营销场景数据源!$AB:$AB,营销场景数据源!$C:$C,$B$29,营销场景数据源!$A:$A,FP2) -> 1 | FQ31: =SUM(FR31:GX31) -> 85 | FR31: =SUMIFS(营销场景数据源!$AB:$AB,营销场景数据源!$C:$C,$B$29,营销场景数据源!$A:$A,FR2) -> 3 | FS31: =SUMIFS(营销场景数据源!$AB:$AB,营销场景数据源!$C:$C,$B$29,营销场景数据源!$A:$A,FS2) -> 2 | FT31: =SUMIFS(营销场景数据源!$AB:$AB,营销场景数据源!$C:$C,$B$29,营销场景数据源!$A:$A,FT2) -> 2 | FU31: =SUMIFS(营销场景数据源!$AB:$AB,营销场景数据源!$C:$C,$B$29,营销场景数据源!$A:$A,FU2) -> 3 | FV31: =SUMIFS(营销场景数据源!$AB:$AB,营销场景数据源!$C:$C,$B$29,营销场景数据源!$A:$A,FV2) -> 2 | FW31: =SUMIFS(营销场景数据源!$AB:$AB,营销场景数据源!$C:$C,$B$29,营销场景数据源!$A:$A,FW2) -> 6 | FX31: =SUMIFS(营销场景数据源!$AB:$AB,营销场景数据源!$C:$C,$B$29,营销场景数据源!$A:$A,FX2) -> 6 | FY31: =SUMIFS(营销场景数据源!$AB:$AB,营销场景数据源!$C:$C,$B$29,营销场景数据源!$A:$A,FY2) -> 3 | ... GP31: =SUMIFS(营销场景数据源!$AB:$AB,营销场景数据源!$C:$C,$B$29,营销场景数据源!$A:$A,GP2) -> 0
C32: 总成交量 | D32: =SUM(E32:P32) -> #REF! | E32: =#REF! -> #REF! | F32: =#REF! -> #REF! | G32: =#REF! -> #REF! | H32: =#REF! -> #REF! | I32: =#REF! -> #REF! | J32: =#REF! -> #REF! | K32: =#REF! -> #REF! | L32: =#REF! -> #REF! | ... P32: =#REF! -> #REF! | Q32: =SUM(R32:AV32) -> 17 | R32: =SUMIFS(营销场景数据源!$U:$U,营销场景数据源!$C:$C,$B$29,营销场景数据源!$A:$A,R2) -> 1 | S32: =SUMIFS(营销场景数据源!$U:$U,营销场景数据源!$C:$C,$B$29,营销场景数据源!$A:$A,S2) -> 1 | T32: =SUMIFS(营销场景数据源!$U:$U,营销场景数据源!$C:$C,$B$29,营销场景数据源!$A:$A,T2) -> 1 | U32: =SUMIFS(营销场景数据源!$U:$U,营销场景数据源!$C:$C,$B$29,营销场景数据源!$A:$A,U2) -> 0 | V32: =SUMIFS(营销场景数据源!$U:$U,营销场景数据源!$C:$C,$B$29,营销场景数据源!$A:$A,V2) -> 1 | W32: =SUMIFS(营销场景数据源!$U:$U,营销场景数据源!$C:$C,$B$29,营销场景数据源!$A:$A,W2) -> 0 | X32: =SUMIFS(营销场景数据源!$U:$U,营销场景数据源!$C:$C,$B$29,营销场景数据源!$A:$A,X2) -> 0 | Y32: =SUMIFS(营销场景数据源!$U:$U,营销场景数据源!$C:$C,$B$29,营销场景数据源!$A:$A,Y2) -> 0 | ... AV32: =SUMIFS(营销场景数据源!$U:$U,营销场景数据源!$C:$C,$B$29,营销场景数据源!$A:$A,AV2) -> 0 | AW32: =SUM(AX32:BY32) -> 3 | AX32: =SUMIFS(营销场景数据源!$U:$U,营销场景数据源!$C:$C,$B$29,营销场景数据源!$A:$A,AX2) -> 0 | AY32: =SUMIFS(营销场景数据源!$U:$U,营销场景数据源!$C:$C,$B$29,营销场景数据源!$A:$A,AY2) -> 0 | AZ32: =SUMIFS(营销场景数据源!$U:$U,营销场景数据源!$C:$C,$B$29,营销场景数据源!$A:$A,AZ2) -> 2 | BA32: =SUMIFS(营销场景数据源!$U:$U,营销场景数据源!$C:$C,$B$29,营销场景数据源!$A:$A,BA2) -> 1 | BB32: =SUMIFS(营销场景数据源!$U:$U,营销场景数据源!$C:$C,$B$29,营销场景数据源!$A:$A,BB2) -> 0 | BC32: =SUMIFS(营销场景数据源!$U:$U,营销场景数据源!$C:$C,$B$29,营销场景数据源!$A:$A,BC2) -> 0 | BD32: =SUMIFS(营销场景数据源!$U:$U,营销场景数据源!$C:$C,$B$29,营销场景数据源!$A:$A,BD2) -> 0 | BE32: =SUMIFS(营销场景数据源!$U:$U,营销场景数据源!$C:$C,$B$29,营销场景数据源!$A:$A,BE2) -> 0 | ... BY32: =SUMIFS(营销场景数据源!$U:$U,营销场景数据源!$C:$C,$B$29,营销场景数据源!$A:$A,BY2) -> 0 | BZ32: =SUM(CA32:DE32) -> 0 | CA32: =SUMIFS(营销场景数据源!$U:$U,营销场景数据源!$C:$C,$B$29,营销场景数据源!$A:$A,CA2) -> 0 | CB32: =SUMIFS(营销场景数据源!$U:$U,营销场景数据源!$C:$C,$B$29,营销场景数据源!$A:$A,CB2) -> 0 | CC32: =SUMIFS(营销场景数据源!$U:$U,营销场景数据源!$C:$C,$B$29,营销场景数据源!$A:$A,CC2) -> 0 | CD32: =SUMIFS(营销场景数据源!$U:$U,营销场景数据源!$C:$C,$B$29,营销场景数据源!$A:$A,CD2) -> 0 | CE32: =SUMIFS(营销场景数据源!$U:$U,营销场景数据源!$C:$C,$B$29,营销场景数据源!$A:$A,CE2) -> 0 | CF32: =SUMIFS(营销场景数据源!$U:$U,营销场景数据源!$C:$C,$B$29,营销场景数据源!$A:$A,CF2) -> 0 | CG32: =SUMIFS(营销场景数据源!$U:$U,营销场景数据源!$C:$C,$B$29,营销场景数据源!$A:$A,CG2) -> 0 | CH32: =SUMIFS(营销场景数据源!$U:$U,营销场景数据源!$C:$C,$B$29,营销场景数据源!$A:$A,CH2) -> 0 | ... DE32: =SUMIFS(营销场景数据源!$U:$U,营销场景数据源!$C:$C,$B$29,营销场景数据源!$A:$A,DE2) -> 0 | DF32: =SUM(DG32:EJ32) -> 31 | DG32: =SUMIFS(营销场景数据源!$U:$U,营销场景数据源!$C:$C,$B$29,营销场景数据源!$A:$A,DG2) -> 0 | DH32: =SUMIFS(营销场景数据源!$U:$U,营销场景数据源!$C:$C,$B$29,营销场景数据源!$A:$A,DH2) -> 0 | DI32: =SUMIFS(营销场景数据源!$U:$U,营销场景数据源!$C:$C,$B$29,营销场景数据源!$A:$A,DI2) -> 0 | DJ32: =SUMIFS(营销场景数据源!$U:$U,营销场景数据源!$C:$C,$B$29,营销场景数据源!$A:$A,DJ2) -> 0 | DK32: =SUMIFS(营销场景数据源!$U:$U,营销场景数据源!$C:$C,$B$29,营销场景数据源!$A:$A,DK2) -> 3 | DL32: =SUMIFS(营销场景数据源!$U:$U,营销场景数据源!$C:$C,$B$29,营销场景数据源!$A:$A,DL2) -> 0 | DM32: =SUMIFS(营销场景数据源!$U:$U,营销场景数据源!$C:$C,$B$29,营销场景数据源!$A:$A,DM2) -> 1 | DN32: =SUMIFS(营销场景数据源!$U:$U,营销场景数据源!$C:$C,$B$29,营销场景数据源!$A:$A,DN2) -> 1 | ... EJ32: =SUMIFS(营销场景数据源!$U:$U,营销场景数据源!$C:$C,$B$29,营销场景数据源!$A:$A,EJ2) -> 0 | EK32: =SUM(EL32:FP32) -> 16 | EL32: =SUMIFS(营销场景数据源!$U:$U,营销场景数据源!$C:$C,$B$29,营销场景数据源!$A:$A,EL2) -> 0 | EM32: =SUMIFS(营销场景数据源!$U:$U,营销场景数据源!$C:$C,$B$29,营销场景数据源!$A:$A,EM2) -> 0 | EN32: =SUMIFS(营销场景数据源!$U:$U,营销场景数据源!$C:$C,$B$29,营销场景数据源!$A:$A,EN2) -> 0 | EO32: =SUMIFS(营销场景数据源!$U:$U,营销场景数据源!$C:$C,$B$29,营销场景数据源!$A:$A,EO2) -> 0 | EP32: =SUMIFS(营销场景数据源!$U:$U,营销场景数据源!$C:$C,$B$29,营销场景数据源!$A:$A,EP2) -> 0 | EQ32: =SUMIFS(营销场景数据源!$U:$U,营销场景数据源!$C:$C,$B$29,营销场景数据源!$A:$A,EQ2) -> 2 | ER32: =SUMIFS(营销场景数据源!$U:$U,营销场景数据源!$C:$C,$B$29,营销场景数据源!$A:$A,ER2) -> 0 | ES32: =SUMIFS(营销场景数据源!$U:$U,营销场景数据源!$C:$C,$B$29,营销场景数据源!$A:$A,ES2) -> 0 | ... FP32: =SUMIFS(营销场景数据源!$U:$U,营销场景数据源!$C:$C,$B$29,营销场景数据源!$A:$A,FP2) -> 0 | FQ32: =SUM(FR32:GX32) -> 10 | FR32: =SUMIFS(营销场景数据源!$U:$U,营销场景数据源!$C:$C,$B$29,营销场景数据源!$A:$A,FR2) -> 0 | FS32: =SUMIFS(营销场景数据源!$U:$U,营销场景数据源!$C:$C,$B$29,营销场景数据源!$A:$A,FS2) -> 1 | FT32: =SUMIFS(营销场景数据源!$U:$U,营销场景数据源!$C:$C,$B$29,营销场景数据源!$A:$A,FT2) -> 0 | FU32: =SUMIFS(营销场景数据源!$U:$U,营销场景数据源!$C:$C,$B$29,营销场景数据源!$A:$A,FU2) -> 1 | FV32: =SUMIFS(营销场景数据源!$U:$U,营销场景数据源!$C:$C,$B$29,营销场景数据源!$A:$A,FV2) -> 0 | FW32: =SUMIFS(营销场景数据源!$U:$U,营销场景数据源!$C:$C,$B$29,营销场景数据源!$A:$A,FW2) -> 1 | FX32: =SUMIFS(营销场景数据源!$U:$U,营销场景数据源!$C:$C,$B$29,营销场景数据源!$A:$A,FX2) -> 0 | FY32: =SUMIFS(营销场景数据源!$U:$U,营销场景数据源!$C:$C,$B$29,营销场景数据源!$A:$A,FY2) -> 2 | ... GP32: =SUMIFS(营销场景数据源!$U:$U,营销场景数据源!$C:$C,$B$29,营销场景数据源!$A:$A,GP2) -> 0
C33: 总成交金额 | D33: =SUM(E33:P33) -> #REF! | E33: =#REF! -> #REF! | F33: =#REF! -> #REF! | G33: =#REF! -> #REF! | H33: =#REF! -> #REF! | I33: =#REF! -> #REF! | J33: =#REF! -> #REF! | K33: =#REF! -> #REF! | L33: =#REF! -> #REF! | ... P33: =#REF! -> #REF! | Q33: =SUM(R33:AV33) -> 3334.85 | R33: =SUMIFS(营销场景数据源!$T:$T,营销场景数据源!$C:$C,$B$29,营销场景数据源!$A:$A,R2) -> 338.3 | S33: =SUMIFS(营销场景数据源!$T:$T,营销场景数据源!$C:$C,$B$29,营销场景数据源!$A:$A,S2) -> 82.17 | T33: =SUMIFS(营销场景数据源!$T:$T,营销场景数据源!$C:$C,$B$29,营销场景数据源!$A:$A,T2) -> 24.65 | U33: =SUMIFS(营销场景数据源!$T:$T,营销场景数据源!$C:$C,$B$29,营销场景数据源!$A:$A,U2) -> 0 | V33: =SUMIFS(营销场景数据源!$T:$T,营销场景数据源!$C:$C,$B$29,营销场景数据源!$A:$A,V2) -> 278.8 | W33: =SUMIFS(营销场景数据源!$T:$T,营销场景数据源!$C:$C,$B$29,营销场景数据源!$A:$A,W2) -> 0 | X33: =SUMIFS(营销场景数据源!$T:$T,营销场景数据源!$C:$C,$B$29,营销场景数据源!$A:$A,X2) -> 0 | Y33: =SUMIFS(营销场景数据源!$T:$T,营销场景数据源!$C:$C,$B$29,营销场景数据源!$A:$A,Y2) -> 0 | ... AV33: =SUMIFS(营销场景数据源!$T:$T,营销场景数据源!$C:$C,$B$29,营销场景数据源!$A:$A,AV2) -> 0 | AW33: =SUM(AX33:BY33) -> 78.85 | AX33: =SUMIFS(营销场景数据源!$T:$T,营销场景数据源!$C:$C,$B$29,营销场景数据源!$A:$A,AX2) -> 0 | AY33: =SUMIFS(营销场景数据源!$T:$T,营销场景数据源!$C:$C,$B$29,营销场景数据源!$A:$A,AY2) -> 0 | AZ33: =SUMIFS(营销场景数据源!$T:$T,营销场景数据源!$C:$C,$B$29,营销场景数据源!$A:$A,AZ2) -> 51.4 | BA33: =SUMIFS(营销场景数据源!$T:$T,营销场景数据源!$C:$C,$B$29,营销场景数据源!$A:$A,BA2) -> 27.45 | BB33: =SUMIFS(营销场景数据源!$T:$T,营销场景数据源!$C:$C,$B$29,营销场景数据源!$A:$A,BB2) -> 0 | BC33: =SUMIFS(营销场景数据源!$T:$T,营销场景数据源!$C:$C,$B$29,营销场景数据源!$A:$A,BC2) -> 0 | BD33: =SUMIFS(营销场景数据源!$T:$T,营销场景数据源!$C:$C,$B$29,营销场景数据源!$A:$A,BD2) -> 0 | BE33: =SUMIFS(营销场景数据源!$T:$T,营销场景数据源!$C:$C,$B$29,营销场景数据源!$A:$A,BE2) -> 0 | ... BY33: =SUMIFS(营销场景数据源!$T:$T,营销场景数据源!$C:$C,$B$29,营销场景数据源!$A:$A,BY2) -> 0 | BZ33: =SUM(CA33:DE33) -> 0 | CA33: =SUMIFS(营销场景数据源!$T:$T,营销场景数据源!$C:$C,$B$29,营销场景数据源!$A:$A,CA2) -> 0 | CB33: =SUMIFS(营销场景数据源!$T:$T,营销场景数据源!$C:$C,$B$29,营销场景数据源!$A:$A,CB2) -> 0 | CC33: =SUMIFS(营销场景数据源!$T:$T,营销场景数据源!$C:$C,$B$29,营销场景数据源!$A:$A,CC2) -> 0 | CD33: =SUMIFS(营销场景数据源!$T:$T,营销场景数据源!$C:$C,$B$29,营销场景数据源!$A:$A,CD2) -> 0 | CE33: =SUMIFS(营销场景数据源!$T:$T,营销场景数据源!$C:$C,$B$29,营销场景数据源!$A:$A,CE2) -> 0 | CF33: =SUMIFS(营销场景数据源!$T:$T,营销场景数据源!$C:$C,$B$29,营销场景数据源!$A:$A,CF2) -> 0 | CG33: =SUMIFS(营销场景数据源!$T:$T,营销场景数据源!$C:$C,$B$29,营销场景数据源!$A:$A,CG2) -> 0 | CH33: =SUMIFS(营销场景数据源!$T:$T,营销场景数据源!$C:$C,$B$29,营销场景数据源!$A:$A,CH2) -> 0 | ... DE33: =SUMIFS(营销场景数据源!$T:$T,营销场景数据源!$C:$C,$B$29,营销场景数据源!$A:$A,DE2) -> 0 | DF33: =SUM(DG33:EJ33) -> 5325.16 | DG33: =SUMIFS(营销场景数据源!$T:$T,营销场景数据源!$C:$C,$B$29,营销场景数据源!$A:$A,DG2) -> 0 | DH33: =SUMIFS(营销场景数据源!$T:$T,营销场景数据源!$C:$C,$B$29,营销场景数据源!$A:$A,DH2) -> 0 | DI33: =SUMIFS(营销场景数据源!$T:$T,营销场景数据源!$C:$C,$B$29,营销场景数据源!$A:$A,DI2) -> 0 | DJ33: =SUMIFS(营销场景数据源!$T:$T,营销场景数据源!$C:$C,$B$29,营销场景数据源!$A:$A,DJ2) -> 0 | DK33: =SUMIFS(营销场景数据源!$T:$T,营销场景数据源!$C:$C,$B$29,营销场景数据源!$A:$A,DK2) -> 709.86 | DL33: =SUMIFS(营销场景数据源!$T:$T,营销场景数据源!$C:$C,$B$29,营销场景数据源!$A:$A,DL2) -> 0 | DM33: =SUMIFS(营销场景数据源!$T:$T,营销场景数据源!$C:$C,$B$29,营销场景数据源!$A:$A,DM2) -> 43.9 | DN33: =SUMIFS(营销场景数据源!$T:$T,营销场景数据源!$C:$C,$B$29,营销场景数据源!$A:$A,DN2) -> 233.93 | ... EJ33: =SUMIFS(营销场景数据源!$T:$T,营销场景数据源!$C:$C,$B$29,营销场景数据源!$A:$A,EJ2) -> 0 | EK33: =SUM(EL33:FP33) -> 1704.15 | EL33: =SUMIFS(营销场景数据源!$T:$T,营销场景数据源!$C:$C,$B$29,营销场景数据源!$A:$A,EL2) -> 0 | EM33: =SUMIFS(营销场景数据源!$T:$T,营销场景数据源!$C:$C,$B$29,营销场景数据源!$A:$A,EM2) -> 0 | EN33: =SUMIFS(营销场景数据源!$T:$T,营销场景数据源!$C:$C,$B$29,营销场景数据源!$A:$A,EN2) -> 0 | EO33: =SUMIFS(营销场景数据源!$T:$T,营销场景数据源!$C:$C,$B$29,营销场景数据源!$A:$A,EO2) -> 0 | EP33: =SUMIFS(营销场景数据源!$T:$T,营销场景数据源!$C:$C,$B$29,营销场景数据源!$A:$A,EP2) -> 0 | EQ33: =SUMIFS(营销场景数据源!$T:$T,营销场景数据源!$C:$C,$B$29,营销场景数据源!$A:$A,EQ2) -> 355.38 | ER33: =SUMIFS(营销场景数据源!$T:$T,营销场景数据源!$C:$C,$B$29,营销场景数据源!$A:$A,ER2) -> 0 | ES33: =SUMIFS(营销场景数据源!$T:$T,营销场景数据源!$C:$C,$B$29,营销场景数据源!$A:$A,ES2) -> 0 | ... FP33: =SUMIFS(营销场景数据源!$T:$T,营销场景数据源!$C:$C,$B$29,营销场景数据源!$A:$A,FP2) -> 0 | FQ33: =SUM(FR33:GX33) -> 1100.06 | FR33: =SUMIFS(营销场景数据源!$T:$T,营销场景数据源!$C:$C,$B$29,营销场景数据源!$A:$A,FR2) -> 0 | FS33: =SUMIFS(营销场景数据源!$T:$T,营销场景数据源!$C:$C,$B$29,营销场景数据源!$A:$A,FS2) -> 90 | FT33: =SUMIFS(营销场景数据源!$T:$T,营销场景数据源!$C:$C,$B$29,营销场景数据源!$A:$A,FT2) -> 0 | FU33: =SUMIFS(营销场景数据源!$T:$T,营销场景数据源!$C:$C,$B$29,营销场景数据源!$A:$A,FU2) -> 138.64 | FV33: =SUMIFS(营销场景数据源!$T:$T,营销场景数据源!$C:$C,$B$29,营销场景数据源!$A:$A,FV2) -> 0 | FW33: =SUMIFS(营销场景数据源!$T:$T,营销场景数据源!$C:$C,$B$29,营销场景数据源!$A:$A,FW2) -> 77.4 | FX33: =SUMIFS(营销场景数据源!$T:$T,营销场景数据源!$C:$C,$B$29,营销场景数据源!$A:$A,FX2) -> 0 | FY33: =SUMIFS(营销场景数据源!$T:$T,营销场景数据源!$C:$C,$B$29,营销场景数据源!$A:$A,FY2) -> 277.28 | ... GP33: =SUMIFS(营销场景数据源!$T:$T,营销场景数据源!$C:$C,$B$29,营销场景数据源!$A:$A,GP2) -> 0
C34: 点击单价 | D34: =IFERROR(D29/D30,0) -> 0 | E34: =IFERROR(E29/E30,0) -> 0 | F34: =IFERROR(F29/F30,0) -> 0 | G34: =IFERROR(G29/G30,0) -> 0 | H34: =IFERROR(H29/H30,0) -> 0 | I34: =IFERROR(I29/I30,0) -> 0 | J34: =IFERROR(J29/J30,0) -> 0 | K34: =IFERROR(K29/K30,0) -> 0 | ... GP34: =IFERROR(GP29/GP30,0) -> 0
C35: 加购成本 | D35: =IFERROR(D29/D31,0) -> 0 | E35: =IFERROR(E29/E31,0) -> 0 | F35: =IFERROR(F29/F31,0) -> 0 | G35: =IFERROR(G29/G31,0) -> 0 | H35: =IFERROR(H29/H31,0) -> 0 | I35: =IFERROR(I29/I31,0) -> 0 | J35: =IFERROR(J29/J31,0) -> 0 | K35: =IFERROR(K29/K31,0) -> 0 | ... GP35: =IFERROR(GP29/GP31,0) -> 0
C36: ROI | D36: =IFERROR(D33/D29,0) -> 0 | E36: =IFERROR(E33/E29,0) -> 0 | F36: =IFERROR(F33/F29,0) -> 0 | G36: =IFERROR(G33/G29,0) -> 0 | H36: =IFERROR(H33/H29,0) -> 0 | I36: =IFERROR(I33/I29,0) -> 0 | J36: =IFERROR(J33/J29,0) -> 0 | K36: =IFERROR(K33/K29,0) -> 0 | ... GP36: =IFERROR(GP33/GP29,0) -> 0
C37: 费用占比 | D37: =D29/D$130 -> #REF! | E37: =E29/E$130 -> #REF! | F37: =F29/F$130 -> #REF! | G37: =G29/G$130 -> #REF! | H37: =H29/H$130 -> #REF! | I37: =I29/I$130 -> #REF! | J37: =J29/J$130 -> #REF! | K37: =K29/K$130 -> #REF! | ... GP37: =GP29/GP$130 -> #DIV/0!
B38: 货品全站推广 | C38: 花费 | D38: =SUM(E38:P38) -> #REF! | E38: =#REF! -> #REF! | F38: =#REF! -> #REF! | G38: =#REF! -> #REF! | H38: =#REF! -> #REF! | I38: =#REF! -> #REF! | J38: =#REF! -> #REF! | K38: =#REF! -> #REF! | L38: =#REF! -> #REF! | ... P38: =#REF! -> #REF! | Q38: =SUM(R38:AV38) -> 3316.56 | R38: =SUMIFS(营销场景数据源!$H:$H,营销场景数据源!$C:$C,$B$38,营销场景数据源!$A:$A,R2) -> 123.17 | S38: =SUMIFS(营销场景数据源!$H:$H,营销场景数据源!$C:$C,$B$38,营销场景数据源!$A:$A,S2) -> 131.99 | T38: =SUMIFS(营销场景数据源!$H:$H,营销场景数据源!$C:$C,$B$38,营销场景数据源!$A:$A,T2) -> 137.45 | U38: =SUMIFS(营销场景数据源!$H:$H,营销场景数据源!$C:$C,$B$38,营销场景数据源!$A:$A,U2) -> 130.88 | V38: =SUMIFS(营销场景数据源!$H:$H,营销场景数据源!$C:$C,$B$38,营销场景数据源!$A:$A,V2) -> 106.59 | W38: =SUMIFS(营销场景数据源!$H:$H,营销场景数据源!$C:$C,$B$38,营销场景数据源!$A:$A,W2) -> 111.5 | X38: =SUMIFS(营销场景数据源!$H:$H,营销场景数据源!$C:$C,$B$38,营销场景数据源!$A:$A,X2) -> 56.79 | Y38: =SUMIFS(营销场景数据源!$H:$H,营销场景数据源!$C:$C,$B$38,营销场景数据源!$A:$A,Y2) -> 132.27 | ... AV38: =SUMIFS(营销场景数据源!$H:$H,营销场景数据源!$C:$C,$B$38,营销场景数据源!$A:$A,AV2) -> 80 | AW38: =SUM(AX38:BY38) -> 2078.67 | AX38: =SUMIFS(营销场景数据源!$H:$H,营销场景数据源!$C:$C,$B$38,营销场景数据源!$A:$A,AX2) -> 73.48 | AY38: =SUMIFS(营销场景数据源!$H:$H,营销场景数据源!$C:$C,$B$38,营销场景数据源!$A:$A,AY2) -> 80 | AZ38: =SUMIFS(营销场景数据源!$H:$H,营销场景数据源!$C:$C,$B$38,营销场景数据源!$A:$A,AZ2) -> 72.34 | BA38: =SUMIFS(营销场景数据源!$H:$H,营销场景数据源!$C:$C,$B$38,营销场景数据源!$A:$A,BA2) -> 66.86 | BB38: =SUMIFS(营销场景数据源!$H:$H,营销场景数据源!$C:$C,$B$38,营销场景数据源!$A:$A,BB2) -> 80 | BC38: =SUMIFS(营销场景数据源!$H:$H,营销场景数据源!$C:$C,$B$38,营销场景数据源!$A:$A,BC2) -> 75.5 | BD38: =SUMIFS(营销场景数据源!$H:$H,营销场景数据源!$C:$C,$B$38,营销场景数据源!$A:$A,BD2) -> 80 | BE38: =SUMIFS(营销场景数据源!$H:$H,营销场景数据源!$C:$C,$B$38,营销场景数据源!$A:$A,BE2) -> 80 | ... BY38: =SUMIFS(营销场景数据源!$H:$H,营销场景数据源!$C:$C,$B$38,营销场景数据源!$A:$A,BY2) -> 80 | BZ38: =SUM(CA38:DE38) -> 2480.16 | CA38: =SUMIFS(营销场景数据源!$H:$H,营销场景数据源!$C:$C,$B$38,营销场景数据源!$A:$A,CA2) -> 69.93 | CB38: =SUMIFS(营销场景数据源!$H:$H,营销场景数据源!$C:$C,$B$38,营销场景数据源!$A:$A,CB2) -> 79.56 | CC38: =SUMIFS(营销场景数据源!$H:$H,营销场景数据源!$C:$C,$B$38,营销场景数据源!$A:$A,CC2) -> 80 | CD38: =SUMIFS(营销场景数据源!$H:$H,营销场景数据源!$C:$C,$B$38,营销场景数据源!$A:$A,CD2) -> 80 | CE38: =SUMIFS(营销场景数据源!$H:$H,营销场景数据源!$C:$C,$B$38,营销场景数据源!$A:$A,CE2) -> 66.54 | CF38: =SUMIFS(营销场景数据源!$H:$H,营销场景数据源!$C:$C,$B$38,营销场景数据源!$A:$A,CF2) -> 80 | CG38: =SUMIFS(营销场景数据源!$H:$H,营销场景数据源!$C:$C,$B$38,营销场景数据源!$A:$A,CG2) -> 78.73 | CH38: =SUMIFS(营销场景数据源!$H:$H,营销场景数据源!$C:$C,$B$38,营销场景数据源!$A:$A,CH2) -> 80 | ... DE38: =SUMIFS(营销场景数据源!$H:$H,营销场景数据源!$C:$C,$B$38,营销场景数据源!$A:$A,DE2) -> 48.42 | DF38: =SUM(DG38:EJ38) -> 1847.72 | DG38: =SUMIFS(营销场景数据源!$H:$H,营销场景数据源!$C:$C,$B$38,营销场景数据源!$A:$A,DG2) -> 49.76 | DH38: =SUMIFS(营销场景数据源!$H:$H,营销场景数据源!$C:$C,$B$38,营销场景数据源!$A:$A,DH2) -> 60 | DI38: =SUMIFS(营销场景数据源!$H:$H,营销场景数据源!$C:$C,$B$38,营销场景数据源!$A:$A,DI2) -> 60 | DJ38: =SUMIFS(营销场景数据源!$H:$H,营销场景数据源!$C:$C,$B$38,营销场景数据源!$A:$A,DJ2) -> 48.02 | DK38: =SUMIFS(营销场景数据源!$H:$H,营销场景数据源!$C:$C,$B$38,营销场景数据源!$A:$A,DK2) -> 60 | DL38: =SUMIFS(营销场景数据源!$H:$H,营销场景数据源!$C:$C,$B$38,营销场景数据源!$A:$A,DL2) -> 46.25 | DM38: =SUMIFS(营销场景数据源!$H:$H,营销场景数据源!$C:$C,$B$38,营销场景数据源!$A:$A,DM2) -> 91 | DN38: =SUMIFS(营销场景数据源!$H:$H,营销场景数据源!$C:$C,$B$38,营销场景数据源!$A:$A,DN2) -> 55.65 | ... EJ38: =SUMIFS(营销场景数据源!$H:$H,营销场景数据源!$C:$C,$B$38,营销场景数据源!$A:$A,EJ2) -> 40.19 | EK38: =SUM(EL38:FP38) -> 1246.47 | EL38: =SUMIFS(营销场景数据源!$H:$H,营销场景数据源!$C:$C,$B$38,营销场景数据源!$A:$A,EL2) -> 36.33 | EM38: =SUMIFS(营销场景数据源!$H:$H,营销场景数据源!$C:$C,$B$38,营销场景数据源!$A:$A,EM2) -> 32.63 | EN38: =SUMIFS(营销场景数据源!$H:$H,营销场景数据源!$C:$C,$B$38,营销场景数据源!$A:$A,EN2) -> 35.22 | EO38: =SUMIFS(营销场景数据源!$H:$H,营销场景数据源!$C:$C,$B$38,营销场景数据源!$A:$A,EO2) -> 34.43 | EP38: =SUMIFS(营销场景数据源!$H:$H,营销场景数据源!$C:$C,$B$38,营销场景数据源!$A:$A,EP2) -> 38.06 | EQ38: =SUMIFS(营销场景数据源!$H:$H,营销场景数据源!$C:$C,$B$38,营销场景数据源!$A:$A,EQ2) -> 41 | ER38: =SUMIFS(营销场景数据源!$H:$H,营销场景数据源!$C:$C,$B$38,营销场景数据源!$A:$A,ER2) -> 35.96 | ES38: =SUMIFS(营销场景数据源!$H:$H,营销场景数据源!$C:$C,$B$38,营销场景数据源!$A:$A,ES2) -> 34.16 | ... FP38: =SUMIFS(营销场景数据源!$H:$H,营销场景数据源!$C:$C,$B$38,营销场景数据源!$A:$A,FP2) -> 35.46 | FQ38: =SUM(FR38:GX38) -> 953.79 | FR38: =SUMIFS(营销场景数据源!$H:$H,营销场景数据源!$C:$C,$B$38,营销场景数据源!$A:$A,FR2) -> 50 | FS38: =SUMIFS(营销场景数据源!$H:$H,营销场景数据源!$C:$C,$B$38,营销场景数据源!$A:$A,FS2) -> 47.8 | FT38: =SUMIFS(营销场景数据源!$H:$H,营销场景数据源!$C:$C,$B$38,营销场景数据源!$A:$A,FT2) -> 50 | FU38: =SUMIFS(营销场景数据源!$H:$H,营销场景数据源!$C:$C,$B$38,营销场景数据源!$A:$A,FU2) -> 49.95 | FV38: =SUMIFS(营销场景数据源!$H:$H,营销场景数据源!$C:$C,$B$38,营销场景数据源!$A:$A,FV2) -> 42.68 | FW38: =SUMIFS(营销场景数据源!$H:$H,营销场景数据源!$C:$C,$B$38,营销场景数据源!$A:$A,FW2) -> 48.03 | FX38: =SUMIFS(营销场景数据源!$H:$H,营销场景数据源!$C:$C,$B$38,营销场景数据源!$A:$A,FX2) -> 50 | FY38: =SUMIFS(营销场景数据源!$H:$H,营销场景数据源!$C:$C,$B$38,营销场景数据源!$A:$A,FY2) -> 39.75 | ... GP38: =SUMIFS(营销场景数据源!$H:$H,营销场景数据源!$C:$C,$B$38,营销场景数据源!$A:$A,GP2) -> 0
C39: 点击量 | D39: =SUM(E39:P39) -> #REF! | E39: =#REF! -> #REF! | F39: =#REF! -> #REF! | G39: =#REF! -> #REF! | H39: =#REF! -> #REF! | I39: =#REF! -> #REF! | J39: =#REF! -> #REF! | K39: =#REF! -> #REF! | L39: =#REF! -> #REF! | ... P39: =#REF! -> #REF! | Q39: =SUM(R39:AV39) -> 1320 | R39: =SUMIFS(营销场景数据源!$G:$G,营销场景数据源!$C:$C,$B$38,营销场景数据源!$A:$A,R2) -> 50 | S39: =SUMIFS(营销场景数据源!$G:$G,营销场景数据源!$C:$C,$B$38,营销场景数据源!$A:$A,S2) -> 77 | T39: =SUMIFS(营销场景数据源!$G:$G,营销场景数据源!$C:$C,$B$38,营销场景数据源!$A:$A,T2) -> 63 | U39: =SUMIFS(营销场景数据源!$G:$G,营销场景数据源!$C:$C,$B$38,营销场景数据源!$A:$A,U2) -> 70 | V39: =SUMIFS(营销场景数据源!$G:$G,营销场景数据源!$C:$C,$B$38,营销场景数据源!$A:$A,V2) -> 51 | W39: =SUMIFS(营销场景数据源!$G:$G,营销场景数据源!$C:$C,$B$38,营销场景数据源!$A:$A,W2) -> 45 | X39: =SUMIFS(营销场景数据源!$G:$G,营销场景数据源!$C:$C,$B$38,营销场景数据源!$A:$A,X2) -> 41 | Y39: =SUMIFS(营销场景数据源!$G:$G,营销场景数据源!$C:$C,$B$38,营销场景数据源!$A:$A,Y2) -> 32 | ... AV39: =SUMIFS(营销场景数据源!$G:$G,营销场景数据源!$C:$C,$B$38,营销场景数据源!$A:$A,AV2) -> 25 | AW39: =SUM(AX39:BY39) -> 1050 | AX39: =SUMIFS(营销场景数据源!$G:$G,营销场景数据源!$C:$C,$B$38,营销场景数据源!$A:$A,AX2) -> 39 | AY39: =SUMIFS(营销场景数据源!$G:$G,营销场景数据源!$C:$C,$B$38,营销场景数据源!$A:$A,AY2) -> 50 | AZ39: =SUMIFS(营销场景数据源!$G:$G,营销场景数据源!$C:$C,$B$38,营销场景数据源!$A:$A,AZ2) -> 37 | BA39: =SUMIFS(营销场景数据源!$G:$G,营销场景数据源!$C:$C,$B$38,营销场景数据源!$A:$A,BA2) -> 48 | BB39: =SUMIFS(营销场景数据源!$G:$G,营销场景数据源!$C:$C,$B$38,营销场景数据源!$A:$A,BB2) -> 49 | BC39: =SUMIFS(营销场景数据源!$G:$G,营销场景数据源!$C:$C,$B$38,营销场景数据源!$A:$A,BC2) -> 38 | BD39: =SUMIFS(营销场景数据源!$G:$G,营销场景数据源!$C:$C,$B$38,营销场景数据源!$A:$A,BD2) -> 14 | BE39: =SUMIFS(营销场景数据源!$G:$G,营销场景数据源!$C:$C,$B$38,营销场景数据源!$A:$A,BE2) -> 15 | ... BY39: =SUMIFS(营销场景数据源!$G:$G,营销场景数据源!$C:$C,$B$38,营销场景数据源!$A:$A,BY2) -> 10 | BZ39: =SUM(CA39:DE39) -> 1376 | CA39: =SUMIFS(营销场景数据源!$G:$G,营销场景数据源!$C:$C,$B$38,营销场景数据源!$A:$A,CA2) -> 34 | CB39: =SUMIFS(营销场景数据源!$G:$G,营销场景数据源!$C:$C,$B$38,营销场景数据源!$A:$A,CB2) -> 28 | CC39: =SUMIFS(营销场景数据源!$G:$G,营销场景数据源!$C:$C,$B$38,营销场景数据源!$A:$A,CC2) -> 41 | CD39: =SUMIFS(营销场景数据源!$G:$G,营销场景数据源!$C:$C,$B$38,营销场景数据源!$A:$A,CD2) -> 15 | CE39: =SUMIFS(营销场景数据源!$G:$G,营销场景数据源!$C:$C,$B$38,营销场景数据源!$A:$A,CE2) -> 36 | CF39: =SUMIFS(营销场景数据源!$G:$G,营销场景数据源!$C:$C,$B$38,营销场景数据源!$A:$A,CF2) -> 35 | CG39: =SUMIFS(营销场景数据源!$G:$G,营销场景数据源!$C:$C,$B$38,营销场景数据源!$A:$A,CG2) -> 47 | CH39: =SUMIFS(营销场景数据源!$G:$G,营销场景数据源!$C:$C,$B$38,营销场景数据源!$A:$A,CH2) -> 28 | ... DE39: =SUMIFS(营销场景数据源!$G:$G,营销场景数据源!$C:$C,$B$38,营销场景数据源!$A:$A,DE2) -> 33 | DF39: =SUM(DG39:EJ39) -> 1044 | DG39: =SUMIFS(营销场景数据源!$G:$G,营销场景数据源!$C:$C,$B$38,营销场景数据源!$A:$A,DG2) -> 24 | DH39: =SUMIFS(营销场景数据源!$G:$G,营销场景数据源!$C:$C,$B$38,营销场景数据源!$A:$A,DH2) -> 25 | DI39: =SUMIFS(营销场景数据源!$G:$G,营销场景数据源!$C:$C,$B$38,营销场景数据源!$A:$A,DI2) -> 25 | DJ39: =SUMIFS(营销场景数据源!$G:$G,营销场景数据源!$C:$C,$B$38,营销场景数据源!$A:$A,DJ2) -> 62 | DK39: =SUMIFS(营销场景数据源!$G:$G,营销场景数据源!$C:$C,$B$38,营销场景数据源!$A:$A,DK2) -> 16 | DL39: =SUMIFS(营销场景数据源!$G:$G,营销场景数据源!$C:$C,$B$38,营销场景数据源!$A:$A,DL2) -> 45 | DM39: =SUMIFS(营销场景数据源!$G:$G,营销场景数据源!$C:$C,$B$38,营销场景数据源!$A:$A,DM2) -> 40 | DN39: =SUMIFS(营销场景数据源!$G:$G,营销场景数据源!$C:$C,$B$38,营销场景数据源!$A:$A,DN2) -> 44 | ... EJ39: =SUMIFS(营销场景数据源!$G:$G,营销场景数据源!$C:$C,$B$38,营销场景数据源!$A:$A,EJ2) -> 33 | EK39: =SUM(EL39:FP39) -> 796 | EL39: =SUMIFS(营销场景数据源!$G:$G,营销场景数据源!$C:$C,$B$38,营销场景数据源!$A:$A,EL2) -> 34 | EM39: =SUMIFS(营销场景数据源!$G:$G,营销场景数据源!$C:$C,$B$38,营销场景数据源!$A:$A,EM2) -> 30 | EN39: =SUMIFS(营销场景数据源!$G:$G,营销场景数据源!$C:$C,$B$38,营销场景数据源!$A:$A,EN2) -> 28 | EO39: =SUMIFS(营销场景数据源!$G:$G,营销场景数据源!$C:$C,$B$38,营销场景数据源!$A:$A,EO2) -> 27 | EP39: =SUMIFS(营销场景数据源!$G:$G,营销场景数据源!$C:$C,$B$38,营销场景数据源!$A:$A,EP2) -> 28 | EQ39: =SUMIFS(营销场景数据源!$G:$G,营销场景数据源!$C:$C,$B$38,营销场景数据源!$A:$A,EQ2) -> 23 | ER39: =SUMIFS(营销场景数据源!$G:$G,营销场景数据源!$C:$C,$B$38,营销场景数据源!$A:$A,ER2) -> 21 | ES39: =SUMIFS(营销场景数据源!$G:$G,营销场景数据源!$C:$C,$B$38,营销场景数据源!$A:$A,ES2) -> 24 | ... FP39: =SUMIFS(营销场景数据源!$G:$G,营销场景数据源!$C:$C,$B$38,营销场景数据源!$A:$A,FP2) -> 31 | FQ39: =SUM(FR39:GX39) -> 698 | FR39: =SUMIFS(营销场景数据源!$G:$G,营销场景数据源!$C:$C,$B$38,营销场景数据源!$A:$A,FR2) -> 25 | FS39: =SUMIFS(营销场景数据源!$G:$G,营销场景数据源!$C:$C,$B$38,营销场景数据源!$A:$A,FS2) -> 25 | FT39: =SUMIFS(营销场景数据源!$G:$G,营销场景数据源!$C:$C,$B$38,营销场景数据源!$A:$A,FT2) -> 39 | FU39: =SUMIFS(营销场景数据源!$G:$G,营销场景数据源!$C:$C,$B$38,营销场景数据源!$A:$A,FU2) -> 23 | FV39: =SUMIFS(营销场景数据源!$G:$G,营销场景数据源!$C:$C,$B$38,营销场景数据源!$A:$A,FV2) -> 59 | FW39: =SUMIFS(营销场景数据源!$G:$G,营销场景数据源!$C:$C,$B$38,营销场景数据源!$A:$A,FW2) -> 88 | FX39: =SUMIFS(营销场景数据源!$G:$G,营销场景数据源!$C:$C,$B$38,营销场景数据源!$A:$A,FX2) -> 68 | FY39: =SUMIFS(营销场景数据源!$G:$G,营销场景数据源!$C:$C,$B$38,营销场景数据源!$A:$A,FY2) -> 21 | ... GP39: =SUMIFS(营销场景数据源!$G:$G,营销场景数据源!$C:$C,$B$38,营销场景数据源!$A:$A,GP2) -> 0
C40: 总购物车数 | D40: =SUM(E40:P40) -> #REF! | E40: =#REF! -> #REF! | F40: =#REF! -> #REF! | G40: =#REF! -> #REF! | H40: =#REF! -> #REF! | I40: =#REF! -> #REF! | J40: =#REF! -> #REF! | K40: =#REF! -> #REF! | L40: =#REF! -> #REF! | ... P40: =#REF! -> #REF! | Q40: =SUM(R40:AV40) -> 138 | R40: =SUMIFS(营销场景数据源!$AB:$AB,营销场景数据源!$C:$C,$B$38,营销场景数据源!$A:$A,R2) -> 4 | S40: =SUMIFS(营销场景数据源!$AB:$AB,营销场景数据源!$C:$C,$B$38,营销场景数据源!$A:$A,S2) -> 4 | T40: =SUMIFS(营销场景数据源!$AB:$AB,营销场景数据源!$C:$C,$B$38,营销场景数据源!$A:$A,T2) -> 6 | U40: =SUMIFS(营销场景数据源!$AB:$AB,营销场景数据源!$C:$C,$B$38,营销场景数据源!$A:$A,U2) -> 2 | V40: =SUMIFS(营销场景数据源!$AB:$AB,营销场景数据源!$C:$C,$B$38,营销场景数据源!$A:$A,V2) -> 8 | W40: =SUMIFS(营销场景数据源!$AB:$AB,营销场景数据源!$C:$C,$B$38,营销场景数据源!$A:$A,W2) -> 0 | X40: =SUMIFS(营销场景数据源!$AB:$AB,营销场景数据源!$C:$C,$B$38,营销场景数据源!$A:$A,X2) -> 2 | Y40: =SUMIFS(营销场景数据源!$AB:$AB,营销场景数据源!$C:$C,$B$38,营销场景数据源!$A:$A,Y2) -> 9 | ... AV40: =SUMIFS(营销场景数据源!$AB:$AB,营销场景数据源!$C:$C,$B$38,营销场景数据源!$A:$A,AV2) -> 1 | AW40: =SUM(AX40:BY40) -> 123 | AX40: =SUMIFS(营销场景数据源!$AB:$AB,营销场景数据源!$C:$C,$B$38,营销场景数据源!$A:$A,AX2) -> 5 | AY40: =SUMIFS(营销场景数据源!$AB:$AB,营销场景数据源!$C:$C,$B$38,营销场景数据源!$A:$A,AY2) -> 8 | AZ40: =SUMIFS(营销场景数据源!$AB:$AB,营销场景数据源!$C:$C,$B$38,营销场景数据源!$A:$A,AZ2) -> 6 | BA40: =SUMIFS(营销场景数据源!$AB:$AB,营销场景数据源!$C:$C,$B$38,营销场景数据源!$A:$A,BA2) -> 0 | BB40: =SUMIFS(营销场景数据源!$AB:$AB,营销场景数据源!$C:$C,$B$38,营销场景数据源!$A:$A,BB2) -> 11 | BC40: =SUMIFS(营销场景数据源!$AB:$AB,营销场景数据源!$C:$C,$B$38,营销场景数据源!$A:$A,BC2) -> 15 | BD40: =SUMIFS(营销场景数据源!$AB:$AB,营销场景数据源!$C:$C,$B$38,营销场景数据源!$A:$A,BD2) -> 4 | BE40: =SUMIFS(营销场景数据源!$AB:$AB,营销场景数据源!$C:$C,$B$38,营销场景数据源!$A:$A,BE2) -> 2 | ... BY40: =SUMIFS(营销场景数据源!$AB:$AB,营销场景数据源!$C:$C,$B$38,营销场景数据源!$A:$A,BY2) -> 2 | BZ40: =SUM(CA40:DE40) -> 228 | CA40: =SUMIFS(营销场景数据源!$AB:$AB,营销场景数据源!$C:$C,$B$38,营销场景数据源!$A:$A,CA2) -> 1 | CB40: =SUMIFS(营销场景数据源!$AB:$AB,营销场景数据源!$C:$C,$B$38,营销场景数据源!$A:$A,CB2) -> 3 | CC40: =SUMIFS(营销场景数据源!$AB:$AB,营销场景数据源!$C:$C,$B$38,营销场景数据源!$A:$A,CC2) -> 4 | CD40: =SUMIFS(营销场景数据源!$AB:$AB,营销场景数据源!$C:$C,$B$38,营销场景数据源!$A:$A,CD2) -> 5 | CE40: =SUMIFS(营销场景数据源!$AB:$AB,营销场景数据源!$C:$C,$B$38,营销场景数据源!$A:$A,CE2) -> 5 | CF40: =SUMIFS(营销场景数据源!$AB:$AB,营销场景数据源!$C:$C,$B$38,营销场景数据源!$A:$A,CF2) -> 3 | CG40: =SUMIFS(营销场景数据源!$AB:$AB,营销场景数据源!$C:$C,$B$38,营销场景数据源!$A:$A,CG2) -> 7 | CH40: =SUMIFS(营销场景数据源!$AB:$AB,营销场景数据源!$C:$C,$B$38,营销场景数据源!$A:$A,CH2) -> 17 | ... DE40: =SUMIFS(营销场景数据源!$AB:$AB,营销场景数据源!$C:$C,$B$38,营销场景数据源!$A:$A,DE2) -> 0 | DF40: =SUM(DG40:EJ40) -> 77 | DG40: =SUMIFS(营销场景数据源!$AB:$AB,营销场景数据源!$C:$C,$B$38,营销场景数据源!$A:$A,DG2) -> 1 | DH40: =SUMIFS(营销场景数据源!$AB:$AB,营销场景数据源!$C:$C,$B$38,营销场景数据源!$A:$A,DH2) -> 0 | DI40: =SUMIFS(营销场景数据源!$AB:$AB,营销场景数据源!$C:$C,$B$38,营销场景数据源!$A:$A,DI2) -> 1 | DJ40: =SUMIFS(营销场景数据源!$AB:$AB,营销场景数据源!$C:$C,$B$38,营销场景数据源!$A:$A,DJ2) -> 4 | DK40: =SUMIFS(营销场景数据源!$AB:$AB,营销场景数据源!$C:$C,$B$38,营销场景数据源!$A:$A,DK2) -> 2 | DL40: =SUMIFS(营销场景数据源!$AB:$AB,营销场景数据源!$C:$C,$B$38,营销场景数据源!$A:$A,DL2) -> 5 | DM40: =SUMIFS(营销场景数据源!$AB:$AB,营销场景数据源!$C:$C,$B$38,营销场景数据源!$A:$A,DM2) -> 2 | DN40: =SUMIFS(营销场景数据源!$AB:$AB,营销场景数据源!$C:$C,$B$38,营销场景数据源!$A:$A,DN2) -> 3 | ... EJ40: =SUMIFS(营销场景数据源!$AB:$AB,营销场景数据源!$C:$C,$B$38,营销场景数据源!$A:$A,EJ2) -> 1 | EK40: =SUM(EL40:FP40) -> 60 | EL40: =SUMIFS(营销场景数据源!$AB:$AB,营销场景数据源!$C:$C,$B$38,营销场景数据源!$A:$A,EL2) -> 1 | EM40: =SUMIFS(营销场景数据源!$AB:$AB,营销场景数据源!$C:$C,$B$38,营销场景数据源!$A:$A,EM2) -> 0 | EN40: =SUMIFS(营销场景数据源!$AB:$AB,营销场景数据源!$C:$C,$B$38,营销场景数据源!$A:$A,EN2) -> 1 | EO40: =SUMIFS(营销场景数据源!$AB:$AB,营销场景数据源!$C:$C,$B$38,营销场景数据源!$A:$A,EO2) -> 1 | EP40: =SUMIFS(营销场景数据源!$AB:$AB,营销场景数据源!$C:$C,$B$38,营销场景数据源!$A:$A,EP2) -> 2 | EQ40: =SUMIFS(营销场景数据源!$AB:$AB,营销场景数据源!$C:$C,$B$38,营销场景数据源!$A:$A,EQ2) -> 7 | ER40: =SUMIFS(营销场景数据源!$AB:$AB,营销场景数据源!$C:$C,$B$38,营销场景数据源!$A:$A,ER2) -> 1 | ES40: =SUMIFS(营销场景数据源!$AB:$AB,营销场景数据源!$C:$C,$B$38,营销场景数据源!$A:$A,ES2) -> 0 | ... FP40: =SUMIFS(营销场景数据源!$AB:$AB,营销场景数据源!$C:$C,$B$38,营销场景数据源!$A:$A,FP2) -> 10 | FQ40: =SUM(FR40:GX40) -> 64 | FR40: =SUMIFS(营销场景数据源!$AB:$AB,营销场景数据源!$C:$C,$B$38,营销场景数据源!$A:$A,FR2) -> 4 | FS40: =SUMIFS(营销场景数据源!$AB:$AB,营销场景数据源!$C:$C,$B$38,营销场景数据源!$A:$A,FS2) -> 0 | FT40: =SUMIFS(营销场景数据源!$AB:$AB,营销场景数据源!$C:$C,$B$38,营销场景数据源!$A:$A,FT2) -> 4 | FU40: =SUMIFS(营销场景数据源!$AB:$AB,营销场景数据源!$C:$C,$B$38,营销场景数据源!$A:$A,FU2) -> 0 | FV40: =SUMIFS(营销场景数据源!$AB:$AB,营销场景数据源!$C:$C,$B$38,营销场景数据源!$A:$A,FV2) -> 8 | FW40: =SUMIFS(营销场景数据源!$AB:$AB,营销场景数据源!$C:$C,$B$38,营销场景数据源!$A:$A,FW2) -> 2 | FX40: =SUMIFS(营销场景数据源!$AB:$AB,营销场景数据源!$C:$C,$B$38,营销场景数据源!$A:$A,FX2) -> 0 | FY40: =SUMIFS(营销场景数据源!$AB:$AB,营销场景数据源!$C:$C,$B$38,营销场景数据源!$A:$A,FY2) -> 3 | ... GP40: =SUMIFS(营销场景数据源!$AB:$AB,营销场景数据源!$C:$C,$B$38,营销场景数据源!$A:$A,GP2) -> 0
C41: 总成交量 | D41: =SUM(E41:P41) -> #REF! | E41: =#REF! -> #REF! | F41: =#REF! -> #REF! | G41: =#REF! -> #REF! | H41: =#REF! -> #REF! | I41: =#REF! -> #REF! | J41: =#REF! -> #REF! | K41: =#REF! -> #REF! | L41: =#REF! -> #REF! | ... P41: =#REF! -> #REF! | Q41: 25 | R41: =SUMIFS(营销场景数据源!$U:$U,营销场景数据源!$C:$C,$B$38,营销场景数据源!$A:$A,R2) -> 0 | S41: =SUMIFS(营销场景数据源!$U:$U,营销场景数据源!$C:$C,$B$38,营销场景数据源!$A:$A,S2) -> 2 | T41: =SUMIFS(营销场景数据源!$U:$U,营销场景数据源!$C:$C,$B$38,营销场景数据源!$A:$A,T2) -> 1 | U41: =SUMIFS(营销场景数据源!$U:$U,营销场景数据源!$C:$C,$B$38,营销场景数据源!$A:$A,U2) -> 3 | V41: =SUMIFS(营销场景数据源!$U:$U,营销场景数据源!$C:$C,$B$38,营销场景数据源!$A:$A,V2) -> 0 | W41: =SUMIFS(营销场景数据源!$U:$U,营销场景数据源!$C:$C,$B$38,营销场景数据源!$A:$A,W2) -> 1 | X41: =SUMIFS(营销场景数据源!$U:$U,营销场景数据源!$C:$C,$B$38,营销场景数据源!$A:$A,X2) -> 0 | Y41: =SUMIFS(营销场景数据源!$U:$U,营销场景数据源!$C:$C,$B$38,营销场景数据源!$A:$A,Y2) -> 2 | ... AV41: =SUMIFS(营销场景数据源!$U:$U,营销场景数据源!$C:$C,$B$38,营销场景数据源!$A:$A,AV2) -> 1 | AW41: 25 | AX41: =SUMIFS(营销场景数据源!$U:$U,营销场景数据源!$C:$C,$B$38,营销场景数据源!$A:$A,AX2) -> 0 | AY41: =SUMIFS(营销场景数据源!$U:$U,营销场景数据源!$C:$C,$B$38,营销场景数据源!$A:$A,AY2) -> 2 | AZ41: =SUMIFS(营销场景数据源!$U:$U,营销场景数据源!$C:$C,$B$38,营销场景数据源!$A:$A,AZ2) -> 2 | BA41: =SUMIFS(营销场景数据源!$U:$U,营销场景数据源!$C:$C,$B$38,营销场景数据源!$A:$A,BA2) -> 0 | BB41: =SUMIFS(营销场景数据源!$U:$U,营销场景数据源!$C:$C,$B$38,营销场景数据源!$A:$A,BB2) -> 7 | BC41: =SUMIFS(营销场景数据源!$U:$U,营销场景数据源!$C:$C,$B$38,营销场景数据源!$A:$A,BC2) -> 5 | BD41: =SUMIFS(营销场景数据源!$U:$U,营销场景数据源!$C:$C,$B$38,营销场景数据源!$A:$A,BD2) -> 5 | BE41: =SUMIFS(营销场景数据源!$U:$U,营销场景数据源!$C:$C,$B$38,营销场景数据源!$A:$A,BE2) -> 1 | ... BY41: =SUMIFS(营销场景数据源!$U:$U,营销场景数据源!$C:$C,$B$38,营销场景数据源!$A:$A,BY2) -> 1 | BZ41: 25 | CA41: =SUMIFS(营销场景数据源!$U:$U,营销场景数据源!$C:$C,$B$38,营销场景数据源!$A:$A,CA2) -> 1 | CB41: =SUMIFS(营销场景数据源!$U:$U,营销场景数据源!$C:$C,$B$38,营销场景数据源!$A:$A,CB2) -> 0 | CC41: =SUMIFS(营销场景数据源!$U:$U,营销场景数据源!$C:$C,$B$38,营销场景数据源!$A:$A,CC2) -> 2 | CD41: =SUMIFS(营销场景数据源!$U:$U,营销场景数据源!$C:$C,$B$38,营销场景数据源!$A:$A,CD2) -> 2 | CE41: =SUMIFS(营销场景数据源!$U:$U,营销场景数据源!$C:$C,$B$38,营销场景数据源!$A:$A,CE2) -> 1 | CF41: =SUMIFS(营销场景数据源!$U:$U,营销场景数据源!$C:$C,$B$38,营销场景数据源!$A:$A,CF2) -> 1 | CG41: =SUMIFS(营销场景数据源!$U:$U,营销场景数据源!$C:$C,$B$38,营销场景数据源!$A:$A,CG2) -> 1 | CH41: =SUMIFS(营销场景数据源!$U:$U,营销场景数据源!$C:$C,$B$38,营销场景数据源!$A:$A,CH2) -> 2 | ... DE41: =SUMIFS(营销场景数据源!$U:$U,营销场景数据源!$C:$C,$B$38,营销场景数据源!$A:$A,DE2) -> 1 | DF41: 25 | DG41: =SUMIFS(营销场景数据源!$U:$U,营销场景数据源!$C:$C,$B$38,营销场景数据源!$A:$A,DG2) -> 0 | DH41: =SUMIFS(营销场景数据源!$U:$U,营销场景数据源!$C:$C,$B$38,营销场景数据源!$A:$A,DH2) -> 1 | DI41: =SUMIFS(营销场景数据源!$U:$U,营销场景数据源!$C:$C,$B$38,营销场景数据源!$A:$A,DI2) -> 2 | DJ41: =SUMIFS(营销场景数据源!$U:$U,营销场景数据源!$C:$C,$B$38,营销场景数据源!$A:$A,DJ2) -> 1 | DK41: =SUMIFS(营销场景数据源!$U:$U,营销场景数据源!$C:$C,$B$38,营销场景数据源!$A:$A,DK2) -> 1 | DL41: =SUMIFS(营销场景数据源!$U:$U,营销场景数据源!$C:$C,$B$38,营销场景数据源!$A:$A,DL2) -> 0 | DM41: =SUMIFS(营销场景数据源!$U:$U,营销场景数据源!$C:$C,$B$38,营销场景数据源!$A:$A,DM2) -> 3 | DN41: =SUMIFS(营销场景数据源!$U:$U,营销场景数据源!$C:$C,$B$38,营销场景数据源!$A:$A,DN2) -> 0 | ... EJ41: =SUMIFS(营销场景数据源!$U:$U,营销场景数据源!$C:$C,$B$38,营销场景数据源!$A:$A,EJ2) -> 0 | EK41: 25 | EL41: =SUMIFS(营销场景数据源!$U:$U,营销场景数据源!$C:$C,$B$38,营销场景数据源!$A:$A,EL2) -> 1 | EM41: =SUMIFS(营销场景数据源!$U:$U,营销场景数据源!$C:$C,$B$38,营销场景数据源!$A:$A,EM2) -> 0 | EN41: =SUMIFS(营销场景数据源!$U:$U,营销场景数据源!$C:$C,$B$38,营销场景数据源!$A:$A,EN2) -> 2 | EO41: =SUMIFS(营销场景数据源!$U:$U,营销场景数据源!$C:$C,$B$38,营销场景数据源!$A:$A,EO2) -> 0 | EP41: =SUMIFS(营销场景数据源!$U:$U,营销场景数据源!$C:$C,$B$38,营销场景数据源!$A:$A,EP2) -> 1 | EQ41: =SUMIFS(营销场景数据源!$U:$U,营销场景数据源!$C:$C,$B$38,营销场景数据源!$A:$A,EQ2) -> 1 | ER41: =SUMIFS(营销场景数据源!$U:$U,营销场景数据源!$C:$C,$B$38,营销场景数据源!$A:$A,ER2) -> 0 | ES41: =SUMIFS(营销场景数据源!$U:$U,营销场景数据源!$C:$C,$B$38,营销场景数据源!$A:$A,ES2) -> 0 | ... FP41: =SUMIFS(营销场景数据源!$U:$U,营销场景数据源!$C:$C,$B$38,营销场景数据源!$A:$A,FP2) -> 1 | FQ41: 25 | FR41: =SUMIFS(营销场景数据源!$U:$U,营销场景数据源!$C:$C,$B$38,营销场景数据源!$A:$A,FR2) -> 1 | FS41: =SUMIFS(营销场景数据源!$U:$U,营销场景数据源!$C:$C,$B$38,营销场景数据源!$A:$A,FS2) -> 0 | FT41: =SUMIFS(营销场景数据源!$U:$U,营销场景数据源!$C:$C,$B$38,营销场景数据源!$A:$A,FT2) -> 3 | FU41: =SUMIFS(营销场景数据源!$U:$U,营销场景数据源!$C:$C,$B$38,营销场景数据源!$A:$A,FU2) -> 2 | FV41: =SUMIFS(营销场景数据源!$U:$U,营销场景数据源!$C:$C,$B$38,营销场景数据源!$A:$A,FV2) -> 8 | FW41: =SUMIFS(营销场景数据源!$U:$U,营销场景数据源!$C:$C,$B$38,营销场景数据源!$A:$A,FW2) -> 1 | FX41: =SUMIFS(营销场景数据源!$U:$U,营销场景数据源!$C:$C,$B$38,营销场景数据源!$A:$A,FX2) -> 0 | FY41: =SUMIFS(营销场景数据源!$U:$U,营销场景数据源!$C:$C,$B$38,营销场景数据源!$A:$A,FY2) -> 0 | ... GP41: =SUMIFS(营销场景数据源!$U:$U,营销场景数据源!$C:$C,$B$38,营销场景数据源!$A:$A,GP2) -> 0
C42: 总成交金额 | D42: =SUM(E42:P42) -> #REF! | E42: =#REF! -> #REF! | F42: =#REF! -> #REF! | G42: =#REF! -> #REF! | H42: =#REF! -> #REF! | I42: =#REF! -> #REF! | J42: =#REF! -> #REF! | K42: =#REF! -> #REF! | L42: =#REF! -> #REF! | ... P42: =#REF! -> #REF! | Q42: =SUM(R42:AV42) -> 11427.2 | R42: =SUMIFS(营销场景数据源!$T:$T,营销场景数据源!$C:$C,$B$38,营销场景数据源!$A:$A,R2) -> 0 | S42: =SUMIFS(营销场景数据源!$T:$T,营销场景数据源!$C:$C,$B$38,营销场景数据源!$A:$A,S2) -> 319.74 | T42: =SUMIFS(营销场景数据源!$T:$T,营销场景数据源!$C:$C,$B$38,营销场景数据源!$A:$A,T2) -> 72.25 | U42: =SUMIFS(营销场景数据源!$T:$T,营销场景数据源!$C:$C,$B$38,营销场景数据源!$A:$A,U2) -> 666 | V42: =SUMIFS(营销场景数据源!$T:$T,营销场景数据源!$C:$C,$B$38,营销场景数据源!$A:$A,V2) -> 0 | W42: =SUMIFS(营销场景数据源!$T:$T,营销场景数据源!$C:$C,$B$38,营销场景数据源!$A:$A,W2) -> 262.4 | X42: =SUMIFS(营销场景数据源!$T:$T,营销场景数据源!$C:$C,$B$38,营销场景数据源!$A:$A,X2) -> 0 | Y42: =SUMIFS(营销场景数据源!$T:$T,营销场景数据源!$C:$C,$B$38,营销场景数据源!$A:$A,Y2) -> 2268 | ... AV42: =SUMIFS(营销场景数据源!$T:$T,营销场景数据源!$C:$C,$B$38,营销场景数据源!$A:$A,AV2) -> 586.64 | AW42: =SUM(AX42:BY42) -> 12889.05 | AX42: =SUMIFS(营销场景数据源!$T:$T,营销场景数据源!$C:$C,$B$38,营销场景数据源!$A:$A,AX2) -> 0 | AY42: =SUMIFS(营销场景数据源!$T:$T,营销场景数据源!$C:$C,$B$38,营销场景数据源!$A:$A,AY2) -> 432 | AZ42: =SUMIFS(营销场景数据源!$T:$T,营销场景数据源!$C:$C,$B$38,营销场景数据源!$A:$A,AZ2) -> 375.76 | BA42: =SUMIFS(营销场景数据源!$T:$T,营销场景数据源!$C:$C,$B$38,营销场景数据源!$A:$A,BA2) -> 0 | BB42: =SUMIFS(营销场景数据源!$T:$T,营销场景数据源!$C:$C,$B$38,营销场景数据源!$A:$A,BB2) -> 2447.26 | BC42: =SUMIFS(营销场景数据源!$T:$T,营销场景数据源!$C:$C,$B$38,营销场景数据源!$A:$A,BC2) -> 779.48 | BD42: =SUMIFS(营销场景数据源!$T:$T,营销场景数据源!$C:$C,$B$38,营销场景数据源!$A:$A,BD2) -> 1021.63 | BE42: =SUMIFS(营销场景数据源!$T:$T,营销场景数据源!$C:$C,$B$38,营销场景数据源!$A:$A,BE2) -> 162.68 | ... BY42: =SUMIFS(营销场景数据源!$T:$T,营销场景数据源!$C:$C,$B$38,营销场景数据源!$A:$A,BY2) -> 176 | BZ42: =SUM(CA42:DE42) -> 9064.44 | CA42: =SUMIFS(营销场景数据源!$T:$T,营销场景数据源!$C:$C,$B$38,营销场景数据源!$A:$A,CA2) -> 172 | CB42: =SUMIFS(营销场景数据源!$T:$T,营销场景数据源!$C:$C,$B$38,营销场景数据源!$A:$A,CB2) -> 0 | CC42: =SUMIFS(营销场景数据源!$T:$T,营销场景数据源!$C:$C,$B$38,营销场景数据源!$A:$A,CC2) -> 135.04 | CD42: =SUMIFS(营销场景数据源!$T:$T,营销场景数据源!$C:$C,$B$38,营销场景数据源!$A:$A,CD2) -> 1480.69 | CE42: =SUMIFS(营销场景数据源!$T:$T,营销场景数据源!$C:$C,$B$38,营销场景数据源!$A:$A,CE2) -> 196 | CF42: =SUMIFS(营销场景数据源!$T:$T,营销场景数据源!$C:$C,$B$38,营销场景数据源!$A:$A,CF2) -> 68.6 | CG42: =SUMIFS(营销场景数据源!$T:$T,营销场景数据源!$C:$C,$B$38,营销场景数据源!$A:$A,CG2) -> 172 | CH42: =SUMIFS(营销场景数据源!$T:$T,营销场景数据源!$C:$C,$B$38,营销场景数据源!$A:$A,CH2) -> 457.04 | ... DE42: =SUMIFS(营销场景数据源!$T:$T,营销场景数据源!$C:$C,$B$38,营销场景数据源!$A:$A,DE2) -> 43.91 | DF42: =SUM(DG42:EJ42) -> 6071.91 | DG42: =SUMIFS(营销场景数据源!$T:$T,营销场景数据源!$C:$C,$B$38,营销场景数据源!$A:$A,DG2) -> 0 | DH42: =SUMIFS(营销场景数据源!$T:$T,营销场景数据源!$C:$C,$B$38,营销场景数据源!$A:$A,DH2) -> 269.64 | DI42: =SUMIFS(营销场景数据源!$T:$T,营销场景数据源!$C:$C,$B$38,营销场景数据源!$A:$A,DI2) -> 302.72 | DJ42: =SUMIFS(营销场景数据源!$T:$T,营销场景数据源!$C:$C,$B$38,营销场景数据源!$A:$A,DJ2) -> 84.15 | DK42: =SUMIFS(营销场景数据源!$T:$T,营销场景数据源!$C:$C,$B$38,营销场景数据源!$A:$A,DK2) -> 295 | DL42: =SUMIFS(营销场景数据源!$T:$T,营销场景数据源!$C:$C,$B$38,营销场景数据源!$A:$A,DL2) -> 0 | DM42: =SUMIFS(营销场景数据源!$T:$T,营销场景数据源!$C:$C,$B$38,营销场景数据源!$A:$A,DM2) -> 512.34 | DN42: =SUMIFS(营销场景数据源!$T:$T,营销场景数据源!$C:$C,$B$38,营销场景数据源!$A:$A,DN2) -> 0 | ... EJ42: =SUMIFS(营销场景数据源!$T:$T,营销场景数据源!$C:$C,$B$38,营销场景数据源!$A:$A,EJ2) -> 0 | EK42: =SUM(EL42:FP42) -> 1747.02 | EL42: =SUMIFS(营销场景数据源!$T:$T,营销场景数据源!$C:$C,$B$38,营销场景数据源!$A:$A,EL2) -> 70.2 | EM42: =SUMIFS(营销场景数据源!$T:$T,营销场景数据源!$C:$C,$B$38,营销场景数据源!$A:$A,EM2) -> 0 | EN42: =SUMIFS(营销场景数据源!$T:$T,营销场景数据源!$C:$C,$B$38,营销场景数据源!$A:$A,EN2) -> 125.1 | EO42: =SUMIFS(营销场景数据源!$T:$T,营销场景数据源!$C:$C,$B$38,营销场景数据源!$A:$A,EO2) -> 0 | EP42: =SUMIFS(营销场景数据源!$T:$T,营销场景数据源!$C:$C,$B$38,营销场景数据源!$A:$A,EP2) -> 138.64 | EQ42: =SUMIFS(营销场景数据源!$T:$T,营销场景数据源!$C:$C,$B$38,营销场景数据源!$A:$A,EQ2) -> 732.28 | ER42: =SUMIFS(营销场景数据源!$T:$T,营销场景数据源!$C:$C,$B$38,营销场景数据源!$A:$A,ER2) -> 0 | ES42: =SUMIFS(营销场景数据源!$T:$T,营销场景数据源!$C:$C,$B$38,营销场景数据源!$A:$A,ES2) -> 0 | ... FP42: =SUMIFS(营销场景数据源!$T:$T,营销场景数据源!$C:$C,$B$38,营销场景数据源!$A:$A,FP2) -> 42.4 | FQ42: =SUM(FR42:GX42) -> 20753.22 | FR42: =SUMIFS(营销场景数据源!$T:$T,营销场景数据源!$C:$C,$B$38,营销场景数据源!$A:$A,FR2) -> 37.93 | FS42: =SUMIFS(营销场景数据源!$T:$T,营销场景数据源!$C:$C,$B$38,营销场景数据源!$A:$A,FS2) -> 0 | FT42: =SUMIFS(营销场景数据源!$T:$T,营销场景数据源!$C:$C,$B$38,营销场景数据源!$A:$A,FT2) -> 930.12 | FU42: =SUMIFS(营销场景数据源!$T:$T,营销场景数据源!$C:$C,$B$38,营销场景数据源!$A:$A,FU2) -> 167.03 | FV42: =SUMIFS(营销场景数据源!$T:$T,营销场景数据源!$C:$C,$B$38,营销场景数据源!$A:$A,FV2) -> 17623.09 | FW42: =SUMIFS(营销场景数据源!$T:$T,营销场景数据源!$C:$C,$B$38,营销场景数据源!$A:$A,FW2) -> 40.41 | FX42: =SUMIFS(营销场景数据源!$T:$T,营销场景数据源!$C:$C,$B$38,营销场景数据源!$A:$A,FX2) -> 0 | FY42: =SUMIFS(营销场景数据源!$T:$T,营销场景数据源!$C:$C,$B$38,营销场景数据源!$A:$A,FY2) -> 0 | ... GP42: =SUMIFS(营销场景数据源!$T:$T,营销场景数据源!$C:$C,$B$38,营销场景数据源!$A:$A,GP2) -> 0
C43: 点击单价 | D43: =IFERROR(D38/D39,0) -> 0 | E43: =IFERROR(E38/E39,0) -> 0 | F43: =IFERROR(F38/F39,0) -> 0 | G43: =IFERROR(G38/G39,0) -> 0 | H43: =IFERROR(H38/H39,0) -> 0 | I43: =IFERROR(I38/I39,0) -> 0 | J43: =IFERROR(J38/J39,0) -> 0 | K43: =IFERROR(K38/K39,0) -> 0 | ... GP43: =IFERROR(GP38/GP39,0) -> 0
C44: 加购成本 | D44: =IFERROR(D38/D40,0) -> 0 | E44: =IFERROR(E38/E40,0) -> 0 | F44: =IFERROR(F38/F40,0) -> 0 | G44: =IFERROR(G38/G40,0) -> 0 | H44: =IFERROR(H38/H40,0) -> 0 | I44: =IFERROR(I38/I40,0) -> 0 | J44: =IFERROR(J38/J40,0) -> 0 | K44: =IFERROR(K38/K40,0) -> 0 | ... GP44: =IFERROR(GP38/GP40,0) -> 0
C45: ROI | D45: =IFERROR(D42/D38,0) -> 0 | E45: =IFERROR(E42/E38,0) -> 0 | F45: =IFERROR(F42/F38,0) -> 0 | G45: =IFERROR(G42/G38,0) -> 0 | H45: =IFERROR(H42/H38,0) -> 0 | I45: =IFERROR(I42/I38,0) -> 0 | J45: =IFERROR(J42/J38,0) -> 0 | K45: =IFERROR(K42/K38,0) -> 0 | ... GP45: =IFERROR(GP42/GP38,0) -> 0
C46: 费用占比 | D46: =D38/D$130 -> #REF! | E46: =E38/E$130 -> #REF! | F46: =F38/F$130 -> #REF! | G46: =G38/G$130 -> #REF! | H46: =H38/H$130 -> #REF! | I46: =I38/I$130 -> #REF! | J46: =J38/J$130 -> #REF! | K46: =K38/K$130 -> #REF! | ... GP46: =GP38/GP$130 -> #DIV/0!
B47: 店铺直达 | C47: 花费 | D47: =SUM(E47:P47) -> #REF! | E47: =#REF! -> #REF! | F47: =#REF! -> #REF! | G47: =#REF! -> #REF! | H47: =#REF! -> #REF! | I47: =#REF! -> #REF! | J47: =#REF! -> #REF! | K47: =#REF! -> #REF! | L47: =#REF! -> #REF! | ... P47: =#REF! -> #REF! | Q47: =SUM(R47:AV47) -> 531.97 | R47: =SUMIFS(营销场景数据源!$H:$H,营销场景数据源!$C:$C,$B$47,营销场景数据源!$A:$A,R2) -> 7.8 | S47: =SUMIFS(营销场景数据源!$H:$H,营销场景数据源!$C:$C,$B$47,营销场景数据源!$A:$A,S2) -> 10.04 | T47: =SUMIFS(营销场景数据源!$H:$H,营销场景数据源!$C:$C,$B$47,营销场景数据源!$A:$A,T2) -> 10.78 | U47: =SUMIFS(营销场景数据源!$H:$H,营销场景数据源!$C:$C,$B$47,营销场景数据源!$A:$A,U2) -> 16.24 | V47: =SUMIFS(营销场景数据源!$H:$H,营销场景数据源!$C:$C,$B$47,营销场景数据源!$A:$A,V2) -> 10.17 | W47: =SUMIFS(营销场景数据源!$H:$H,营销场景数据源!$C:$C,$B$47,营销场景数据源!$A:$A,W2) -> 11.67 | X47: =SUMIFS(营销场景数据源!$H:$H,营销场景数据源!$C:$C,$B$47,营销场景数据源!$A:$A,X2) -> 18.68 | Y47: =SUMIFS(营销场景数据源!$H:$H,营销场景数据源!$C:$C,$B$47,营销场景数据源!$A:$A,Y2) -> 13.9 | ... AV47: =SUMIFS(营销场景数据源!$H:$H,营销场景数据源!$C:$C,$B$47,营销场景数据源!$A:$A,AV2) -> 23.92 | AW47: =SUM(AX47:BY47) -> 548.21 | AX47: =SUMIFS(营销场景数据源!$H:$H,营销场景数据源!$C:$C,$B$47,营销场景数据源!$A:$A,AX2) -> 24.35 | AY47: =SUMIFS(营销场景数据源!$H:$H,营销场景数据源!$C:$C,$B$47,营销场景数据源!$A:$A,AY2) -> 21.38 | AZ47: =SUMIFS(营销场景数据源!$H:$H,营销场景数据源!$C:$C,$B$47,营销场景数据源!$A:$A,AZ2) -> 19.34 | BA47: =SUMIFS(营销场景数据源!$H:$H,营销场景数据源!$C:$C,$B$47,营销场景数据源!$A:$A,BA2) -> 31.56 | BB47: =SUMIFS(营销场景数据源!$H:$H,营销场景数据源!$C:$C,$B$47,营销场景数据源!$A:$A,BB2) -> 21.41 | BC47: =SUMIFS(营销场景数据源!$H:$H,营销场景数据源!$C:$C,$B$47,营销场景数据源!$A:$A,BC2) -> 32.32 | BD47: =SUMIFS(营销场景数据源!$H:$H,营销场景数据源!$C:$C,$B$47,营销场景数据源!$A:$A,BD2) -> 18.57 | BE47: =SUMIFS(营销场景数据源!$H:$H,营销场景数据源!$C:$C,$B$47,营销场景数据源!$A:$A,BE2) -> 21.4 | ... BY47: =SUMIFS(营销场景数据源!$H:$H,营销场景数据源!$C:$C,$B$47,营销场景数据源!$A:$A,BY2) -> 23.04 | BZ47: =SUM(CA47:DE47) -> 791.2 | CA47: =SUMIFS(营销场景数据源!$H:$H,营销场景数据源!$C:$C,$B$47,营销场景数据源!$A:$A,CA2) -> 13.69 | CB47: =SUMIFS(营销场景数据源!$H:$H,营销场景数据源!$C:$C,$B$47,营销场景数据源!$A:$A,CB2) -> 13.45 | CC47: =SUMIFS(营销场景数据源!$H:$H,营销场景数据源!$C:$C,$B$47,营销场景数据源!$A:$A,CC2) -> 31.37 | CD47: =SUMIFS(营销场景数据源!$H:$H,营销场景数据源!$C:$C,$B$47,营销场景数据源!$A:$A,CD2) -> 28.53 | CE47: =SUMIFS(营销场景数据源!$H:$H,营销场景数据源!$C:$C,$B$47,营销场景数据源!$A:$A,CE2) -> 23.88 | CF47: =SUMIFS(营销场景数据源!$H:$H,营销场景数据源!$C:$C,$B$47,营销场景数据源!$A:$A,CF2) -> 23.36 | CG47: =SUMIFS(营销场景数据源!$H:$H,营销场景数据源!$C:$C,$B$47,营销场景数据源!$A:$A,CG2) -> 23 | CH47: =SUMIFS(营销场景数据源!$H:$H,营销场景数据源!$C:$C,$B$47,营销场景数据源!$A:$A,CH2) -> 59.41 | ... DE47: =SUMIFS(营销场景数据源!$H:$H,营销场景数据源!$C:$C,$B$47,营销场景数据源!$A:$A,DE2) -> 14.06 | DF47: =SUM(DG47:EJ47) -> 401 | DG47: =SUMIFS(营销场景数据源!$H:$H,营销场景数据源!$C:$C,$B$47,营销场景数据源!$A:$A,DG2) -> 19.19 | DH47: =SUMIFS(营销场景数据源!$H:$H,营销场景数据源!$C:$C,$B$47,营销场景数据源!$A:$A,DH2) -> 11.04 | DI47: =SUMIFS(营销场景数据源!$H:$H,营销场景数据源!$C:$C,$B$47,营销场景数据源!$A:$A,DI2) -> 10.84 | DJ47: =SUMIFS(营销场景数据源!$H:$H,营销场景数据源!$C:$C,$B$47,营销场景数据源!$A:$A,DJ2) -> 9.56 | DK47: =SUMIFS(营销场景数据源!$H:$H,营销场景数据源!$C:$C,$B$47,营销场景数据源!$A:$A,DK2) -> 11.53 | DL47: =SUMIFS(营销场景数据源!$H:$H,营销场景数据源!$C:$C,$B$47,营销场景数据源!$A:$A,DL2) -> 11.07 | DM47: =SUMIFS(营销场景数据源!$H:$H,营销场景数据源!$C:$C,$B$47,营销场景数据源!$A:$A,DM2) -> 15.24 | DN47: =SUMIFS(营销场景数据源!$H:$H,营销场景数据源!$C:$C,$B$47,营销场景数据源!$A:$A,DN2) -> 13.77 | ... EJ47: =SUMIFS(营销场景数据源!$H:$H,营销场景数据源!$C:$C,$B$47,营销场景数据源!$A:$A,EJ2) -> 14.68 | EK47: =SUM(EL47:FP47) -> 406.28 | EL47: =SUMIFS(营销场景数据源!$H:$H,营销场景数据源!$C:$C,$B$47,营销场景数据源!$A:$A,EL2) -> 12.83 | EM47: =SUMIFS(营销场景数据源!$H:$H,营销场景数据源!$C:$C,$B$47,营销场景数据源!$A:$A,EM2) -> 9.56 | EN47: =SUMIFS(营销场景数据源!$H:$H,营销场景数据源!$C:$C,$B$47,营销场景数据源!$A:$A,EN2) -> 9.05 | EO47: =SUMIFS(营销场景数据源!$H:$H,营销场景数据源!$C:$C,$B$47,营销场景数据源!$A:$A,EO2) -> 9.32 | EP47: =SUMIFS(营销场景数据源!$H:$H,营销场景数据源!$C:$C,$B$47,营销场景数据源!$A:$A,EP2) -> 13.43 | EQ47: =SUMIFS(营销场景数据源!$H:$H,营销场景数据源!$C:$C,$B$47,营销场景数据源!$A:$A,EQ2) -> 12.56 | ER47: =SUMIFS(营销场景数据源!$H:$H,营销场景数据源!$C:$C,$B$47,营销场景数据源!$A:$A,ER2) -> 13.63 | ES47: =SUMIFS(营销场景数据源!$H:$H,营销场景数据源!$C:$C,$B$47,营销场景数据源!$A:$A,ES2) -> 11.94 | ... FP47: =SUMIFS(营销场景数据源!$H:$H,营销场景数据源!$C:$C,$B$47,营销场景数据源!$A:$A,FP2) -> 10.07 | FQ47: =SUM(FR47:GX47) -> 290.68 | FR47: =SUMIFS(营销场景数据源!$H:$H,营销场景数据源!$C:$C,$B$47,营销场景数据源!$A:$A,FR2) -> 16.38 | FS47: =SUMIFS(营销场景数据源!$H:$H,营销场景数据源!$C:$C,$B$47,营销场景数据源!$A:$A,FS2) -> 14.33 | FT47: =SUMIFS(营销场景数据源!$H:$H,营销场景数据源!$C:$C,$B$47,营销场景数据源!$A:$A,FT2) -> 21.21 | FU47: =SUMIFS(营销场景数据源!$H:$H,营销场景数据源!$C:$C,$B$47,营销场景数据源!$A:$A,FU2) -> 16.73 | FV47: =SUMIFS(营销场景数据源!$H:$H,营销场景数据源!$C:$C,$B$47,营销场景数据源!$A:$A,FV2) -> 20.6 | FW47: =SUMIFS(营销场景数据源!$H:$H,营销场景数据源!$C:$C,$B$47,营销场景数据源!$A:$A,FW2) -> 10.41 | FX47: =SUMIFS(营销场景数据源!$H:$H,营销场景数据源!$C:$C,$B$47,营销场景数据源!$A:$A,FX2) -> 14.95 | FY47: =SUMIFS(营销场景数据源!$H:$H,营销场景数据源!$C:$C,$B$47,营销场景数据源!$A:$A,FY2) -> 12.74 | ... GP47: =SUMIFS(营销场景数据源!$H:$H,营销场景数据源!$C:$C,$B$47,营销场景数据源!$A:$A,GP2) -> 0
C48: 点击量 | D48: =SUM(E48:P48) -> #REF! | E48: =#REF! -> #REF! | F48: =#REF! -> #REF! | G48: =#REF! -> #REF! | H48: =#REF! -> #REF! | I48: =#REF! -> #REF! | J48: =#REF! -> #REF! | K48: =#REF! -> #REF! | L48: =#REF! -> #REF! | ... P48: =#REF! -> #REF! | Q48: =SUM(R48:AV48) -> 825 | R48: =SUMIFS(营销场景数据源!$G:$G,营销场景数据源!$C:$C,$B$47,营销场景数据源!$A:$A,R2) -> 15 | S48: =SUMIFS(营销场景数据源!$G:$G,营销场景数据源!$C:$C,$B$47,营销场景数据源!$A:$A,S2) -> 16 | T48: =SUMIFS(营销场景数据源!$G:$G,营销场景数据源!$C:$C,$B$47,营销场景数据源!$A:$A,T2) -> 11 | U48: =SUMIFS(营销场景数据源!$G:$G,营销场景数据源!$C:$C,$B$47,营销场景数据源!$A:$A,U2) -> 23 | V48: =SUMIFS(营销场景数据源!$G:$G,营销场景数据源!$C:$C,$B$47,营销场景数据源!$A:$A,V2) -> 14 | W48: =SUMIFS(营销场景数据源!$G:$G,营销场景数据源!$C:$C,$B$47,营销场景数据源!$A:$A,W2) -> 14 | X48: =SUMIFS(营销场景数据源!$G:$G,营销场景数据源!$C:$C,$B$47,营销场景数据源!$A:$A,X2) -> 33 | Y48: =SUMIFS(营销场景数据源!$G:$G,营销场景数据源!$C:$C,$B$47,营销场景数据源!$A:$A,Y2) -> 22 | ... AV48: =SUMIFS(营销场景数据源!$G:$G,营销场景数据源!$C:$C,$B$47,营销场景数据源!$A:$A,AV2) -> 33 | AW48: =SUM(AX48:BY48) -> 812 | AX48: =SUMIFS(营销场景数据源!$G:$G,营销场景数据源!$C:$C,$B$47,营销场景数据源!$A:$A,AX2) -> 40 | AY48: =SUMIFS(营销场景数据源!$G:$G,营销场景数据源!$C:$C,$B$47,营销场景数据源!$A:$A,AY2) -> 30 | AZ48: =SUMIFS(营销场景数据源!$G:$G,营销场景数据源!$C:$C,$B$47,营销场景数据源!$A:$A,AZ2) -> 28 | BA48: =SUMIFS(营销场景数据源!$G:$G,营销场景数据源!$C:$C,$B$47,营销场景数据源!$A:$A,BA2) -> 54 | BB48: =SUMIFS(营销场景数据源!$G:$G,营销场景数据源!$C:$C,$B$47,营销场景数据源!$A:$A,BB2) -> 33 | BC48: =SUMIFS(营销场景数据源!$G:$G,营销场景数据源!$C:$C,$B$47,营销场景数据源!$A:$A,BC2) -> 47 | BD48: =SUMIFS(营销场景数据源!$G:$G,营销场景数据源!$C:$C,$B$47,营销场景数据源!$A:$A,BD2) -> 21 | BE48: =SUMIFS(营销场景数据源!$G:$G,营销场景数据源!$C:$C,$B$47,营销场景数据源!$A:$A,BE2) -> 36 | ... BY48: =SUMIFS(营销场景数据源!$G:$G,营销场景数据源!$C:$C,$B$47,营销场景数据源!$A:$A,BY2) -> 42 | BZ48: =SUM(CA48:DE48) -> 1312 | CA48: =SUMIFS(营销场景数据源!$G:$G,营销场景数据源!$C:$C,$B$47,营销场景数据源!$A:$A,CA2) -> 28 | CB48: =SUMIFS(营销场景数据源!$G:$G,营销场景数据源!$C:$C,$B$47,营销场景数据源!$A:$A,CB2) -> 22 | CC48: =SUMIFS(营销场景数据源!$G:$G,营销场景数据源!$C:$C,$B$47,营销场景数据源!$A:$A,CC2) -> 49 | CD48: =SUMIFS(营销场景数据源!$G:$G,营销场景数据源!$C:$C,$B$47,营销场景数据源!$A:$A,CD2) -> 50 | CE48: =SUMIFS(营销场景数据源!$G:$G,营销场景数据源!$C:$C,$B$47,营销场景数据源!$A:$A,CE2) -> 48 | CF48: =SUMIFS(营销场景数据源!$G:$G,营销场景数据源!$C:$C,$B$47,营销场景数据源!$A:$A,CF2) -> 36 | CG48: =SUMIFS(营销场景数据源!$G:$G,营销场景数据源!$C:$C,$B$47,营销场景数据源!$A:$A,CG2) -> 37 | CH48: =SUMIFS(营销场景数据源!$G:$G,营销场景数据源!$C:$C,$B$47,营销场景数据源!$A:$A,CH2) -> 97 | ... DE48: =SUMIFS(营销场景数据源!$G:$G,营销场景数据源!$C:$C,$B$47,营销场景数据源!$A:$A,DE2) -> 17 | DF48: =SUM(DG48:EJ48) -> 634 | DG48: =SUMIFS(营销场景数据源!$G:$G,营销场景数据源!$C:$C,$B$47,营销场景数据源!$A:$A,DG2) -> 29 | DH48: =SUMIFS(营销场景数据源!$G:$G,营销场景数据源!$C:$C,$B$47,营销场景数据源!$A:$A,DH2) -> 22 | DI48: =SUMIFS(营销场景数据源!$G:$G,营销场景数据源!$C:$C,$B$47,营销场景数据源!$A:$A,DI2) -> 24 | DJ48: =SUMIFS(营销场景数据源!$G:$G,营销场景数据源!$C:$C,$B$47,营销场景数据源!$A:$A,DJ2) -> 15 | DK48: =SUMIFS(营销场景数据源!$G:$G,营销场景数据源!$C:$C,$B$47,营销场景数据源!$A:$A,DK2) -> 17 | DL48: =SUMIFS(营销场景数据源!$G:$G,营销场景数据源!$C:$C,$B$47,营销场景数据源!$A:$A,DL2) -> 21 | DM48: =SUMIFS(营销场景数据源!$G:$G,营销场景数据源!$C:$C,$B$47,营销场景数据源!$A:$A,DM2) -> 29 | DN48: =SUMIFS(营销场景数据源!$G:$G,营销场景数据源!$C:$C,$B$47,营销场景数据源!$A:$A,DN2) -> 32 | ... EJ48: =SUMIFS(营销场景数据源!$G:$G,营销场景数据源!$C:$C,$B$47,营销场景数据源!$A:$A,EJ2) -> 22 | EK48: =SUM(EL48:FP48) -> 555 | EL48: =SUMIFS(营销场景数据源!$G:$G,营销场景数据源!$C:$C,$B$47,营销场景数据源!$A:$A,EL2) -> 18 | EM48: =SUMIFS(营销场景数据源!$G:$G,营销场景数据源!$C:$C,$B$47,营销场景数据源!$A:$A,EM2) -> 14 | EN48: =SUMIFS(营销场景数据源!$G:$G,营销场景数据源!$C:$C,$B$47,营销场景数据源!$A:$A,EN2) -> 12 | EO48: =SUMIFS(营销场景数据源!$G:$G,营销场景数据源!$C:$C,$B$47,营销场景数据源!$A:$A,EO2) -> 13 | EP48: =SUMIFS(营销场景数据源!$G:$G,营销场景数据源!$C:$C,$B$47,营销场景数据源!$A:$A,EP2) -> 21 | EQ48: =SUMIFS(营销场景数据源!$G:$G,营销场景数据源!$C:$C,$B$47,营销场景数据源!$A:$A,EQ2) -> 21 | ER48: =SUMIFS(营销场景数据源!$G:$G,营销场景数据源!$C:$C,$B$47,营销场景数据源!$A:$A,ER2) -> 18 | ES48: =SUMIFS(营销场景数据源!$G:$G,营销场景数据源!$C:$C,$B$47,营销场景数据源!$A:$A,ES2) -> 22 | ... FP48: =SUMIFS(营销场景数据源!$G:$G,营销场景数据源!$C:$C,$B$47,营销场景数据源!$A:$A,FP2) -> 15 | FQ48: =SUM(FR48:GX48) -> 350 | FR48: =SUMIFS(营销场景数据源!$G:$G,营销场景数据源!$C:$C,$B$47,营销场景数据源!$A:$A,FR2) -> 23 | FS48: =SUMIFS(营销场景数据源!$G:$G,营销场景数据源!$C:$C,$B$47,营销场景数据源!$A:$A,FS2) -> 20 | FT48: =SUMIFS(营销场景数据源!$G:$G,营销场景数据源!$C:$C,$B$47,营销场景数据源!$A:$A,FT2) -> 25 | FU48: =SUMIFS(营销场景数据源!$G:$G,营销场景数据源!$C:$C,$B$47,营销场景数据源!$A:$A,FU2) -> 22 | FV48: =SUMIFS(营销场景数据源!$G:$G,营销场景数据源!$C:$C,$B$47,营销场景数据源!$A:$A,FV2) -> 23 | FW48: =SUMIFS(营销场景数据源!$G:$G,营销场景数据源!$C:$C,$B$47,营销场景数据源!$A:$A,FW2) -> 16 | FX48: =SUMIFS(营销场景数据源!$G:$G,营销场景数据源!$C:$C,$B$47,营销场景数据源!$A:$A,FX2) -> 23 | FY48: =SUMIFS(营销场景数据源!$G:$G,营销场景数据源!$C:$C,$B$47,营销场景数据源!$A:$A,FY2) -> 21 | ... GP48: =SUMIFS(营销场景数据源!$G:$G,营销场景数据源!$C:$C,$B$47,营销场景数据源!$A:$A,GP2) -> 0
C49: 总购物车数 | D49: =SUM(E49:P49) -> #REF! | E49: =#REF! -> #REF! | F49: =#REF! -> #REF! | G49: =#REF! -> #REF! | H49: =#REF! -> #REF! | I49: =#REF! -> #REF! | J49: =#REF! -> #REF! | K49: =#REF! -> #REF! | L49: =#REF! -> #REF! | ... P49: =#REF! -> #REF! | Q49: =SUM(R49:AV49) -> 153 | R49: =SUMIFS(营销场景数据源!$AB:$AB,营销场景数据源!$C:$C,$B$47,营销场景数据源!$A:$A,R2) -> 2 | S49: =SUMIFS(营销场景数据源!$AB:$AB,营销场景数据源!$C:$C,$B$47,营销场景数据源!$A:$A,S2) -> 3 | T49: =SUMIFS(营销场景数据源!$AB:$AB,营销场景数据源!$C:$C,$B$47,营销场景数据源!$A:$A,T2) -> 0 | U49: =SUMIFS(营销场景数据源!$AB:$AB,营销场景数据源!$C:$C,$B$47,营销场景数据源!$A:$A,U2) -> 7 | V49: =SUMIFS(营销场景数据源!$AB:$AB,营销场景数据源!$C:$C,$B$47,营销场景数据源!$A:$A,V2) -> 1 | W49: =SUMIFS(营销场景数据源!$AB:$AB,营销场景数据源!$C:$C,$B$47,营销场景数据源!$A:$A,W2) -> 6 | X49: =SUMIFS(营销场景数据源!$AB:$AB,营销场景数据源!$C:$C,$B$47,营销场景数据源!$A:$A,X2) -> 2 | Y49: =SUMIFS(营销场景数据源!$AB:$AB,营销场景数据源!$C:$C,$B$47,营销场景数据源!$A:$A,Y2) -> 2 | ... AV49: =SUMIFS(营销场景数据源!$AB:$AB,营销场景数据源!$C:$C,$B$47,营销场景数据源!$A:$A,AV2) -> 16 | AW49: =SUM(AX49:BY49) -> 185 | AX49: =SUMIFS(营销场景数据源!$AB:$AB,营销场景数据源!$C:$C,$B$47,营销场景数据源!$A:$A,AX2) -> 21 | AY49: =SUMIFS(营销场景数据源!$AB:$AB,营销场景数据源!$C:$C,$B$47,营销场景数据源!$A:$A,AY2) -> 1 | AZ49: =SUMIFS(营销场景数据源!$AB:$AB,营销场景数据源!$C:$C,$B$47,营销场景数据源!$A:$A,AZ2) -> 4 | BA49: =SUMIFS(营销场景数据源!$AB:$AB,营销场景数据源!$C:$C,$B$47,营销场景数据源!$A:$A,BA2) -> 8 | BB49: =SUMIFS(营销场景数据源!$AB:$AB,营销场景数据源!$C:$C,$B$47,营销场景数据源!$A:$A,BB2) -> 3 | BC49: =SUMIFS(营销场景数据源!$AB:$AB,营销场景数据源!$C:$C,$B$47,营销场景数据源!$A:$A,BC2) -> 21 | BD49: =SUMIFS(营销场景数据源!$AB:$AB,营销场景数据源!$C:$C,$B$47,营销场景数据源!$A:$A,BD2) -> 8 | BE49: =SUMIFS(营销场景数据源!$AB:$AB,营销场景数据源!$C:$C,$B$47,营销场景数据源!$A:$A,BE2) -> 8 | ... BY49: =SUMIFS(营销场景数据源!$AB:$AB,营销场景数据源!$C:$C,$B$47,营销场景数据源!$A:$A,BY2) -> 10 | BZ49: =SUM(CA49:DE49) -> 336 | CA49: =SUMIFS(营销场景数据源!$AB:$AB,营销场景数据源!$C:$C,$B$47,营销场景数据源!$A:$A,CA2) -> 11 | CB49: =SUMIFS(营销场景数据源!$AB:$AB,营销场景数据源!$C:$C,$B$47,营销场景数据源!$A:$A,CB2) -> 4 | CC49: =SUMIFS(营销场景数据源!$AB:$AB,营销场景数据源!$C:$C,$B$47,营销场景数据源!$A:$A,CC2) -> 12 | CD49: =SUMIFS(营销场景数据源!$AB:$AB,营销场景数据源!$C:$C,$B$47,营销场景数据源!$A:$A,CD2) -> 9 | CE49: =SUMIFS(营销场景数据源!$AB:$AB,营销场景数据源!$C:$C,$B$47,营销场景数据源!$A:$A,CE2) -> 7 | CF49: =SUMIFS(营销场景数据源!$AB:$AB,营销场景数据源!$C:$C,$B$47,营销场景数据源!$A:$A,CF2) -> 5 | CG49: =SUMIFS(营销场景数据源!$AB:$AB,营销场景数据源!$C:$C,$B$47,营销场景数据源!$A:$A,CG2) -> 12 | CH49: =SUMIFS(营销场景数据源!$AB:$AB,营销场景数据源!$C:$C,$B$47,营销场景数据源!$A:$A,CH2) -> 23 | ... DE49: =SUMIFS(营销场景数据源!$AB:$AB,营销场景数据源!$C:$C,$B$47,营销场景数据源!$A:$A,DE2) -> 6 | DF49: =SUM(DG49:EJ49) -> 106 | DG49: =SUMIFS(营销场景数据源!$AB:$AB,营销场景数据源!$C:$C,$B$47,营销场景数据源!$A:$A,DG2) -> 4 | DH49: =SUMIFS(营销场景数据源!$AB:$AB,营销场景数据源!$C:$C,$B$47,营销场景数据源!$A:$A,DH2) -> 5 | DI49: =SUMIFS(营销场景数据源!$AB:$AB,营销场景数据源!$C:$C,$B$47,营销场景数据源!$A:$A,DI2) -> 1 | DJ49: =SUMIFS(营销场景数据源!$AB:$AB,营销场景数据源!$C:$C,$B$47,营销场景数据源!$A:$A,DJ2) -> 1 | DK49: =SUMIFS(营销场景数据源!$AB:$AB,营销场景数据源!$C:$C,$B$47,营销场景数据源!$A:$A,DK2) -> 3 | DL49: =SUMIFS(营销场景数据源!$AB:$AB,营销场景数据源!$C:$C,$B$47,营销场景数据源!$A:$A,DL2) -> 4 | DM49: =SUMIFS(营销场景数据源!$AB:$AB,营销场景数据源!$C:$C,$B$47,营销场景数据源!$A:$A,DM2) -> 7 | DN49: =SUMIFS(营销场景数据源!$AB:$AB,营销场景数据源!$C:$C,$B$47,营销场景数据源!$A:$A,DN2) -> 14 | ... EJ49: =SUMIFS(营销场景数据源!$AB:$AB,营销场景数据源!$C:$C,$B$47,营销场景数据源!$A:$A,EJ2) -> 9 | EK49: =SUM(EL49:FP49) -> 113 | EL49: =SUMIFS(营销场景数据源!$AB:$AB,营销场景数据源!$C:$C,$B$47,营销场景数据源!$A:$A,EL2) -> 0 | EM49: =SUMIFS(营销场景数据源!$AB:$AB,营销场景数据源!$C:$C,$B$47,营销场景数据源!$A:$A,EM2) -> 2 | EN49: =SUMIFS(营销场景数据源!$AB:$AB,营销场景数据源!$C:$C,$B$47,营销场景数据源!$A:$A,EN2) -> 3 | EO49: =SUMIFS(营销场景数据源!$AB:$AB,营销场景数据源!$C:$C,$B$47,营销场景数据源!$A:$A,EO2) -> 1 | EP49: =SUMIFS(营销场景数据源!$AB:$AB,营销场景数据源!$C:$C,$B$47,营销场景数据源!$A:$A,EP2) -> 21 | EQ49: =SUMIFS(营销场景数据源!$AB:$AB,营销场景数据源!$C:$C,$B$47,营销场景数据源!$A:$A,EQ2) -> 3 | ER49: =SUMIFS(营销场景数据源!$AB:$AB,营销场景数据源!$C:$C,$B$47,营销场景数据源!$A:$A,ER2) -> 2 | ES49: =SUMIFS(营销场景数据源!$AB:$AB,营销场景数据源!$C:$C,$B$47,营销场景数据源!$A:$A,ES2) -> 1 | ... FP49: =SUMIFS(营销场景数据源!$AB:$AB,营销场景数据源!$C:$C,$B$47,营销场景数据源!$A:$A,FP2) -> 7 | FQ49: =SUM(FR49:GX49) -> 61 | FR49: =SUMIFS(营销场景数据源!$AB:$AB,营销场景数据源!$C:$C,$B$47,营销场景数据源!$A:$A,FR2) -> 1 | FS49: =SUMIFS(营销场景数据源!$AB:$AB,营销场景数据源!$C:$C,$B$47,营销场景数据源!$A:$A,FS2) -> 3 | FT49: =SUMIFS(营销场景数据源!$AB:$AB,营销场景数据源!$C:$C,$B$47,营销场景数据源!$A:$A,FT2) -> 1 | FU49: =SUMIFS(营销场景数据源!$AB:$AB,营销场景数据源!$C:$C,$B$47,营销场景数据源!$A:$A,FU2) -> 7 | FV49: =SUMIFS(营销场景数据源!$AB:$AB,营销场景数据源!$C:$C,$B$47,营销场景数据源!$A:$A,FV2) -> 2 | FW49: =SUMIFS(营销场景数据源!$AB:$AB,营销场景数据源!$C:$C,$B$47,营销场景数据源!$A:$A,FW2) -> 0 | FX49: =SUMIFS(营销场景数据源!$AB:$AB,营销场景数据源!$C:$C,$B$47,营销场景数据源!$A:$A,FX2) -> 5 | FY49: =SUMIFS(营销场景数据源!$AB:$AB,营销场景数据源!$C:$C,$B$47,营销场景数据源!$A:$A,FY2) -> 7 | ... GP49: =SUMIFS(营销场景数据源!$AB:$AB,营销场景数据源!$C:$C,$B$47,营销场景数据源!$A:$A,GP2) -> 0
C50: 总成交量 | D50: =SUM(E50:P50) -> #REF! | E50: =#REF! -> #REF! | F50: =#REF! -> #REF! | G50: =#REF! -> #REF! | H50: =#REF! -> #REF! | I50: =#REF! -> #REF! | J50: =#REF! -> #REF! | K50: =#REF! -> #REF! | L50: =#REF! -> #REF! | ... P50: =#REF! -> #REF! | Q50: =SUM(R50:AV50) -> 38 | R50: =SUMIFS(营销场景数据源!$U:$U,营销场景数据源!$C:$C,$B$47,营销场景数据源!$A:$A,R2) -> 1 | S50: =SUMIFS(营销场景数据源!$U:$U,营销场景数据源!$C:$C,$B$47,营销场景数据源!$A:$A,S2) -> 0 | T50: =SUMIFS(营销场景数据源!$U:$U,营销场景数据源!$C:$C,$B$47,营销场景数据源!$A:$A,T2) -> 0 | U50: =SUMIFS(营销场景数据源!$U:$U,营销场景数据源!$C:$C,$B$47,营销场景数据源!$A:$A,U2) -> 3 | V50: =SUMIFS(营销场景数据源!$U:$U,营销场景数据源!$C:$C,$B$47,营销场景数据源!$A:$A,V2) -> 0 | W50: =SUMIFS(营销场景数据源!$U:$U,营销场景数据源!$C:$C,$B$47,营销场景数据源!$A:$A,W2) -> 1 | X50: =SUMIFS(营销场景数据源!$U:$U,营销场景数据源!$C:$C,$B$47,营销场景数据源!$A:$A,X2) -> 0 | Y50: =SUMIFS(营销场景数据源!$U:$U,营销场景数据源!$C:$C,$B$47,营销场景数据源!$A:$A,Y2) -> 0 | ... AV50: =SUMIFS(营销场景数据源!$U:$U,营销场景数据源!$C:$C,$B$47,营销场景数据源!$A:$A,AV2) -> 4 | AW50: =SUM(AX50:BY50) -> 28 | AX50: =SUMIFS(营销场景数据源!$U:$U,营销场景数据源!$C:$C,$B$47,营销场景数据源!$A:$A,AX2) -> 2 | AY50: =SUMIFS(营销场景数据源!$U:$U,营销场景数据源!$C:$C,$B$47,营销场景数据源!$A:$A,AY2) -> 0 | AZ50: =SUMIFS(营销场景数据源!$U:$U,营销场景数据源!$C:$C,$B$47,营销场景数据源!$A:$A,AZ2) -> 0 | BA50: =SUMIFS(营销场景数据源!$U:$U,营销场景数据源!$C:$C,$B$47,营销场景数据源!$A:$A,BA2) -> 6 | BB50: =SUMIFS(营销场景数据源!$U:$U,营销场景数据源!$C:$C,$B$47,营销场景数据源!$A:$A,BB2) -> 1 | BC50: =SUMIFS(营销场景数据源!$U:$U,营销场景数据源!$C:$C,$B$47,营销场景数据源!$A:$A,BC2) -> 7 | BD50: =SUMIFS(营销场景数据源!$U:$U,营销场景数据源!$C:$C,$B$47,营销场景数据源!$A:$A,BD2) -> 2 | BE50: =SUMIFS(营销场景数据源!$U:$U,营销场景数据源!$C:$C,$B$47,营销场景数据源!$A:$A,BE2) -> 1 | ... BY50: =SUMIFS(营销场景数据源!$U:$U,营销场景数据源!$C:$C,$B$47,营销场景数据源!$A:$A,BY2) -> 0 | BZ50: =SUM(CA50:DE50) -> 66 | CA50: =SUMIFS(营销场景数据源!$U:$U,营销场景数据源!$C:$C,$B$47,营销场景数据源!$A:$A,CA2) -> 2 | CB50: =SUMIFS(营销场景数据源!$U:$U,营销场景数据源!$C:$C,$B$47,营销场景数据源!$A:$A,CB2) -> 0 | CC50: =SUMIFS(营销场景数据源!$U:$U,营销场景数据源!$C:$C,$B$47,营销场景数据源!$A:$A,CC2) -> 2 | CD50: =SUMIFS(营销场景数据源!$U:$U,营销场景数据源!$C:$C,$B$47,营销场景数据源!$A:$A,CD2) -> 1 | CE50: =SUMIFS(营销场景数据源!$U:$U,营销场景数据源!$C:$C,$B$47,营销场景数据源!$A:$A,CE2) -> 0 | CF50: =SUMIFS(营销场景数据源!$U:$U,营销场景数据源!$C:$C,$B$47,营销场景数据源!$A:$A,CF2) -> 0 | CG50: =SUMIFS(营销场景数据源!$U:$U,营销场景数据源!$C:$C,$B$47,营销场景数据源!$A:$A,CG2) -> 2 | CH50: =SUMIFS(营销场景数据源!$U:$U,营销场景数据源!$C:$C,$B$47,营销场景数据源!$A:$A,CH2) -> 4 | ... DE50: =SUMIFS(营销场景数据源!$U:$U,营销场景数据源!$C:$C,$B$47,营销场景数据源!$A:$A,DE2) -> 4 | DF50: =SUM(DG50:EJ50) -> 13 | DG50: =SUMIFS(营销场景数据源!$U:$U,营销场景数据源!$C:$C,$B$47,营销场景数据源!$A:$A,DG2) -> 3 | DH50: =SUMIFS(营销场景数据源!$U:$U,营销场景数据源!$C:$C,$B$47,营销场景数据源!$A:$A,DH2) -> 2 | DI50: =SUMIFS(营销场景数据源!$U:$U,营销场景数据源!$C:$C,$B$47,营销场景数据源!$A:$A,DI2) -> 0 | DJ50: =SUMIFS(营销场景数据源!$U:$U,营销场景数据源!$C:$C,$B$47,营销场景数据源!$A:$A,DJ2) -> 0 | DK50: =SUMIFS(营销场景数据源!$U:$U,营销场景数据源!$C:$C,$B$47,营销场景数据源!$A:$A,DK2) -> 1 | DL50: =SUMIFS(营销场景数据源!$U:$U,营销场景数据源!$C:$C,$B$47,营销场景数据源!$A:$A,DL2) -> 0 | DM50: =SUMIFS(营销场景数据源!$U:$U,营销场景数据源!$C:$C,$B$47,营销场景数据源!$A:$A,DM2) -> 2 | DN50: =SUMIFS(营销场景数据源!$U:$U,营销场景数据源!$C:$C,$B$47,营销场景数据源!$A:$A,DN2) -> 0 | ... EJ50: =SUMIFS(营销场景数据源!$U:$U,营销场景数据源!$C:$C,$B$47,营销场景数据源!$A:$A,EJ2) -> 0 | EK50: =SUM(EL50:FP50) -> 44 | EL50: =SUMIFS(营销场景数据源!$U:$U,营销场景数据源!$C:$C,$B$47,营销场景数据源!$A:$A,EL2) -> 2 | EM50: =SUMIFS(营销场景数据源!$U:$U,营销场景数据源!$C:$C,$B$47,营销场景数据源!$A:$A,EM2) -> 0 | EN50: =SUMIFS(营销场景数据源!$U:$U,营销场景数据源!$C:$C,$B$47,营销场景数据源!$A:$A,EN2) -> 0 | EO50: =SUMIFS(营销场景数据源!$U:$U,营销场景数据源!$C:$C,$B$47,营销场景数据源!$A:$A,EO2) -> 0 | EP50: =SUMIFS(营销场景数据源!$U:$U,营销场景数据源!$C:$C,$B$47,营销场景数据源!$A:$A,EP2) -> 19 | EQ50: =SUMIFS(营销场景数据源!$U:$U,营销场景数据源!$C:$C,$B$47,营销场景数据源!$A:$A,EQ2) -> 0 | ER50: =SUMIFS(营销场景数据源!$U:$U,营销场景数据源!$C:$C,$B$47,营销场景数据源!$A:$A,ER2) -> 0 | ES50: =SUMIFS(营销场景数据源!$U:$U,营销场景数据源!$C:$C,$B$47,营销场景数据源!$A:$A,ES2) -> 1 | ... FP50: =SUMIFS(营销场景数据源!$U:$U,营销场景数据源!$C:$C,$B$47,营销场景数据源!$A:$A,FP2) -> 0 | FQ50: =SUM(FR50:GX50) -> 10 | FR50: =SUMIFS(营销场景数据源!$U:$U,营销场景数据源!$C:$C,$B$47,营销场景数据源!$A:$A,FR2) -> 1 | FS50: =SUMIFS(营销场景数据源!$U:$U,营销场景数据源!$C:$C,$B$47,营销场景数据源!$A:$A,FS2) -> 0 | FT50: =SUMIFS(营销场景数据源!$U:$U,营销场景数据源!$C:$C,$B$47,营销场景数据源!$A:$A,FT2) -> 0 | FU50: =SUMIFS(营销场景数据源!$U:$U,营销场景数据源!$C:$C,$B$47,营销场景数据源!$A:$A,FU2) -> 2 | FV50: =SUMIFS(营销场景数据源!$U:$U,营销场景数据源!$C:$C,$B$47,营销场景数据源!$A:$A,FV2) -> 1 | FW50: =SUMIFS(营销场景数据源!$U:$U,营销场景数据源!$C:$C,$B$47,营销场景数据源!$A:$A,FW2) -> 0 | FX50: =SUMIFS(营销场景数据源!$U:$U,营销场景数据源!$C:$C,$B$47,营销场景数据源!$A:$A,FX2) -> 1 | FY50: =SUMIFS(营销场景数据源!$U:$U,营销场景数据源!$C:$C,$B$47,营销场景数据源!$A:$A,FY2) -> 1 | ... GP50: =SUMIFS(营销场景数据源!$U:$U,营销场景数据源!$C:$C,$B$47,营销场景数据源!$A:$A,GP2) -> 0
C51: 总成交金额 | D51: =SUM(E51:P51) -> #REF! | E51: =#REF! -> #REF! | F51: =#REF! -> #REF! | G51: =#REF! -> #REF! | H51: =#REF! -> #REF! | I51: =#REF! -> #REF! | J51: =#REF! -> #REF! | K51: =#REF! -> #REF! | L51: =#REF! -> #REF! | ... P51: =#REF! -> #REF! | Q51: =SUM(R51:AV51) -> 173238.85 | R51: =SUMIFS(营销场景数据源!$T:$T,营销场景数据源!$C:$C,$B$47,营销场景数据源!$A:$A,R2) -> 278.8 | S51: =SUMIFS(营销场景数据源!$T:$T,营销场景数据源!$C:$C,$B$47,营销场景数据源!$A:$A,S2) -> 0 | T51: =SUMIFS(营销场景数据源!$T:$T,营销场景数据源!$C:$C,$B$47,营销场景数据源!$A:$A,T2) -> 0 | U51: =SUMIFS(营销场景数据源!$T:$T,营销场景数据源!$C:$C,$B$47,营销场景数据源!$A:$A,U2) -> 6178.52 | V51: =SUMIFS(营销场景数据源!$T:$T,营销场景数据源!$C:$C,$B$47,营销场景数据源!$A:$A,V2) -> 0 | W51: =SUMIFS(营销场景数据源!$T:$T,营销场景数据源!$C:$C,$B$47,营销场景数据源!$A:$A,W2) -> 726.16 | X51: =SUMIFS(营销场景数据源!$T:$T,营销场景数据源!$C:$C,$B$47,营销场景数据源!$A:$A,X2) -> 0 | Y51: =SUMIFS(营销场景数据源!$T:$T,营销场景数据源!$C:$C,$B$47,营销场景数据源!$A:$A,Y2) -> 0 | ... AV51: =SUMIFS(营销场景数据源!$T:$T,营销场景数据源!$C:$C,$B$47,营销场景数据源!$A:$A,AV2) -> 1283.84 | AW51: =SUM(AX51:BY51) -> 9294.48 | AX51: =SUMIFS(营销场景数据源!$T:$T,营销场景数据源!$C:$C,$B$47,营销场景数据源!$A:$A,AX2) -> 498.27 | AY51: =SUMIFS(营销场景数据源!$T:$T,营销场景数据源!$C:$C,$B$47,营销场景数据源!$A:$A,AY2) -> 0 | AZ51: =SUMIFS(营销场景数据源!$T:$T,营销场景数据源!$C:$C,$B$47,营销场景数据源!$A:$A,AZ2) -> 0 | BA51: =SUMIFS(营销场景数据源!$T:$T,营销场景数据源!$C:$C,$B$47,营销场景数据源!$A:$A,BA2) -> 3706.31 | BB51: =SUMIFS(营销场景数据源!$T:$T,营销场景数据源!$C:$C,$B$47,营销场景数据源!$A:$A,BB2) -> 1154.56 | BC51: =SUMIFS(营销场景数据源!$T:$T,营销场景数据源!$C:$C,$B$47,营销场景数据源!$A:$A,BC2) -> 1746.96 | BD51: =SUMIFS(营销场景数据源!$T:$T,营销场景数据源!$C:$C,$B$47,营销场景数据源!$A:$A,BD2) -> 65.35 | BE51: =SUMIFS(营销场景数据源!$T:$T,营销场景数据源!$C:$C,$B$47,营销场景数据源!$A:$A,BE2) -> 147.24 | ... BY51: =SUMIFS(营销场景数据源!$T:$T,营销场景数据源!$C:$C,$B$47,营销场景数据源!$A:$A,BY2) -> 0 | BZ51: =SUM(CA51:DE51) -> 7406.71 | CA51: =SUMIFS(营销场景数据源!$T:$T,营销场景数据源!$C:$C,$B$47,营销场景数据源!$A:$A,CA2) -> 318.7 | CB51: =SUMIFS(营销场景数据源!$T:$T,营销场景数据源!$C:$C,$B$47,营销场景数据源!$A:$A,CB2) -> 0 | CC51: =SUMIFS(营销场景数据源!$T:$T,营销场景数据源!$C:$C,$B$47,营销场景数据源!$A:$A,CC2) -> 291.24 | CD51: =SUMIFS(营销场景数据源!$T:$T,营销场景数据源!$C:$C,$B$47,营销场景数据源!$A:$A,CD2) -> 262.24 | CE51: =SUMIFS(营销场景数据源!$T:$T,营销场景数据源!$C:$C,$B$47,营销场景数据源!$A:$A,CE2) -> 0 | CF51: =SUMIFS(营销场景数据源!$T:$T,营销场景数据源!$C:$C,$B$47,营销场景数据源!$A:$A,CF2) -> 0 | CG51: =SUMIFS(营销场景数据源!$T:$T,营销场景数据源!$C:$C,$B$47,营销场景数据源!$A:$A,CG2) -> 148.4 | CH51: =SUMIFS(营销场景数据源!$T:$T,营销场景数据源!$C:$C,$B$47,营销场景数据源!$A:$A,CH2) -> 384.49 | ... DE51: =SUMIFS(营销场景数据源!$T:$T,营销场景数据源!$C:$C,$B$47,营销场景数据源!$A:$A,DE2) -> 249.2 | DF51: =SUM(DG51:EJ51) -> 2746.02 | DG51: =SUMIFS(营销场景数据源!$T:$T,营销场景数据源!$C:$C,$B$47,营销场景数据源!$A:$A,DG2) -> 183.71 | DH51: =SUMIFS(营销场景数据源!$T:$T,营销场景数据源!$C:$C,$B$47,营销场景数据源!$A:$A,DH2) -> 63.9 | DI51: =SUMIFS(营销场景数据源!$T:$T,营销场景数据源!$C:$C,$B$47,营销场景数据源!$A:$A,DI2) -> 0 | DJ51: =SUMIFS(营销场景数据源!$T:$T,营销场景数据源!$C:$C,$B$47,营销场景数据源!$A:$A,DJ2) -> 0 | DK51: =SUMIFS(营销场景数据源!$T:$T,营销场景数据源!$C:$C,$B$47,营销场景数据源!$A:$A,DK2) -> 70.2 | DL51: =SUMIFS(营销场景数据源!$T:$T,营销场景数据源!$C:$C,$B$47,营销场景数据源!$A:$A,DL2) -> 0 | DM51: =SUMIFS(营销场景数据源!$T:$T,营销场景数据源!$C:$C,$B$47,营销场景数据源!$A:$A,DM2) -> 900.94 | DN51: =SUMIFS(营销场景数据源!$T:$T,营销场景数据源!$C:$C,$B$47,营销场景数据源!$A:$A,DN2) -> 0 | ... EJ51: =SUMIFS(营销场景数据源!$T:$T,营销场景数据源!$C:$C,$B$47,营销场景数据源!$A:$A,EJ2) -> 0 | EK51: =SUM(EL51:FP51) -> 23029.77 | EL51: =SUMIFS(营销场景数据源!$T:$T,营销场景数据源!$C:$C,$B$47,营销场景数据源!$A:$A,EL2) -> 189.05 | EM51: =SUMIFS(营销场景数据源!$T:$T,营销场景数据源!$C:$C,$B$47,营销场景数据源!$A:$A,EM2) -> 0 | EN51: =SUMIFS(营销场景数据源!$T:$T,营销场景数据源!$C:$C,$B$47,营销场景数据源!$A:$A,EN2) -> 0 | EO51: =SUMIFS(营销场景数据源!$T:$T,营销场景数据源!$C:$C,$B$47,营销场景数据源!$A:$A,EO2) -> 0 | EP51: =SUMIFS(营销场景数据源!$T:$T,营销场景数据源!$C:$C,$B$47,营销场景数据源!$A:$A,EP2) -> 4537.75 | EQ51: =SUMIFS(营销场景数据源!$T:$T,营销场景数据源!$C:$C,$B$47,营销场景数据源!$A:$A,EQ2) -> 0 | ER51: =SUMIFS(营销场景数据源!$T:$T,营销场景数据源!$C:$C,$B$47,营销场景数据源!$A:$A,ER2) -> 0 | ES51: =SUMIFS(营销场景数据源!$T:$T,营销场景数据源!$C:$C,$B$47,营销场景数据源!$A:$A,ES2) -> 81.13 | ... FP51: =SUMIFS(营销场景数据源!$T:$T,营销场景数据源!$C:$C,$B$47,营销场景数据源!$A:$A,FP2) -> 0 | FQ51: =SUM(FR51:GX51) -> 2038.54 | FR51: =SUMIFS(营销场景数据源!$T:$T,营销场景数据源!$C:$C,$B$47,营销场景数据源!$A:$A,FR2) -> 37.93 | FS51: =SUMIFS(营销场景数据源!$T:$T,营销场景数据源!$C:$C,$B$47,营销场景数据源!$A:$A,FS2) -> 0 | FT51: =SUMIFS(营销场景数据源!$T:$T,营销场景数据源!$C:$C,$B$47,营销场景数据源!$A:$A,FT2) -> 0 | FU51: =SUMIFS(营销场景数据源!$T:$T,营销场景数据源!$C:$C,$B$47,营销场景数据源!$A:$A,FU2) -> 383.64 | FV51: =SUMIFS(营销场景数据源!$T:$T,营销场景数据源!$C:$C,$B$47,营销场景数据源!$A:$A,FV2) -> 245 | FW51: =SUMIFS(营销场景数据源!$T:$T,营销场景数据源!$C:$C,$B$47,营销场景数据源!$A:$A,FW2) -> 0 | FX51: =SUMIFS(营销场景数据源!$T:$T,营销场景数据源!$C:$C,$B$47,营销场景数据源!$A:$A,FX2) -> 414 | FY51: =SUMIFS(营销场景数据源!$T:$T,营销场景数据源!$C:$C,$B$47,营销场景数据源!$A:$A,FY2) -> 331.73 | ... GP51: =SUMIFS(营销场景数据源!$T:$T,营销场景数据源!$C:$C,$B$47,营销场景数据源!$A:$A,GP2) -> 0
C52: 点击单价 | D52: =IFERROR(D47/D48,0) -> 0 | E52: =IFERROR(E47/E48,0) -> 0 | F52: =IFERROR(F47/F48,0) -> 0 | G52: =IFERROR(G47/G48,0) -> 0 | H52: =IFERROR(H47/H48,0) -> 0 | I52: =IFERROR(I47/I48,0) -> 0 | J52: =IFERROR(J47/J48,0) -> 0 | K52: =IFERROR(K47/K48,0) -> 0 | ... GP52: =IFERROR(GP47/GP48,0) -> 0
C53: 加购成本 | D53: =IFERROR(D47/D49,0) -> 0 | E53: =IFERROR(E47/E49,0) -> 0 | F53: =IFERROR(F47/F49,0) -> 0 | G53: =IFERROR(G47/G49,0) -> 0 | H53: =IFERROR(H47/H49,0) -> 0 | I53: =IFERROR(I47/I49,0) -> 0 | J53: =IFERROR(J47/J49,0) -> 0 | K53: =IFERROR(K47/K49,0) -> 0 | ... GP53: =IFERROR(GP47/GP49,0) -> 0
C54: ROI | D54: =IFERROR(D51/D47,0) -> 0 | E54: =IFERROR(E51/E47,0) -> 0 | F54: =IFERROR(F51/F47,0) -> 0 | G54: =IFERROR(G51/G47,0) -> 0 | H54: =IFERROR(H51/H47,0) -> 0 | I54: =IFERROR(I51/I47,0) -> 0 | J54: =IFERROR(J51/J47,0) -> 0 | K54: =IFERROR(K51/K47,0) -> 0 | ... GP54: =IFERROR(GP51/GP47,0) -> 0
C55: 费用占比 | D55: =D47/D$130 -> #REF! | E55: =E47/E$130 -> #REF! | F55: =F47/F$130 -> #REF! | G55: =G47/G$130 -> #REF! | H55: =H47/H$130 -> #REF! | I55: =I47/I$130 -> #REF! | J55: =J47/J$130 -> #REF! | K55: =K47/K$130 -> #REF! | ... GP55: =GP47/GP$130 -> #DIV/0!
B56: 超级短视频 | C56: 花费 | D56: =SUM(E56:P56) -> #REF! | E56: =#REF! -> #REF! | F56: =#REF! -> #REF! | G56: =#REF! -> #REF! | H56: =#REF! -> #REF! | I56: =#REF! -> #REF! | J56: =#REF! -> #REF! | K56: =#REF! -> #REF! | L56: =#REF! -> #REF! | ... P56: =#REF! -> #REF! | Q56: =SUM(R56:AV56) -> 2784.46 | R56: =SUMIFS(营销场景数据源!$H:$H,营销场景数据源!$C:$C,$B$56,营销场景数据源!$A:$A,R2) -> 0 | S56: =SUMIFS(营销场景数据源!$H:$H,营销场景数据源!$C:$C,$B$56,营销场景数据源!$A:$A,S2) -> 0 | T56: =SUMIFS(营销场景数据源!$H:$H,营销场景数据源!$C:$C,$B$56,营销场景数据源!$A:$A,T2) -> 0 | U56: =SUMIFS(营销场景数据源!$H:$H,营销场景数据源!$C:$C,$B$56,营销场景数据源!$A:$A,U2) -> 94.16 | V56: =SUMIFS(营销场景数据源!$H:$H,营销场景数据源!$C:$C,$B$56,营销场景数据源!$A:$A,V2) -> 99.45 | W56: =SUMIFS(营销场景数据源!$H:$H,营销场景数据源!$C:$C,$B$56,营销场景数据源!$A:$A,W2) -> 100 | X56: =SUMIFS(营销场景数据源!$H:$H,营销场景数据源!$C:$C,$B$56,营销场景数据源!$A:$A,X2) -> 98.66 | Y56: =SUMIFS(营销场景数据源!$H:$H,营销场景数据源!$C:$C,$B$56,营销场景数据源!$A:$A,Y2) -> 98.93 | ... AV56: =SUMIFS(营销场景数据源!$H:$H,营销场景数据源!$C:$C,$B$56,营销场景数据源!$A:$A,AV2) -> 100 | AW56: =SUM(AX56:BY56) -> 1796.64 | AX56: =SUMIFS(营销场景数据源!$H:$H,营销场景数据源!$C:$C,$B$56,营销场景数据源!$A:$A,AX2) -> 100 | AY56: =SUMIFS(营销场景数据源!$H:$H,营销场景数据源!$C:$C,$B$56,营销场景数据源!$A:$A,AY2) -> 100 | AZ56: =SUMIFS(营销场景数据源!$H:$H,营销场景数据源!$C:$C,$B$56,营销场景数据源!$A:$A,AZ2) -> 100 | BA56: =SUMIFS(营销场景数据源!$H:$H,营销场景数据源!$C:$C,$B$56,营销场景数据源!$A:$A,BA2) -> 100 | BB56: =SUMIFS(营销场景数据源!$H:$H,营销场景数据源!$C:$C,$B$56,营销场景数据源!$A:$A,BB2) -> 100 | BC56: =SUMIFS(营销场景数据源!$H:$H,营销场景数据源!$C:$C,$B$56,营销场景数据源!$A:$A,BC2) -> 100 | BD56: =SUMIFS(营销场景数据源!$H:$H,营销场景数据源!$C:$C,$B$56,营销场景数据源!$A:$A,BD2) -> 100 | BE56: =SUMIFS(营销场景数据源!$H:$H,营销场景数据源!$C:$C,$B$56,营销场景数据源!$A:$A,BE2) -> 100 | ... BY56: =SUMIFS(营销场景数据源!$H:$H,营销场景数据源!$C:$C,$B$56,营销场景数据源!$A:$A,BY2) -> 100 | BZ56: =SUM(CA56:DE56) -> 5927.76 | CA56: =SUMIFS(营销场景数据源!$H:$H,营销场景数据源!$C:$C,$B$56,营销场景数据源!$A:$A,CA2) -> 100 | CB56: =SUMIFS(营销场景数据源!$H:$H,营销场景数据源!$C:$C,$B$56,营销场景数据源!$A:$A,CB2) -> 100 | CC56: =SUMIFS(营销场景数据源!$H:$H,营销场景数据源!$C:$C,$B$56,营销场景数据源!$A:$A,CC2) -> 100 | CD56: =SUMIFS(营销场景数据源!$H:$H,营销场景数据源!$C:$C,$B$56,营销场景数据源!$A:$A,CD2) -> 178.09 | CE56: =SUMIFS(营销场景数据源!$H:$H,营销场景数据源!$C:$C,$B$56,营销场景数据源!$A:$A,CE2) -> 197.65 | CF56: =SUMIFS(营销场景数据源!$H:$H,营销场景数据源!$C:$C,$B$56,营销场景数据源!$A:$A,CF2) -> 173.28 | CG56: =SUMIFS(营销场景数据源!$H:$H,营销场景数据源!$C:$C,$B$56,营销场景数据源!$A:$A,CG2) -> 100 | CH56: =SUMIFS(营销场景数据源!$H:$H,营销场景数据源!$C:$C,$B$56,营销场景数据源!$A:$A,CH2) -> 100 | ... DE56: =SUMIFS(营销场景数据源!$H:$H,营销场景数据源!$C:$C,$B$56,营销场景数据源!$A:$A,DE2) -> 200 | DF56: =SUM(DG56:EJ56) -> 4495.99 | DG56: =SUMIFS(营销场景数据源!$H:$H,营销场景数据源!$C:$C,$B$56,营销场景数据源!$A:$A,DG2) -> 140.38 | DH56: =SUMIFS(营销场景数据源!$H:$H,营销场景数据源!$C:$C,$B$56,营销场景数据源!$A:$A,DH2) -> 100 | DI56: =SUMIFS(营销场景数据源!$H:$H,营销场景数据源!$C:$C,$B$56,营销场景数据源!$A:$A,DI2) -> 100 | DJ56: =SUMIFS(营销场景数据源!$H:$H,营销场景数据源!$C:$C,$B$56,营销场景数据源!$A:$A,DJ2) -> 100 | DK56: =SUMIFS(营销场景数据源!$H:$H,营销场景数据源!$C:$C,$B$56,营销场景数据源!$A:$A,DK2) -> 100 | DL56: =SUMIFS(营销场景数据源!$H:$H,营销场景数据源!$C:$C,$B$56,营销场景数据源!$A:$A,DL2) -> 100 | DM56: =SUMIFS(营销场景数据源!$H:$H,营销场景数据源!$C:$C,$B$56,营销场景数据源!$A:$A,DM2) -> 242.7 | DN56: =SUMIFS(营销场景数据源!$H:$H,营销场景数据源!$C:$C,$B$56,营销场景数据源!$A:$A,DN2) -> 346.91 | ... EJ56: =SUMIFS(营销场景数据源!$H:$H,营销场景数据源!$C:$C,$B$56,营销场景数据源!$A:$A,EJ2) -> 100 | EK56: =SUM(EL56:FP56) -> 3982.76 | EL56: =SUMIFS(营销场景数据源!$H:$H,营销场景数据源!$C:$C,$B$56,营销场景数据源!$A:$A,EL2) -> 100 | EM56: =SUMIFS(营销场景数据源!$H:$H,营销场景数据源!$C:$C,$B$56,营销场景数据源!$A:$A,EM2) -> 100 | EN56: =SUMIFS(营销场景数据源!$H:$H,营销场景数据源!$C:$C,$B$56,营销场景数据源!$A:$A,EN2) -> 100 | EO56: =SUMIFS(营销场景数据源!$H:$H,营销场景数据源!$C:$C,$B$56,营销场景数据源!$A:$A,EO2) -> 100 | EP56: =SUMIFS(营销场景数据源!$H:$H,营销场景数据源!$C:$C,$B$56,营销场景数据源!$A:$A,EP2) -> 100 | EQ56: =SUMIFS(营销场景数据源!$H:$H,营销场景数据源!$C:$C,$B$56,营销场景数据源!$A:$A,EQ2) -> 100 | ER56: =SUMIFS(营销场景数据源!$H:$H,营销场景数据源!$C:$C,$B$56,营销场景数据源!$A:$A,ER2) -> 100 | ES56: =SUMIFS(营销场景数据源!$H:$H,营销场景数据源!$C:$C,$B$56,营销场景数据源!$A:$A,ES2) -> 277.77 | ... FP56: =SUMIFS(营销场景数据源!$H:$H,营销场景数据源!$C:$C,$B$56,营销场景数据源!$A:$A,FP2) -> 100 | FQ56: =SUM(FR56:GX56) -> 2392.3 | FR56: =SUMIFS(营销场景数据源!$H:$H,营销场景数据源!$C:$C,$B$56,营销场景数据源!$A:$A,FR2) -> 100 | FS56: =SUMIFS(营销场景数据源!$H:$H,营销场景数据源!$C:$C,$B$56,营销场景数据源!$A:$A,FS2) -> 100 | FT56: =SUMIFS(营销场景数据源!$H:$H,营销场景数据源!$C:$C,$B$56,营销场景数据源!$A:$A,FT2) -> 100 | FU56: =SUMIFS(营销场景数据源!$H:$H,营销场景数据源!$C:$C,$B$56,营销场景数据源!$A:$A,FU2) -> 100 | FV56: =SUMIFS(营销场景数据源!$H:$H,营销场景数据源!$C:$C,$B$56,营销场景数据源!$A:$A,FV2) -> 100 | FW56: =SUMIFS(营销场景数据源!$H:$H,营销场景数据源!$C:$C,$B$56,营销场景数据源!$A:$A,FW2) -> 100 | FX56: =SUMIFS(营销场景数据源!$H:$H,营销场景数据源!$C:$C,$B$56,营销场景数据源!$A:$A,FX2) -> 100 | FY56: =SUMIFS(营销场景数据源!$H:$H,营销场景数据源!$C:$C,$B$56,营销场景数据源!$A:$A,FY2) -> 100 | ... GP56: =SUMIFS(营销场景数据源!$H:$H,营销场景数据源!$C:$C,$B$56,营销场景数据源!$A:$A,GP2) -> 0
C57: 点击量 | D57: =SUM(E57:P57) -> #REF! | E57: =#REF! -> #REF! | F57: =#REF! -> #REF! | G57: =#REF! -> #REF! | H57: =#REF! -> #REF! | I57: =#REF! -> #REF! | J57: =#REF! -> #REF! | K57: =#REF! -> #REF! | L57: =#REF! -> #REF! | ... P57: =#REF! -> #REF! | Q57: =SUM(R57:AV57) -> 1804 | R57: =SUMIFS(营销场景数据源!$G:$G,营销场景数据源!$C:$C,$B$56,营销场景数据源!$A:$A,R2) -> 0 | S57: =SUMIFS(营销场景数据源!$G:$G,营销场景数据源!$C:$C,$B$56,营销场景数据源!$A:$A,S2) -> 0 | T57: =SUMIFS(营销场景数据源!$G:$G,营销场景数据源!$C:$C,$B$56,营销场景数据源!$A:$A,T2) -> 0 | U57: =SUMIFS(营销场景数据源!$G:$G,营销场景数据源!$C:$C,$B$56,营销场景数据源!$A:$A,U2) -> 44 | V57: =SUMIFS(营销场景数据源!$G:$G,营销场景数据源!$C:$C,$B$56,营销场景数据源!$A:$A,V2) -> 67 | W57: =SUMIFS(营销场景数据源!$G:$G,营销场景数据源!$C:$C,$B$56,营销场景数据源!$A:$A,W2) -> 64 | X57: =SUMIFS(营销场景数据源!$G:$G,营销场景数据源!$C:$C,$B$56,营销场景数据源!$A:$A,X2) -> 74 | Y57: =SUMIFS(营销场景数据源!$G:$G,营销场景数据源!$C:$C,$B$56,营销场景数据源!$A:$A,Y2) -> 86 | ... AV57: =SUMIFS(营销场景数据源!$G:$G,营销场景数据源!$C:$C,$B$56,营销场景数据源!$A:$A,AV2) -> 48 | AW57: =SUM(AX57:BY57) -> 775 | AX57: =SUMIFS(营销场景数据源!$G:$G,营销场景数据源!$C:$C,$B$56,营销场景数据源!$A:$A,AX2) -> 43 | AY57: =SUMIFS(营销场景数据源!$G:$G,营销场景数据源!$C:$C,$B$56,营销场景数据源!$A:$A,AY2) -> 53 | AZ57: =SUMIFS(营销场景数据源!$G:$G,营销场景数据源!$C:$C,$B$56,营销场景数据源!$A:$A,AZ2) -> 39 | BA57: =SUMIFS(营销场景数据源!$G:$G,营销场景数据源!$C:$C,$B$56,营销场景数据源!$A:$A,BA2) -> 43 | BB57: =SUMIFS(营销场景数据源!$G:$G,营销场景数据源!$C:$C,$B$56,营销场景数据源!$A:$A,BB2) -> 33 | BC57: =SUMIFS(营销场景数据源!$G:$G,营销场景数据源!$C:$C,$B$56,营销场景数据源!$A:$A,BC2) -> 43 | BD57: =SUMIFS(营销场景数据源!$G:$G,营销场景数据源!$C:$C,$B$56,营销场景数据源!$A:$A,BD2) -> 40 | BE57: =SUMIFS(营销场景数据源!$G:$G,营销场景数据源!$C:$C,$B$56,营销场景数据源!$A:$A,BE2) -> 44 | ... BY57: =SUMIFS(营销场景数据源!$G:$G,营销场景数据源!$C:$C,$B$56,营销场景数据源!$A:$A,BY2) -> 48 | BZ57: =SUM(CA57:DE57) -> 3119 | CA57: =SUMIFS(营销场景数据源!$G:$G,营销场景数据源!$C:$C,$B$56,营销场景数据源!$A:$A,CA2) -> 56 | CB57: =SUMIFS(营销场景数据源!$G:$G,营销场景数据源!$C:$C,$B$56,营销场景数据源!$A:$A,CB2) -> 50 | CC57: =SUMIFS(营销场景数据源!$G:$G,营销场景数据源!$C:$C,$B$56,营销场景数据源!$A:$A,CC2) -> 40 | CD57: =SUMIFS(营销场景数据源!$G:$G,营销场景数据源!$C:$C,$B$56,营销场景数据源!$A:$A,CD2) -> 72 | CE57: =SUMIFS(营销场景数据源!$G:$G,营销场景数据源!$C:$C,$B$56,营销场景数据源!$A:$A,CE2) -> 110 | CF57: =SUMIFS(营销场景数据源!$G:$G,营销场景数据源!$C:$C,$B$56,营销场景数据源!$A:$A,CF2) -> 119 | CG57: =SUMIFS(营销场景数据源!$G:$G,营销场景数据源!$C:$C,$B$56,营销场景数据源!$A:$A,CG2) -> 42 | CH57: =SUMIFS(营销场景数据源!$G:$G,营销场景数据源!$C:$C,$B$56,营销场景数据源!$A:$A,CH2) -> 62 | ... DE57: =SUMIFS(营销场景数据源!$G:$G,营销场景数据源!$C:$C,$B$56,营销场景数据源!$A:$A,DE2) -> 111 | DF57: =SUM(DG57:EJ57) -> 1981 | DG57: =SUMIFS(营销场景数据源!$G:$G,营销场景数据源!$C:$C,$B$56,营销场景数据源!$A:$A,DG2) -> 80 | DH57: =SUMIFS(营销场景数据源!$G:$G,营销场景数据源!$C:$C,$B$56,营销场景数据源!$A:$A,DH2) -> 43 | DI57: =SUMIFS(营销场景数据源!$G:$G,营销场景数据源!$C:$C,$B$56,营销场景数据源!$A:$A,DI2) -> 42 | DJ57: =SUMIFS(营销场景数据源!$G:$G,营销场景数据源!$C:$C,$B$56,营销场景数据源!$A:$A,DJ2) -> 48 | DK57: =SUMIFS(营销场景数据源!$G:$G,营销场景数据源!$C:$C,$B$56,营销场景数据源!$A:$A,DK2) -> 47 | DL57: =SUMIFS(营销场景数据源!$G:$G,营销场景数据源!$C:$C,$B$56,营销场景数据源!$A:$A,DL2) -> 55 | DM57: =SUMIFS(营销场景数据源!$G:$G,营销场景数据源!$C:$C,$B$56,营销场景数据源!$A:$A,DM2) -> 85 | DN57: =SUMIFS(营销场景数据源!$G:$G,营销场景数据源!$C:$C,$B$56,营销场景数据源!$A:$A,DN2) -> 136 | ... EJ57: =SUMIFS(营销场景数据源!$G:$G,营销场景数据源!$C:$C,$B$56,营销场景数据源!$A:$A,EJ2) -> 52 | EK57: =SUM(EL57:FP57) -> 2607 | EL57: =SUMIFS(营销场景数据源!$G:$G,营销场景数据源!$C:$C,$B$56,营销场景数据源!$A:$A,EL2) -> 50 | EM57: =SUMIFS(营销场景数据源!$G:$G,营销场景数据源!$C:$C,$B$56,营销场景数据源!$A:$A,EM2) -> 49 | EN57: =SUMIFS(营销场景数据源!$G:$G,营销场景数据源!$C:$C,$B$56,营销场景数据源!$A:$A,EN2) -> 52 | EO57: =SUMIFS(营销场景数据源!$G:$G,营销场景数据源!$C:$C,$B$56,营销场景数据源!$A:$A,EO2) -> 58 | EP57: =SUMIFS(营销场景数据源!$G:$G,营销场景数据源!$C:$C,$B$56,营销场景数据源!$A:$A,EP2) -> 52 | EQ57: =SUMIFS(营销场景数据源!$G:$G,营销场景数据源!$C:$C,$B$56,营销场景数据源!$A:$A,EQ2) -> 40 | ER57: =SUMIFS(营销场景数据源!$G:$G,营销场景数据源!$C:$C,$B$56,营销场景数据源!$A:$A,ER2) -> 42 | ES57: =SUMIFS(营销场景数据源!$G:$G,营销场景数据源!$C:$C,$B$56,营销场景数据源!$A:$A,ES2) -> 320 | ... FP57: =SUMIFS(营销场景数据源!$G:$G,营销场景数据源!$C:$C,$B$56,营销场景数据源!$A:$A,FP2) -> 40 | FQ57: =SUM(FR57:GX57) -> 911 | FR57: =SUMIFS(营销场景数据源!$G:$G,营销场景数据源!$C:$C,$B$56,营销场景数据源!$A:$A,FR2) -> 39 | FS57: =SUMIFS(营销场景数据源!$G:$G,营销场景数据源!$C:$C,$B$56,营销场景数据源!$A:$A,FS2) -> 46 | FT57: =SUMIFS(营销场景数据源!$G:$G,营销场景数据源!$C:$C,$B$56,营销场景数据源!$A:$A,FT2) -> 51 | FU57: =SUMIFS(营销场景数据源!$G:$G,营销场景数据源!$C:$C,$B$56,营销场景数据源!$A:$A,FU2) -> 38 | FV57: =SUMIFS(营销场景数据源!$G:$G,营销场景数据源!$C:$C,$B$56,营销场景数据源!$A:$A,FV2) -> 46 | FW57: =SUMIFS(营销场景数据源!$G:$G,营销场景数据源!$C:$C,$B$56,营销场景数据源!$A:$A,FW2) -> 40 | FX57: =SUMIFS(营销场景数据源!$G:$G,营销场景数据源!$C:$C,$B$56,营销场景数据源!$A:$A,FX2) -> 45 | FY57: =SUMIFS(营销场景数据源!$G:$G,营销场景数据源!$C:$C,$B$56,营销场景数据源!$A:$A,FY2) -> 42 | ... GP57: =SUMIFS(营销场景数据源!$G:$G,营销场景数据源!$C:$C,$B$56,营销场景数据源!$A:$A,GP2) -> 0
C58: 总购物车数 | D58: =SUM(E58:P58) -> #REF! | E58: =#REF! -> #REF! | F58: =#REF! -> #REF! | G58: =#REF! -> #REF! | H58: =#REF! -> #REF! | I58: =#REF! -> #REF! | J58: =#REF! -> #REF! | K58: =#REF! -> #REF! | L58: =#REF! -> #REF! | ... P58: =#REF! -> #REF! | Q58: =SUM(R58:AV58) -> 179 | R58: =SUMIFS(营销场景数据源!$AB:$AB,营销场景数据源!$C:$C,$B$56,营销场景数据源!$A:$A,R2) -> 0 | S58: =SUMIFS(营销场景数据源!$AB:$AB,营销场景数据源!$C:$C,$B$56,营销场景数据源!$A:$A,S2) -> 0 | T58: =SUMIFS(营销场景数据源!$AB:$AB,营销场景数据源!$C:$C,$B$56,营销场景数据源!$A:$A,T2) -> 0 | U58: =SUMIFS(营销场景数据源!$AB:$AB,营销场景数据源!$C:$C,$B$56,营销场景数据源!$A:$A,U2) -> 6 | V58: =SUMIFS(营销场景数据源!$AB:$AB,营销场景数据源!$C:$C,$B$56,营销场景数据源!$A:$A,V2) -> 5 | W58: =SUMIFS(营销场景数据源!$AB:$AB,营销场景数据源!$C:$C,$B$56,营销场景数据源!$A:$A,W2) -> 8 | X58: =SUMIFS(营销场景数据源!$AB:$AB,营销场景数据源!$C:$C,$B$56,营销场景数据源!$A:$A,X2) -> 11 | Y58: =SUMIFS(营销场景数据源!$AB:$AB,营销场景数据源!$C:$C,$B$56,营销场景数据源!$A:$A,Y2) -> 5 | ... AV58: =SUMIFS(营销场景数据源!$AB:$AB,营销场景数据源!$C:$C,$B$56,营销场景数据源!$A:$A,AV2) -> 5 | AW58: =SUM(AX58:BY58) -> 103 | AX58: =SUMIFS(营销场景数据源!$AB:$AB,营销场景数据源!$C:$C,$B$56,营销场景数据源!$A:$A,AX2) -> 8 | AY58: =SUMIFS(营销场景数据源!$AB:$AB,营销场景数据源!$C:$C,$B$56,营销场景数据源!$A:$A,AY2) -> 5 | AZ58: =SUMIFS(营销场景数据源!$AB:$AB,营销场景数据源!$C:$C,$B$56,营销场景数据源!$A:$A,AZ2) -> 5 | BA58: =SUMIFS(营销场景数据源!$AB:$AB,营销场景数据源!$C:$C,$B$56,营销场景数据源!$A:$A,BA2) -> 1 | BB58: =SUMIFS(营销场景数据源!$AB:$AB,营销场景数据源!$C:$C,$B$56,营销场景数据源!$A:$A,BB2) -> 3 | BC58: =SUMIFS(营销场景数据源!$AB:$AB,营销场景数据源!$C:$C,$B$56,营销场景数据源!$A:$A,BC2) -> 7 | BD58: =SUMIFS(营销场景数据源!$AB:$AB,营销场景数据源!$C:$C,$B$56,营销场景数据源!$A:$A,BD2) -> 6 | BE58: =SUMIFS(营销场景数据源!$AB:$AB,营销场景数据源!$C:$C,$B$56,营销场景数据源!$A:$A,BE2) -> 17 | ... BY58: =SUMIFS(营销场景数据源!$AB:$AB,营销场景数据源!$C:$C,$B$56,营销场景数据源!$A:$A,BY2) -> 2 | BZ58: =SUM(CA58:DE58) -> 279 | CA58: =SUMIFS(营销场景数据源!$AB:$AB,营销场景数据源!$C:$C,$B$56,营销场景数据源!$A:$A,CA2) -> 9 | CB58: =SUMIFS(营销场景数据源!$AB:$AB,营销场景数据源!$C:$C,$B$56,营销场景数据源!$A:$A,CB2) -> 8 | CC58: =SUMIFS(营销场景数据源!$AB:$AB,营销场景数据源!$C:$C,$B$56,营销场景数据源!$A:$A,CC2) -> 3 | CD58: =SUMIFS(营销场景数据源!$AB:$AB,营销场景数据源!$C:$C,$B$56,营销场景数据源!$A:$A,CD2) -> 10 | CE58: =SUMIFS(营销场景数据源!$AB:$AB,营销场景数据源!$C:$C,$B$56,营销场景数据源!$A:$A,CE2) -> 5 | CF58: =SUMIFS(营销场景数据源!$AB:$AB,营销场景数据源!$C:$C,$B$56,营销场景数据源!$A:$A,CF2) -> 3 | CG58: =SUMIFS(营销场景数据源!$AB:$AB,营销场景数据源!$C:$C,$B$56,营销场景数据源!$A:$A,CG2) -> 7 | CH58: =SUMIFS(营销场景数据源!$AB:$AB,营销场景数据源!$C:$C,$B$56,营销场景数据源!$A:$A,CH2) -> 17 | ... DE58: =SUMIFS(营销场景数据源!$AB:$AB,营销场景数据源!$C:$C,$B$56,营销场景数据源!$A:$A,DE2) -> 7 | DF58: =SUM(DG58:EJ58) -> 142 | DG58: =SUMIFS(营销场景数据源!$AB:$AB,营销场景数据源!$C:$C,$B$56,营销场景数据源!$A:$A,DG2) -> 3 | DH58: =SUMIFS(营销场景数据源!$AB:$AB,营销场景数据源!$C:$C,$B$56,营销场景数据源!$A:$A,DH2) -> 3 | DI58: =SUMIFS(营销场景数据源!$AB:$AB,营销场景数据源!$C:$C,$B$56,营销场景数据源!$A:$A,DI2) -> 0 | DJ58: =SUMIFS(营销场景数据源!$AB:$AB,营销场景数据源!$C:$C,$B$56,营销场景数据源!$A:$A,DJ2) -> 2 | DK58: =SUMIFS(营销场景数据源!$AB:$AB,营销场景数据源!$C:$C,$B$56,营销场景数据源!$A:$A,DK2) -> 4 | DL58: =SUMIFS(营销场景数据源!$AB:$AB,营销场景数据源!$C:$C,$B$56,营销场景数据源!$A:$A,DL2) -> 4 | DM58: =SUMIFS(营销场景数据源!$AB:$AB,营销场景数据源!$C:$C,$B$56,营销场景数据源!$A:$A,DM2) -> 4 | DN58: =SUMIFS(营销场景数据源!$AB:$AB,营销场景数据源!$C:$C,$B$56,营销场景数据源!$A:$A,DN2) -> 3 | ... EJ58: =SUMIFS(营销场景数据源!$AB:$AB,营销场景数据源!$C:$C,$B$56,营销场景数据源!$A:$A,EJ2) -> 2 | EK58: =SUM(EL58:FP58) -> 179 | EL58: =SUMIFS(营销场景数据源!$AB:$AB,营销场景数据源!$C:$C,$B$56,营销场景数据源!$A:$A,EL2) -> 6 | EM58: =SUMIFS(营销场景数据源!$AB:$AB,营销场景数据源!$C:$C,$B$56,营销场景数据源!$A:$A,EM2) -> 1 | EN58: =SUMIFS(营销场景数据源!$AB:$AB,营销场景数据源!$C:$C,$B$56,营销场景数据源!$A:$A,EN2) -> 4 | EO58: =SUMIFS(营销场景数据源!$AB:$AB,营销场景数据源!$C:$C,$B$56,营销场景数据源!$A:$A,EO2) -> 4 | EP58: =SUMIFS(营销场景数据源!$AB:$AB,营销场景数据源!$C:$C,$B$56,营销场景数据源!$A:$A,EP2) -> 2 | EQ58: =SUMIFS(营销场景数据源!$AB:$AB,营销场景数据源!$C:$C,$B$56,营销场景数据源!$A:$A,EQ2) -> 1 | ER58: =SUMIFS(营销场景数据源!$AB:$AB,营销场景数据源!$C:$C,$B$56,营销场景数据源!$A:$A,ER2) -> 4 | ES58: =SUMIFS(营销场景数据源!$AB:$AB,营销场景数据源!$C:$C,$B$56,营销场景数据源!$A:$A,ES2) -> 4 | ... FP58: =SUMIFS(营销场景数据源!$AB:$AB,营销场景数据源!$C:$C,$B$56,营销场景数据源!$A:$A,FP2) -> 3 | FQ58: =SUM(FR58:GX58) -> 99 | FR58: =SUMIFS(营销场景数据源!$AB:$AB,营销场景数据源!$C:$C,$B$56,营销场景数据源!$A:$A,FR2) -> 3 | FS58: =SUMIFS(营销场景数据源!$AB:$AB,营销场景数据源!$C:$C,$B$56,营销场景数据源!$A:$A,FS2) -> 5 | FT58: =SUMIFS(营销场景数据源!$AB:$AB,营销场景数据源!$C:$C,$B$56,营销场景数据源!$A:$A,FT2) -> 4 | FU58: =SUMIFS(营销场景数据源!$AB:$AB,营销场景数据源!$C:$C,$B$56,营销场景数据源!$A:$A,FU2) -> 3 | FV58: =SUMIFS(营销场景数据源!$AB:$AB,营销场景数据源!$C:$C,$B$56,营销场景数据源!$A:$A,FV2) -> 2 | FW58: =SUMIFS(营销场景数据源!$AB:$AB,营销场景数据源!$C:$C,$B$56,营销场景数据源!$A:$A,FW2) -> 3 | FX58: =SUMIFS(营销场景数据源!$AB:$AB,营销场景数据源!$C:$C,$B$56,营销场景数据源!$A:$A,FX2) -> 11 | FY58: =SUMIFS(营销场景数据源!$AB:$AB,营销场景数据源!$C:$C,$B$56,营销场景数据源!$A:$A,FY2) -> 4 | ... GP58: =SUMIFS(营销场景数据源!$AB:$AB,营销场景数据源!$C:$C,$B$56,营销场景数据源!$A:$A,GP2) -> 0
C59: 总成交量 | D59: =SUM(E59:P59) -> #REF! | E59: =#REF! -> #REF! | F59: =#REF! -> #REF! | G59: =#REF! -> #REF! | H59: =#REF! -> #REF! | I59: =#REF! -> #REF! | J59: =#REF! -> #REF! | K59: =#REF! -> #REF! | L59: =#REF! -> #REF! | ... P59: =#REF! -> #REF! | Q59: =SUM(R59:AV59) -> 38 | R59: =SUMIFS(营销场景数据源!$U:$U,营销场景数据源!$C:$C,$B$56,营销场景数据源!$A:$A,R2) -> 0 | S59: =SUMIFS(营销场景数据源!$U:$U,营销场景数据源!$C:$C,$B$56,营销场景数据源!$A:$A,S2) -> 0 | T59: =SUMIFS(营销场景数据源!$U:$U,营销场景数据源!$C:$C,$B$56,营销场景数据源!$A:$A,T2) -> 0 | U59: =SUMIFS(营销场景数据源!$U:$U,营销场景数据源!$C:$C,$B$56,营销场景数据源!$A:$A,U2) -> 4 | V59: =SUMIFS(营销场景数据源!$U:$U,营销场景数据源!$C:$C,$B$56,营销场景数据源!$A:$A,V2) -> 1 | W59: =SUMIFS(营销场景数据源!$U:$U,营销场景数据源!$C:$C,$B$56,营销场景数据源!$A:$A,W2) -> 1 | X59: =SUMIFS(营销场景数据源!$U:$U,营销场景数据源!$C:$C,$B$56,营销场景数据源!$A:$A,X2) -> 2 | Y59: =SUMIFS(营销场景数据源!$U:$U,营销场景数据源!$C:$C,$B$56,营销场景数据源!$A:$A,Y2) -> 1 | ... AV59: =SUMIFS(营销场景数据源!$U:$U,营销场景数据源!$C:$C,$B$56,营销场景数据源!$A:$A,AV2) -> 0 | AW59: =SUM(AX59:BY59) -> 18 | AX59: =SUMIFS(营销场景数据源!$U:$U,营销场景数据源!$C:$C,$B$56,营销场景数据源!$A:$A,AX2) -> 2 | AY59: =SUMIFS(营销场景数据源!$U:$U,营销场景数据源!$C:$C,$B$56,营销场景数据源!$A:$A,AY2) -> 0 | AZ59: =SUMIFS(营销场景数据源!$U:$U,营销场景数据源!$C:$C,$B$56,营销场景数据源!$A:$A,AZ2) -> 0 | BA59: =SUMIFS(营销场景数据源!$U:$U,营销场景数据源!$C:$C,$B$56,营销场景数据源!$A:$A,BA2) -> 1 | BB59: =SUMIFS(营销场景数据源!$U:$U,营销场景数据源!$C:$C,$B$56,营销场景数据源!$A:$A,BB2) -> 0 | BC59: =SUMIFS(营销场景数据源!$U:$U,营销场景数据源!$C:$C,$B$56,营销场景数据源!$A:$A,BC2) -> 2 | BD59: =SUMIFS(营销场景数据源!$U:$U,营销场景数据源!$C:$C,$B$56,营销场景数据源!$A:$A,BD2) -> 2 | BE59: =SUMIFS(营销场景数据源!$U:$U,营销场景数据源!$C:$C,$B$56,营销场景数据源!$A:$A,BE2) -> 3 | ... BY59: =SUMIFS(营销场景数据源!$U:$U,营销场景数据源!$C:$C,$B$56,营销场景数据源!$A:$A,BY2) -> 0 | BZ59: =SUM(CA59:DE59) -> 41 | CA59: =SUMIFS(营销场景数据源!$U:$U,营销场景数据源!$C:$C,$B$56,营销场景数据源!$A:$A,CA2) -> 1 | CB59: =SUMIFS(营销场景数据源!$U:$U,营销场景数据源!$C:$C,$B$56,营销场景数据源!$A:$A,CB2) -> 1 | CC59: =SUMIFS(营销场景数据源!$U:$U,营销场景数据源!$C:$C,$B$56,营销场景数据源!$A:$A,CC2) -> 0 | CD59: =SUMIFS(营销场景数据源!$U:$U,营销场景数据源!$C:$C,$B$56,营销场景数据源!$A:$A,CD2) -> 2 | CE59: =SUMIFS(营销场景数据源!$U:$U,营销场景数据源!$C:$C,$B$56,营销场景数据源!$A:$A,CE2) -> 1 | CF59: =SUMIFS(营销场景数据源!$U:$U,营销场景数据源!$C:$C,$B$56,营销场景数据源!$A:$A,CF2) -> 1 | CG59: =SUMIFS(营销场景数据源!$U:$U,营销场景数据源!$C:$C,$B$56,营销场景数据源!$A:$A,CG2) -> 0 | CH59: =SUMIFS(营销场景数据源!$U:$U,营销场景数据源!$C:$C,$B$56,营销场景数据源!$A:$A,CH2) -> 2 | ... DE59: =SUMIFS(营销场景数据源!$U:$U,营销场景数据源!$C:$C,$B$56,营销场景数据源!$A:$A,DE2) -> 0 | DF59: =SUM(DG59:EJ59) -> 52 | DG59: =SUMIFS(营销场景数据源!$U:$U,营销场景数据源!$C:$C,$B$56,营销场景数据源!$A:$A,DG2) -> 1 | DH59: =SUMIFS(营销场景数据源!$U:$U,营销场景数据源!$C:$C,$B$56,营销场景数据源!$A:$A,DH2) -> 0 | DI59: =SUMIFS(营销场景数据源!$U:$U,营销场景数据源!$C:$C,$B$56,营销场景数据源!$A:$A,DI2) -> 2 | DJ59: =SUMIFS(营销场景数据源!$U:$U,营销场景数据源!$C:$C,$B$56,营销场景数据源!$A:$A,DJ2) -> 0 | DK59: =SUMIFS(营销场景数据源!$U:$U,营销场景数据源!$C:$C,$B$56,营销场景数据源!$A:$A,DK2) -> 1 | DL59: =SUMIFS(营销场景数据源!$U:$U,营销场景数据源!$C:$C,$B$56,营销场景数据源!$A:$A,DL2) -> 2 | DM59: =SUMIFS(营销场景数据源!$U:$U,营销场景数据源!$C:$C,$B$56,营销场景数据源!$A:$A,DM2) -> 1 | DN59: =SUMIFS(营销场景数据源!$U:$U,营销场景数据源!$C:$C,$B$56,营销场景数据源!$A:$A,DN2) -> 3 | ... EJ59: =SUMIFS(营销场景数据源!$U:$U,营销场景数据源!$C:$C,$B$56,营销场景数据源!$A:$A,EJ2) -> 1 | EK59: =SUM(EL59:FP59) -> 31 | EL59: =SUMIFS(营销场景数据源!$U:$U,营销场景数据源!$C:$C,$B$56,营销场景数据源!$A:$A,EL2) -> 0 | EM59: =SUMIFS(营销场景数据源!$U:$U,营销场景数据源!$C:$C,$B$56,营销场景数据源!$A:$A,EM2) -> 0 | EN59: =SUMIFS(营销场景数据源!$U:$U,营销场景数据源!$C:$C,$B$56,营销场景数据源!$A:$A,EN2) -> 0 | EO59: =SUMIFS(营销场景数据源!$U:$U,营销场景数据源!$C:$C,$B$56,营销场景数据源!$A:$A,EO2) -> 0 | EP59: =SUMIFS(营销场景数据源!$U:$U,营销场景数据源!$C:$C,$B$56,营销场景数据源!$A:$A,EP2) -> 0 | EQ59: =SUMIFS(营销场景数据源!$U:$U,营销场景数据源!$C:$C,$B$56,营销场景数据源!$A:$A,EQ2) -> 0 | ER59: =SUMIFS(营销场景数据源!$U:$U,营销场景数据源!$C:$C,$B$56,营销场景数据源!$A:$A,ER2) -> 1 | ES59: =SUMIFS(营销场景数据源!$U:$U,营销场景数据源!$C:$C,$B$56,营销场景数据源!$A:$A,ES2) -> 0 | ... FP59: =SUMIFS(营销场景数据源!$U:$U,营销场景数据源!$C:$C,$B$56,营销场景数据源!$A:$A,FP2) -> 0 | FQ59: =SUM(FR59:GX59) -> 27 | FR59: =SUMIFS(营销场景数据源!$U:$U,营销场景数据源!$C:$C,$B$56,营销场景数据源!$A:$A,FR2) -> 0 | FS59: =SUMIFS(营销场景数据源!$U:$U,营销场景数据源!$C:$C,$B$56,营销场景数据源!$A:$A,FS2) -> 2 | FT59: =SUMIFS(营销场景数据源!$U:$U,营销场景数据源!$C:$C,$B$56,营销场景数据源!$A:$A,FT2) -> 1 | FU59: =SUMIFS(营销场景数据源!$U:$U,营销场景数据源!$C:$C,$B$56,营销场景数据源!$A:$A,FU2) -> 1 | FV59: =SUMIFS(营销场景数据源!$U:$U,营销场景数据源!$C:$C,$B$56,营销场景数据源!$A:$A,FV2) -> 1 | FW59: =SUMIFS(营销场景数据源!$U:$U,营销场景数据源!$C:$C,$B$56,营销场景数据源!$A:$A,FW2) -> 2 | FX59: =SUMIFS(营销场景数据源!$U:$U,营销场景数据源!$C:$C,$B$56,营销场景数据源!$A:$A,FX2) -> 4 | FY59: =SUMIFS(营销场景数据源!$U:$U,营销场景数据源!$C:$C,$B$56,营销场景数据源!$A:$A,FY2) -> 1 | ... GP59: =SUMIFS(营销场景数据源!$U:$U,营销场景数据源!$C:$C,$B$56,营销场景数据源!$A:$A,GP2) -> 0
C60: 总成交金额 | D60: =SUM(E60:P60) -> #REF! | E60: =#REF! -> #REF! | F60: =#REF! -> #REF! | G60: =#REF! -> #REF! | H60: =#REF! -> #REF! | I60: =#REF! -> #REF! | J60: =#REF! -> #REF! | K60: =#REF! -> #REF! | L60: =#REF! -> #REF! | ... P60: =#REF! -> #REF! | Q60: =SUM(R60:AV60) -> 12210.78 | R60: =SUMIFS(营销场景数据源!$T:$T,营销场景数据源!$C:$C,$B$56,营销场景数据源!$A:$A,R2) -> 0 | S60: =SUMIFS(营销场景数据源!$T:$T,营销场景数据源!$C:$C,$B$56,营销场景数据源!$A:$A,S2) -> 0 | T60: =SUMIFS(营销场景数据源!$T:$T,营销场景数据源!$C:$C,$B$56,营销场景数据源!$A:$A,T2) -> 0 | U60: =SUMIFS(营销场景数据源!$T:$T,营销场景数据源!$C:$C,$B$56,营销场景数据源!$A:$A,U2) -> 106.97 | V60: =SUMIFS(营销场景数据源!$T:$T,营销场景数据源!$C:$C,$B$56,营销场景数据源!$A:$A,V2) -> 1514.6 | W60: =SUMIFS(营销场景数据源!$T:$T,营销场景数据源!$C:$C,$B$56,营销场景数据源!$A:$A,W2) -> 139.44 | X60: =SUMIFS(营销场景数据源!$T:$T,营销场景数据源!$C:$C,$B$56,营销场景数据源!$A:$A,X2) -> 122.56 | Y60: =SUMIFS(营销场景数据源!$T:$T,营销场景数据源!$C:$C,$B$56,营销场景数据源!$A:$A,Y2) -> 139.44 | ... AV60: =SUMIFS(营销场景数据源!$T:$T,营销场景数据源!$C:$C,$B$56,营销场景数据源!$A:$A,AV2) -> 0 | AW60: =SUM(AX60:BY60) -> 7490.25 | AX60: =SUMIFS(营销场景数据源!$T:$T,营销场景数据源!$C:$C,$B$56,营销场景数据源!$A:$A,AX2) -> 2280.32 | AY60: =SUMIFS(营销场景数据源!$T:$T,营销场景数据源!$C:$C,$B$56,营销场景数据源!$A:$A,AY2) -> 0 | AZ60: =SUMIFS(营销场景数据源!$T:$T,营销场景数据源!$C:$C,$B$56,营销场景数据源!$A:$A,AZ2) -> 0 | BA60: =SUMIFS(营销场景数据源!$T:$T,营销场景数据源!$C:$C,$B$56,营销场景数据源!$A:$A,BA2) -> 2076 | BB60: =SUMIFS(营销场景数据源!$T:$T,营销场景数据源!$C:$C,$B$56,营销场景数据源!$A:$A,BB2) -> 0 | BC60: =SUMIFS(营销场景数据源!$T:$T,营销场景数据源!$C:$C,$B$56,营销场景数据源!$A:$A,BC2) -> 65.35 | BD60: =SUMIFS(营销场景数据源!$T:$T,营销场景数据源!$C:$C,$B$56,营销场景数据源!$A:$A,BD2) -> 183.26 | BE60: =SUMIFS(营销场景数据源!$T:$T,营销场景数据源!$C:$C,$B$56,营销场景数据源!$A:$A,BE2) -> 516.89 | ... BY60: =SUMIFS(营销场景数据源!$T:$T,营销场景数据源!$C:$C,$B$56,营销场景数据源!$A:$A,BY2) -> 0 | BZ60: =SUM(CA60:DE60) -> 11617.44 | CA60: =SUMIFS(营销场景数据源!$T:$T,营销场景数据源!$C:$C,$B$56,营销场景数据源!$A:$A,CA2) -> 77.17 | CB60: =SUMIFS(营销场景数据源!$T:$T,营销场景数据源!$C:$C,$B$56,营销场景数据源!$A:$A,CB2) -> 236 | CC60: =SUMIFS(营销场景数据源!$T:$T,营销场景数据源!$C:$C,$B$56,营销场景数据源!$A:$A,CC2) -> 0 | CD60: =SUMIFS(营销场景数据源!$T:$T,营销场景数据源!$C:$C,$B$56,营销场景数据源!$A:$A,CD2) -> 171.6 | CE60: =SUMIFS(营销场景数据源!$T:$T,营销场景数据源!$C:$C,$B$56,营销场景数据源!$A:$A,CE2) -> 113.44 | CF60: =SUMIFS(营销场景数据源!$T:$T,营销场景数据源!$C:$C,$B$56,营销场景数据源!$A:$A,CF2) -> 978.22 | CG60: =SUMIFS(营销场景数据源!$T:$T,营销场景数据源!$C:$C,$B$56,营销场景数据源!$A:$A,CG2) -> 0 | CH60: =SUMIFS(营销场景数据源!$T:$T,营销场景数据源!$C:$C,$B$56,营销场景数据源!$A:$A,CH2) -> 369.64 | ... DE60: =SUMIFS(营销场景数据源!$T:$T,营销场景数据源!$C:$C,$B$56,营销场景数据源!$A:$A,DE2) -> 0 | DF60: =SUM(DG60:EJ60) -> 12597.59 | DG60: =SUMIFS(营销场景数据源!$T:$T,营销场景数据源!$C:$C,$B$56,营销场景数据源!$A:$A,DG2) -> 88.51 | DH60: =SUMIFS(营销场景数据源!$T:$T,营销场景数据源!$C:$C,$B$56,营销场景数据源!$A:$A,DH2) -> 0 | DI60: =SUMIFS(营销场景数据源!$T:$T,营销场景数据源!$C:$C,$B$56,营销场景数据源!$A:$A,DI2) -> 137.8 | DJ60: =SUMIFS(营销场景数据源!$T:$T,营销场景数据源!$C:$C,$B$56,营销场景数据源!$A:$A,DJ2) -> 0 | DK60: =SUMIFS(营销场景数据源!$T:$T,营销场景数据源!$C:$C,$B$56,营销场景数据源!$A:$A,DK2) -> 87.12 | DL60: =SUMIFS(营销场景数据源!$T:$T,营销场景数据源!$C:$C,$B$56,营销场景数据源!$A:$A,DL2) -> 194.9 | DM60: =SUMIFS(营销场景数据源!$T:$T,营销场景数据源!$C:$C,$B$56,营销场景数据源!$A:$A,DM2) -> 753.3 | DN60: =SUMIFS(营销场景数据源!$T:$T,营销场景数据源!$C:$C,$B$56,营销场景数据源!$A:$A,DN2) -> 2703 | ... EJ60: =SUMIFS(营销场景数据源!$T:$T,营销场景数据源!$C:$C,$B$56,营销场景数据源!$A:$A,EJ2) -> 85.12 | EK60: =SUM(EL60:FP60) -> 4869.39 | EL60: =SUMIFS(营销场景数据源!$T:$T,营销场景数据源!$C:$C,$B$56,营销场景数据源!$A:$A,EL2) -> 0 | EM60: =SUMIFS(营销场景数据源!$T:$T,营销场景数据源!$C:$C,$B$56,营销场景数据源!$A:$A,EM2) -> 0 | EN60: =SUMIFS(营销场景数据源!$T:$T,营销场景数据源!$C:$C,$B$56,营销场景数据源!$A:$A,EN2) -> 0 | EO60: =SUMIFS(营销场景数据源!$T:$T,营销场景数据源!$C:$C,$B$56,营销场景数据源!$A:$A,EO2) -> 0 | EP60: =SUMIFS(营销场景数据源!$T:$T,营销场景数据源!$C:$C,$B$56,营销场景数据源!$A:$A,EP2) -> 0 | EQ60: =SUMIFS(营销场景数据源!$T:$T,营销场景数据源!$C:$C,$B$56,营销场景数据源!$A:$A,EQ2) -> 0 | ER60: =SUMIFS(营销场景数据源!$T:$T,营销场景数据源!$C:$C,$B$56,营销场景数据源!$A:$A,ER2) -> 82.9 | ES60: =SUMIFS(营销场景数据源!$T:$T,营销场景数据源!$C:$C,$B$56,营销场景数据源!$A:$A,ES2) -> 0 | ... FP60: =SUMIFS(营销场景数据源!$T:$T,营销场景数据源!$C:$C,$B$56,营销场景数据源!$A:$A,FP2) -> 0 | FQ60: =SUM(FR60:GX60) -> 7127.69 | FR60: =SUMIFS(营销场景数据源!$T:$T,营销场景数据源!$C:$C,$B$56,营销场景数据源!$A:$A,FR2) -> 0 | FS60: =SUMIFS(营销场景数据源!$T:$T,营销场景数据源!$C:$C,$B$56,营销场景数据源!$A:$A,FS2) -> 223.92 | FT60: =SUMIFS(营销场景数据源!$T:$T,营销场景数据源!$C:$C,$B$56,营销场景数据源!$A:$A,FT2) -> 281.31 | FU60: =SUMIFS(营销场景数据源!$T:$T,营销场景数据源!$C:$C,$B$56,营销场景数据源!$A:$A,FU2) -> 37.46 | FV60: =SUMIFS(营销场景数据源!$T:$T,营销场景数据源!$C:$C,$B$56,营销场景数据源!$A:$A,FV2) -> 133.6 | FW60: =SUMIFS(营销场景数据源!$T:$T,营销场景数据源!$C:$C,$B$56,营销场景数据源!$A:$A,FW2) -> 144.87 | FX60: =SUMIFS(营销场景数据源!$T:$T,营销场景数据源!$C:$C,$B$56,营销场景数据源!$A:$A,FX2) -> 227.76 | FY60: =SUMIFS(营销场景数据源!$T:$T,营销场景数据源!$C:$C,$B$56,营销场景数据源!$A:$A,FY2) -> 76.18 | ... GP60: =SUMIFS(营销场景数据源!$T:$T,营销场景数据源!$C:$C,$B$56,营销场景数据源!$A:$A,GP2) -> 0
C61: 点击单价 | D61: =IFERROR(D56/D57,0) -> 0 | E61: =IFERROR(E56/E57,0) -> 0 | F61: =IFERROR(F56/F57,0) -> 0 | G61: =IFERROR(G56/G57,0) -> 0 | H61: =IFERROR(H56/H57,0) -> 0 | I61: =IFERROR(I56/I57,0) -> 0 | J61: =IFERROR(J56/J57,0) -> 0 | K61: =IFERROR(K56/K57,0) -> 0 | ... GP61: =IFERROR(GP56/GP57,0) -> 0
C62: 加购成本 | D62: =IFERROR(D56/D58,0) -> 0 | E62: =IFERROR(E56/E58,0) -> 0 | F62: =IFERROR(F56/F58,0) -> 0 | G62: =IFERROR(G56/G58,0) -> 0 | H62: =IFERROR(H56/H58,0) -> 0 | I62: =IFERROR(I56/I58,0) -> 0 | J62: =IFERROR(J56/J58,0) -> 0 | K62: =IFERROR(K56/K58,0) -> 0 | ... GP62: =IFERROR(GP56/GP58,0) -> 0
C63: ROI | D63: =IFERROR(D60/D56,0) -> 0 | E63: =IFERROR(E60/E56,0) -> 0 | F63: =IFERROR(F60/F56,0) -> 0 | G63: =IFERROR(G60/G56,0) -> 0 | H63: =IFERROR(H60/H56,0) -> 0 | I63: =IFERROR(I60/I56,0) -> 0 | J63: =IFERROR(J60/J56,0) -> 0 | K63: =IFERROR(K60/K56,0) -> 0 | ... GP63: =IFERROR(GP60/GP56,0) -> 0
C64: 费用占比 | D64: =D56/D$130 -> #REF! | E64: =E56/E$130 -> #REF! | F64: =F56/F$130 -> #REF! | G64: =G56/G$130 -> #REF! | H64: =H56/H$130 -> #REF! | I64: =I56/I$130 -> #REF! | J64: =J56/J$130 -> #REF! | K64: =K56/K$130 -> #REF! | ... GP64: =GP56/GP$130 -> #DIV/0!
B65: 超级直播 | C65: 花费 | D65: =SUM(E65:P65) -> #REF! | E65: =#REF! -> #REF! | F65: =#REF! -> #REF! | G65: =#REF! -> #REF! | H65: =#REF! -> #REF! | I65: =#REF! -> #REF! | J65: =#REF! -> #REF! | K65: =#REF! -> #REF! | L65: =#REF! -> #REF! | ... P65: =#REF! -> #REF! | Q65: =SUM(R65:AV65) -> 0 | R65: =SUMIFS(营销场景数据源!$H:$H,营销场景数据源!$C:$C,$B$65,营销场景数据源!$A:$A,R2) -> 0 | S65: =SUMIFS(营销场景数据源!$H:$H,营销场景数据源!$C:$C,$B$65,营销场景数据源!$A:$A,S2) -> 0 | T65: =SUMIFS(营销场景数据源!$H:$H,营销场景数据源!$C:$C,$B$65,营销场景数据源!$A:$A,T2) -> 0 | U65: =SUMIFS(营销场景数据源!$H:$H,营销场景数据源!$C:$C,$B$65,营销场景数据源!$A:$A,U2) -> 0 | V65: =SUMIFS(营销场景数据源!$H:$H,营销场景数据源!$C:$C,$B$65,营销场景数据源!$A:$A,V2) -> 0 | W65: =SUMIFS(营销场景数据源!$H:$H,营销场景数据源!$C:$C,$B$65,营销场景数据源!$A:$A,W2) -> 0 | X65: =SUMIFS(营销场景数据源!$H:$H,营销场景数据源!$C:$C,$B$65,营销场景数据源!$A:$A,X2) -> 0 | Y65: =SUMIFS(营销场景数据源!$H:$H,营销场景数据源!$C:$C,$B$65,营销场景数据源!$A:$A,Y2) -> 0 | ... AV65: =SUMIFS(营销场景数据源!$H:$H,营销场景数据源!$C:$C,$B$65,营销场景数据源!$A:$A,AV2) -> 0 | AW65: =SUM(AX65:BY65) -> 0 | AX65: =SUMIFS(营销场景数据源!$H:$H,营销场景数据源!$C:$C,$B$65,营销场景数据源!$A:$A,AX2) -> 0 | AY65: =SUMIFS(营销场景数据源!$H:$H,营销场景数据源!$C:$C,$B$65,营销场景数据源!$A:$A,AY2) -> 0 | AZ65: =SUMIFS(营销场景数据源!$H:$H,营销场景数据源!$C:$C,$B$65,营销场景数据源!$A:$A,AZ2) -> 0 | BA65: =SUMIFS(营销场景数据源!$H:$H,营销场景数据源!$C:$C,$B$65,营销场景数据源!$A:$A,BA2) -> 0 | BB65: =SUMIFS(营销场景数据源!$H:$H,营销场景数据源!$C:$C,$B$65,营销场景数据源!$A:$A,BB2) -> 0 | BC65: =SUMIFS(营销场景数据源!$H:$H,营销场景数据源!$C:$C,$B$65,营销场景数据源!$A:$A,BC2) -> 0 | BD65: =SUMIFS(营销场景数据源!$H:$H,营销场景数据源!$C:$C,$B$65,营销场景数据源!$A:$A,BD2) -> 0 | BE65: =SUMIFS(营销场景数据源!$H:$H,营销场景数据源!$C:$C,$B$65,营销场景数据源!$A:$A,BE2) -> 0 | ... BY65: =SUMIFS(营销场景数据源!$H:$H,营销场景数据源!$C:$C,$B$65,营销场景数据源!$A:$A,BY2) -> 0 | BZ65: =SUM(CA65:DE65) -> 0 | CA65: =SUMIFS(营销场景数据源!$H:$H,营销场景数据源!$C:$C,$B$65,营销场景数据源!$A:$A,CA2) -> 0 | CB65: =SUMIFS(营销场景数据源!$H:$H,营销场景数据源!$C:$C,$B$65,营销场景数据源!$A:$A,CB2) -> 0 | CC65: =SUMIFS(营销场景数据源!$H:$H,营销场景数据源!$C:$C,$B$65,营销场景数据源!$A:$A,CC2) -> 0 | CD65: =SUMIFS(营销场景数据源!$H:$H,营销场景数据源!$C:$C,$B$65,营销场景数据源!$A:$A,CD2) -> 0 | CE65: =SUMIFS(营销场景数据源!$H:$H,营销场景数据源!$C:$C,$B$65,营销场景数据源!$A:$A,CE2) -> 0 | CF65: =SUMIFS(营销场景数据源!$H:$H,营销场景数据源!$C:$C,$B$65,营销场景数据源!$A:$A,CF2) -> 0 | CG65: =SUMIFS(营销场景数据源!$H:$H,营销场景数据源!$C:$C,$B$65,营销场景数据源!$A:$A,CG2) -> 0 | CH65: =SUMIFS(营销场景数据源!$H:$H,营销场景数据源!$C:$C,$B$65,营销场景数据源!$A:$A,CH2) -> 0 | ... DE65: =SUMIFS(营销场景数据源!$H:$H,营销场景数据源!$C:$C,$B$65,营销场景数据源!$A:$A,DE2) -> 0 | DF65: =SUM(DG65:EJ65) -> 0 | DG65: =SUMIFS(营销场景数据源!$H:$H,营销场景数据源!$C:$C,$B$65,营销场景数据源!$A:$A,DG2) -> 0 | DH65: =SUMIFS(营销场景数据源!$H:$H,营销场景数据源!$C:$C,$B$65,营销场景数据源!$A:$A,DH2) -> 0 | DI65: =SUMIFS(营销场景数据源!$H:$H,营销场景数据源!$C:$C,$B$65,营销场景数据源!$A:$A,DI2) -> 0 | DJ65: =SUMIFS(营销场景数据源!$H:$H,营销场景数据源!$C:$C,$B$65,营销场景数据源!$A:$A,DJ2) -> 0 | DK65: =SUMIFS(营销场景数据源!$H:$H,营销场景数据源!$C:$C,$B$65,营销场景数据源!$A:$A,DK2) -> 0 | DL65: =SUMIFS(营销场景数据源!$H:$H,营销场景数据源!$C:$C,$B$65,营销场景数据源!$A:$A,DL2) -> 0 | DM65: =SUMIFS(营销场景数据源!$H:$H,营销场景数据源!$C:$C,$B$65,营销场景数据源!$A:$A,DM2) -> 0 | DN65: =SUMIFS(营销场景数据源!$H:$H,营销场景数据源!$C:$C,$B$65,营销场景数据源!$A:$A,DN2) -> 0 | ... EJ65: =SUMIFS(营销场景数据源!$H:$H,营销场景数据源!$C:$C,$B$65,营销场景数据源!$A:$A,EJ2) -> 0 | EK65: =SUM(EL65:FP65) -> 0 | EL65: =SUMIFS(营销场景数据源!$H:$H,营销场景数据源!$C:$C,$B$65,营销场景数据源!$A:$A,EL2) -> 0 | EM65: =SUMIFS(营销场景数据源!$H:$H,营销场景数据源!$C:$C,$B$65,营销场景数据源!$A:$A,EM2) -> 0 | EN65: =SUMIFS(营销场景数据源!$H:$H,营销场景数据源!$C:$C,$B$65,营销场景数据源!$A:$A,EN2) -> 0 | EO65: =SUMIFS(营销场景数据源!$H:$H,营销场景数据源!$C:$C,$B$65,营销场景数据源!$A:$A,EO2) -> 0 | EP65: =SUMIFS(营销场景数据源!$H:$H,营销场景数据源!$C:$C,$B$65,营销场景数据源!$A:$A,EP2) -> 0 | EQ65: =SUMIFS(营销场景数据源!$H:$H,营销场景数据源!$C:$C,$B$65,营销场景数据源!$A:$A,EQ2) -> 0 | ER65: =SUMIFS(营销场景数据源!$H:$H,营销场景数据源!$C:$C,$B$65,营销场景数据源!$A:$A,ER2) -> 0 | ES65: =SUMIFS(营销场景数据源!$H:$H,营销场景数据源!$C:$C,$B$65,营销场景数据源!$A:$A,ES2) -> 0 | ... FP65: =SUMIFS(营销场景数据源!$H:$H,营销场景数据源!$C:$C,$B$65,营销场景数据源!$A:$A,FP2) -> 0 | FQ65: =SUM(FR65:GX65) -> 0 | FR65: =SUMIFS(营销场景数据源!$H:$H,营销场景数据源!$C:$C,$B$65,营销场景数据源!$A:$A,FR2) -> 0 | FS65: =SUMIFS(营销场景数据源!$H:$H,营销场景数据源!$C:$C,$B$65,营销场景数据源!$A:$A,FS2) -> 0 | FT65: =SUMIFS(营销场景数据源!$H:$H,营销场景数据源!$C:$C,$B$65,营销场景数据源!$A:$A,FT2) -> 0 | FU65: =SUMIFS(营销场景数据源!$H:$H,营销场景数据源!$C:$C,$B$65,营销场景数据源!$A:$A,FU2) -> 0 | FV65: =SUMIFS(营销场景数据源!$H:$H,营销场景数据源!$C:$C,$B$65,营销场景数据源!$A:$A,FV2) -> 0 | FW65: =SUMIFS(营销场景数据源!$H:$H,营销场景数据源!$C:$C,$B$65,营销场景数据源!$A:$A,FW2) -> 0 | FX65: =SUMIFS(营销场景数据源!$H:$H,营销场景数据源!$C:$C,$B$65,营销场景数据源!$A:$A,FX2) -> 0 | FY65: =SUMIFS(营销场景数据源!$H:$H,营销场景数据源!$C:$C,$B$65,营销场景数据源!$A:$A,FY2) -> 0 | ... GP65: =SUMIFS(营销场景数据源!$H:$H,营销场景数据源!$C:$C,$B$65,营销场景数据源!$A:$A,GP2) -> 0
C66: 点击量 | D66: =SUM(E66:P66) -> #REF! | E66: =#REF! -> #REF! | F66: =#REF! -> #REF! | G66: =#REF! -> #REF! | H66: =#REF! -> #REF! | I66: =#REF! -> #REF! | J66: =#REF! -> #REF! | K66: =#REF! -> #REF! | L66: =#REF! -> #REF! | ... P66: =#REF! -> #REF! | Q66: =SUM(R66:AV66) -> 0 | R66: =SUMIFS(营销场景数据源!$G:$G,营销场景数据源!$C:$C,$B$65,营销场景数据源!$A:$A,R2) -> 0 | S66: =SUMIFS(营销场景数据源!$G:$G,营销场景数据源!$C:$C,$B$65,营销场景数据源!$A:$A,S2) -> 0 | T66: =SUMIFS(营销场景数据源!$G:$G,营销场景数据源!$C:$C,$B$65,营销场景数据源!$A:$A,T2) -> 0 | U66: =SUMIFS(营销场景数据源!$G:$G,营销场景数据源!$C:$C,$B$65,营销场景数据源!$A:$A,U2) -> 0 | V66: =SUMIFS(营销场景数据源!$G:$G,营销场景数据源!$C:$C,$B$65,营销场景数据源!$A:$A,V2) -> 0 | W66: =SUMIFS(营销场景数据源!$G:$G,营销场景数据源!$C:$C,$B$65,营销场景数据源!$A:$A,W2) -> 0 | X66: =SUMIFS(营销场景数据源!$G:$G,营销场景数据源!$C:$C,$B$65,营销场景数据源!$A:$A,X2) -> 0 | Y66: =SUMIFS(营销场景数据源!$G:$G,营销场景数据源!$C:$C,$B$65,营销场景数据源!$A:$A,Y2) -> 0 | ... AV66: =SUMIFS(营销场景数据源!$G:$G,营销场景数据源!$C:$C,$B$65,营销场景数据源!$A:$A,AV2) -> 0 | AW66: =SUM(AX66:BY66) -> 0 | AX66: =SUMIFS(营销场景数据源!$G:$G,营销场景数据源!$C:$C,$B$65,营销场景数据源!$A:$A,AX2) -> 0 | AY66: =SUMIFS(营销场景数据源!$G:$G,营销场景数据源!$C:$C,$B$65,营销场景数据源!$A:$A,AY2) -> 0 | AZ66: =SUMIFS(营销场景数据源!$G:$G,营销场景数据源!$C:$C,$B$65,营销场景数据源!$A:$A,AZ2) -> 0 | BA66: =SUMIFS(营销场景数据源!$G:$G,营销场景数据源!$C:$C,$B$65,营销场景数据源!$A:$A,BA2) -> 0 | BB66: =SUMIFS(营销场景数据源!$G:$G,营销场景数据源!$C:$C,$B$65,营销场景数据源!$A:$A,BB2) -> 0 | BC66: =SUMIFS(营销场景数据源!$G:$G,营销场景数据源!$C:$C,$B$65,营销场景数据源!$A:$A,BC2) -> 0 | BD66: =SUMIFS(营销场景数据源!$G:$G,营销场景数据源!$C:$C,$B$65,营销场景数据源!$A:$A,BD2) -> 0 | BE66: =SUMIFS(营销场景数据源!$G:$G,营销场景数据源!$C:$C,$B$65,营销场景数据源!$A:$A,BE2) -> 0 | ... BY66: =SUMIFS(营销场景数据源!$G:$G,营销场景数据源!$C:$C,$B$65,营销场景数据源!$A:$A,BY2) -> 0 | BZ66: =SUM(CA66:DE66) -> 0 | CA66: =SUMIFS(营销场景数据源!$G:$G,营销场景数据源!$C:$C,$B$65,营销场景数据源!$A:$A,CA2) -> 0 | CB66: =SUMIFS(营销场景数据源!$G:$G,营销场景数据源!$C:$C,$B$65,营销场景数据源!$A:$A,CB2) -> 0 | CC66: =SUMIFS(营销场景数据源!$G:$G,营销场景数据源!$C:$C,$B$65,营销场景数据源!$A:$A,CC2) -> 0 | CD66: =SUMIFS(营销场景数据源!$G:$G,营销场景数据源!$C:$C,$B$65,营销场景数据源!$A:$A,CD2) -> 0 | CE66: =SUMIFS(营销场景数据源!$G:$G,营销场景数据源!$C:$C,$B$65,营销场景数据源!$A:$A,CE2) -> 0 | CF66: =SUMIFS(营销场景数据源!$G:$G,营销场景数据源!$C:$C,$B$65,营销场景数据源!$A:$A,CF2) -> 0 | CG66: =SUMIFS(营销场景数据源!$G:$G,营销场景数据源!$C:$C,$B$65,营销场景数据源!$A:$A,CG2) -> 0 | CH66: =SUMIFS(营销场景数据源!$G:$G,营销场景数据源!$C:$C,$B$65,营销场景数据源!$A:$A,CH2) -> 0 | ... DE66: =SUMIFS(营销场景数据源!$G:$G,营销场景数据源!$C:$C,$B$65,营销场景数据源!$A:$A,DE2) -> 0 | DF66: =SUM(DG66:EJ66) -> 0 | DG66: =SUMIFS(营销场景数据源!$G:$G,营销场景数据源!$C:$C,$B$65,营销场景数据源!$A:$A,DG2) -> 0 | DH66: =SUMIFS(营销场景数据源!$G:$G,营销场景数据源!$C:$C,$B$65,营销场景数据源!$A:$A,DH2) -> 0 | DI66: =SUMIFS(营销场景数据源!$G:$G,营销场景数据源!$C:$C,$B$65,营销场景数据源!$A:$A,DI2) -> 0 | DJ66: =SUMIFS(营销场景数据源!$G:$G,营销场景数据源!$C:$C,$B$65,营销场景数据源!$A:$A,DJ2) -> 0 | DK66: =SUMIFS(营销场景数据源!$G:$G,营销场景数据源!$C:$C,$B$65,营销场景数据源!$A:$A,DK2) -> 0 | DL66: =SUMIFS(营销场景数据源!$G:$G,营销场景数据源!$C:$C,$B$65,营销场景数据源!$A:$A,DL2) -> 0 | DM66: =SUMIFS(营销场景数据源!$G:$G,营销场景数据源!$C:$C,$B$65,营销场景数据源!$A:$A,DM2) -> 0 | DN66: =SUMIFS(营销场景数据源!$G:$G,营销场景数据源!$C:$C,$B$65,营销场景数据源!$A:$A,DN2) -> 0 | ... EJ66: =SUMIFS(营销场景数据源!$G:$G,营销场景数据源!$C:$C,$B$65,营销场景数据源!$A:$A,EJ2) -> 0 | EK66: =SUM(EL66:FP66) -> 0 | EL66: =SUMIFS(营销场景数据源!$G:$G,营销场景数据源!$C:$C,$B$65,营销场景数据源!$A:$A,EL2) -> 0 | EM66: =SUMIFS(营销场景数据源!$G:$G,营销场景数据源!$C:$C,$B$65,营销场景数据源!$A:$A,EM2) -> 0 | EN66: =SUMIFS(营销场景数据源!$G:$G,营销场景数据源!$C:$C,$B$65,营销场景数据源!$A:$A,EN2) -> 0 | EO66: =SUMIFS(营销场景数据源!$G:$G,营销场景数据源!$C:$C,$B$65,营销场景数据源!$A:$A,EO2) -> 0 | EP66: =SUMIFS(营销场景数据源!$G:$G,营销场景数据源!$C:$C,$B$65,营销场景数据源!$A:$A,EP2) -> 0 | EQ66: =SUMIFS(营销场景数据源!$G:$G,营销场景数据源!$C:$C,$B$65,营销场景数据源!$A:$A,EQ2) -> 0 | ER66: =SUMIFS(营销场景数据源!$G:$G,营销场景数据源!$C:$C,$B$65,营销场景数据源!$A:$A,ER2) -> 0 | ES66: =SUMIFS(营销场景数据源!$G:$G,营销场景数据源!$C:$C,$B$65,营销场景数据源!$A:$A,ES2) -> 0 | ... FP66: =SUMIFS(营销场景数据源!$G:$G,营销场景数据源!$C:$C,$B$65,营销场景数据源!$A:$A,FP2) -> 0 | FQ66: =SUM(FR66:GX66) -> 0 | FR66: =SUMIFS(营销场景数据源!$G:$G,营销场景数据源!$C:$C,$B$65,营销场景数据源!$A:$A,FR2) -> 0 | FS66: =SUMIFS(营销场景数据源!$G:$G,营销场景数据源!$C:$C,$B$65,营销场景数据源!$A:$A,FS2) -> 0 | FT66: =SUMIFS(营销场景数据源!$G:$G,营销场景数据源!$C:$C,$B$65,营销场景数据源!$A:$A,FT2) -> 0 | FU66: =SUMIFS(营销场景数据源!$G:$G,营销场景数据源!$C:$C,$B$65,营销场景数据源!$A:$A,FU2) -> 0 | FV66: =SUMIFS(营销场景数据源!$G:$G,营销场景数据源!$C:$C,$B$65,营销场景数据源!$A:$A,FV2) -> 0 | FW66: =SUMIFS(营销场景数据源!$G:$G,营销场景数据源!$C:$C,$B$65,营销场景数据源!$A:$A,FW2) -> 0 | FX66: =SUMIFS(营销场景数据源!$G:$G,营销场景数据源!$C:$C,$B$65,营销场景数据源!$A:$A,FX2) -> 0 | FY66: =SUMIFS(营销场景数据源!$G:$G,营销场景数据源!$C:$C,$B$65,营销场景数据源!$A:$A,FY2) -> 0 | ... GP66: =SUMIFS(营销场景数据源!$G:$G,营销场景数据源!$C:$C,$B$65,营销场景数据源!$A:$A,GP2) -> 0
C67: 总购物车数 | D67: =SUM(E67:P67) -> #REF! | E67: =#REF! -> #REF! | F67: =#REF! -> #REF! | G67: =#REF! -> #REF! | H67: =#REF! -> #REF! | I67: =#REF! -> #REF! | J67: =#REF! -> #REF! | K67: =#REF! -> #REF! | L67: =#REF! -> #REF! | ... P67: =#REF! -> #REF! | Q67: =SUM(R67:AV67) -> 0 | R67: =SUMIFS(营销场景数据源!$AB:$AB,营销场景数据源!$C:$C,$B$65,营销场景数据源!$A:$A,R2) -> 0 | S67: =SUMIFS(营销场景数据源!$AB:$AB,营销场景数据源!$C:$C,$B$65,营销场景数据源!$A:$A,S2) -> 0 | T67: =SUMIFS(营销场景数据源!$AB:$AB,营销场景数据源!$C:$C,$B$65,营销场景数据源!$A:$A,T2) -> 0 | U67: =SUMIFS(营销场景数据源!$AB:$AB,营销场景数据源!$C:$C,$B$65,营销场景数据源!$A:$A,U2) -> 0 | V67: =SUMIFS(营销场景数据源!$AB:$AB,营销场景数据源!$C:$C,$B$65,营销场景数据源!$A:$A,V2) -> 0 | W67: =SUMIFS(营销场景数据源!$AB:$AB,营销场景数据源!$C:$C,$B$65,营销场景数据源!$A:$A,W2) -> 0 | X67: =SUMIFS(营销场景数据源!$AB:$AB,营销场景数据源!$C:$C,$B$65,营销场景数据源!$A:$A,X2) -> 0 | Y67: =SUMIFS(营销场景数据源!$AB:$AB,营销场景数据源!$C:$C,$B$65,营销场景数据源!$A:$A,Y2) -> 0 | ... AV67: =SUMIFS(营销场景数据源!$AB:$AB,营销场景数据源!$C:$C,$B$65,营销场景数据源!$A:$A,AV2) -> 0 | AW67: =SUM(AX67:BY67) -> 0 | AX67: =SUMIFS(营销场景数据源!$AB:$AB,营销场景数据源!$C:$C,$B$65,营销场景数据源!$A:$A,AX2) -> 0 | AY67: =SUMIFS(营销场景数据源!$AB:$AB,营销场景数据源!$C:$C,$B$65,营销场景数据源!$A:$A,AY2) -> 0 | AZ67: =SUMIFS(营销场景数据源!$AB:$AB,营销场景数据源!$C:$C,$B$65,营销场景数据源!$A:$A,AZ2) -> 0 | BA67: =SUMIFS(营销场景数据源!$AB:$AB,营销场景数据源!$C:$C,$B$65,营销场景数据源!$A:$A,BA2) -> 0 | BB67: =SUMIFS(营销场景数据源!$AB:$AB,营销场景数据源!$C:$C,$B$65,营销场景数据源!$A:$A,BB2) -> 0 | BC67: =SUMIFS(营销场景数据源!$AB:$AB,营销场景数据源!$C:$C,$B$65,营销场景数据源!$A:$A,BC2) -> 0 | BD67: =SUMIFS(营销场景数据源!$AB:$AB,营销场景数据源!$C:$C,$B$65,营销场景数据源!$A:$A,BD2) -> 0 | BE67: =SUMIFS(营销场景数据源!$AB:$AB,营销场景数据源!$C:$C,$B$65,营销场景数据源!$A:$A,BE2) -> 0 | ... BY67: =SUMIFS(营销场景数据源!$AB:$AB,营销场景数据源!$C:$C,$B$65,营销场景数据源!$A:$A,BY2) -> 0 | BZ67: =SUM(CA67:DE67) -> 0 | CA67: =SUMIFS(营销场景数据源!$AB:$AB,营销场景数据源!$C:$C,$B$65,营销场景数据源!$A:$A,CA2) -> 0 | CB67: =SUMIFS(营销场景数据源!$AB:$AB,营销场景数据源!$C:$C,$B$65,营销场景数据源!$A:$A,CB2) -> 0 | CC67: =SUMIFS(营销场景数据源!$AB:$AB,营销场景数据源!$C:$C,$B$65,营销场景数据源!$A:$A,CC2) -> 0 | CD67: =SUMIFS(营销场景数据源!$AB:$AB,营销场景数据源!$C:$C,$B$65,营销场景数据源!$A:$A,CD2) -> 0 | CE67: =SUMIFS(营销场景数据源!$AB:$AB,营销场景数据源!$C:$C,$B$65,营销场景数据源!$A:$A,CE2) -> 0 | CF67: =SUMIFS(营销场景数据源!$AB:$AB,营销场景数据源!$C:$C,$B$65,营销场景数据源!$A:$A,CF2) -> 0 | CG67: =SUMIFS(营销场景数据源!$AB:$AB,营销场景数据源!$C:$C,$B$65,营销场景数据源!$A:$A,CG2) -> 0 | CH67: =SUMIFS(营销场景数据源!$AB:$AB,营销场景数据源!$C:$C,$B$65,营销场景数据源!$A:$A,CH2) -> 0 | ... DE67: =SUMIFS(营销场景数据源!$AB:$AB,营销场景数据源!$C:$C,$B$65,营销场景数据源!$A:$A,DE2) -> 0 | DF67: =SUM(DG67:EJ67) -> 0 | DG67: =SUMIFS(营销场景数据源!$AB:$AB,营销场景数据源!$C:$C,$B$65,营销场景数据源!$A:$A,DG2) -> 0 | DH67: =SUMIFS(营销场景数据源!$AB:$AB,营销场景数据源!$C:$C,$B$65,营销场景数据源!$A:$A,DH2) -> 0 | DI67: =SUMIFS(营销场景数据源!$AB:$AB,营销场景数据源!$C:$C,$B$65,营销场景数据源!$A:$A,DI2) -> 0 | DJ67: =SUMIFS(营销场景数据源!$AB:$AB,营销场景数据源!$C:$C,$B$65,营销场景数据源!$A:$A,DJ2) -> 0 | DK67: =SUMIFS(营销场景数据源!$AB:$AB,营销场景数据源!$C:$C,$B$65,营销场景数据源!$A:$A,DK2) -> 0 | DL67: =SUMIFS(营销场景数据源!$AB:$AB,营销场景数据源!$C:$C,$B$65,营销场景数据源!$A:$A,DL2) -> 0 | DM67: =SUMIFS(营销场景数据源!$AB:$AB,营销场景数据源!$C:$C,$B$65,营销场景数据源!$A:$A,DM2) -> 0 | DN67: =SUMIFS(营销场景数据源!$AB:$AB,营销场景数据源!$C:$C,$B$65,营销场景数据源!$A:$A,DN2) -> 0 | ... EJ67: =SUMIFS(营销场景数据源!$AB:$AB,营销场景数据源!$C:$C,$B$65,营销场景数据源!$A:$A,EJ2) -> 0 | EK67: =SUM(EL67:FP67) -> 0 | EL67: =SUMIFS(营销场景数据源!$AB:$AB,营销场景数据源!$C:$C,$B$65,营销场景数据源!$A:$A,EL2) -> 0 | EM67: =SUMIFS(营销场景数据源!$AB:$AB,营销场景数据源!$C:$C,$B$65,营销场景数据源!$A:$A,EM2) -> 0 | EN67: =SUMIFS(营销场景数据源!$AB:$AB,营销场景数据源!$C:$C,$B$65,营销场景数据源!$A:$A,EN2) -> 0 | EO67: =SUMIFS(营销场景数据源!$AB:$AB,营销场景数据源!$C:$C,$B$65,营销场景数据源!$A:$A,EO2) -> 0 | EP67: =SUMIFS(营销场景数据源!$AB:$AB,营销场景数据源!$C:$C,$B$65,营销场景数据源!$A:$A,EP2) -> 0 | EQ67: =SUMIFS(营销场景数据源!$AB:$AB,营销场景数据源!$C:$C,$B$65,营销场景数据源!$A:$A,EQ2) -> 0 | ER67: =SUMIFS(营销场景数据源!$AB:$AB,营销场景数据源!$C:$C,$B$65,营销场景数据源!$A:$A,ER2) -> 0 | ES67: =SUMIFS(营销场景数据源!$AB:$AB,营销场景数据源!$C:$C,$B$65,营销场景数据源!$A:$A,ES2) -> 0 | ... FP67: =SUMIFS(营销场景数据源!$AB:$AB,营销场景数据源!$C:$C,$B$65,营销场景数据源!$A:$A,FP2) -> 0 | FQ67: =SUM(FR67:GX67) -> 0 | FR67: =SUMIFS(营销场景数据源!$AB:$AB,营销场景数据源!$C:$C,$B$65,营销场景数据源!$A:$A,FR2) -> 0 | FS67: =SUMIFS(营销场景数据源!$AB:$AB,营销场景数据源!$C:$C,$B$65,营销场景数据源!$A:$A,FS2) -> 0 | FT67: =SUMIFS(营销场景数据源!$AB:$AB,营销场景数据源!$C:$C,$B$65,营销场景数据源!$A:$A,FT2) -> 0 | FU67: =SUMIFS(营销场景数据源!$AB:$AB,营销场景数据源!$C:$C,$B$65,营销场景数据源!$A:$A,FU2) -> 0 | FV67: =SUMIFS(营销场景数据源!$AB:$AB,营销场景数据源!$C:$C,$B$65,营销场景数据源!$A:$A,FV2) -> 0 | FW67: =SUMIFS(营销场景数据源!$AB:$AB,营销场景数据源!$C:$C,$B$65,营销场景数据源!$A:$A,FW2) -> 0 | FX67: =SUMIFS(营销场景数据源!$AB:$AB,营销场景数据源!$C:$C,$B$65,营销场景数据源!$A:$A,FX2) -> 0 | FY67: =SUMIFS(营销场景数据源!$AB:$AB,营销场景数据源!$C:$C,$B$65,营销场景数据源!$A:$A,FY2) -> 0 | ... GP67: =SUMIFS(营销场景数据源!$AB:$AB,营销场景数据源!$C:$C,$B$65,营销场景数据源!$A:$A,GP2) -> 0
C68: 总成交量 | D68: =SUM(E68:P68) -> #REF! | E68: =#REF! -> #REF! | F68: =#REF! -> #REF! | G68: =#REF! -> #REF! | H68: =#REF! -> #REF! | I68: =#REF! -> #REF! | J68: =#REF! -> #REF! | K68: =#REF! -> #REF! | L68: =#REF! -> #REF! | ... P68: =#REF! -> #REF! | Q68: =SUM(R68:AV68) -> 0 | R68: =SUMIFS(营销场景数据源!$U:$U,营销场景数据源!$C:$C,$B$65,营销场景数据源!$A:$A,R2) -> 0 | S68: =SUMIFS(营销场景数据源!$U:$U,营销场景数据源!$C:$C,$B$65,营销场景数据源!$A:$A,S2) -> 0 | T68: =SUMIFS(营销场景数据源!$U:$U,营销场景数据源!$C:$C,$B$65,营销场景数据源!$A:$A,T2) -> 0 | U68: =SUMIFS(营销场景数据源!$U:$U,营销场景数据源!$C:$C,$B$65,营销场景数据源!$A:$A,U2) -> 0 | V68: =SUMIFS(营销场景数据源!$U:$U,营销场景数据源!$C:$C,$B$65,营销场景数据源!$A:$A,V2) -> 0 | W68: =SUMIFS(营销场景数据源!$U:$U,营销场景数据源!$C:$C,$B$65,营销场景数据源!$A:$A,W2) -> 0 | X68: =SUMIFS(营销场景数据源!$U:$U,营销场景数据源!$C:$C,$B$65,营销场景数据源!$A:$A,X2) -> 0 | Y68: =SUMIFS(营销场景数据源!$U:$U,营销场景数据源!$C:$C,$B$65,营销场景数据源!$A:$A,Y2) -> 0 | ... AV68: =SUMIFS(营销场景数据源!$U:$U,营销场景数据源!$C:$C,$B$65,营销场景数据源!$A:$A,AV2) -> 0 | AW68: =SUM(AX68:BY68) -> 0 | AX68: =SUMIFS(营销场景数据源!$U:$U,营销场景数据源!$C:$C,$B$65,营销场景数据源!$A:$A,AX2) -> 0 | AY68: =SUMIFS(营销场景数据源!$U:$U,营销场景数据源!$C:$C,$B$65,营销场景数据源!$A:$A,AY2) -> 0 | AZ68: =SUMIFS(营销场景数据源!$U:$U,营销场景数据源!$C:$C,$B$65,营销场景数据源!$A:$A,AZ2) -> 0 | BA68: =SUMIFS(营销场景数据源!$U:$U,营销场景数据源!$C:$C,$B$65,营销场景数据源!$A:$A,BA2) -> 0 | BB68: =SUMIFS(营销场景数据源!$U:$U,营销场景数据源!$C:$C,$B$65,营销场景数据源!$A:$A,BB2) -> 0 | BC68: =SUMIFS(营销场景数据源!$U:$U,营销场景数据源!$C:$C,$B$65,营销场景数据源!$A:$A,BC2) -> 0 | BD68: =SUMIFS(营销场景数据源!$U:$U,营销场景数据源!$C:$C,$B$65,营销场景数据源!$A:$A,BD2) -> 0 | BE68: =SUMIFS(营销场景数据源!$U:$U,营销场景数据源!$C:$C,$B$65,营销场景数据源!$A:$A,BE2) -> 0 | ... BY68: =SUMIFS(营销场景数据源!$U:$U,营销场景数据源!$C:$C,$B$65,营销场景数据源!$A:$A,BY2) -> 0 | BZ68: =SUM(CA68:DE68) -> 0 | CA68: =SUMIFS(营销场景数据源!$U:$U,营销场景数据源!$C:$C,$B$65,营销场景数据源!$A:$A,CA2) -> 0 | CB68: =SUMIFS(营销场景数据源!$U:$U,营销场景数据源!$C:$C,$B$65,营销场景数据源!$A:$A,CB2) -> 0 | CC68: =SUMIFS(营销场景数据源!$U:$U,营销场景数据源!$C:$C,$B$65,营销场景数据源!$A:$A,CC2) -> 0 | CD68: =SUMIFS(营销场景数据源!$U:$U,营销场景数据源!$C:$C,$B$65,营销场景数据源!$A:$A,CD2) -> 0 | CE68: =SUMIFS(营销场景数据源!$U:$U,营销场景数据源!$C:$C,$B$65,营销场景数据源!$A:$A,CE2) -> 0 | CF68: =SUMIFS(营销场景数据源!$U:$U,营销场景数据源!$C:$C,$B$65,营销场景数据源!$A:$A,CF2) -> 0 | CG68: =SUMIFS(营销场景数据源!$U:$U,营销场景数据源!$C:$C,$B$65,营销场景数据源!$A:$A,CG2) -> 0 | CH68: =SUMIFS(营销场景数据源!$U:$U,营销场景数据源!$C:$C,$B$65,营销场景数据源!$A:$A,CH2) -> 0 | ... DE68: =SUMIFS(营销场景数据源!$U:$U,营销场景数据源!$C:$C,$B$65,营销场景数据源!$A:$A,DE2) -> 0 | DF68: =SUM(DG68:EJ68) -> 0 | DG68: =SUMIFS(营销场景数据源!$U:$U,营销场景数据源!$C:$C,$B$65,营销场景数据源!$A:$A,DG2) -> 0 | DH68: =SUMIFS(营销场景数据源!$U:$U,营销场景数据源!$C:$C,$B$65,营销场景数据源!$A:$A,DH2) -> 0 | DI68: =SUMIFS(营销场景数据源!$U:$U,营销场景数据源!$C:$C,$B$65,营销场景数据源!$A:$A,DI2) -> 0 | DJ68: =SUMIFS(营销场景数据源!$U:$U,营销场景数据源!$C:$C,$B$65,营销场景数据源!$A:$A,DJ2) -> 0 | DK68: =SUMIFS(营销场景数据源!$U:$U,营销场景数据源!$C:$C,$B$65,营销场景数据源!$A:$A,DK2) -> 0 | DL68: =SUMIFS(营销场景数据源!$U:$U,营销场景数据源!$C:$C,$B$65,营销场景数据源!$A:$A,DL2) -> 0 | DM68: =SUMIFS(营销场景数据源!$U:$U,营销场景数据源!$C:$C,$B$65,营销场景数据源!$A:$A,DM2) -> 0 | DN68: =SUMIFS(营销场景数据源!$U:$U,营销场景数据源!$C:$C,$B$65,营销场景数据源!$A:$A,DN2) -> 0 | ... EJ68: =SUMIFS(营销场景数据源!$U:$U,营销场景数据源!$C:$C,$B$65,营销场景数据源!$A:$A,EJ2) -> 0 | EK68: =SUM(EL68:FP68) -> 0 | EL68: =SUMIFS(营销场景数据源!$U:$U,营销场景数据源!$C:$C,$B$65,营销场景数据源!$A:$A,EL2) -> 0 | EM68: =SUMIFS(营销场景数据源!$U:$U,营销场景数据源!$C:$C,$B$65,营销场景数据源!$A:$A,EM2) -> 0 | EN68: =SUMIFS(营销场景数据源!$U:$U,营销场景数据源!$C:$C,$B$65,营销场景数据源!$A:$A,EN2) -> 0 | EO68: =SUMIFS(营销场景数据源!$U:$U,营销场景数据源!$C:$C,$B$65,营销场景数据源!$A:$A,EO2) -> 0 | EP68: =SUMIFS(营销场景数据源!$U:$U,营销场景数据源!$C:$C,$B$65,营销场景数据源!$A:$A,EP2) -> 0 | EQ68: =SUMIFS(营销场景数据源!$U:$U,营销场景数据源!$C:$C,$B$65,营销场景数据源!$A:$A,EQ2) -> 0 | ER68: =SUMIFS(营销场景数据源!$U:$U,营销场景数据源!$C:$C,$B$65,营销场景数据源!$A:$A,ER2) -> 0 | ES68: =SUMIFS(营销场景数据源!$U:$U,营销场景数据源!$C:$C,$B$65,营销场景数据源!$A:$A,ES2) -> 0 | ... FP68: =SUMIFS(营销场景数据源!$U:$U,营销场景数据源!$C:$C,$B$65,营销场景数据源!$A:$A,FP2) -> 0 | FQ68: =SUM(FR68:GX68) -> 0 | FR68: =SUMIFS(营销场景数据源!$U:$U,营销场景数据源!$C:$C,$B$65,营销场景数据源!$A:$A,FR2) -> 0 | FS68: =SUMIFS(营销场景数据源!$U:$U,营销场景数据源!$C:$C,$B$65,营销场景数据源!$A:$A,FS2) -> 0 | FT68: =SUMIFS(营销场景数据源!$U:$U,营销场景数据源!$C:$C,$B$65,营销场景数据源!$A:$A,FT2) -> 0 | FU68: =SUMIFS(营销场景数据源!$U:$U,营销场景数据源!$C:$C,$B$65,营销场景数据源!$A:$A,FU2) -> 0 | FV68: =SUMIFS(营销场景数据源!$U:$U,营销场景数据源!$C:$C,$B$65,营销场景数据源!$A:$A,FV2) -> 0 | FW68: =SUMIFS(营销场景数据源!$U:$U,营销场景数据源!$C:$C,$B$65,营销场景数据源!$A:$A,FW2) -> 0 | FX68: =SUMIFS(营销场景数据源!$U:$U,营销场景数据源!$C:$C,$B$65,营销场景数据源!$A:$A,FX2) -> 0 | FY68: =SUMIFS(营销场景数据源!$U:$U,营销场景数据源!$C:$C,$B$65,营销场景数据源!$A:$A,FY2) -> 0 | ... GP68: =SUMIFS(营销场景数据源!$U:$U,营销场景数据源!$C:$C,$B$65,营销场景数据源!$A:$A,GP2) -> 0
C69: 总成交金额 | D69: =SUM(E69:P69) -> #REF! | E69: =#REF! -> #REF! | F69: =#REF! -> #REF! | G69: =#REF! -> #REF! | H69: =#REF! -> #REF! | I69: =#REF! -> #REF! | J69: =#REF! -> #REF! | K69: =#REF! -> #REF! | L69: =#REF! -> #REF! | ... P69: =#REF! -> #REF! | Q69: =SUM(R69:AV69) -> 0 | R69: =SUMIFS(营销场景数据源!$T:$T,营销场景数据源!$C:$C,$B$65,营销场景数据源!$A:$A,R2) -> 0 | S69: =SUMIFS(营销场景数据源!$T:$T,营销场景数据源!$C:$C,$B$65,营销场景数据源!$A:$A,S2) -> 0 | T69: =SUMIFS(营销场景数据源!$T:$T,营销场景数据源!$C:$C,$B$65,营销场景数据源!$A:$A,T2) -> 0 | U69: =SUMIFS(营销场景数据源!$T:$T,营销场景数据源!$C:$C,$B$65,营销场景数据源!$A:$A,U2) -> 0 | V69: =SUMIFS(营销场景数据源!$T:$T,营销场景数据源!$C:$C,$B$65,营销场景数据源!$A:$A,V2) -> 0 | W69: =SUMIFS(营销场景数据源!$T:$T,营销场景数据源!$C:$C,$B$65,营销场景数据源!$A:$A,W2) -> 0 | X69: =SUMIFS(营销场景数据源!$T:$T,营销场景数据源!$C:$C,$B$65,营销场景数据源!$A:$A,X2) -> 0 | Y69: =SUMIFS(营销场景数据源!$T:$T,营销场景数据源!$C:$C,$B$65,营销场景数据源!$A:$A,Y2) -> 0 | ... AV69: =SUMIFS(营销场景数据源!$T:$T,营销场景数据源!$C:$C,$B$65,营销场景数据源!$A:$A,AV2) -> 0 | AW69: =SUM(AX69:BY69) -> 0 | AX69: =SUMIFS(营销场景数据源!$T:$T,营销场景数据源!$C:$C,$B$65,营销场景数据源!$A:$A,AX2) -> 0 | AY69: =SUMIFS(营销场景数据源!$T:$T,营销场景数据源!$C:$C,$B$65,营销场景数据源!$A:$A,AY2) -> 0 | AZ69: =SUMIFS(营销场景数据源!$T:$T,营销场景数据源!$C:$C,$B$65,营销场景数据源!$A:$A,AZ2) -> 0 | BA69: =SUMIFS(营销场景数据源!$T:$T,营销场景数据源!$C:$C,$B$65,营销场景数据源!$A:$A,BA2) -> 0 | BB69: =SUMIFS(营销场景数据源!$T:$T,营销场景数据源!$C:$C,$B$65,营销场景数据源!$A:$A,BB2) -> 0 | BC69: =SUMIFS(营销场景数据源!$T:$T,营销场景数据源!$C:$C,$B$65,营销场景数据源!$A:$A,BC2) -> 0 | BD69: =SUMIFS(营销场景数据源!$T:$T,营销场景数据源!$C:$C,$B$65,营销场景数据源!$A:$A,BD2) -> 0 | BE69: =SUMIFS(营销场景数据源!$T:$T,营销场景数据源!$C:$C,$B$65,营销场景数据源!$A:$A,BE2) -> 0 | ... BY69: =SUMIFS(营销场景数据源!$T:$T,营销场景数据源!$C:$C,$B$65,营销场景数据源!$A:$A,BY2) -> 0 | BZ69: =SUM(CA69:DE69) -> 0 | CA69: =SUMIFS(营销场景数据源!$T:$T,营销场景数据源!$C:$C,$B$65,营销场景数据源!$A:$A,CA2) -> 0 | CB69: =SUMIFS(营销场景数据源!$T:$T,营销场景数据源!$C:$C,$B$65,营销场景数据源!$A:$A,CB2) -> 0 | CC69: =SUMIFS(营销场景数据源!$T:$T,营销场景数据源!$C:$C,$B$65,营销场景数据源!$A:$A,CC2) -> 0 | CD69: =SUMIFS(营销场景数据源!$T:$T,营销场景数据源!$C:$C,$B$65,营销场景数据源!$A:$A,CD2) -> 0 | CE69: =SUMIFS(营销场景数据源!$T:$T,营销场景数据源!$C:$C,$B$65,营销场景数据源!$A:$A,CE2) -> 0 | CF69: =SUMIFS(营销场景数据源!$T:$T,营销场景数据源!$C:$C,$B$65,营销场景数据源!$A:$A,CF2) -> 0 | CG69: =SUMIFS(营销场景数据源!$T:$T,营销场景数据源!$C:$C,$B$65,营销场景数据源!$A:$A,CG2) -> 0 | CH69: =SUMIFS(营销场景数据源!$T:$T,营销场景数据源!$C:$C,$B$65,营销场景数据源!$A:$A,CH2) -> 0 | ... DE69: =SUMIFS(营销场景数据源!$T:$T,营销场景数据源!$C:$C,$B$65,营销场景数据源!$A:$A,DE2) -> 0 | DF69: =SUM(DG69:EJ69) -> 0 | DG69: =SUMIFS(营销场景数据源!$T:$T,营销场景数据源!$C:$C,$B$65,营销场景数据源!$A:$A,DG2) -> 0 | DH69: =SUMIFS(营销场景数据源!$T:$T,营销场景数据源!$C:$C,$B$65,营销场景数据源!$A:$A,DH2) -> 0 | DI69: =SUMIFS(营销场景数据源!$T:$T,营销场景数据源!$C:$C,$B$65,营销场景数据源!$A:$A,DI2) -> 0 | DJ69: =SUMIFS(营销场景数据源!$T:$T,营销场景数据源!$C:$C,$B$65,营销场景数据源!$A:$A,DJ2) -> 0 | DK69: =SUMIFS(营销场景数据源!$T:$T,营销场景数据源!$C:$C,$B$65,营销场景数据源!$A:$A,DK2) -> 0 | DL69: =SUMIFS(营销场景数据源!$T:$T,营销场景数据源!$C:$C,$B$65,营销场景数据源!$A:$A,DL2) -> 0 | DM69: =SUMIFS(营销场景数据源!$T:$T,营销场景数据源!$C:$C,$B$65,营销场景数据源!$A:$A,DM2) -> 0 | DN69: =SUMIFS(营销场景数据源!$T:$T,营销场景数据源!$C:$C,$B$65,营销场景数据源!$A:$A,DN2) -> 0 | ... EJ69: =SUMIFS(营销场景数据源!$T:$T,营销场景数据源!$C:$C,$B$65,营销场景数据源!$A:$A,EJ2) -> 0 | EK69: =SUM(EL69:FP69) -> 0 | EL69: =SUMIFS(营销场景数据源!$T:$T,营销场景数据源!$C:$C,$B$65,营销场景数据源!$A:$A,EL2) -> 0 | EM69: =SUMIFS(营销场景数据源!$T:$T,营销场景数据源!$C:$C,$B$65,营销场景数据源!$A:$A,EM2) -> 0 | EN69: =SUMIFS(营销场景数据源!$T:$T,营销场景数据源!$C:$C,$B$65,营销场景数据源!$A:$A,EN2) -> 0 | EO69: =SUMIFS(营销场景数据源!$T:$T,营销场景数据源!$C:$C,$B$65,营销场景数据源!$A:$A,EO2) -> 0 | EP69: =SUMIFS(营销场景数据源!$T:$T,营销场景数据源!$C:$C,$B$65,营销场景数据源!$A:$A,EP2) -> 0 | EQ69: =SUMIFS(营销场景数据源!$T:$T,营销场景数据源!$C:$C,$B$65,营销场景数据源!$A:$A,EQ2) -> 0 | ER69: =SUMIFS(营销场景数据源!$T:$T,营销场景数据源!$C:$C,$B$65,营销场景数据源!$A:$A,ER2) -> 0 | ES69: =SUMIFS(营销场景数据源!$T:$T,营销场景数据源!$C:$C,$B$65,营销场景数据源!$A:$A,ES2) -> 0 | ... FP69: =SUMIFS(营销场景数据源!$T:$T,营销场景数据源!$C:$C,$B$65,营销场景数据源!$A:$A,FP2) -> 0 | FQ69: =SUM(FR69:GX69) -> 0 | FR69: =SUMIFS(营销场景数据源!$T:$T,营销场景数据源!$C:$C,$B$65,营销场景数据源!$A:$A,FR2) -> 0 | FS69: =SUMIFS(营销场景数据源!$T:$T,营销场景数据源!$C:$C,$B$65,营销场景数据源!$A:$A,FS2) -> 0 | FT69: =SUMIFS(营销场景数据源!$T:$T,营销场景数据源!$C:$C,$B$65,营销场景数据源!$A:$A,FT2) -> 0 | FU69: =SUMIFS(营销场景数据源!$T:$T,营销场景数据源!$C:$C,$B$65,营销场景数据源!$A:$A,FU2) -> 0 | FV69: =SUMIFS(营销场景数据源!$T:$T,营销场景数据源!$C:$C,$B$65,营销场景数据源!$A:$A,FV2) -> 0 | FW69: =SUMIFS(营销场景数据源!$T:$T,营销场景数据源!$C:$C,$B$65,营销场景数据源!$A:$A,FW2) -> 0 | FX69: =SUMIFS(营销场景数据源!$T:$T,营销场景数据源!$C:$C,$B$65,营销场景数据源!$A:$A,FX2) -> 0 | FY69: =SUMIFS(营销场景数据源!$T:$T,营销场景数据源!$C:$C,$B$65,营销场景数据源!$A:$A,FY2) -> 0 | ... GP69: =SUMIFS(营销场景数据源!$T:$T,营销场景数据源!$C:$C,$B$65,营销场景数据源!$A:$A,GP2) -> 0
C70: 点击单价 | D70: =IFERROR(D65/D66,0) -> 0 | E70: =IFERROR(E65/E66,0) -> 0 | F70: =IFERROR(F65/F66,0) -> 0 | G70: =IFERROR(G65/G66,0) -> 0 | H70: =IFERROR(H65/H66,0) -> 0 | I70: =IFERROR(I65/I66,0) -> 0 | J70: =IFERROR(J65/J66,0) -> 0 | K70: =IFERROR(K65/K66,0) -> 0 | ... GP70: =IFERROR(GP65/GP66,0) -> 0
C71: 加购成本 | D71: =IFERROR(D65/D67,0) -> 0 | E71: =IFERROR(E65/E67,0) -> 0 | F71: =IFERROR(F65/F67,0) -> 0 | G71: =IFERROR(G65/G67,0) -> 0 | H71: =IFERROR(H65/H67,0) -> 0 | I71: =IFERROR(I65/I67,0) -> 0 | J71: =IFERROR(J65/J67,0) -> 0 | K71: =IFERROR(K65/K67,0) -> 0 | ... GP71: =IFERROR(GP65/GP67,0) -> 0
C72: ROI | D72: =IFERROR(D69/D65,0) -> 0 | E72: =IFERROR(E69/E65,0) -> 0 | F72: =IFERROR(F69/F65,0) -> 0 | G72: =IFERROR(G69/G65,0) -> 0 | H72: =IFERROR(H69/H65,0) -> 0 | I72: =IFERROR(I69/I65,0) -> 0 | J72: =IFERROR(J69/J65,0) -> 0 | K72: =IFERROR(K69/K65,0) -> 0 | ... GP72: =IFERROR(GP69/GP65,0) -> 0
C73: 费用占比 | D73: =D65/D$130 -> #REF! | E73: =E65/E$130 -> #REF! | F73: =F65/F$130 -> #REF! | G73: =G65/G$130 -> #REF! | H73: =H65/H$130 -> #REF! | I73: =I65/I$130 -> #REF! | J73: =J65/J$130 -> #REF! | K73: =K65/K$130 -> #REF! | ... GP73: =GP65/GP$130 -> #DIV/0!
B74: 荔枝香 | C74: 花费 | D74: =SUM(E74:P74) -> #REF! | E74: =#REF! -> #REF! | F74: =#REF! -> #REF! | G74: =#REF! -> #REF! | H74: =#REF! -> #REF! | I74: =#REF! -> #REF! | J74: =#REF! -> #REF! | K74: =#REF! -> #REF! | L74: =#REF! -> #REF! | ... P74: =#REF! -> #REF! | Q74: =SUM(R74:AV74) -> 495.9 | R74: =SUMIFS(商品数据源!$H:$H,商品数据源!$A:$A,$B$74,商品数据源!$B:$B,R2) -> 40.29 | S74: =SUMIFS(商品数据源!$H:$H,商品数据源!$A:$A,$B$74,商品数据源!$B:$B,S2) -> 45.63 | T74: =SUMIFS(商品数据源!$H:$H,商品数据源!$A:$A,$B$74,商品数据源!$B:$B,T2) -> 43.16 | U74: =SUMIFS(商品数据源!$H:$H,商品数据源!$A:$A,$B$74,商品数据源!$B:$B,U2) -> 34.04 | V74: =SUMIFS(商品数据源!$H:$H,商品数据源!$A:$A,$B$74,商品数据源!$B:$B,V2) -> 33.74 | W74: =SUMIFS(商品数据源!$H:$H,商品数据源!$A:$A,$B$74,商品数据源!$B:$B,W2) -> 14.44 | X74: =SUMIFS(商品数据源!$H:$H,商品数据源!$A:$A,$B$74,商品数据源!$B:$B,X2) -> 19.26 | Y74: =SUMIFS(商品数据源!$H:$H,商品数据源!$A:$A,$B$74,商品数据源!$B:$B,Y2) -> 19.2 | ... AV74: =SUMIFS(商品数据源!$H:$H,商品数据源!$A:$A,$B$74,商品数据源!$B:$B,AV2) -> 0 | AW74: =SUM(AX74:BY74) -> 0 | AX74: =SUMIFS(商品数据源!$H:$H,商品数据源!$A:$A,$B$74,商品数据源!$B:$B,AX2) -> 0 | AY74: =SUMIFS(商品数据源!$H:$H,商品数据源!$A:$A,$B$74,商品数据源!$B:$B,AY2) -> 0 | AZ74: =SUMIFS(商品数据源!$H:$H,商品数据源!$A:$A,$B$74,商品数据源!$B:$B,AZ2) -> 0 | BA74: =SUMIFS(商品数据源!$H:$H,商品数据源!$A:$A,$B$74,商品数据源!$B:$B,BA2) -> 0 | BB74: =SUMIFS(商品数据源!$H:$H,商品数据源!$A:$A,$B$74,商品数据源!$B:$B,BB2) -> 0 | BC74: =SUMIFS(商品数据源!$H:$H,商品数据源!$A:$A,$B$74,商品数据源!$B:$B,BC2) -> 0 | BD74: =SUMIFS(商品数据源!$H:$H,商品数据源!$A:$A,$B$74,商品数据源!$B:$B,BD2) -> 0 | BE74: =SUMIFS(商品数据源!$H:$H,商品数据源!$A:$A,$B$74,商品数据源!$B:$B,BE2) -> 0 | ... BL74: =SUMIFS(商品数据源!$H:$H,商品数据源!$A:$A,$B$74,商品数据源!$B:$B,BL2) -> 0 | BP74: =SUMIFS(商品数据源!$H:$H,商品数据源!$A:$A,$B$74,商品数据源!$B:$B,BP2) -> 0 | BQ74: =SUMIFS(商品数据源!$H:$H,商品数据源!$A:$A,$B$74,商品数据源!$B:$B,BQ2) -> 0 | BR74: =SUMIFS(商品数据源!$H:$H,商品数据源!$A:$A,$B$74,商品数据源!$B:$B,BR2) -> 0 | BS74: =SUMIFS(商品数据源!$H:$H,商品数据源!$A:$A,$B$74,商品数据源!$B:$B,BS2) -> 0 | BT74: =SUMIFS(商品数据源!$H:$H,商品数据源!$A:$A,$B$74,商品数据源!$B:$B,BT2) -> 0 | BU74: =SUMIFS(商品数据源!$H:$H,商品数据源!$A:$A,$B$74,商品数据源!$B:$B,BU2) -> 0 | BV74: =SUMIFS(商品数据源!$H:$H,商品数据源!$A:$A,$B$74,商品数据源!$B:$B,BV2) -> 0 | BW74: =SUMIFS(商品数据源!$H:$H,商品数据源!$A:$A,$B$74,商品数据源!$B:$B,BW2) -> 0 | ... BY74: =SUMIFS(商品数据源!$H:$H,商品数据源!$A:$A,$B$74,商品数据源!$B:$B,BY2) -> 0 | BZ74: =SUM(CA74:DE74) -> 299.24 | CA74: =SUMIFS(商品数据源!$H:$H,商品数据源!$A:$A,$B$74,商品数据源!$B:$B,CA2) -> 0 | CB74: =SUMIFS(商品数据源!$H:$H,商品数据源!$A:$A,$B$74,商品数据源!$B:$B,CB2) -> 0 | CC74: =SUMIFS(商品数据源!$H:$H,商品数据源!$A:$A,$B$74,商品数据源!$B:$B,CC2) -> 0 | CD74: =SUMIFS(商品数据源!$H:$H,商品数据源!$A:$A,$B$74,商品数据源!$B:$B,CD2) -> 0 | CE74: =SUMIFS(商品数据源!$H:$H,商品数据源!$A:$A,$B$74,商品数据源!$B:$B,CE2) -> 0 | CF74: =SUMIFS(商品数据源!$H:$H,商品数据源!$A:$A,$B$74,商品数据源!$B:$B,CF2) -> 0 | CG74: =SUMIFS(商品数据源!$H:$H,商品数据源!$A:$A,$B$74,商品数据源!$B:$B,CG2) -> 0 | CH74: =SUMIFS(商品数据源!$H:$H,商品数据源!$A:$A,$B$74,商品数据源!$B:$B,CH2) -> 0 | ... DE74: =SUMIFS(商品数据源!$H:$H,商品数据源!$A:$A,$B$74,商品数据源!$B:$B,DE2) -> 0 | DF74: =SUM(DG74:EJ74) -> 272.22 | DG74: =SUMIFS(商品数据源!$H:$H,商品数据源!$A:$A,$B$74,商品数据源!$B:$B,DG2) -> 0 | DH74: =SUMIFS(商品数据源!$H:$H,商品数据源!$A:$A,$B$74,商品数据源!$B:$B,DH2) -> 0 | DI74: =SUMIFS(商品数据源!$H:$H,商品数据源!$A:$A,$B$74,商品数据源!$B:$B,DI2) -> 0 | DJ74: =SUMIFS(商品数据源!$H:$H,商品数据源!$A:$A,$B$74,商品数据源!$B:$B,DJ2) -> 0 | DK74: =SUMIFS(商品数据源!$H:$H,商品数据源!$A:$A,$B$74,商品数据源!$B:$B,DK2) -> 0 | DL74: =SUMIFS(商品数据源!$H:$H,商品数据源!$A:$A,$B$74,商品数据源!$B:$B,DL2) -> 0 | DM74: =SUMIFS(商品数据源!$H:$H,商品数据源!$A:$A,$B$74,商品数据源!$B:$B,DM2) -> 0 | DN74: =SUMIFS(商品数据源!$H:$H,商品数据源!$A:$A,$B$74,商品数据源!$B:$B,DN2) -> 0 | ... EJ74: =SUMIFS(商品数据源!$H:$H,商品数据源!$A:$A,$B$74,商品数据源!$B:$B,EJ2) -> 72.39 | EK74: =SUM(EL74:FP74) -> 3385.14 | EL74: =SUMIFS(商品数据源!$H:$H,商品数据源!$A:$A,$B$74,商品数据源!$B:$B,EL2) -> 87.91 | EM74: =SUMIFS(商品数据源!$H:$H,商品数据源!$A:$A,$B$74,商品数据源!$B:$B,EM2) -> 80.11 | EN74: =SUMIFS(商品数据源!$H:$H,商品数据源!$A:$A,$B$74,商品数据源!$B:$B,EN2) -> 94.64 | EO74: =SUMIFS(商品数据源!$H:$H,商品数据源!$A:$A,$B$74,商品数据源!$B:$B,EO2) -> 88.71 | EP74: =SUMIFS(商品数据源!$H:$H,商品数据源!$A:$A,$B$74,商品数据源!$B:$B,EP2) -> 91.44 | EQ74: =SUMIFS(商品数据源!$H:$H,商品数据源!$A:$A,$B$74,商品数据源!$B:$B,EQ2) -> 76.23 | ER74: =SUMIFS(商品数据源!$H:$H,商品数据源!$A:$A,$B$74,商品数据源!$B:$B,ER2) -> 67.13 | ES74: =SUMIFS(商品数据源!$H:$H,商品数据源!$A:$A,$B$74,商品数据源!$B:$B,ES2) -> 93.56 | ... FP74: =SUMIFS(商品数据源!$H:$H,商品数据源!$A:$A,$B$74,商品数据源!$B:$B,FP2) -> 151.87 | FQ74: =SUM(FR74:GX74) -> 1847.05 | FR74: =SUMIFS(商品数据源!$H:$H,商品数据源!$A:$A,$B$74,商品数据源!$B:$B,FR2) -> 74.2 | FS74: =SUMIFS(商品数据源!$H:$H,商品数据源!$A:$A,$B$74,商品数据源!$B:$B,FS2) -> 79.09 | FT74: =SUMIFS(商品数据源!$H:$H,商品数据源!$A:$A,$B$74,商品数据源!$B:$B,FT2) -> 57.54 | FU74: =SUMIFS(商品数据源!$H:$H,商品数据源!$A:$A,$B$74,商品数据源!$B:$B,FU2) -> 95.8 | FV74: =SUMIFS(商品数据源!$H:$H,商品数据源!$A:$A,$B$74,商品数据源!$B:$B,FV2) -> 74.3 | FW74: =SUMIFS(商品数据源!$H:$H,商品数据源!$A:$A,$B$74,商品数据源!$B:$B,FW2) -> 116.93 | FX74: =SUMIFS(商品数据源!$H:$H,商品数据源!$A:$A,$B$74,商品数据源!$B:$B,FX2) -> 113.6 | FY74: =SUMIFS(商品数据源!$H:$H,商品数据源!$A:$A,$B$74,商品数据源!$B:$B,FY2) -> 108.87 | ... GP74: =SUMIFS(商品数据源!$H:$H,商品数据源!$A:$A,$B$74,商品数据源!$B:$B,GP2) -> 0
C75: 点击量 | D75: =SUM(E75:P75) -> #REF! | E75: =#REF! -> #REF! | F75: =#REF! -> #REF! | G75: =#REF! -> #REF! | H75: =#REF! -> #REF! | I75: =#REF! -> #REF! | J75: =#REF! -> #REF! | K75: =#REF! -> #REF! | L75: =#REF! -> #REF! | ... P75: =#REF! -> #REF! | Q75: =SUM(R75:AV75) -> 410 | R75: =SUMIFS(商品数据源!$G:$G,商品数据源!$A:$A,$B$74,商品数据源!$B:$B,R2) -> 30 | S75: =SUMIFS(商品数据源!$G:$G,商品数据源!$A:$A,$B$74,商品数据源!$B:$B,S2) -> 63 | T75: =SUMIFS(商品数据源!$G:$G,商品数据源!$A:$A,$B$74,商品数据源!$B:$B,T2) -> 46 | U75: =SUMIFS(商品数据源!$G:$G,商品数据源!$A:$A,$B$74,商品数据源!$B:$B,U2) -> 32 | V75: =SUMIFS(商品数据源!$G:$G,商品数据源!$A:$A,$B$74,商品数据源!$B:$B,V2) -> 33 | W75: =SUMIFS(商品数据源!$G:$G,商品数据源!$A:$A,$B$74,商品数据源!$B:$B,W2) -> 13 | X75: =SUMIFS(商品数据源!$G:$G,商品数据源!$A:$A,$B$74,商品数据源!$B:$B,X2) -> 16 | Y75: =SUMIFS(商品数据源!$G:$G,商品数据源!$A:$A,$B$74,商品数据源!$B:$B,Y2) -> 11 | ... AV75: =SUMIFS(商品数据源!$G:$G,商品数据源!$A:$A,$B$74,商品数据源!$B:$B,AV2) -> 0 | AW75: =SUM(AX75:BY75) -> 0 | AX75: =SUMIFS(商品数据源!$G:$G,商品数据源!$A:$A,$B$74,商品数据源!$B:$B,AX2) -> 0 | AY75: =SUMIFS(商品数据源!$G:$G,商品数据源!$A:$A,$B$74,商品数据源!$B:$B,AY2) -> 0 | AZ75: =SUMIFS(商品数据源!$G:$G,商品数据源!$A:$A,$B$74,商品数据源!$B:$B,AZ2) -> 0 | BA75: =SUMIFS(商品数据源!$G:$G,商品数据源!$A:$A,$B$74,商品数据源!$B:$B,BA2) -> 0 | BB75: =SUMIFS(商品数据源!$G:$G,商品数据源!$A:$A,$B$74,商品数据源!$B:$B,BB2) -> 0 | BC75: =SUMIFS(商品数据源!$G:$G,商品数据源!$A:$A,$B$74,商品数据源!$B:$B,BC2) -> 0 | BD75: =SUMIFS(商品数据源!$G:$G,商品数据源!$A:$A,$B$74,商品数据源!$B:$B,BD2) -> 0 | BE75: =SUMIFS(商品数据源!$G:$G,商品数据源!$A:$A,$B$74,商品数据源!$B:$B,BE2) -> 0 | ... BK75: =SUMIFS(商品数据源!$G:$G,商品数据源!$A:$A,$B$74,商品数据源!$B:$B,BK2) -> 0 | BP75: =SUMIFS(商品数据源!$G:$G,商品数据源!$A:$A,$B$74,商品数据源!$B:$B,BP2) -> 0 | BQ75: =SUMIFS(商品数据源!$G:$G,商品数据源!$A:$A,$B$74,商品数据源!$B:$B,BQ2) -> 0 | BR75: =SUMIFS(商品数据源!$G:$G,商品数据源!$A:$A,$B$74,商品数据源!$B:$B,BR2) -> 0 | BS75: =SUMIFS(商品数据源!$G:$G,商品数据源!$A:$A,$B$74,商品数据源!$B:$B,BS2) -> 0 | BT75: =SUMIFS(商品数据源!$G:$G,商品数据源!$A:$A,$B$74,商品数据源!$B:$B,BT2) -> 0 | BU75: =SUMIFS(商品数据源!$G:$G,商品数据源!$A:$A,$B$74,商品数据源!$B:$B,BU2) -> 0 | BV75: =SUMIFS(商品数据源!$G:$G,商品数据源!$A:$A,$B$74,商品数据源!$B:$B,BV2) -> 0 | BW75: =SUMIFS(商品数据源!$G:$G,商品数据源!$A:$A,$B$74,商品数据源!$B:$B,BW2) -> 0 | ... BY75: =SUMIFS(商品数据源!$G:$G,商品数据源!$A:$A,$B$74,商品数据源!$B:$B,BY2) -> 0 | BZ75: =SUM(CA75:DE75) -> 203 | CA75: =SUMIFS(商品数据源!$G:$G,商品数据源!$A:$A,$B$74,商品数据源!$B:$B,CA2) -> 0 | CB75: =SUMIFS(商品数据源!$G:$G,商品数据源!$A:$A,$B$74,商品数据源!$B:$B,CB2) -> 0 | CC75: =SUMIFS(商品数据源!$G:$G,商品数据源!$A:$A,$B$74,商品数据源!$B:$B,CC2) -> 0 | CD75: =SUMIFS(商品数据源!$G:$G,商品数据源!$A:$A,$B$74,商品数据源!$B:$B,CD2) -> 0 | CE75: =SUMIFS(商品数据源!$G:$G,商品数据源!$A:$A,$B$74,商品数据源!$B:$B,CE2) -> 0 | CF75: =SUMIFS(商品数据源!$G:$G,商品数据源!$A:$A,$B$74,商品数据源!$B:$B,CF2) -> 0 | CG75: =SUMIFS(商品数据源!$G:$G,商品数据源!$A:$A,$B$74,商品数据源!$B:$B,CG2) -> 0 | CH75: =SUMIFS(商品数据源!$G:$G,商品数据源!$A:$A,$B$74,商品数据源!$B:$B,CH2) -> 0 | ... DE75: =SUMIFS(商品数据源!$G:$G,商品数据源!$A:$A,$B$74,商品数据源!$B:$B,DE2) -> 0 | DF75: =SUM(DG75:EJ75) -> 836 | DG75: =SUMIFS(商品数据源!$G:$G,商品数据源!$A:$A,$B$74,商品数据源!$B:$B,DG2) -> 0 | DH75: =SUMIFS(商品数据源!$G:$G,商品数据源!$A:$A,$B$74,商品数据源!$B:$B,DH2) -> 0 | DI75: =SUMIFS(商品数据源!$G:$G,商品数据源!$A:$A,$B$74,商品数据源!$B:$B,DI2) -> 0 | DJ75: =SUMIFS(商品数据源!$G:$G,商品数据源!$A:$A,$B$74,商品数据源!$B:$B,DJ2) -> 0 | DK75: =SUMIFS(商品数据源!$G:$G,商品数据源!$A:$A,$B$74,商品数据源!$B:$B,DK2) -> 0 | DL75: =SUMIFS(商品数据源!$G:$G,商品数据源!$A:$A,$B$74,商品数据源!$B:$B,DL2) -> 0 | DM75: =SUMIFS(商品数据源!$G:$G,商品数据源!$A:$A,$B$74,商品数据源!$B:$B,DM2) -> 0 | DN75: =SUMIFS(商品数据源!$G:$G,商品数据源!$A:$A,$B$74,商品数据源!$B:$B,DN2) -> 0 | ... EJ75: =SUMIFS(商品数据源!$G:$G,商品数据源!$A:$A,$B$74,商品数据源!$B:$B,EJ2) -> 242 | EK75: =SUM(EL75:FP75) -> 8934 | EL75: =SUMIFS(商品数据源!$G:$G,商品数据源!$A:$A,$B$74,商品数据源!$B:$B,EL2) -> 298 | EM75: =SUMIFS(商品数据源!$G:$G,商品数据源!$A:$A,$B$74,商品数据源!$B:$B,EM2) -> 278 | EN75: =SUMIFS(商品数据源!$G:$G,商品数据源!$A:$A,$B$74,商品数据源!$B:$B,EN2) -> 301 | EO75: =SUMIFS(商品数据源!$G:$G,商品数据源!$A:$A,$B$74,商品数据源!$B:$B,EO2) -> 291 | EP75: =SUMIFS(商品数据源!$G:$G,商品数据源!$A:$A,$B$74,商品数据源!$B:$B,EP2) -> 301 | EQ75: =SUMIFS(商品数据源!$G:$G,商品数据源!$A:$A,$B$74,商品数据源!$B:$B,EQ2) -> 252 | ER75: =SUMIFS(商品数据源!$G:$G,商品数据源!$A:$A,$B$74,商品数据源!$B:$B,ER2) -> 227 | ES75: =SUMIFS(商品数据源!$G:$G,商品数据源!$A:$A,$B$74,商品数据源!$B:$B,ES2) -> 297 | ... FP75: =SUMIFS(商品数据源!$G:$G,商品数据源!$A:$A,$B$74,商品数据源!$B:$B,FP2) -> 387 | FQ75: =SUM(FR75:GX75) -> 3764 | FR75: =SUMIFS(商品数据源!$G:$G,商品数据源!$A:$A,$B$74,商品数据源!$B:$B,FR2) -> 162 | FS75: =SUMIFS(商品数据源!$G:$G,商品数据源!$A:$A,$B$74,商品数据源!$B:$B,FS2) -> 134 | FT75: =SUMIFS(商品数据源!$G:$G,商品数据源!$A:$A,$B$74,商品数据源!$B:$B,FT2) -> 114 | FU75: =SUMIFS(商品数据源!$G:$G,商品数据源!$A:$A,$B$74,商品数据源!$B:$B,FU2) -> 183 | FV75: =SUMIFS(商品数据源!$G:$G,商品数据源!$A:$A,$B$74,商品数据源!$B:$B,FV2) -> 126 | FW75: =SUMIFS(商品数据源!$G:$G,商品数据源!$A:$A,$B$74,商品数据源!$B:$B,FW2) -> 230 | FX75: =SUMIFS(商品数据源!$G:$G,商品数据源!$A:$A,$B$74,商品数据源!$B:$B,FX2) -> 269 | FY75: =SUMIFS(商品数据源!$G:$G,商品数据源!$A:$A,$B$74,商品数据源!$B:$B,FY2) -> 203 | ... GP75: =SUMIFS(商品数据源!$G:$G,商品数据源!$A:$A,$B$74,商品数据源!$B:$B,GP2) -> 0
C76: 点击单价 | D76: =D74/D75 -> #REF! | E76: =E74/E75 -> #REF! | F76: =F74/F75 -> #REF! | G76: =G74/G75 -> #REF! | H76: =H74/H75 -> #REF! | I76: =I74/I75 -> #REF! | J76: =J74/J75 -> #REF! | K76: =K74/K75 -> #REF! | ... BK76: =BK74/BK75 -> #DIV/0! | BP76: =BP74/BP75 -> #DIV/0! | BQ76: =BQ74/BQ75 -> #DIV/0! | BR76: =BR74/BR75 -> #DIV/0! | BS76: =BS74/BS75 -> #DIV/0! | BT76: =BT74/BT75 -> #DIV/0! | BU76: =BU74/BU75 -> #DIV/0! | BV76: =BV74/BV75 -> #DIV/0! | BW76: =BW74/BW75 -> #DIV/0! | ... GP76: =GP74/GP75 -> #DIV/0!
C77: 总购物车数 | D77: =SUM(E77:P77) -> #REF! | E77: =#REF! -> #REF! | F77: =#REF! -> #REF! | G77: =#REF! -> #REF! | H77: =#REF! -> #REF! | I77: =#REF! -> #REF! | J77: =#REF! -> #REF! | K77: =#REF! -> #REF! | L77: =#REF! -> #REF! | ... P77: =#REF! -> #REF! | Q77: =SUM(R77:AV77) -> 26 | R77: =SUMIFS(商品数据源!$AB:$AB,商品数据源!$A:$A,$B$74,商品数据源!$B:$B,R2) -> 2 | S77: =SUMIFS(商品数据源!$AB:$AB,商品数据源!$A:$A,$B$74,商品数据源!$B:$B,S2) -> 6 | T77: =SUMIFS(商品数据源!$AB:$AB,商品数据源!$A:$A,$B$74,商品数据源!$B:$B,T2) -> 3 | U77: =SUMIFS(商品数据源!$AB:$AB,商品数据源!$A:$A,$B$74,商品数据源!$B:$B,U2) -> 1 | V77: =SUMIFS(商品数据源!$AB:$AB,商品数据源!$A:$A,$B$74,商品数据源!$B:$B,V2) -> 1 | W77: =SUMIFS(商品数据源!$AB:$AB,商品数据源!$A:$A,$B$74,商品数据源!$B:$B,W2) -> 3 | X77: =SUMIFS(商品数据源!$AB:$AB,商品数据源!$A:$A,$B$74,商品数据源!$B:$B,X2) -> 1 | Y77: =SUMIFS(商品数据源!$AB:$AB,商品数据源!$A:$A,$B$74,商品数据源!$B:$B,Y2) -> 0 | ... AV77: =SUMIFS(商品数据源!$AB:$AB,商品数据源!$A:$A,$B$74,商品数据源!$B:$B,AV2) -> 0 | AW77: =SUM(AX77:BY77) -> 0 | AX77: =SUMIFS(商品数据源!$AB:$AB,商品数据源!$A:$A,$B$74,商品数据源!$B:$B,AX2) -> 0 | AY77: =SUMIFS(商品数据源!$AB:$AB,商品数据源!$A:$A,$B$74,商品数据源!$B:$B,AY2) -> 0 | AZ77: =SUMIFS(商品数据源!$AB:$AB,商品数据源!$A:$A,$B$74,商品数据源!$B:$B,AZ2) -> 0 | BA77: =SUMIFS(商品数据源!$AB:$AB,商品数据源!$A:$A,$B$74,商品数据源!$B:$B,BA2) -> 0 | BB77: =SUMIFS(商品数据源!$AB:$AB,商品数据源!$A:$A,$B$74,商品数据源!$B:$B,BB2) -> 0 | BC77: =SUMIFS(商品数据源!$AB:$AB,商品数据源!$A:$A,$B$74,商品数据源!$B:$B,BC2) -> 0 | BD77: =SUMIFS(商品数据源!$AB:$AB,商品数据源!$A:$A,$B$74,商品数据源!$B:$B,BD2) -> 0 | BE77: =SUMIFS(商品数据源!$AB:$AB,商品数据源!$A:$A,$B$74,商品数据源!$B:$B,BE2) -> 0 | ... BK77: =SUMIFS(商品数据源!$AB:$AB,商品数据源!$A:$A,$B$74,商品数据源!$B:$B,BK2) -> 0 | BP77: =SUMIFS(商品数据源!$AB:$AB,商品数据源!$A:$A,$B$74,商品数据源!$B:$B,BP2) -> 0 | BQ77: =SUMIFS(商品数据源!$AB:$AB,商品数据源!$A:$A,$B$74,商品数据源!$B:$B,BQ2) -> 0 | BR77: =SUMIFS(商品数据源!$AB:$AB,商品数据源!$A:$A,$B$74,商品数据源!$B:$B,BR2) -> 0 | BS77: =SUMIFS(商品数据源!$AB:$AB,商品数据源!$A:$A,$B$74,商品数据源!$B:$B,BS2) -> 0 | BT77: =SUMIFS(商品数据源!$AB:$AB,商品数据源!$A:$A,$B$74,商品数据源!$B:$B,BT2) -> 0 | BU77: =SUMIFS(商品数据源!$AB:$AB,商品数据源!$A:$A,$B$74,商品数据源!$B:$B,BU2) -> 0 | BV77: =SUMIFS(商品数据源!$AB:$AB,商品数据源!$A:$A,$B$74,商品数据源!$B:$B,BV2) -> 0 | BW77: =SUMIFS(商品数据源!$AB:$AB,商品数据源!$A:$A,$B$74,商品数据源!$B:$B,BW2) -> 0 | ... BY77: =SUMIFS(商品数据源!$AB:$AB,商品数据源!$A:$A,$B$74,商品数据源!$B:$B,BY2) -> 0 | BZ77: =SUM(CA77:DE77) -> 32 | CA77: =SUMIFS(商品数据源!$AB:$AB,商品数据源!$A:$A,$B$74,商品数据源!$B:$B,CA2) -> 0 | CB77: =SUMIFS(商品数据源!$AB:$AB,商品数据源!$A:$A,$B$74,商品数据源!$B:$B,CB2) -> 0 | CC77: =SUMIFS(商品数据源!$AB:$AB,商品数据源!$A:$A,$B$74,商品数据源!$B:$B,CC2) -> 0 | CD77: =SUMIFS(商品数据源!$AB:$AB,商品数据源!$A:$A,$B$74,商品数据源!$B:$B,CD2) -> 0 | CE77: =SUMIFS(商品数据源!$AB:$AB,商品数据源!$A:$A,$B$74,商品数据源!$B:$B,CE2) -> 0 | CF77: =SUMIFS(商品数据源!$AB:$AB,商品数据源!$A:$A,$B$74,商品数据源!$B:$B,CF2) -> 0 | CG77: =SUMIFS(商品数据源!$AB:$AB,商品数据源!$A:$A,$B$74,商品数据源!$B:$B,CG2) -> 0 | CH77: =SUMIFS(商品数据源!$AB:$AB,商品数据源!$A:$A,$B$74,商品数据源!$B:$B,CH2) -> 0 | ... DE77: =SUMIFS(商品数据源!$AB:$AB,商品数据源!$A:$A,$B$74,商品数据源!$B:$B,DE2) -> 0 | DF77: =SUM(DG77:EJ77) -> 15 | DG77: =SUMIFS(商品数据源!$AB:$AB,商品数据源!$A:$A,$B$74,商品数据源!$B:$B,DG2) -> 0 | DH77: =SUMIFS(商品数据源!$AB:$AB,商品数据源!$A:$A,$B$74,商品数据源!$B:$B,DH2) -> 0 | DI77: =SUMIFS(商品数据源!$AB:$AB,商品数据源!$A:$A,$B$74,商品数据源!$B:$B,DI2) -> 0 | DJ77: =SUMIFS(商品数据源!$AB:$AB,商品数据源!$A:$A,$B$74,商品数据源!$B:$B,DJ2) -> 0 | DK77: =SUMIFS(商品数据源!$AB:$AB,商品数据源!$A:$A,$B$74,商品数据源!$B:$B,DK2) -> 0 | DL77: =SUMIFS(商品数据源!$AB:$AB,商品数据源!$A:$A,$B$74,商品数据源!$B:$B,DL2) -> 0 | DM77: =SUMIFS(商品数据源!$AB:$AB,商品数据源!$A:$A,$B$74,商品数据源!$B:$B,DM2) -> 0 | DN77: =SUMIFS(商品数据源!$AB:$AB,商品数据源!$A:$A,$B$74,商品数据源!$B:$B,DN2) -> 0 | ... EJ77: =SUMIFS(商品数据源!$AB:$AB,商品数据源!$A:$A,$B$74,商品数据源!$B:$B,EJ2) -> 0 | EK77: =SUM(EL77:FP77) -> 208 | EL77: =SUMIFS(商品数据源!$AB:$AB,商品数据源!$A:$A,$B$74,商品数据源!$B:$B,EL2) -> 10 | EM77: =SUMIFS(商品数据源!$AB:$AB,商品数据源!$A:$A,$B$74,商品数据源!$B:$B,EM2) -> 5 | EN77: =SUMIFS(商品数据源!$AB:$AB,商品数据源!$A:$A,$B$74,商品数据源!$B:$B,EN2) -> 5 | EO77: =SUMIFS(商品数据源!$AB:$AB,商品数据源!$A:$A,$B$74,商品数据源!$B:$B,EO2) -> 9 | EP77: =SUMIFS(商品数据源!$AB:$AB,商品数据源!$A:$A,$B$74,商品数据源!$B:$B,EP2) -> 8 | EQ77: =SUMIFS(商品数据源!$AB:$AB,商品数据源!$A:$A,$B$74,商品数据源!$B:$B,EQ2) -> 4 | ER77: =SUMIFS(商品数据源!$AB:$AB,商品数据源!$A:$A,$B$74,商品数据源!$B:$B,ER2) -> 16 | ES77: =SUMIFS(商品数据源!$AB:$AB,商品数据源!$A:$A,$B$74,商品数据源!$B:$B,ES2) -> 8 | ... FP77: =SUMIFS(商品数据源!$AB:$AB,商品数据源!$A:$A,$B$74,商品数据源!$B:$B,FP2) -> 3 | FQ77: =SUM(FR77:GX77) -> 122 | FR77: =SUMIFS(商品数据源!$AB:$AB,商品数据源!$A:$A,$B$74,商品数据源!$B:$B,FR2) -> 3 | FS77: =SUMIFS(商品数据源!$AB:$AB,商品数据源!$A:$A,$B$74,商品数据源!$B:$B,FS2) -> 1 | FT77: =SUMIFS(商品数据源!$AB:$AB,商品数据源!$A:$A,$B$74,商品数据源!$B:$B,FT2) -> 5 | FU77: =SUMIFS(商品数据源!$AB:$AB,商品数据源!$A:$A,$B$74,商品数据源!$B:$B,FU2) -> 5 | FV77: =SUMIFS(商品数据源!$AB:$AB,商品数据源!$A:$A,$B$74,商品数据源!$B:$B,FV2) -> 2 | FW77: =SUMIFS(商品数据源!$AB:$AB,商品数据源!$A:$A,$B$74,商品数据源!$B:$B,FW2) -> 12 | FX77: =SUMIFS(商品数据源!$AB:$AB,商品数据源!$A:$A,$B$74,商品数据源!$B:$B,FX2) -> 9 | FY77: =SUMIFS(商品数据源!$AB:$AB,商品数据源!$A:$A,$B$74,商品数据源!$B:$B,FY2) -> 6 | ... GP77: =SUMIFS(商品数据源!$AB:$AB,商品数据源!$A:$A,$B$74,商品数据源!$B:$B,GP2) -> 0
C78: 加购成本 | D78: =D74/D77 -> #REF! | E78: =E74/E77 -> #REF! | F78: =F74/F77 -> #REF! | G78: =G74/G77 -> #REF! | H78: =H74/H77 -> #REF! | I78: =I74/I77 -> #REF! | J78: =J74/J77 -> #REF! | K78: =K74/K77 -> #REF! | ... BK78: =BK74/BK77 -> #DIV/0! | BP78: =BP74/BP77 -> #DIV/0! | BQ78: =BQ74/BQ77 -> #DIV/0! | BR78: =BR74/BR77 -> #DIV/0! | BS78: =BS74/BS77 -> #DIV/0! | BT78: =BT74/BT77 -> #DIV/0! | BU78: =BU74/BU77 -> #DIV/0! | BV78: =BV74/BV77 -> #DIV/0! | BW78: =BW74/BW77 -> #DIV/0! | ... GP78: =GP74/GP77 -> #DIV/0!
C79: 总成交量 | D79: =SUM(E79:P79) -> #REF! | E79: =#REF! -> #REF! | F79: =#REF! -> #REF! | G79: =#REF! -> #REF! | H79: =#REF! -> #REF! | I79: =#REF! -> #REF! | J79: =#REF! -> #REF! | K79: =#REF! -> #REF! | L79: =#REF! -> #REF! | ... P79: =#REF! -> #REF! | Q79: =SUM(R79:AV79) -> 3 | R79: =SUMIFS(商品数据源!$U:$U,商品数据源!$A:$A,$B$74,商品数据源!$B:$B,R2) -> 0 | S79: =SUMIFS(商品数据源!$U:$U,商品数据源!$A:$A,$B$74,商品数据源!$B:$B,S2) -> 1 | T79: =SUMIFS(商品数据源!$U:$U,商品数据源!$A:$A,$B$74,商品数据源!$B:$B,T2) -> 1 | U79: =SUMIFS(商品数据源!$U:$U,商品数据源!$A:$A,$B$74,商品数据源!$B:$B,U2) -> 0 | V79: =SUMIFS(商品数据源!$U:$U,商品数据源!$A:$A,$B$74,商品数据源!$B:$B,V2) -> 0 | W79: =SUMIFS(商品数据源!$U:$U,商品数据源!$A:$A,$B$74,商品数据源!$B:$B,W2) -> 0 | X79: =SUMIFS(商品数据源!$U:$U,商品数据源!$A:$A,$B$74,商品数据源!$B:$B,X2) -> 0 | Y79: =SUMIFS(商品数据源!$U:$U,商品数据源!$A:$A,$B$74,商品数据源!$B:$B,Y2) -> 0 | ... AV79: =SUMIFS(商品数据源!$U:$U,商品数据源!$A:$A,$B$74,商品数据源!$B:$B,AV2) -> 0 | AW79: =SUM(AX79:BY79) -> 0 | AX79: =SUMIFS(商品数据源!$U:$U,商品数据源!$A:$A,$B$74,商品数据源!$B:$B,AX2) -> 0 | AY79: =SUMIFS(商品数据源!$U:$U,商品数据源!$A:$A,$B$74,商品数据源!$B:$B,AY2) -> 0 | AZ79: =SUMIFS(商品数据源!$U:$U,商品数据源!$A:$A,$B$74,商品数据源!$B:$B,AZ2) -> 0 | BA79: =SUMIFS(商品数据源!$U:$U,商品数据源!$A:$A,$B$74,商品数据源!$B:$B,BA2) -> 0 | BB79: =SUMIFS(商品数据源!$U:$U,商品数据源!$A:$A,$B$74,商品数据源!$B:$B,BB2) -> 0 | BC79: =SUMIFS(商品数据源!$U:$U,商品数据源!$A:$A,$B$74,商品数据源!$B:$B,BC2) -> 0 | BD79: =SUMIFS(商品数据源!$U:$U,商品数据源!$A:$A,$B$74,商品数据源!$B:$B,BD2) -> 0 | BE79: =SUMIFS(商品数据源!$U:$U,商品数据源!$A:$A,$B$74,商品数据源!$B:$B,BE2) -> 0 | ... BK79: =SUMIFS(商品数据源!$U:$U,商品数据源!$A:$A,$B$74,商品数据源!$B:$B,BK2) -> 0 | BP79: =SUMIFS(商品数据源!$U:$U,商品数据源!$A:$A,$B$74,商品数据源!$B:$B,BP2) -> 0 | BQ79: =SUMIFS(商品数据源!$U:$U,商品数据源!$A:$A,$B$74,商品数据源!$B:$B,BQ2) -> 0 | BR79: =SUMIFS(商品数据源!$U:$U,商品数据源!$A:$A,$B$74,商品数据源!$B:$B,BR2) -> 0 | BS79: =SUMIFS(商品数据源!$U:$U,商品数据源!$A:$A,$B$74,商品数据源!$B:$B,BS2) -> 0 | BT79: =SUMIFS(商品数据源!$U:$U,商品数据源!$A:$A,$B$74,商品数据源!$B:$B,BT2) -> 0 | BU79: =SUMIFS(商品数据源!$U:$U,商品数据源!$A:$A,$B$74,商品数据源!$B:$B,BU2) -> 0 | BV79: =SUMIFS(商品数据源!$U:$U,商品数据源!$A:$A,$B$74,商品数据源!$B:$B,BV2) -> 0 | BW79: =SUMIFS(商品数据源!$U:$U,商品数据源!$A:$A,$B$74,商品数据源!$B:$B,BW2) -> 0 | ... BY79: =SUMIFS(商品数据源!$U:$U,商品数据源!$A:$A,$B$74,商品数据源!$B:$B,BY2) -> 0 | BZ79: =SUM(CA79:DE79) -> 9 | CA79: =SUMIFS(商品数据源!$U:$U,商品数据源!$A:$A,$B$74,商品数据源!$B:$B,CA2) -> 0 | CB79: =SUMIFS(商品数据源!$U:$U,商品数据源!$A:$A,$B$74,商品数据源!$B:$B,CB2) -> 0 | CC79: =SUMIFS(商品数据源!$U:$U,商品数据源!$A:$A,$B$74,商品数据源!$B:$B,CC2) -> 0 | CD79: =SUMIFS(商品数据源!$U:$U,商品数据源!$A:$A,$B$74,商品数据源!$B:$B,CD2) -> 0 | CE79: =SUMIFS(商品数据源!$U:$U,商品数据源!$A:$A,$B$74,商品数据源!$B:$B,CE2) -> 0 | CF79: =SUMIFS(商品数据源!$U:$U,商品数据源!$A:$A,$B$74,商品数据源!$B:$B,CF2) -> 0 | CG79: =SUMIFS(商品数据源!$U:$U,商品数据源!$A:$A,$B$74,商品数据源!$B:$B,CG2) -> 0 | CH79: =SUMIFS(商品数据源!$U:$U,商品数据源!$A:$A,$B$74,商品数据源!$B:$B,CH2) -> 0 | ... DE79: =SUMIFS(商品数据源!$U:$U,商品数据源!$A:$A,$B$74,商品数据源!$B:$B,DE2) -> 0 | DF79: =SUM(DG79:EJ79) -> 3 | DG79: =SUMIFS(商品数据源!$U:$U,商品数据源!$A:$A,$B$74,商品数据源!$B:$B,DG2) -> 0 | DH79: =SUMIFS(商品数据源!$U:$U,商品数据源!$A:$A,$B$74,商品数据源!$B:$B,DH2) -> 0 | DI79: =SUMIFS(商品数据源!$U:$U,商品数据源!$A:$A,$B$74,商品数据源!$B:$B,DI2) -> 0 | DJ79: =SUMIFS(商品数据源!$U:$U,商品数据源!$A:$A,$B$74,商品数据源!$B:$B,DJ2) -> 0 | DK79: =SUMIFS(商品数据源!$U:$U,商品数据源!$A:$A,$B$74,商品数据源!$B:$B,DK2) -> 0 | DL79: =SUMIFS(商品数据源!$U:$U,商品数据源!$A:$A,$B$74,商品数据源!$B:$B,DL2) -> 0 | DM79: =SUMIFS(商品数据源!$U:$U,商品数据源!$A:$A,$B$74,商品数据源!$B:$B,DM2) -> 0 | DN79: =SUMIFS(商品数据源!$U:$U,商品数据源!$A:$A,$B$74,商品数据源!$B:$B,DN2) -> 0 | ... EJ79: =SUMIFS(商品数据源!$U:$U,商品数据源!$A:$A,$B$74,商品数据源!$B:$B,EJ2) -> 0 | EK79: =SUM(EL79:FP79) -> 19 | EL79: =SUMIFS(商品数据源!$U:$U,商品数据源!$A:$A,$B$74,商品数据源!$B:$B,EL2) -> 0 | EM79: =SUMIFS(商品数据源!$U:$U,商品数据源!$A:$A,$B$74,商品数据源!$B:$B,EM2) -> 1 | EN79: =SUMIFS(商品数据源!$U:$U,商品数据源!$A:$A,$B$74,商品数据源!$B:$B,EN2) -> 0 | EO79: =SUMIFS(商品数据源!$U:$U,商品数据源!$A:$A,$B$74,商品数据源!$B:$B,EO2) -> 0 | EP79: =SUMIFS(商品数据源!$U:$U,商品数据源!$A:$A,$B$74,商品数据源!$B:$B,EP2) -> 0 | EQ79: =SUMIFS(商品数据源!$U:$U,商品数据源!$A:$A,$B$74,商品数据源!$B:$B,EQ2) -> 1 | ER79: =SUMIFS(商品数据源!$U:$U,商品数据源!$A:$A,$B$74,商品数据源!$B:$B,ER2) -> 0 | ES79: =SUMIFS(商品数据源!$U:$U,商品数据源!$A:$A,$B$74,商品数据源!$B:$B,ES2) -> 0 | ... FP79: =SUMIFS(商品数据源!$U:$U,商品数据源!$A:$A,$B$74,商品数据源!$B:$B,FP2) -> 0 | FQ79: =SUM(FR79:GX79) -> 14 | FR79: =SUMIFS(商品数据源!$U:$U,商品数据源!$A:$A,$B$74,商品数据源!$B:$B,FR2) -> 0 | FS79: =SUMIFS(商品数据源!$U:$U,商品数据源!$A:$A,$B$74,商品数据源!$B:$B,FS2) -> 1 | FT79: =SUMIFS(商品数据源!$U:$U,商品数据源!$A:$A,$B$74,商品数据源!$B:$B,FT2) -> 1 | FU79: =SUMIFS(商品数据源!$U:$U,商品数据源!$A:$A,$B$74,商品数据源!$B:$B,FU2) -> 1 | FV79: =SUMIFS(商品数据源!$U:$U,商品数据源!$A:$A,$B$74,商品数据源!$B:$B,FV2) -> 0 | FW79: =SUMIFS(商品数据源!$U:$U,商品数据源!$A:$A,$B$74,商品数据源!$B:$B,FW2) -> 2 | FX79: =SUMIFS(商品数据源!$U:$U,商品数据源!$A:$A,$B$74,商品数据源!$B:$B,FX2) -> 0 | FY79: =SUMIFS(商品数据源!$U:$U,商品数据源!$A:$A,$B$74,商品数据源!$B:$B,FY2) -> 2 | ... GP79: =SUMIFS(商品数据源!$U:$U,商品数据源!$A:$A,$B$74,商品数据源!$B:$B,GP2) -> 0
C80: 总成交金额 | D80: =SUM(E80:P80) -> #REF! | E80: =#REF! -> #REF! | F80: =#REF! -> #REF! | G80: =#REF! -> #REF! | H80: =#REF! -> #REF! | I80: =#REF! -> #REF! | J80: =#REF! -> #REF! | K80: =#REF! -> #REF! | L80: =#REF! -> #REF! | ... P80: =#REF! -> #REF! | Q80: =SUM(R80:AV80) -> 166.68 | R80: =SUMIFS(商品数据源!$T:$T,商品数据源!$A:$A,$B$74,商品数据源!$B:$B,R2) -> 0 | S80: =SUMIFS(商品数据源!$T:$T,商品数据源!$A:$A,$B$74,商品数据源!$B:$B,S2) -> 82.17 | T80: =SUMIFS(商品数据源!$T:$T,商品数据源!$A:$A,$B$74,商品数据源!$B:$B,T2) -> 24.65 | U80: =SUMIFS(商品数据源!$T:$T,商品数据源!$A:$A,$B$74,商品数据源!$B:$B,U2) -> 0 | V80: =SUMIFS(商品数据源!$T:$T,商品数据源!$A:$A,$B$74,商品数据源!$B:$B,V2) -> 0 | W80: =SUMIFS(商品数据源!$T:$T,商品数据源!$A:$A,$B$74,商品数据源!$B:$B,W2) -> 0 | X80: =SUMIFS(商品数据源!$T:$T,商品数据源!$A:$A,$B$74,商品数据源!$B:$B,X2) -> 0 | Y80: =SUMIFS(商品数据源!$T:$T,商品数据源!$A:$A,$B$74,商品数据源!$B:$B,Y2) -> 0 | ... AV80: =SUMIFS(商品数据源!$T:$T,商品数据源!$A:$A,$B$74,商品数据源!$B:$B,AV2) -> 0 | AW80: =SUM(AX80:BY80) -> 0 | AX80: =SUMIFS(商品数据源!$T:$T,商品数据源!$A:$A,$B$74,商品数据源!$B:$B,AX2) -> 0 | AY80: =SUMIFS(商品数据源!$T:$T,商品数据源!$A:$A,$B$74,商品数据源!$B:$B,AY2) -> 0 | AZ80: =SUMIFS(商品数据源!$T:$T,商品数据源!$A:$A,$B$74,商品数据源!$B:$B,AZ2) -> 0 | BA80: =SUMIFS(商品数据源!$T:$T,商品数据源!$A:$A,$B$74,商品数据源!$B:$B,BA2) -> 0 | BB80: =SUMIFS(商品数据源!$T:$T,商品数据源!$A:$A,$B$74,商品数据源!$B:$B,BB2) -> 0 | BC80: =SUMIFS(商品数据源!$T:$T,商品数据源!$A:$A,$B$74,商品数据源!$B:$B,BC2) -> 0 | BD80: =SUMIFS(商品数据源!$T:$T,商品数据源!$A:$A,$B$74,商品数据源!$B:$B,BD2) -> 0 | BE80: =SUMIFS(商品数据源!$T:$T,商品数据源!$A:$A,$B$74,商品数据源!$B:$B,BE2) -> 0 | ... BK80: =SUMIFS(商品数据源!$T:$T,商品数据源!$A:$A,$B$74,商品数据源!$B:$B,BK2) -> 0 | BP80: =SUMIFS(商品数据源!$T:$T,商品数据源!$A:$A,$B$74,商品数据源!$B:$B,BP2) -> 0 | BQ80: =SUMIFS(商品数据源!$T:$T,商品数据源!$A:$A,$B$74,商品数据源!$B:$B,BQ2) -> 0 | BR80: =SUMIFS(商品数据源!$T:$T,商品数据源!$A:$A,$B$74,商品数据源!$B:$B,BR2) -> 0 | BS80: =SUMIFS(商品数据源!$T:$T,商品数据源!$A:$A,$B$74,商品数据源!$B:$B,BS2) -> 0 | BT80: =SUMIFS(商品数据源!$T:$T,商品数据源!$A:$A,$B$74,商品数据源!$B:$B,BT2) -> 0 | BU80: =SUMIFS(商品数据源!$T:$T,商品数据源!$A:$A,$B$74,商品数据源!$B:$B,BU2) -> 0 | BV80: =SUMIFS(商品数据源!$T:$T,商品数据源!$A:$A,$B$74,商品数据源!$B:$B,BV2) -> 0 | BW80: =SUMIFS(商品数据源!$T:$T,商品数据源!$A:$A,$B$74,商品数据源!$B:$B,BW2) -> 0 | ... BY80: =SUMIFS(商品数据源!$T:$T,商品数据源!$A:$A,$B$74,商品数据源!$B:$B,BY2) -> 0 | BZ80: =SUM(CA80:DE80) -> 958.55 | CA80: =SUMIFS(商品数据源!$T:$T,商品数据源!$A:$A,$B$74,商品数据源!$B:$B,CA2) -> 0 | CB80: =SUMIFS(商品数据源!$T:$T,商品数据源!$A:$A,$B$74,商品数据源!$B:$B,CB2) -> 0 | CC80: =SUMIFS(商品数据源!$T:$T,商品数据源!$A:$A,$B$74,商品数据源!$B:$B,CC2) -> 0 | CD80: =SUMIFS(商品数据源!$T:$T,商品数据源!$A:$A,$B$74,商品数据源!$B:$B,CD2) -> 0 | CE80: =SUMIFS(商品数据源!$T:$T,商品数据源!$A:$A,$B$74,商品数据源!$B:$B,CE2) -> 0 | CF80: =SUMIFS(商品数据源!$T:$T,商品数据源!$A:$A,$B$74,商品数据源!$B:$B,CF2) -> 0 | CG80: =SUMIFS(商品数据源!$T:$T,商品数据源!$A:$A,$B$74,商品数据源!$B:$B,CG2) -> 0 | CH80: =SUMIFS(商品数据源!$T:$T,商品数据源!$A:$A,$B$74,商品数据源!$B:$B,CH2) -> 0 | ... DE80: =SUMIFS(商品数据源!$T:$T,商品数据源!$A:$A,$B$74,商品数据源!$B:$B,DE2) -> 0 | DF80: =SUM(DG80:EJ80) -> 452.54 | DG80: =SUMIFS(商品数据源!$T:$T,商品数据源!$A:$A,$B$74,商品数据源!$B:$B,DG2) -> 0 | DH80: =SUMIFS(商品数据源!$T:$T,商品数据源!$A:$A,$B$74,商品数据源!$B:$B,DH2) -> 0 | DI80: =SUMIFS(商品数据源!$T:$T,商品数据源!$A:$A,$B$74,商品数据源!$B:$B,DI2) -> 0 | DJ80: =SUMIFS(商品数据源!$T:$T,商品数据源!$A:$A,$B$74,商品数据源!$B:$B,DJ2) -> 0 | DK80: =SUMIFS(商品数据源!$T:$T,商品数据源!$A:$A,$B$74,商品数据源!$B:$B,DK2) -> 0 | DL80: =SUMIFS(商品数据源!$T:$T,商品数据源!$A:$A,$B$74,商品数据源!$B:$B,DL2) -> 0 | DM80: =SUMIFS(商品数据源!$T:$T,商品数据源!$A:$A,$B$74,商品数据源!$B:$B,DM2) -> 0 | DN80: =SUMIFS(商品数据源!$T:$T,商品数据源!$A:$A,$B$74,商品数据源!$B:$B,DN2) -> 0 | ... EJ80: =SUMIFS(商品数据源!$T:$T,商品数据源!$A:$A,$B$74,商品数据源!$B:$B,EJ2) -> 0 | EK80: =SUM(EL80:FP80) -> 1903.46 | EL80: =SUMIFS(商品数据源!$T:$T,商品数据源!$A:$A,$B$74,商品数据源!$B:$B,EL2) -> 0 | EM80: =SUMIFS(商品数据源!$T:$T,商品数据源!$A:$A,$B$74,商品数据源!$B:$B,EM2) -> 151 | EN80: =SUMIFS(商品数据源!$T:$T,商品数据源!$A:$A,$B$74,商品数据源!$B:$B,EN2) -> 0 | EO80: =SUMIFS(商品数据源!$T:$T,商品数据源!$A:$A,$B$74,商品数据源!$B:$B,EO2) -> 0 | EP80: =SUMIFS(商品数据源!$T:$T,商品数据源!$A:$A,$B$74,商品数据源!$B:$B,EP2) -> 0 | EQ80: =SUMIFS(商品数据源!$T:$T,商品数据源!$A:$A,$B$74,商品数据源!$B:$B,EQ2) -> 133.6 | ER80: =SUMIFS(商品数据源!$T:$T,商品数据源!$A:$A,$B$74,商品数据源!$B:$B,ER2) -> 0 | ES80: =SUMIFS(商品数据源!$T:$T,商品数据源!$A:$A,$B$74,商品数据源!$B:$B,ES2) -> 0 | ... FP80: =SUMIFS(商品数据源!$T:$T,商品数据源!$A:$A,$B$74,商品数据源!$B:$B,FP2) -> 0 | FQ80: =SUM(FR80:GX80) -> 1350.81 | FR80: =SUMIFS(商品数据源!$T:$T,商品数据源!$A:$A,$B$74,商品数据源!$B:$B,FR2) -> 0 | FS80: =SUMIFS(商品数据源!$T:$T,商品数据源!$A:$A,$B$74,商品数据源!$B:$B,FS2) -> 90 | FT80: =SUMIFS(商品数据源!$T:$T,商品数据源!$A:$A,$B$74,商品数据源!$B:$B,FT2) -> 90 | FU80: =SUMIFS(商品数据源!$T:$T,商品数据源!$A:$A,$B$74,商品数据源!$B:$B,FU2) -> 138.64 | FV80: =SUMIFS(商品数据源!$T:$T,商品数据源!$A:$A,$B$74,商品数据源!$B:$B,FV2) -> 0 | FW80: =SUMIFS(商品数据源!$T:$T,商品数据源!$A:$A,$B$74,商品数据源!$B:$B,FW2) -> 125 | FX80: =SUMIFS(商品数据源!$T:$T,商品数据源!$A:$A,$B$74,商品数据源!$B:$B,FX2) -> 0 | FY80: =SUMIFS(商品数据源!$T:$T,商品数据源!$A:$A,$B$74,商品数据源!$B:$B,FY2) -> 277.28 | ... GP80: =SUMIFS(商品数据源!$T:$T,商品数据源!$A:$A,$B$74,商品数据源!$B:$B,GP2) -> 0
C81: ROI | D81: =D80/D74 -> #REF! | E81: =E80/E74 -> #REF! | F81: =F80/F74 -> #REF! | G81: =G80/G74 -> #REF! | H81: =H80/H74 -> #REF! | I81: =I80/I74 -> #REF! | J81: =J80/J74 -> #REF! | K81: =K80/K74 -> #REF! | ... BK81: =BK80/BK74 -> #DIV/0! | BP81: =BP80/BP74 -> #DIV/0! | BQ81: =BQ80/BQ74 -> #DIV/0! | BR81: =BR80/BR74 -> #DIV/0! | BS81: =BS80/BS74 -> #DIV/0! | BT81: =BT80/BT74 -> #DIV/0! | BU81: =BU80/BU74 -> #DIV/0! | BV81: =BV80/BV74 -> #DIV/0! | BW81: =BW80/BW74 -> #DIV/0! | ... GP81: =GP80/GP74 -> #DIV/0!
C82: 费用占比 | D82: =D74/D$128 -> #REF! | E82: =E74/E$128 -> #REF! | F82: =F74/F$128 -> #REF! | G82: =G74/G$128 -> #REF! | H82: =H74/H$128 -> #REF! | I82: =I74/I$128 -> #REF! | J82: =J74/J$128 -> #REF! | K82: =K74/K$128 -> #REF! | ... BK82: =BK74/BK$128 -> 0 | BP82: =BP74/BP$128 -> 0 | BQ82: =BQ74/BQ$128 -> 0 | BR82: =BR74/BR$128 -> 0 | BS82: =BS74/BS$128 -> 0 | BT82: =BT74/BT$128 -> 0 | BU82: =BU74/BU$128 -> 0 | BV82: =BV74/BV$128 -> 0 | BW82: =BW74/BW$128 -> 0 | ... GP82: =GP74/GP$128 -> #DIV/0!
B83: 四季线香 | C83: 花费 | D83: =SUM(E83:P83) -> #REF! | E83: =#REF! -> #REF! | F83: =#REF! -> #REF! | G83: =#REF! -> #REF! | H83: =#REF! -> #REF! | I83: =#REF! -> #REF! | J83: =#REF! -> #REF! | K83: =#REF! -> #REF! | L83: =#REF! -> #REF! | ... P83: =#REF! -> #REF! | Q83: =SUM(R83:AV83) -> 1177.01 | R83: =SUMIFS(商品数据源!$H:$H,商品数据源!$A:$A,$B$83,商品数据源!$B:$B,R2) -> 48.98 | S83: =SUMIFS(商品数据源!$H:$H,商品数据源!$A:$A,$B$83,商品数据源!$B:$B,S2) -> 35.71 | T83: =SUMIFS(商品数据源!$H:$H,商品数据源!$A:$A,$B$83,商品数据源!$B:$B,T2) -> 29.93 | U83: =SUMIFS(商品数据源!$H:$H,商品数据源!$A:$A,$B$83,商品数据源!$B:$B,U2) -> 57.63 | V83: =SUMIFS(商品数据源!$H:$H,商品数据源!$A:$A,$B$83,商品数据源!$B:$B,V2) -> 54.64 | W83: =SUMIFS(商品数据源!$H:$H,商品数据源!$A:$A,$B$83,商品数据源!$B:$B,W2) -> 70.82 | X83: =SUMIFS(商品数据源!$H:$H,商品数据源!$A:$A,$B$83,商品数据源!$B:$B,X2) -> 52.67 | Y83: =SUMIFS(商品数据源!$H:$H,商品数据源!$A:$A,$B$83,商品数据源!$B:$B,Y2) -> 57.05 | ... AV83: =SUMIFS(商品数据源!$H:$H,商品数据源!$A:$A,$B$83,商品数据源!$B:$B,AV2) -> 16.95 | AW83: =SUM(AX83:BY83) -> 265.91 | AX83: =SUMIFS(商品数据源!$H:$H,商品数据源!$A:$A,$B$83,商品数据源!$B:$B,AX2) -> 19.59 | AY83: =SUMIFS(商品数据源!$H:$H,商品数据源!$A:$A,$B$83,商品数据源!$B:$B,AY2) -> 23.14 | AZ83: =SUMIFS(商品数据源!$H:$H,商品数据源!$A:$A,$B$83,商品数据源!$B:$B,AZ2) -> 24.8 | BA83: =SUMIFS(商品数据源!$H:$H,商品数据源!$A:$A,$B$83,商品数据源!$B:$B,BA2) -> 31.01 | BB83: =SUMIFS(商品数据源!$H:$H,商品数据源!$A:$A,$B$83,商品数据源!$B:$B,BB2) -> 42.08 | BC83: =SUMIFS(商品数据源!$H:$H,商品数据源!$A:$A,$B$83,商品数据源!$B:$B,BC2) -> 20.9 | BD83: =SUMIFS(商品数据源!$H:$H,商品数据源!$A:$A,$B$83,商品数据源!$B:$B,BD2) -> 32.71 | BE83: =SUMIFS(商品数据源!$H:$H,商品数据源!$A:$A,$B$83,商品数据源!$B:$B,BE2) -> 35 | ... BY83: =SUMIFS(商品数据源!$H:$H,商品数据源!$A:$A,$B$83,商品数据源!$B:$B,BY2) -> 0 | BZ83: =SUM(CA83:DE83) -> 0 | CA83: =SUMIFS(商品数据源!$H:$H,商品数据源!$A:$A,$B$83,商品数据源!$B:$B,CA2) -> 0 | CB83: =SUMIFS(商品数据源!$H:$H,商品数据源!$A:$A,$B$83,商品数据源!$B:$B,CB2) -> 0 | CC83: =SUMIFS(商品数据源!$H:$H,商品数据源!$A:$A,$B$83,商品数据源!$B:$B,CC2) -> 0 | CD83: =SUMIFS(商品数据源!$H:$H,商品数据源!$A:$A,$B$83,商品数据源!$B:$B,CD2) -> 0 | CE83: =SUMIFS(商品数据源!$H:$H,商品数据源!$A:$A,$B$83,商品数据源!$B:$B,CE2) -> 0 | CF83: =SUMIFS(商品数据源!$H:$H,商品数据源!$A:$A,$B$83,商品数据源!$B:$B,CF2) -> 0 | CG83: =SUMIFS(商品数据源!$H:$H,商品数据源!$A:$A,$B$83,商品数据源!$B:$B,CG2) -> 0 | CH83: =SUMIFS(商品数据源!$H:$H,商品数据源!$A:$A,$B$83,商品数据源!$B:$B,CH2) -> 0 | ... DE83: =SUMIFS(商品数据源!$H:$H,商品数据源!$A:$A,$B$83,商品数据源!$B:$B,DE2) -> 0 | DF83: =SUM(DG83:EJ83) -> 0 | DG83: =SUMIFS(商品数据源!$H:$H,商品数据源!$A:$A,$B$83,商品数据源!$B:$B,DG2) -> 0 | DH83: =SUMIFS(商品数据源!$H:$H,商品数据源!$A:$A,$B$83,商品数据源!$B:$B,DH2) -> 0 | DI83: =SUMIFS(商品数据源!$H:$H,商品数据源!$A:$A,$B$83,商品数据源!$B:$B,DI2) -> 0 | DJ83: =SUMIFS(商品数据源!$H:$H,商品数据源!$A:$A,$B$83,商品数据源!$B:$B,DJ2) -> 0 | DK83: =SUMIFS(商品数据源!$H:$H,商品数据源!$A:$A,$B$83,商品数据源!$B:$B,DK2) -> 0 | DL83: =SUMIFS(商品数据源!$H:$H,商品数据源!$A:$A,$B$83,商品数据源!$B:$B,DL2) -> 0 | DM83: =SUMIFS(商品数据源!$H:$H,商品数据源!$A:$A,$B$83,商品数据源!$B:$B,DM2) -> 0 | DN83: =SUMIFS(商品数据源!$H:$H,商品数据源!$A:$A,$B$83,商品数据源!$B:$B,DN2) -> 0 | ... EJ83: =SUMIFS(商品数据源!$H:$H,商品数据源!$A:$A,$B$83,商品数据源!$B:$B,EJ2) -> 0 | EK83: =SUM(EL83:FP83) -> 0 | EL83: =SUMIFS(商品数据源!$H:$H,商品数据源!$A:$A,$B$83,商品数据源!$B:$B,EL2) -> 0 | EM83: =SUMIFS(商品数据源!$H:$H,商品数据源!$A:$A,$B$83,商品数据源!$B:$B,EM2) -> 0 | EN83: =SUMIFS(商品数据源!$H:$H,商品数据源!$A:$A,$B$83,商品数据源!$B:$B,EN2) -> 0 | EO83: =SUMIFS(商品数据源!$H:$H,商品数据源!$A:$A,$B$83,商品数据源!$B:$B,EO2) -> 0 | EP83: =SUMIFS(商品数据源!$H:$H,商品数据源!$A:$A,$B$83,商品数据源!$B:$B,EP2) -> 0 | EQ83: =SUMIFS(商品数据源!$H:$H,商品数据源!$A:$A,$B$83,商品数据源!$B:$B,EQ2) -> 0 | ER83: =SUMIFS(商品数据源!$H:$H,商品数据源!$A:$A,$B$83,商品数据源!$B:$B,ER2) -> 0 | ES83: =SUMIFS(商品数据源!$H:$H,商品数据源!$A:$A,$B$83,商品数据源!$B:$B,ES2) -> 0 | ... FP83: =SUMIFS(商品数据源!$H:$H,商品数据源!$A:$A,$B$83,商品数据源!$B:$B,FP2) -> 0 | FQ83: =SUM(FR83:GX83) -> 0 | FR83: =SUMIFS(商品数据源!$H:$H,商品数据源!$A:$A,$B$83,商品数据源!$B:$B,FR2) -> 0 | FS83: =SUMIFS(商品数据源!$H:$H,商品数据源!$A:$A,$B$83,商品数据源!$B:$B,FS2) -> 0 | FT83: =SUMIFS(商品数据源!$H:$H,商品数据源!$A:$A,$B$83,商品数据源!$B:$B,FT2) -> 0 | FU83: =SUMIFS(商品数据源!$H:$H,商品数据源!$A:$A,$B$83,商品数据源!$B:$B,FU2) -> 0 | FV83: =SUMIFS(商品数据源!$H:$H,商品数据源!$A:$A,$B$83,商品数据源!$B:$B,FV2) -> 0 | FW83: =SUMIFS(商品数据源!$H:$H,商品数据源!$A:$A,$B$83,商品数据源!$B:$B,FW2) -> 0 | FX83: =SUMIFS(商品数据源!$H:$H,商品数据源!$A:$A,$B$83,商品数据源!$B:$B,FX2) -> 0 | FY83: =SUMIFS(商品数据源!$H:$H,商品数据源!$A:$A,$B$83,商品数据源!$B:$B,FY2) -> 0 | ... GP83: =SUMIFS(商品数据源!$H:$H,商品数据源!$A:$A,$B$83,商品数据源!$B:$B,GP2) -> 0
